Workbook

Sheet 00_INDICE
A1: Hoja | B1: Rol | C1: Origen
A2: 01_PRODUCTOS | B2: ENTRADA_PYTHON | C2: OPERATIVA 02_PRODUCTOS
A3: 02_MATERIALES | B3: REFERENCIA | C3: OPERATIVA 03_MATERIALES
A4: 03_DESPIECE | B4: ENTRADA_PYTHON (opcional) | C4: OPERATIVA 04_DESPIECE (valores materializados)
A5: 04_MAQUINAS | B5: ENTRADA_PYTHON | C5: OPERATIVA 05_RECURSOS
A6: 05_RUTAS | B6: ENTRADA_PYTHON | C6: OPERATIVA 06_RUTAS
A7: 06B_HABILIDADES | B7: ENTRADA_PYTHON | C7: SIMULACION 03_HABILIDADES_SIM
A8: 06_OPERARIOS | B8: ENTRADA_PYTHON | C8: OPERATIVA 08_PERSONAL + SIMULACION 02_PERFILES_SIM
A9: 07_CALENDARIO | B9: ENTRADA_PYTHON | C9: OPERATIVA 09_CALENDARIO
A10: 08_PEDIDOS | B10: ENTRADA_PYTHON | C10: SIMULACION 01_PEDIDOS_SIM
A11: 09_CARGA_ORDEN | B11: DERIVADA (fórmulas) | C11: 08_PEDIDOS × 05_RUTAS
A12: 10_MATERIALES_ORDEN | B12: DERIVADA (fórmulas) | C12: 08_PEDIDOS × 03_DESPIECE
... A29: Naturaleza | B29: REAL / REFERENCIA / CALCULADO / ESTIMADO / SIMULADO / CONFIGURACION / PENDIENTE | C29: Definiciones en SAGAPI_BD_OPERATIVA_v2_0.xlsx, hoja 00_CODIGOS

Sheet 01_PRODUCTOS
A1: Familia | B1: Nombre completo | C1: Tipo | D1: Alto cm | E1: Ancho cm | F1: Fondo cm | G1: Puertas | H1: Lote guía | I1: Componentes | J1: Pasos de ruta | K1: Familia válida (1/0) | L1: Dimensiones genéricas (1/0) | M1: Naturaleza
A2: Racks industriales | B2: Minirack metálico con bandejas | C2: Estantería liviana | D2: 200 | E2: 120 | F2: 60 | H2: 10 | I2: =COUNTIF('03_DESPIECE'!$A$2:$A$225,B2) -> 7 | J2: =COUNTIF('05_RUTAS'!$A$2:$A$407,B2) -> 13 | K2: =IF(COUNTIF('12_PRECIOS'!$A$2:$A$5,A2)>0,1,0) -> 1 | L2: =IF(COUNTIFS($D$2:$D$51,D2,$E$2:$E$51,E2,$F$2:$F$51,F2)>=5,1,0) -> 0 | M2: ESTIMADO
A3: Racks industriales | B3: Estante reforzado modular | C3: Estantería reforzada | D3: 200 | E3: 120 | F3: 60 | H3: 10 | I3: =COUNTIF('03_DESPIECE'!$A$2:$A$225,B3) -> 6 | J3: =COUNTIF('05_RUTAS'!$A$2:$A$407,B3) -> 13 | K3: =IF(COUNTIF('12_PRECIOS'!$A$2:$A$5,A3)>0,1,0) -> 1 | L3: =IF(COUNTIFS($D$2:$D$51,D3,$E$2:$E$51,E3,$F$2:$F$51,F3)>=5,1,0) -> 0 | M3: ESTIMADO
A4: Racks industriales | B4: Rack selectivo para pallets | C4: Selectivo | D4: 400 | E4: 270 | F4: 110 | H4: 10 | I4: =COUNTIF('03_DESPIECE'!$A$2:$A$225,B4) -> 4 | J4: =COUNTIF('05_RUTAS'!$A$2:$A$407,B4) -> 8 | K4: =IF(COUNTIF('12_PRECIOS'!$A$2:$A$5,A4)>0,1,0) -> 1 | L4: =IF(COUNTIFS($D$2:$D$51,D4,$E$2:$E$51,E4,$F$2:$F$51,F4)>=5,1,0) -> 0 | M4: ESTIMADO
A5: Racks industriales | B5: Rack cantilever 3 niveles | C5: Cantilever | D5: 300 | E5: 150 | F5: 100 | H5: 10 | I5: =COUNTIF('03_DESPIECE'!$A$2:$A$225,B5) -> 4 | J5: =COUNTIF('05_RUTAS'!$A$2:$A$407,B5) -> 8 | K5: =IF(COUNTIF('12_PRECIOS'!$A$2:$A$5,A5)>0,1,0) -> 1 | L5: =IF(COUNTIFS($D$2:$D$51,D5,$E$2:$E$51,E5,$F$2:$F$51,F5)>=5,1,0) -> 0 | M5: ESTIMADO
A6: Racks industriales | B6: Estantería metálica K45 5 niveles | C6: Picking | D6: 200 | E6: 120 | F6: 60 | H6: 10 | I6: =COUNTIF('03_DESPIECE'!$A$2:$A$225,B6) -> 4 | J6: =COUNTIF('05_RUTAS'!$A$2:$A$407,B6) -> 10 | K6: =IF(COUNTIF('12_PRECIOS'!$A$2:$A$5,A6)>0,1,0) -> 1 | L6: =IF(COUNTIFS($D$2:$D$51,D6,$E$2:$E$51,E6,$F$2:$F$51,F6)>=5,1,0) -> 0 | M6: ESTIMADO
A7: Racks industriales | B7: Rack Mecano Strong MY-075-1 | C7: Semindustrial | D7: 200 | E7: 120 | F7: 60 | H7: 10 | I7: =COUNTIF('03_DESPIECE'!$A$2:$A$225,B7) -> 4 | J7: =COUNTIF('05_RUTAS'!$A$2:$A$407,B7) -> 8 | K7: =IF(COUNTIF('12_PRECIOS'!$A$2:$A$5,A7)>0,1,0) -> 1 | L7: =IF(COUNTIFS($D$2:$D$51,D7,$E$2:$E$51,E7,$F$2:$F$51,F7)>=5,1,0) -> 0 | M7: ESTIMADO
A8: Góndolas comerciales | B8: Góndola central comercial | C8: Góndola central | D8: 160 | E8: 100 | F8: 90 | H8: 10 | I8: =COUNTIF('03_DESPIECE'!$A$2:$A$225,B8) -> 7 | J8: =COUNTIF('05_RUTAS'!$A$2:$A$407,B8) -> 12 | K8: =IF(COUNTIF('12_PRECIOS'!$A$2:$A$5,A8)>0,1,0) -> 1 | L8: =IF(COUNTIFS($D$2:$D$51,D8,$E$2:$E$51,E8,$F$2:$F$51,F8)>=5,1,0) -> 0 | M8: ESTIMADO
A9: Góndolas comerciales | B9: Góndola mural | C9: Góndola mural | D9: 200 | E9: 100 | F9: 45 | H9: 10 | I9: =COUNTIF('03_DESPIECE'!$A$2:$A$225,B9) -> 6 | J9: =COUNTIF('05_RUTAS'!$A$2:$A$407,B9) -> 13 | K9: =IF(COUNTIF('12_PRECIOS'!$A$2:$A$5,A9)>0,1,0) -> 1 | L9: =IF(COUNTIFS($D$2:$D$51,D9,$E$2:$E$51,E9,$F$2:$F$51,F9)>=5,1,0) -> 0 | M9: ESTIMADO
A10: Góndolas comerciales | B10: Góndola central doble forro liso | C10: Central | D10: 160 | E10: 100 | F10: 90 | H10: 10 | I10: =COUNTIF('03_DESPIECE'!$A$2:$A$225,B10) -> 5 | J10: =COUNTIF('05_RUTAS'!$A$2:$A$407,B10) -> 10 | K10: =IF(COUNTIF('12_PRECIOS'!$A$2:$A$5,A10)>0,1,0) -> 1 | L10: =IF(COUNTIFS($D$2:$D$51,D10,$E$2:$E$51,E10,$F$2:$F$51,F10)>=5,1,0) -> 0 | M10: ESTIMADO
A11: Góndolas comerciales | B11: Góndola mural de forro liso | C11: Pared | D11: 200 | E11: 100 | F11: 45 | H11: 10 | I11: =COUNTIF('03_DESPIECE'!$A$2:$A$225,B11) -> 5 | J11: =COUNTIF('05_RUTAS'!$A$2:$A$407,B11) -> 10 | K11: =IF(COUNTIF('12_PRECIOS'!$A$2:$A$5,A11)>0,1,0) -> 1 | L11: =IF(COUNTIFS($D$2:$D$51,D11,$E$2:$E$51,E11,$F$2:$F$51,F11)>=5,1,0) -> 0 | M11: ESTIMADO
A12: Góndolas comerciales | B12: Góndola de cabecera liso | C12: Cabecera | D12: 150 | E12: 90 | F12: 45 | H12: 10 | I12: =COUNTIF('03_DESPIECE'!$A$2:$A$225,B12) -> 5 | J12: =COUNTIF('05_RUTAS'!$A$2:$A$407,B12) -> 10 | K12: =IF(COUNTIF('12_PRECIOS'!$A$2:$A$5,A12)>0,1,0) -> 1 | L12: =IF(COUNTIFS($D$2:$D$51,D12,$E$2:$E$51,E12,$F$2:$F$51,F12)>=5,1,0) -> 0 | M12: ESTIMADO
A13: Góndolas comerciales | B13: Góndola isla modular | C13: Isla | D13: 160 | E13: 100 | F13: 90 | H13: 10 | I13: =COUNTIF('03_DESPIECE'!$A$2:$A$225,B13) -> 5 | J13: =COUNTIF('05_RUTAS'!$A$2:$A$407,B13) -> 10 | K13: =IF(COUNTIF('12_PRECIOS'!$A$2:$A$5,A13)>0,1,0) -> 1 | L13: =IF(COUNTIFS($D$2:$D$51,D13,$E$2:$E$51,E13,$F$2:$F$51,F13)>=5,1,0) -> 0 | M13: ESTIMADO
A14: Lockers metálicos | B14: Locker de 4 puertas | C14: Locker de 4 compartimentos | D14: 180 | E14: 80 | F14: 45 | G14: 4 | H14: 10 | I14: =COUNTIF('03_DESPIECE'!$A$2:$A$225,B14) -> 7 | J14: =COUNTIF('05_RUTAS'!$A$2:$A$407,B14) -> 11 | K14: =IF(COUNTIF('12_PRECIOS'!$A$2:$A$5,A14)>0,1,0) -> 1 | L14: =IF(COUNTIFS($D$2:$D$51,D14,$E$2:$E$51,E14,$F$2:$F$51,F14)>=5,1,0) -> 0 | M14: ESTIMADO
A15: Lockers metálicos | B15: Locker de 6 puertas | C15: Locker de 6 compartimentos | D15: 180 | E15: 80 | F15: 45 | G15: 6 | H15: 10 | I15: =COUNTIF('03_DESPIECE'!$A$2:$A$225,B15) -> 8 | J15: =COUNTIF('05_RUTAS'!$A$2:$A$407,B15) -> 11 | K15: =IF(COUNTIF('12_PRECIOS'!$A$2:$A$5,A15)>0,1,0) -> 1 | L15: =IF(COUNTIFS($D$2:$D$51,D15,$E$2:$E$51,E15,$F$2:$F$51,F15)>=5,1,0) -> 0 | M15: ESTIMADO
A16: Lockers metálicos | B16: Locker metálico simple MK1-01 | C16: 1 puertas | D16: 180 | E16: 40 | F16: 45 | G16: 1 | H16: 10 | I16: =COUNTIF('03_DESPIECE'!$A$2:$A$225,B16) -> 5 | J16: =COUNTIF('05_RUTAS'!$A$2:$A$407,B16) -> 8 | K16: =IF(COUNTIF('12_PRECIOS'!$A$2:$A$5,A16)>0,1,0) -> 1 | L16: =IF(COUNTIFS($D$2:$D$51,D16,$E$2:$E$51,E16,$F$2:$F$51,F16)>=5,1,0) -> 0 | M16: ESTIMADO
A17: Lockers metálicos | B17: Locker metálico simple MK2-01 | C17: 2 puertas | D17: 180 | E17: 40 | F17: 45 | G17: 2 | H17: 10 | I17: =COUNTIF('03_DESPIECE'!$A$2:$A$225,B17) -> 5 | J17: =COUNTIF('05_RUTAS'!$A$2:$A$407,B17) -> 8 | K17: =IF(COUNTIF('12_PRECIOS'!$A$2:$A$5,A17)>0,1,0) -> 1 | L17: =IF(COUNTIFS($D$2:$D$51,D17,$E$2:$E$51,E17,$F$2:$F$51,F17)>=5,1,0) -> 0 | M17: ESTIMADO
A18: Lockers metálicos | B18: Locker metálico simple MK3-01 | C18: 3 puertas | D18: 180 | E18: 40 | F18: 45 | G18: 3 | H18: 10 | I18: =COUNTIF('03_DESPIECE'!$A$2:$A$225,B18) -> 5 | J18: =COUNTIF('05_RUTAS'!$A$2:$A$407,B18) -> 8 | K18: =IF(COUNTIF('12_PRECIOS'!$A$2:$A$5,A18)>0,1,0) -> 1 | L18: =IF(COUNTIFS($D$2:$D$51,D18,$E$2:$E$51,E18,$F$2:$F$51,F18)>=5,1,0) -> 0 | M18: ESTIMADO
A19: Lockers metálicos | B19: Locker metálico simple MK4-01 | C19: 4 puertas | D19: 180 | E19: 40 | F19: 45 | G19: 4 | H19: 10 | I19: =COUNTIF('03_DESPIECE'!$A$2:$A$225,B19) -> 5 | J19: =COUNTIF('05_RUTAS'!$A$2:$A$407,B19) -> 8 | K19: =IF(COUNTIF('12_PRECIOS'!$A$2:$A$5,A19)>0,1,0) -> 1 | L19: =IF(COUNTIFS($D$2:$D$51,D19,$E$2:$E$51,E19,$F$2:$F$51,F19)>=5,1,0) -> 0 | M19: ESTIMADO
A20: Otros productos metalmecánicos | B20: Armario metálico | C20: Gabinete metálico | D20: 85 | E20: 120 | F20: 60 | H20: 10 | I20: =COUNTIF('03_DESPIECE'!$A$2:$A$225,B20) -> 7 | J20: =COUNTIF('05_RUTAS'!$A$2:$A$407,B20) -> 11 | K20: =IF(COUNTIF('12_PRECIOS'!$A$2:$A$5,A20)>0,1,0) -> 1 | L20: =IF(COUNTIFS($D$2:$D$51,D20,$E$2:$E$51,E20,$F$2:$F$51,F20)>=5,1,0) -> 1 | M20: ESTIMADO
A21: Otros productos metalmecánicos | B21: Estantería liviana metálica | C21: Estantería liviana | D21: 85 | E21: 120 | F21: 60 | H21: 10 | I21: =COUNTIF('03_DESPIECE'!$A$2:$A$225,B21) -> 5 | J21: =COUNTIF('05_RUTAS'!$A$2:$A$407,B21) -> 12 | K21: =IF(COUNTIF('12_PRECIOS'!$A$2:$A$5,A21)>0,1,0) -> 1 | L21: =IF(COUNTIFS($D$2:$D$51,D21,$E$2:$E$51,E21,$F$2:$F$51,F21)>=5,1,0) -> 1 | M21: ESTIMADO
A22: Otros productos metalmecánicos | B22: Silla fija PC0173 | C22: Silla | D22: 85 | E22: 45 | F22: 50 | H22: 10 | I22: =COUNTIF('03_DESPIECE'!$A$2:$A$225,B22) -> 3 | J22: =COUNTIF('05_RUTAS'!$A$2:$A$407,B22) -> 8 | K22: =IF(COUNTIF('12_PRECIOS'!$A$2:$A$5,A22)>0,1,0) -> 1 | L22: =IF(COUNTIFS($D$2:$D$51,D22,$E$2:$E$51,E22,$F$2:$F$51,F22)>=5,1,0) -> 1 | M22: ESTIMADO
A23: Otros productos metalmecánicos | B23: Silla capacitación 105 | C23: Silla | D23: 85 | E23: 45 | F23: 50 | H23: 10 | I23: =COUNTIF('03_DESPIECE'!$A$2:$A$225,B23) -> 3 | J23: =COUNTIF('05_RUTAS'!$A$2:$A$407,B23) -> 2 | K23: =IF(COUNTIF('12_PRECIOS'!$A$2:$A$5,A23)>0,1,0) -> 1 | L23: =IF(COUNTIFS($D$2:$D$51,D23,$E$2:$E$51,E23,$F$2:$F$51,F23)>=5,1,0) -> 1 | M23: ESTIMADO
A24: Otros productos metalmecánicos | B24: Cajonera metálica P1019 | C24: Archivador | D24: 85 | E24: 120 | F24: 60 | H24: 10 | I24: =COUNTIF('03_DESPIECE'!$A$2:$A$225,B24) -> 4 | J24: =COUNTIF('05_RUTAS'!$A$2:$A$407,B24) -> 8 | K24: =IF(COUNTIF('12_PRECIOS'!$A$2:$A$5,A24)>0,1,0) -> 1 | L24: =IF(COUNTIFS($D$2:$D$51,D24,$E$2:$E$51,E24,$F$2:$F$51,F24)>=5,1,0) -> 1 | M24: ESTIMADO
A25: Otros productos metalmecánicos | B25: Archivador metálico 3 cajones | C25: Archivador | D25: 85 | E25: 120 | F25: 60 | H25: 10 | I25: =COUNTIF('03_DESPIECE'!$A$2:$A$225,B25) -> 4 | J25: =COUNTIF('05_RUTAS'!$A$2:$A$407,B25) -> 8 | K25: =IF(COUNTIF('12_PRECIOS'!$A$2:$A$5,A25)>0,1,0) -> 1 | L25: =IF(COUNTIFS($D$2:$D$51,D25,$E$2:$E$51,E25,$F$2:$F$51,F25)>=5,1,0) -> 1 | M25: ESTIMADO
A26: Otros productos metalmecánicos | B26: Archivador metálico 4 cajones | C26: Archivador | D26: 85 | E26: 120 | F26: 60 | H26: 10 | I26: =COUNTIF('03_DESPIECE'!$A$2:$A$225,B26) -> 4 | J26: =COUNTIF('05_RUTAS'!$A$2:$A$407,B26) -> 8 | K26: =IF(COUNTIF('12_PRECIOS'!$A$2:$A$5,A26)>0,1,0) -> 1 | L26: =IF(COUNTIFS($D$2:$D$51,D26,$E$2:$E$51,E26,$F$2:$F$51,F26)>=5,1,0) -> 1 | M26: ESTIMADO
A27: Otros productos metalmecánicos | B27: Armario metálico KD-034 | C27: Gabinete | D27: 85 | E27: 120 | F27: 60 | H27: 10 | I27: =COUNTIF('03_DESPIECE'!$A$2:$A$225,B27) -> 4 | J27: =COUNTIF('05_RUTAS'!$A$2:$A$407,B27) -> 8 | K27: =IF(COUNTIF('12_PRECIOS'!$A$2:$A$5,A27)>0,1,0) -> 1 | L27: =IF(COUNTIFS($D$2:$D$51,D27,$E$2:$E$51,E27,$F$2:$F$51,F27)>=5,1,0) -> 1 | M27: ESTIMADO
A28: Otros productos metalmecánicos | B28: Banqueta con patas metálicas | C28: Banco | D28: 85 | E28: 120 | F28: 60 | H28: 10 | I28: =COUNTIF('03_DESPIECE'!$A$2:$A$225,B28) -> 4 | J28: =COUNTIF('05_RUTAS'!$A$2:$A$407,B28) -> 8 | K28: =IF(COUNTIF('12_PRECIOS'!$A$2:$A$5,A28)>0,1,0) -> 1 | L28: =IF(COUNTIFS($D$2:$D$51,D28,$E$2:$E$51,E28,$F$2:$F$51,F28)>=5,1,0) -> 1 | M28: ESTIMADO
A29: Otros productos metalmecánicos | B29: Armario herramientas MY-TC-03 | C29: Gabinete | D29: 85 | E29: 120 | F29: 60 | H29: 10 | I29: =COUNTIF('03_DESPIECE'!$A$2:$A$225,B29) -> 4 | J29: =COUNTIF('05_RUTAS'!$A$2:$A$407,B29) -> 8 | K29: =IF(COUNTIF('12_PRECIOS'!$A$2:$A$5,A29)>0,1,0) -> 1 | L29: =IF(COUNTIFS($D$2:$D$51,D29,$E$2:$E$51,E29,$F$2:$F$51,F29)>=5,1,0) -> 1 | M29: ESTIMADO
A30: Otros productos metalmecánicos | B30: Armario herramientas MY-TC-04 | C30: Gabinete | D30: 85 | E30: 120 | F30: 60 | H30: 10 | I30: =COUNTIF('03_DESPIECE'!$A$2:$A$225,B30) -> 4 | J30: =COUNTIF('05_RUTAS'!$A$2:$A$407,B30) -> 8 | K30: =IF(COUNTIF('12_PRECIOS'!$A$2:$A$5,A30)>0,1,0) -> 1 | L30: =IF(COUNTIFS($D$2:$D$51,D30,$E$2:$E$51,E30,$F$2:$F$51,F30)>=5,1,0) -> 1 | M30: ESTIMADO
A31: Otros productos metalmecánicos | B31: Armario herramientas MY-TC-05 | C31: Gabinete | D31: 85 | E31: 120 | F31: 60 | H31: 10 | I31: =COUNTIF('03_DESPIECE'!$A$2:$A$225,B31) -> 4 | J31: =COUNTIF('05_RUTAS'!$A$2:$A$407,B31) -> 8 | K31: =IF(COUNTIF('12_PRECIOS'!$A$2:$A$5,A31)>0,1,0) -> 1 | L31: =IF(COUNTIFS($D$2:$D$51,D31,$E$2:$E$51,E31,$F$2:$F$51,F31)>=5,1,0) -> 1 | M31: ESTIMADO
... A51: Otros productos metalmecánicos | B51: Silla terraza New Bistro | C51: Silla | D51: 85 | E51: 45 | F51: 50 | H51: 10 | I51: =COUNTIF('03_DESPIECE'!$A$2:$A$225,B51) -> 3 | J51: =COUNTIF('05_RUTAS'!$A$2:$A$407,B51) -> 8 | K51: =IF(COUNTIF('12_PRECIOS'!$A$2:$A$5,A51)>0,1,0) -> 1 | L51: =IF(COUNTIFS($D$2:$D$51,D51,$E$2:$E$51,E51,$F$2:$F$51,F51)>=5,1,0) -> 1 | M51: ESTIMADO

Sheet 02_MATERIALES
A1: Material o accesorio (nombre completo) | B1: Clave técnica auxiliar | C1: Grupo | D1: Unidad de costo | E1: Espesor mm | F1: Ancho m | G1: Largo m | H1: Costo unitario S/ | I1: Material genérico (1/0) | J1: Naturaleza
A2: Plancha de acero laminado en caliente de 2 mm, 1.20 × 2.40 m | B2: MAT-LAC2 | C2: CHAPA | D2: kg | E2: 2 | F2: 1.2 | G2: 2.4 | H2: 6.8 | I2: 0 | J2: ESTIMADO
A3: Lámina LAF o acero 1.0 mm (alternativa V4) | B3: MAT-CH-1.0 | C3: CHAPA | D3: kg | E3: 1 | H3: 6.8 | I3: 0 | J3: ESTIMADO
A4: Lámina LAF o acero 1.5 mm (alternativa V4) | B4: MAT-CH-1.5 | C4: CHAPA | D4: kg | E4: 1.5 | H4: 6.8 | I4: 0 | J4: ESTIMADO
A5: Lámina LAF 0.6 mm (catálogo lockers) | B5: MAT-LAF06 | C5: CHAPA | D5: kg | E5: 0.6 | H5: 6.8 | I5: 0 | J5: ESTIMADO
A6: Lámina LAF 0.8 mm (catálogo góndolas) | B6: MAT-LAF08 | C6: CHAPA | D6: kg | E6: 0.8 | H6: 6.8 | I6: 0 | J6: ESTIMADO
A7: Lámina LAF 1.2 mm (taller) | B7: MAT-LAF12 | C7: CHAPA | D7: kg | E7: 1.2 | H7: 6.8 | I7: 0 | J7: ESTIMADO
A8: Tubo o perfil de acero (sección por definir) | B8: MAT-PR-1 | C8: PERFIL | D8: m | H8: 6.1 | I8: 1 | J8: ESTIMADO
A9: Elementos de fijación metálica (tipo por desagregar) | B9: MAT-FIJ | C9: HERRAJE | D9: und | H9: 0.9 | I9: 1 | J9: ESTIMADO
A10: Tablero melamina/MDP 18 mm comprado | B10: MAT-MEL18 | C10: OTRO | D10: und | E10: 18 | I10: 0 | J10: PENDIENTE
A11: Asiento, ruedas, vidrio, PVC o mecanismos comprados | B11: MAT-OTR | C11: OTRO | D11: und | I11: 1 | J11: PENDIENTE
A12: Pintura electrostática en polvo poliéster | B12: COM-001 | C12: PINTURA | D12: kg | I12: 0 | J12: PENDIENTE
A13: Pintura en polvo epoxi-poliéster | B13: COM-002 | C13: PINTURA | D13: kg | I13: 0 | J13: PENDIENTE
A14: Desengrasante industrial | B14: COM-003 | C14: PREPARACION_SUPERFICIAL | D14: l | I14: 0 | J14: PENDIENTE
A15: Disco abrasivo de corte | B15: COM-004 | C15: CONSUMIBLE | D15: und | I15: 0 | J15: PENDIENTE
A16: Disco abrasivo para desbarbado | B16: COM-005 | C16: CONSUMIBLE | D16: und | I16: 0 | J16: PENDIENTE
A17: Alambre para soldadura MIG/MAG | B17: COM-006 | C17: SOLDADURA | D17: kg | I17: 0 | J17: PENDIENTE
A18: Electrodo revestido para soldadura | B18: COM-007 | C18: SOLDADURA | D18: kg | I18: 0 | J18: PENDIENTE
A19: Gas protector para soldadura MIG/MAG | B19: COM-008 | C19: SOLDADURA | D19: m3 | I19: 0 | J19: PENDIENTE
A20: Tubo cuadrado de acero 30 × 30 mm | B20: COM-009 | C20: PERFIL | D20: m | I20: 0 | J20: PENDIENTE
A21: Tubo cuadrado de acero 40 × 40 mm | B21: COM-010 | C21: PERFIL | D21: m | I21: 0 | J21: PENDIENTE
A22: Ángulo de acero estructural | B22: COM-011 | C22: PERFIL | D22: m | I22: 0 | J22: PENDIENTE
... A42: Guante anticorte reutilizable | B42: COM-031 | C42: SEGURIDAD | D42: par | I42: 0 | J42: PENDIENTE

Sheet 03_DESPIECE
A1: Producto | B1: Componente | C1: Material | D1: Piezas por unidad | E1: Ancho pieza mm | F1: Alto pieza mm | G1: Longitud pieza m | H1: Área de chapa m² | I1: Masa kg / producto | J1: Costo S/ / producto | K1: Planchas 1.20×2.40 equivalentes / producto | L1: Costo disponible (1/0) | M1: Tipo de cálculo | N1: Naturaleza
A2: Minirack metálico con bandejas | B2: Parante vertical | C2: Tubo o perfil de acero (sección por definir) | D2: 4 | G2: 1.8 | I2: 10.8 | J2: 68.625 | L2: 1 | M2: PERFIL_LONGITUD | N2: ESTIMADO
A3: Minirack metálico con bandejas | B3: Larguero horizontal | C3: Tubo o perfil de acero (sección por definir) | D3: 8 | G3: 1.2 | I3: 14.4 | J3: 91.5 | L3: 1 | M3: PERFIL_LONGITUD | N3: ESTIMADO
A4: Minirack metálico con bandejas | B4: Refuerzo transversal | C4: Tubo o perfil de acero (sección por definir) | D4: 4 | G4: 0.6 | I4: 3.6 | J4: 22.875 | L4: 1 | M4: PERFIL_LONGITUD | N4: ESTIMADO
A5: Minirack metálico con bandejas | B5: Bandeja acero | C5: Plancha de acero laminado en caliente de 2 mm, 1.20 × 2.40 m | D5: 4 | H5: 0.72 | I5: 45.216 | J5: 334.20522 | K5: 1 | L5: 1 | M5: CHAPA_AREA | N5: ESTIMADO
A6: Minirack metálico con bandejas | B6: Cartela unión | C6: Plancha de acero laminado en caliente de 2 mm, 1.20 × 2.40 m | D6: 8 | H6: 0.025 | I6: 3.14 | J6: 23.208696 | K6: 0.069444444 | L6: 1 | M6: CHAPA_AREA | N6: ESTIMADO
A7: Minirack metálico con bandejas | B7: Tornillería sujeción | C7: Elementos de fijación metálica (tipo por desagregar) | D7: 24 | J7: 21.6 | L7: 1 | M7: UNIDAD | N7: ESTIMADO
A8: Minirack metálico con bandejas | B8: Tapa protectora | C8: Elementos de fijación metálica (tipo por desagregar) | D8: 4 | J8: 3.6 | L8: 1 | M8: UNIDAD | N8: ESTIMADO
A9: Estante reforzado modular | B9: Parante perfil | C9: Tubo o perfil de acero (sección por definir) | D9: 4 | G9: 2 | I9: 12 | J9: 76.25 | L9: 1 | M9: PERFIL_LONGITUD | N9: ESTIMADO
A10: Estante reforzado modular | B10: Travesaño frontal | C10: Tubo o perfil de acero (sección por definir) | D10: 8 | G10: 1 | I10: 12 | J10: 76.25 | L10: 1 | M10: PERFIL_LONGITUD | N10: ESTIMADO
A11: Estante reforzado modular | B11: Travesaño lateral | C11: Tubo o perfil de acero (sección por definir) | D11: 8 | G11: 0.5 | I11: 6 | J11: 38.125 | L11: 1 | M11: PERFIL_LONGITUD | N11: ESTIMADO
A12: Estante reforzado modular | B12: Bandeja reforzada | C12: Plancha de acero laminado en caliente de 2 mm, 1.20 × 2.40 m | D12: 5 | H12: 0.5 | I12: 39.25 | J12: 290.1087 | K12: 0.86805556 | L12: 1 | M12: CHAPA_AREA | N12: ESTIMADO
A13: Estante reforzado modular | B13: Cartela | C13: Plancha de acero laminado en caliente de 2 mm, 1.20 × 2.40 m | D13: 8 | H13: 0.035 | I13: 4.396 | J13: 32.492174 | K13: 0.097222222 | L13: 1 | M13: CHAPA_AREA | N13: ESTIMADO
A14: Estante reforzado modular | B14: Juego pernos | C14: Elementos de fijación metálica (tipo por desagregar) | D14: 28 | J14: 25.2 | L14: 1 | M14: UNIDAD | N14: ESTIMADO
A15: Góndola central comercial | B15: Columna doble | C15: Tubo o perfil de acero (sección por definir) | D15: 2 | G15: 1.65 | I15: 4.95 | J15: 31.453125 | L15: 1 | M15: PERFIL_LONGITUD | N15: ESTIMADO
A16: Góndola central comercial | B16: Base apoyo | C16: Lámina LAF o acero 1.0 mm (alternativa V4) | D16: 2 | H16: 0.3 | I16: 4.71 | J16: 34.813043 | K16: 0.20833333 | L16: 1 | M16: CHAPA_AREA | N16: ESTIMADO
A17: Góndola central comercial | B17: Panel trasero | C17: Lámina LAF o acero 1.0 mm (alternativa V4) | D17: 4 | H17: 0.56 | I17: 17.584 | J17: 129.9687 | K17: 0.77777778 | L17: 1 | M17: CHAPA_AREA | N17: ESTIMADO
A18: Góndola central comercial | B18: Estante de exposición | C18: Lámina LAF o acero 1.0 mm (alternativa V4) | D18: 8 | H18: 0.4 | I18: 25.12 | J18: 185.66957 | K18: 1.1111111 | L18: 1 | M18: CHAPA_AREA | N18: ESTIMADO
A19: Góndola central comercial | B19: Ménsula | C19: Lámina LAF o acero 1.0 mm (alternativa V4) | D19: 16 | H19: 0.04 | I19: 5.024 | J19: 37.133913 | K19: 0.22222222 | L19: 1 | M19: CHAPA_AREA | N19: ESTIMADO
A20: Góndola central comercial | B20: Zócalo frontal | C20: Lámina LAF o acero 1.0 mm (alternativa V4) | D20: 2 | H20: 0.12 | I20: 1.884 | J20: 13.925217 | K20: 0.083333333 | L20: 1 | M20: CHAPA_AREA | N20: ESTIMADO
A21: Góndola central comercial | B21: Pernos de ensamble | C21: Elementos de fijación metálica (tipo por desagregar) | D21: 36 | J21: 32.4 | L21: 1 | M21: UNIDAD | N21: ESTIMADO
A22: Góndola mural | B22: Montante mural | C22: Tubo o perfil de acero (sección por definir) | D22: 2 | G22: 1.9 | I22: 5.7 | J22: 36.21875 | L22: 1 | M22: PERFIL_LONGITUD | N22: ESTIMADO
A23: Góndola mural | B23: Panel de fondo | C23: Lámina LAF o acero 1.0 mm (alternativa V4) | D23: 3 | H23: 0.55 | I23: 12.9525 | J23: 95.73587 | K23: 0.57291667 | L23: 1 | M23: CHAPA_AREA | N23: ESTIMADO
A24: Góndola mural | B24: Bandeja | C24: Lámina LAF o acero 1.0 mm (alternativa V4) | D24: 5 | H24: 0.42 | I24: 16.485 | J24: 121.84565 | K24: 0.72916667 | L24: 1 | M24: CHAPA_AREA | N24: ESTIMADO
A25: Góndola mural | B25: Soporte bandeja | C25: Lámina LAF o acero 1.0 mm (alternativa V4) | D25: 10 | H25: 0.04 | I25: 3.14 | J25: 23.208696 | K25: 0.13888889 | L25: 1 | M25: CHAPA_AREA | N25: ESTIMADO
A26: Góndola mural | B26: Pie soporte | C26: Lámina LAF o acero 1.0 mm (alternativa V4) | D26: 2 | H26: 0.25 | I26: 3.925 | J26: 29.01087 | K26: 0.17361111 | L26: 1 | M26: CHAPA_AREA | N26: ESTIMADO
A27: Góndola mural | B27: Fijaciones | C27: Elementos de fijación metálica (tipo por desagregar) | D27: 26 | J27: 23.4 | L27: 1 | M27: UNIDAD | N27: ESTIMADO
A28: Locker de 4 puertas | B28: Panel lateral | C28: Lámina LAF o acero 1.5 mm (alternativa V4) | D28: 2 | H28: 0.95 | I28: 22.3725 | J28: 165.36196 | K28: 0.65972222 | L28: 1 | M28: CHAPA_AREA | N28: ESTIMADO
A29: Locker de 4 puertas | B29: Techo/base | C29: Lámina LAF o acero 1.5 mm (alternativa V4) | D29: 2 | H29: 0.35 | I29: 8.2425 | J29: 60.922826 | K29: 0.24305556 | L29: 1 | M29: CHAPA_AREA | N29: ESTIMADO
A30: Locker de 4 puertas | B30: Panel posterior | C30: Lámina LAF o acero 1.5 mm (alternativa V4) | D30: 1 | H30: 1.7 | I30: 20.0175 | J30: 147.95543 | K30: 0.59027778 | L30: 1 | M30: CHAPA_AREA | N30: ESTIMADO
A31: Locker de 4 puertas | B31: Puerta individual | C31: Lámina LAF o acero 1.5 mm (alternativa V4) | D31: 4 | H31: 0.37 | I31: 17.427 | J31: 128.80826 | K31: 0.51388889 | L31: 1 | M31: CHAPA_AREA | N31: ESTIMADO
A32: Locker de 4 puertas | B32: Separador interior | C32: Lámina LAF o acero 1.5 mm (alternativa V4) | D32: 3 | H32: 0.35 | I32: 12.36375 | J32: 91.384239 | K32: 0.36458333 | L32: 1 | M32: CHAPA_AREA | N32: ESTIMADO
A33: Locker de 4 puertas | B33: Bisagra | C33: Elementos de fijación metálica (tipo por desagregar) | D33: 8 | J33: 7.2 | L33: 1 | M33: UNIDAD | N33: ESTIMADO
A34: Locker de 4 puertas | B34: Cerradura | C34: Elementos de fijación metálica (tipo por desagregar) | D34: 4 | J34: 3.6 | L34: 1 | M34: UNIDAD | N34: ESTIMADO
A35: Locker de 6 puertas | B35: Costado externo | C35: Lámina LAF o acero 1.5 mm (alternativa V4) | D35: 2 | H35: 1.1 | I35: 25.905 | J35: 191.47174 | K35: 0.76388889 | L35: 1 | M35: CHAPA_AREA | N35: ESTIMADO
A36: Locker de 6 puertas | B36: Panel techo/base | C36: Lámina LAF o acero 1.5 mm (alternativa V4) | D36: 2 | H36: 0.48 | I36: 11.304 | J36: 83.551304 | K36: 0.33333333 | L36: 1 | M36: CHAPA_AREA | N36: ESTIMADO
A37: Locker de 6 puertas | B37: Fondo | C37: Lámina LAF o acero 1.5 mm (alternativa V4) | D37: 1 | H37: 1.8 | I37: 21.195 | J37: 156.6587 | K37: 0.625 | L37: 1 | M37: CHAPA_AREA | N37: ESTIMADO
A38: Locker de 6 puertas | B38: Puerta con rejilla | C38: Lámina LAF o acero 1.5 mm (alternativa V4) | D38: 6 | H38: 0.3 | I38: 21.195 | J38: 156.6587 | K38: 0.625 | L38: 1 | M38: CHAPA_AREA | N38: ESTIMADO
A39: Locker de 6 puertas | B39: Separador vertical | C39: Lámina LAF o acero 1.5 mm (alternativa V4) | D39: 2 | H39: 0.7 | I39: 16.485 | J39: 121.84565 | K39: 0.48611111 | L39: 1 | M39: CHAPA_AREA | N39: ESTIMADO
A40: Locker de 6 puertas | B40: Entrepiso | C40: Lámina LAF o acero 1.5 mm (alternativa V4) | D40: 4 | H40: 0.4 | I40: 18.84 | J40: 139.25217 | K40: 0.55555556 | L40: 1 | M40: CHAPA_AREA | N40: ESTIMADO
A41: Locker de 6 puertas | B41: Bisagra | C41: Elementos de fijación metálica (tipo por desagregar) | D41: 12 | J41: 10.8 | L41: 1 | M41: UNIDAD | N41: ESTIMADO
A42: Locker de 6 puertas | B42: Cerradura | C42: Elementos de fijación metálica (tipo por desagregar) | D42: 6 | J42: 5.4 | L42: 1 | M42: UNIDAD | N42: ESTIMADO
A43: Armario metálico | B43: Lateral gabinete | C43: Lámina LAF o acero 1.0 mm (alternativa V4) | D43: 2 | H43: 0.95 | I43: 14.915 | J43: 110.2413 | K43: 0.65972222 | L43: 1 | M43: CHAPA_AREA | N43: ESTIMADO
A44: Armario metálico | B44: Panel posterior | C44: Lámina LAF o acero 1.0 mm (alternativa V4) | D44: 1 | H44: 1.3 | I44: 10.205 | J44: 75.428261 | K44: 0.45138889 | L44: 1 | M44: CHAPA_AREA | N44: ESTIMADO
A45: Armario metálico | B45: Panel techo/base | C45: Lámina LAF o acero 1.0 mm (alternativa V4) | D45: 2 | H45: 0.5 | I45: 7.85 | J45: 58.021739 | K45: 0.34722222 | L45: 1 | M45: CHAPA_AREA | N45: ESTIMADO
A46: Armario metálico | B46: Puerta | C46: Lámina LAF o acero 1.0 mm (alternativa V4) | D46: 2 | H46: 0.7 | I46: 10.99 | J46: 81.230435 | K46: 0.48611111 | L46: 1 | M46: CHAPA_AREA | N46: ESTIMADO
A47: Armario metálico | B47: Bandeja | C47: Lámina LAF o acero 1.0 mm (alternativa V4) | D47: 3 | H47: 0.48 | I47: 11.304 | J47: 83.551304 | K47: 0.5 | L47: 1 | M47: CHAPA_AREA | N47: ESTIMADO
A48: Armario metálico | B48: Bisagra | C48: Elementos de fijación metálica (tipo por desagregar) | D48: 4 | J48: 3.6 | L48: 1 | M48: UNIDAD | N48: ESTIMADO
A49: Armario metálico | B49: Cerradura | C49: Elementos de fijación metálica (tipo por desagregar) | D49: 2 | J49: 1.8 | L49: 1 | M49: UNIDAD | N49: ESTIMADO
A50: Estantería liviana metálica | B50: Parante | C50: Tubo o perfil de acero (sección por definir) | D50: 4 | G50: 1.65 | I50: 9.9 | J50: 62.90625 | L50: 1 | M50: PERFIL_LONGITUD | N50: ESTIMADO
A51: Estantería liviana metálica | B51: Travesaño | C51: Tubo o perfil de acero (sección por definir) | D51: 8 | G51: 0.9 | I51: 10.8 | J51: 68.625 | L51: 1 | M51: PERFIL_LONGITUD | N51: ESTIMADO
A52: Estantería liviana metálica | B52: Bandeja | C52: Lámina LAF o acero 1.0 mm (alternativa V4) | D52: 5 | H52: 0.4 | I52: 15.7 | J52: 116.04348 | K52: 0.69444444 | L52: 1 | M52: CHAPA_AREA | N52: ESTIMADO
A53: Estantería liviana metálica | B53: Escuadra | C53: Lámina LAF o acero 1.0 mm (alternativa V4) | D53: 8 | H53: 0.035 | I53: 2.198 | J53: 16.246087 | K53: 0.097222222 | L53: 1 | M53: CHAPA_AREA | N53: ESTIMADO
A54: Estantería liviana metálica | B54: Tornillería | C54: Elementos de fijación metálica (tipo por desagregar) | D54: 32 | J54: 28.8 | L54: 1 | M54: UNIDAD | N54: ESTIMADO
A55: Rack selectivo para pallets | B55: Montante estructural | C55: Tubo o perfil de acero (sección por definir) | D55: 4 | G55: 4.5 | I55: 27 | J55: 171.5625 | L55: 1 | M55: PERFIL_LONGITUD | N55: ESTIMADO
A56: Rack selectivo para pallets | B56: Viga longitudinal | C56: Tubo o perfil de acero (sección por definir) | D56: 8 | G56: 2.7 | I56: 32.4 | J56: 205.875 | L56: 1 | M56: PERFIL_LONGITUD | N56: ESTIMADO
A57: Rack selectivo para pallets | B57: Travesaño lateral | C57: Tubo o perfil de acero (sección por definir) | D57: 8 | G57: 1 | I57: 12 | J57: 76.25 | L57: 1 | M57: PERFIL_LONGITUD | N57: ESTIMADO
A58: Rack selectivo para pallets | B58: Anclajes/seguros | C58: Elementos de fijación metálica (tipo por desagregar) | D58: 16 | J58: 14.4 | L58: 1 | M58: UNIDAD | N58: ESTIMADO
A59: Rack cantilever 3 niveles | B59: Montante estructural | C59: Tubo o perfil de acero (sección por definir) | D59: 4 | G59: 3 | I59: 18 | J59: 114.375 | L59: 1 | M59: PERFIL_LONGITUD | N59: ESTIMADO
A60: Rack cantilever 3 niveles | B60: Viga longitudinal | C60: Tubo o perfil de acero (sección por definir) | D60: 8 | G60: 2 | I60: 24 | J60: 152.5 | L60: 1 | M60: PERFIL_LONGITUD | N60: ESTIMADO
A61: Rack cantilever 3 niveles | B61: Travesaño lateral | C61: Tubo o perfil de acero (sección por definir) | D61: 8 | G61: 1.5 | I61: 18 | J61: 114.375 | L61: 1 | M61: PERFIL_LONGITUD | N61: ESTIMADO
A62: Rack cantilever 3 niveles | B62: Anclajes/seguros | C62: Elementos de fijación metálica (tipo por desagregar) | D62: 16 | J62: 14.4 | L62: 1 | M62: UNIDAD | N62: ESTIMADO
A63: Estantería metálica K45 5 niveles | B63: Montante estructural | C63: Tubo o perfil de acero (sección por definir) | D63: 4 | G63: 1.8 | I63: 10.8 | J63: 68.625 | L63: 1 | M63: PERFIL_LONGITUD | N63: ESTIMADO
A64: Estantería metálica K45 5 niveles | B64: Viga longitudinal | C64: Tubo o perfil de acero (sección por definir) | D64: 8 | G64: 0.9 | I64: 10.8 | J64: 68.625 | L64: 1 | M64: PERFIL_LONGITUD | N64: ESTIMADO
A65: Estantería metálica K45 5 niveles | B65: Travesaño lateral | C65: Tubo o perfil de acero (sección por definir) | D65: 8 | G65: 0.45 | I65: 5.4 | J65: 34.3125 | L65: 1 | M65: PERFIL_LONGITUD | N65: ESTIMADO
A66: Estantería metálica K45 5 niveles | B66: Panel/bandeja desmontable segmento | C66: Lámina LAF 0.8 mm (catálogo góndolas) | D66: 4 | E66: 828 | F66: 423 | H66: 0.350244 | I66: 8.7981293 | J66: 65.029651 | K66: 0.48645 | L66: 1 | M66: CHAPA_AREA | N66: ESTIMADO
A67: Rack Mecano Strong MY-075-1 | B67: Montante estructural | C67: Tubo o perfil de acero (sección por definir) | D67: 4 | G67: 2 | I67: 12 | J67: 76.25 | L67: 1 | M67: PERFIL_LONGITUD | N67: ESTIMADO
A68: Rack Mecano Strong MY-075-1 | B68: Viga longitudinal | C68: Tubo o perfil de acero (sección por definir) | D68: 8 | G68: 2 | I68: 24 | J68: 152.5 | L68: 1 | M68: PERFIL_LONGITUD | N68: ESTIMADO
A69: Rack Mecano Strong MY-075-1 | B69: Travesaño lateral | C69: Tubo o perfil de acero (sección por definir) | D69: 8 | G69: 0.6 | I69: 7.2 | J69: 45.75 | L69: 1 | M69: PERFIL_LONGITUD | N69: ESTIMADO
A70: Rack Mecano Strong MY-075-1 | B70: Anclajes/seguros | C70: Elementos de fijación metálica (tipo por desagregar) | D70: 16 | J70: 14.4 | L70: 1 | M70: UNIDAD | N70: ESTIMADO
A71: Góndola central doble forro liso | B71: Bastidor vertical tubular | C71: Tubo o perfil de acero (sección por definir) | D71: 2 | G71: 1.5 | I71: 4.5 | J71: 28.59375 | L71: 1 | M71: PERFIL_LONGITUD | N71: ESTIMADO
A72: Góndola central doble forro liso | B72: Panel trasero chapa | C72: Lámina LAF 0.8 mm (catálogo góndolas) | D72: 1 | E72: 1092.5 | F72: 1350 | H72: 1.474875 | I72: 9.262215 | J72: 68.45985 | K72: 0.51210937 | L72: 1 | M72: CHAPA_AREA | N72: ESTIMADO
A73: Góndola central doble forro liso | B73: Bandeja de exhibición | C73: Lámina LAF 0.8 mm (catálogo góndolas) | D73: 5 | E73: 1058 | F73: 405 | H73: 0.42849 | I73: 13.454586 | J73: 99.44694 | K73: 0.74390625 | L73: 1 | M73: CHAPA_AREA | N73: ESTIMADO
A74: Góndola central doble forro liso | B74: Base y refuerzo perfil | C74: Tubo o perfil de acero (sección por definir) | D74: 2 | G74: 0.9 | I74: 2.7 | J74: 17.15625 | L74: 1 | M74: PERFIL_LONGITUD | N74: ESTIMADO
A75: Góndola central doble forro liso | B75: Ménsula y herrajes | C75: Elementos de fijación metálica (tipo por desagregar) | D75: 10 | J75: 9 | L75: 1 | M75: UNIDAD | N75: ESTIMADO
A76: Góndola mural de forro liso | B76: Bastidor vertical tubular | C76: Tubo o perfil de acero (sección por definir) | D76: 2 | G76: 1.85 | I76: 5.55 | J76: 35.265625 | L76: 1 | M76: PERFIL_LONGITUD | N76: ESTIMADO
A77: Góndola mural de forro liso | B77: Panel trasero chapa | C77: Lámina LAF 0.8 mm (catálogo góndolas) | D77: 1 | E77: 1092.5 | F77: 1665 | H77: 1.8190125 | I77: 11.423398 | J77: 84.433815 | K77: 0.63160156 | L77: 1 | M77: CHAPA_AREA | N77: ESTIMADO
A78: Góndola mural de forro liso | B78: Bandeja de exhibición | C78: Lámina LAF 0.8 mm (catálogo góndolas) | D78: 5 | E78: 1058 | F78: 180 | H78: 0.19044 | I78: 5.979816 | J78: 44.19864 | K78: 0.330625 | L78: 1 | M78: CHAPA_AREA | N78: ESTIMADO
A79: Góndola mural de forro liso | B79: Base y refuerzo perfil | C79: Tubo o perfil de acero (sección por definir) | D79: 2 | G79: 0.4 | I79: 1.2 | J79: 7.625 | L79: 1 | M79: PERFIL_LONGITUD | N79: ESTIMADO
A80: Góndola mural de forro liso | B80: Ménsula y herrajes | C80: Elementos de fijación metálica (tipo por desagregar) | D80: 10 | J80: 9 | L80: 1 | M80: UNIDAD | N80: ESTIMADO
A81: Góndola de cabecera liso | B81: Bastidor vertical tubular | C81: Tubo o perfil de acero (sección por definir) | D81: 2 | G81: 1.5 | I81: 4.5 | J81: 28.59375 | L81: 1 | M81: PERFIL_LONGITUD | N81: ESTIMADO
A82: Góndola de cabecera liso | B82: Panel trasero chapa | C82: Lámina LAF 0.8 mm (catálogo góndolas) | D82: 1 | E82: 855 | F82: 1350 | H82: 1.15425 | I82: 7.24869 | J82: 53.577274 | K82: 0.40078125 | L82: 1 | M82: CHAPA_AREA | N82: ESTIMADO
A83: Góndola de cabecera liso | B83: Bandeja de exhibición | C83: Lámina LAF 0.8 mm (catálogo góndolas) | D83: 5 | E83: 828 | F83: 180 | H83: 0.14904 | I83: 4.679856 | J83: 34.59024 | K83: 0.25875 | L83: 1 | M83: CHAPA_AREA | N83: ESTIMADO
A84: Góndola de cabecera liso | B84: Base y refuerzo perfil | C84: Tubo o perfil de acero (sección por definir) | D84: 2 | G84: 0.4 | I84: 1.2 | J84: 7.625 | L84: 1 | M84: PERFIL_LONGITUD | N84: ESTIMADO
A85: Góndola de cabecera liso | B85: Ménsula y herrajes | C85: Elementos de fijación metálica (tipo por desagregar) | D85: 10 | J85: 9 | L85: 1 | M85: UNIDAD | N85: ESTIMADO
A86: Góndola isla modular | B86: Bastidor vertical tubular | C86: Tubo o perfil de acero (sección por definir) | D86: 2 | G86: 1.5 | I86: 4.5 | J86: 28.59375 | L86: 1 | M86: PERFIL_LONGITUD | N86: ESTIMADO
A87: Góndola isla modular | B87: Panel trasero chapa | C87: Lámina LAF 0.8 mm (catálogo góndolas) | D87: 1 | E87: 665 | F87: 1350 | H87: 0.89775 | I87: 5.63787 | J87: 41.671213 | K87: 0.31171875 | L87: 1 | M87: CHAPA_AREA | N87: ESTIMADO
A88: Góndola isla modular | B88: Bandeja de exhibición | C88: Lámina LAF 0.8 mm (catálogo góndolas) | D88: 5 | E88: 644 | F88: 315 | H88: 0.20286 | I88: 6.369804 | J88: 47.08116 | K88: 0.3521875 | L88: 1 | M88: CHAPA_AREA | N88: ESTIMADO
A89: Góndola isla modular | B89: Base y refuerzo perfil | C89: Tubo o perfil de acero (sección por definir) | D89: 2 | G89: 0.7 | I89: 2.1 | J89: 13.34375 | L89: 1 | M89: PERFIL_LONGITUD | N89: ESTIMADO
A90: Góndola isla modular | B90: Ménsula y herrajes | C90: Elementos de fijación metálica (tipo por desagregar) | D90: 10 | J90: 9 | L90: 1 | M90: UNIDAD | N90: ESTIMADO
A91: Locker metálico simple MK1-01 | B91: Costados chapa | C91: Lámina LAF 0.6 mm (catálogo lockers) | D91: 2 | E91: 376 | F91: 1656 | H91: 0.622656 | I91: 5.8654195 | J91: 43.353101 | K91: 0.4324 | L91: 1 | M91: CHAPA_AREA | N91: ESTIMADO
A92: Locker metálico simple MK1-01 | B92: Panel posterior segmentado | C92: Lámina LAF 0.6 mm (catálogo lockers) | D92: 1 | E92: 339.5 | F92: 1620 | H92: 0.54999 | I92: 2.5904529 | J92: 19.146826 | K92: 0.19096875 | L92: 1 | M92: CHAPA_AREA | N92: ESTIMADO
A93: Locker metálico simple MK1-01 | B93: Puerta con ventilación | C93: Lámina LAF 0.6 mm (catálogo lockers) | D93: 1 | E93: 324.8 | F93: 1548 | H93: 0.5027904 | I93: 2.3681428 | J93: 17.503664 | K93: 0.17458 | L93: 1 | M93: CHAPA_AREA | N93: ESTIMADO
A94: Locker metálico simple MK1-01 | B94: Tapa superior/inferior | C94: Lámina LAF 0.6 mm (catálogo lockers) | D94: 2 | E94: 328.5 | F94: 376 | H94: 0.123516 | I94: 1.1635207 | J94: 8.5999358 | K94: 0.085775 | L94: 1 | M94: CHAPA_AREA | N94: ESTIMADO
A95: Locker metálico simple MK1-01 | B95: Bisagras/cerraduras | C95: Elementos de fijación metálica (tipo por desagregar) | D95: 3 | J95: 2.7 | L95: 1 | M95: UNIDAD | N95: ESTIMADO
A96: Locker metálico simple MK2-01 | B96: Costados chapa | C96: Lámina LAF 0.6 mm (catálogo lockers) | D96: 2 | E96: 376 | F96: 1656 | H96: 0.622656 | I96: 5.8654195 | J96: 43.353101 | K96: 0.4324 | L96: 1 | M96: CHAPA_AREA | N96: ESTIMADO
A97: Locker metálico simple MK2-01 | B97: Panel posterior segmentado | C97: Lámina LAF 0.6 mm (catálogo lockers) | D97: 1 | E97: 651 | F97: 1620 | H97: 1.05462 | I97: 4.9672602 | J97: 36.714532 | K97: 0.3661875 | L97: 1 | M97: CHAPA_AREA | N97: ESTIMADO
A98: Locker metálico simple MK2-01 | B98: Puerta con ventilación | C98: Lámina LAF 0.6 mm (catálogo lockers) | D98: 2 | E98: 311.5 | F98: 1548 | H98: 0.482202 | I98: 4.5423428 | J98: 33.573838 | K98: 0.3348625 | L98: 1 | M98: CHAPA_AREA | N98: ESTIMADO
A99: Locker metálico simple MK2-01 | B99: Tapa superior/inferior | C99: Lámina LAF 0.6 mm (catálogo lockers) | D99: 2 | E99: 630 | F99: 376 | H99: 0.23688 | I99: 2.2314096 | J99: 16.493027 | K99: 0.1645 | L99: 1 | M99: CHAPA_AREA | N99: ESTIMADO
A100: Locker metálico simple MK2-01 | B100: Bisagras/cerraduras | C100: Elementos de fijación metálica (tipo por desagregar) | D100: 6 | J100: 5.4 | L100: 1 | M100: UNIDAD | N100: ESTIMADO
...

Sheet 04_MAQUINAS
A1: Equipo o recurso completo | B1: Clave interna | C1: Tipo técnico | D1: Tipo de recurso | E1: Cantidad de escenario | F1: Costo de uso S//h | G1: Potencia nominal kW (referencia) | H1: Factor de carga medio | I1: Grupo de operarios | J1: Máquina crítica (1/0) | K1: Operarios habilitados (simulado) | L1: Horas requeridas 2025 (calculado) | M1: Utilización anual 2025 | N1: Usado en rutas (1/0) | O1: Naturaleza
A2: Guillotina hidráulica para corte de planchas de acero | B2: CCH-01 | C2: Guillotina hidráulica de chapa, hasta 4 mm | D2: MAQUINA | E2: 1 | F2: 24 | G2: 5.5 | H2: 0.5 | I2: Corte | J2: 0 | K2: =SUMPRODUCT(('06B_HABILIDADES'!$B$1:$Q$1=A2)*('06B_HABILIDADES'!$B$2:$Q$26)) -> 6 | L2: =SUMIF('09_CARGA_ORDEN'!$E$2:$E$1153,A2,'09_CARGA_ORDEN'!$J$2:$J$1153) -> 658.53608 | M2: =IF(N(E2)=0,"",L2/(SUMPRODUCT((YEAR('07_CALENDARIO'!$A$2:$A$397)=p_anio_base)*'07_CALENDARIO'!$D$2:$D$397)*p_horas_productivas_dia*E2)) -> 0.31539084 | N2: =IF(COUNTIF('05_RUTAS'!$E$2:$E$407,A2)>0,1,0) -> 1 | O2: ESTIMADO
A3: Sierra de cinta para corte de tubos y perfiles | B3: CPR-01 | C3: Sierra de cinta para metal | D3: MAQUINA | E3: 1 | F3: 22 | G3: 0.75 | H3: 0.6 | I3: Corte | J3: 0 | K3: =SUMPRODUCT(('06B_HABILIDADES'!$B$1:$Q$1=A3)*('06B_HABILIDADES'!$B$2:$Q$26)) -> 3 | L3: =SUMIF('09_CARGA_ORDEN'!$E$2:$E$1153,A3,'09_CARGA_ORDEN'!$J$2:$J$1153) -> 331.64067 | M3: =IF(N(E3)=0,"",L3/(SUMPRODUCT((YEAR('07_CALENDARIO'!$A$2:$A$397)=p_anio_base)*'07_CALENDARIO'!$D$2:$D$397)*p_horas_productivas_dia*E3)) -> 0.15883174 | N3: =IF(COUNTIF('05_RUTAS'!$E$2:$E$407,A3)>0,1,0) -> 1 | O3: ESTIMADO
A4: Taladro de banco para perforación de acero | B4: PER-01 | C4: Taladro de banco industrial | D4: MAQUINA | E4: 1 | F4: 22 | G4: 0.55 | H4: 0.5 | I4: Perforación | J4: 0 | K4: =SUMPRODUCT(('06B_HABILIDADES'!$B$1:$Q$1=A4)*('06B_HABILIDADES'!$B$2:$Q$26)) -> 3 | L4: =SUMIF('09_CARGA_ORDEN'!$E$2:$E$1153,A4,'09_CARGA_ORDEN'!$J$2:$J$1153) -> 782.07 | M4: =IF(N(E4)=0,"",L4/(SUMPRODUCT((YEAR('07_CALENDARIO'!$A$2:$A$397)=p_anio_base)*'07_CALENDARIO'!$D$2:$D$397)*p_horas_productivas_dia*E4)) -> 0.3745546 | N4: =IF(COUNTIF('05_RUTAS'!$E$2:$E$407,A4)>0,1,0) -> 1 | O4: ESTIMADO
A5: Plegadora hidráulica de chapa metálica | B5: PLE-01 | C5: Plegadora hidráulica compacta | D5: MAQUINA | E5: 1 | F5: 28 | G5: 5.5 | H5: 0.45 | I5: Plegado | J5: 1 | K5: =SUMPRODUCT(('06B_HABILIDADES'!$B$1:$Q$1=A5)*('06B_HABILIDADES'!$B$2:$Q$26)) -> 3 | L5: =SUMIF('09_CARGA_ORDEN'!$E$2:$E$1153,A5,'09_CARGA_ORDEN'!$J$2:$J$1153) -> 1437.25 | M5: =IF(N(E5)=0,"",L5/(SUMPRODUCT((YEAR('07_CALENDARIO'!$A$2:$A$397)=p_anio_base)*'07_CALENDARIO'!$D$2:$D$397)*p_horas_productivas_dia*E5)) -> 0.68833812 | N5: =IF(COUNTIF('05_RUTAS'!$E$2:$E$407,A5)>0,1,0) -> 1 | O5: ESTIMADO
A6: Máquina de soldadura por arco MIG/MAG | B6: SOL-01 | C6: Soldadora inversora MIG/MAG | D6: MAQUINA | E6: 1 | F6: 32 | G6: 5 | H6: 0.35 | I6: Soldadura y armado | J6: 0 | K6: =SUMPRODUCT(('06B_HABILIDADES'!$B$1:$Q$1=A6)*('06B_HABILIDADES'!$B$2:$Q$26)) -> 5 | L6: =SUMIF('09_CARGA_ORDEN'!$E$2:$E$1153,A6,'09_CARGA_ORDEN'!$J$2:$J$1153) -> 403.58667 | M6: =IF(N(E6)=0,"",L6/(SUMPRODUCT((YEAR('07_CALENDARIO'!$A$2:$A$397)=p_anio_base)*'07_CALENDARIO'!$D$2:$D$397)*p_horas_productivas_dia*E6)) -> 0.19328863 | N6: =IF(COUNTIF('05_RUTAS'!$E$2:$E$407,A6)>0,1,0) -> 1 | O6: ESTIMADO
A7: Mesa de desbarbado/esmerilado | B7: DES-01 | C7: Mesa de desbarbado/esmerilado | D7: PUESTO_MANUAL | E7: 1 | F7: 21 | G7: 1.5 | H7: 0.5 | I7: Acabado | J7: 0 | K7: =SUMPRODUCT(('06B_HABILIDADES'!$B$1:$Q$1=A7)*('06B_HABILIDADES'!$B$2:$Q$26)) -> 5 | L7: =SUMIF('09_CARGA_ORDEN'!$E$2:$E$1153,A7,'09_CARGA_ORDEN'!$J$2:$J$1153) -> 508.225 | M7: =IF(N(E7)=0,"",L7/(SUMPRODUCT((YEAR('07_CALENDARIO'!$A$2:$A$397)=p_anio_base)*'07_CALENDARIO'!$D$2:$D$397)*p_horas_productivas_dia*E7)) -> 0.24340278 | N7: =IF(COUNTIF('05_RUTAS'!$E$2:$E$407,A7)>0,1,0) -> 1 | O7: ESTIMADO
A8: Zona de preparación superficial | B8: PRE-01 | C8: Zona de preparación superficial | D8: AREA | E8: 1 | F8: 19 | G8: 2.2 | H8: 0.4 | I8: Acabado | J8: 0 | K8: =SUMPRODUCT(('06B_HABILIDADES'!$B$1:$Q$1=A8)*('06B_HABILIDADES'!$B$2:$Q$26)) -> 4 | L8: =SUMIF('09_CARGA_ORDEN'!$E$2:$E$1153,A8,'09_CARGA_ORDEN'!$J$2:$J$1153) -> 437.39343 | M8: =IF(N(E8)=0,"",L8/(SUMPRODUCT((YEAR('07_CALENDARIO'!$A$2:$A$397)=p_anio_base)*'07_CALENDARIO'!$D$2:$D$397)*p_horas_productivas_dia*E8)) -> 0.20947961 | N8: =IF(COUNTIF('05_RUTAS'!$E$2:$E$407,A8)>0,1,0) -> 1 | O8: ESTIMADO
A9: Pistola manual de pintura electrostática en polvo | B9: PIN-01 | C9: Pistola manual de pintura electrostática en polvo | D9: EQUIPO_MANUAL | E9: 1 | F9: 32 | G9: 1.5 | H9: 0.7 | I9: Pintura y curado | J9: 0 | K9: =SUMPRODUCT(('06B_HABILIDADES'!$B$1:$Q$1=A9)*('06B_HABILIDADES'!$B$2:$Q$26)) -> 4 | L9: =SUMIF('09_CARGA_ORDEN'!$E$2:$E$1153,A9,'09_CARGA_ORDEN'!$J$2:$J$1153) -> 128.86083 | M9: =IF(N(E9)=0,"",L9/(SUMPRODUCT((YEAR('07_CALENDARIO'!$A$2:$A$397)=p_anio_base)*'07_CALENDARIO'!$D$2:$D$397)*p_horas_productivas_dia*E9)) -> 0.061714958 | N9: =IF(COUNTIF('05_RUTAS'!$E$2:$E$407,A9)>0,1,0) -> 1 | O9: ESTIMADO
A10: Mesa de armado | B10: ARM-01 | C10: Mesa de armado | D10: PUESTO_MANUAL | E10: 1 | F10: 19 | G10: 1 | H10: 0.3 | I10: Soldadura y armado | J10: 0 | K10: =SUMPRODUCT(('06B_HABILIDADES'!$B$1:$Q$1=A10)*('06B_HABILIDADES'!$B$2:$Q$26)) -> 5 | L10: =SUMIF('09_CARGA_ORDEN'!$E$2:$E$1153,A10,'09_CARGA_ORDEN'!$J$2:$J$1153) -> 775.975 | M10: =IF(N(E10)=0,"",L10/(SUMPRODUCT((YEAR('07_CALENDARIO'!$A$2:$A$397)=p_anio_base)*'07_CALENDARIO'!$D$2:$D$397)*p_horas_productivas_dia*E10)) -> 0.37163554 | N10: =IF(COUNTIF('05_RUTAS'!$E$2:$E$407,A10)>0,1,0) -> 1 | O10: ESTIMADO
A11: Área de inspección | B11: CAL-01 | C11: Área de inspección | D11: AREA | E11: 1 | F11: 20 | G11: 0.2 | H11: 0.5 | I11: Calidad y despacho | J11: 0 | K11: =SUMPRODUCT(('06B_HABILIDADES'!$B$1:$Q$1=A11)*('06B_HABILIDADES'!$B$2:$Q$26)) -> 5 | L11: =SUMIF('09_CARGA_ORDEN'!$E$2:$E$1153,A11,'09_CARGA_ORDEN'!$J$2:$J$1153) -> 56.082833 | M11: =IF(N(E11)=0,"",L11/(SUMPRODUCT((YEAR('07_CALENDARIO'!$A$2:$A$397)=p_anio_base)*'07_CALENDARIO'!$D$2:$D$397)*p_horas_productivas_dia*E11)) -> 0.026859595 | N11: =IF(COUNTIF('05_RUTAS'!$E$2:$E$407,A11)>0,1,0) -> 1 | O11: ESTIMADO
A12: Zona de protección y embalaje | B12: EMP-01 | C12: Zona de protección y embalaje | D12: AREA | E12: 1 | F12: 18 | G12: 0.3 | H12: 0.3 | I12: Calidad y despacho | J12: 0 | K12: =SUMPRODUCT(('06B_HABILIDADES'!$B$1:$Q$1=A12)*('06B_HABILIDADES'!$B$2:$Q$26)) -> 5 | L12: =SUMIF('09_CARGA_ORDEN'!$E$2:$E$1153,A12,'09_CARGA_ORDEN'!$J$2:$J$1153) -> 74.947 | M12: =IF(N(E12)=0,"",L12/(SUMPRODUCT((YEAR('07_CALENDARIO'!$A$2:$A$397)=p_anio_base)*'07_CALENDARIO'!$D$2:$D$397)*p_horas_productivas_dia*E12)) -> 0.035894157 | N12: =IF(COUNTIF('05_RUTAS'!$E$2:$E$407,A12)>0,1,0) -> 1 | O12: ESTIMADO
A13: Segundo taladro (alternativo) | B13: PER-02 | C13: Segundo taladro (alternativo) | D13: MAQUINA | E13: 1 | F13: 22 | G13: 0.75 | H13: 0.5 | I13: Perforación | J13: 0 | K13: =SUMPRODUCT(('06B_HABILIDADES'!$B$1:$Q$1=A13)*('06B_HABILIDADES'!$B$2:$Q$26)) -> 3 | L13: =SUMIF('09_CARGA_ORDEN'!$E$2:$E$1153,A13,'09_CARGA_ORDEN'!$J$2:$J$1153) -> 0 | M13: =IF(N(E13)=0,"",L13/(SUMPRODUCT((YEAR('07_CALENDARIO'!$A$2:$A$397)=p_anio_base)*'07_CALENDARIO'!$D$2:$D$397)*p_horas_productivas_dia*E13)) -> 0 | N13: =IF(COUNTIF('05_RUTAS'!$E$2:$E$407,A13)>0,1,0) -> 1 | O13: ESTIMADO
A14: Segunda estación soldadura (alternativa) | B14: SOL-02 | C14: Segunda estación soldadura (alternativa) | D14: MAQUINA | E14: 1 | F14: 32 | G14: 5 | H14: 0.35 | I14: Soldadura y armado | J14: 0 | K14: =SUMPRODUCT(('06B_HABILIDADES'!$B$1:$Q$1=A14)*('06B_HABILIDADES'!$B$2:$Q$26)) -> 5 | L14: =SUMIF('09_CARGA_ORDEN'!$E$2:$E$1153,A14,'09_CARGA_ORDEN'!$J$2:$J$1153) -> 0 | M14: =IF(N(E14)=0,"",L14/(SUMPRODUCT((YEAR('07_CALENDARIO'!$A$2:$A$397)=p_anio_base)*'07_CALENDARIO'!$D$2:$D$397)*p_horas_productivas_dia*E14)) -> 0 | N14: =IF(COUNTIF('05_RUTAS'!$E$2:$E$407,A14)>0,1,0) -> 1 | O14: ESTIMADO
A15: Proveedor de pintura externo | B15: PIN-EXT | C15: Proveedor de pintura externo | D15: EXTERNO | E15: 0 | G15: 0 | H15: 0 | I15: No aplica | J15: 0 | K15: =SUMPRODUCT(('06B_HABILIDADES'!$B$1:$Q$1=A15)*('06B_HABILIDADES'!$B$2:$Q$26)) -> 0 | L15: =SUMIF('09_CARGA_ORDEN'!$E$2:$E$1153,A15,'09_CARGA_ORDEN'!$J$2:$J$1153) -> 0 | M15: =IF(N(E15)=0,"",L15/(SUMPRODUCT((YEAR('07_CALENDARIO'!$A$2:$A$397)=p_anio_base)*'07_CALENDARIO'!$D$2:$D$397)*p_horas_productivas_dia*E15)) | N15: =IF(COUNTIF('05_RUTAS'!$E$2:$E$407,A15)>0,1,0) -> 0 | O15: ESTIMADO
A16: Horno de curado de pintura electrostática por lotes | B16: HOR-01 | C16: Horno de curado de pintura electrostática por lotes | D16: MAQUINA | E16: 1 | F16: 26 | G16: 24 | H16: 0.6 | I16: Pintura y curado | J16: 0 | K16: =SUMPRODUCT(('06B_HABILIDADES'!$B$1:$Q$1=A16)*('06B_HABILIDADES'!$B$2:$Q$26)) -> 2 | L16: =SUMIF('09_CARGA_ORDEN'!$E$2:$E$1153,A16,'09_CARGA_ORDEN'!$J$2:$J$1153) -> 94.5 | M16: =IF(N(E16)=0,"",L16/(SUMPRODUCT((YEAR('07_CALENDARIO'!$A$2:$A$397)=p_anio_base)*'07_CALENDARIO'!$D$2:$D$397)*p_horas_productivas_dia*E16)) -> 0.045258621 | N16: =IF(COUNTIF('05_RUTAS'!$E$2:$E$407,A16)>0,1,0) -> 1 | O16: ESTIMADO
A17: Manipulación y enfriamiento de piezas | B17: MAN-01 | C17: Manipulación y enfriamiento de piezas | D17: PUESTO_MANUAL | E17: 1 | F17: 16 | G17: 0.5 | H17: 0.5 | I17: Pintura y curado | J17: 0 | K17: =SUMPRODUCT(('06B_HABILIDADES'!$B$1:$Q$1=A17)*('06B_HABILIDADES'!$B$2:$Q$26)) -> 2 | L17: =SUMIF('09_CARGA_ORDEN'!$E$2:$E$1153,A17,'09_CARGA_ORDEN'!$J$2:$J$1153) -> 52.655167 | M17: =IF(N(E17)=0,"",L17/(SUMPRODUCT((YEAR('07_CALENDARIO'!$A$2:$A$397)=p_anio_base)*'07_CALENDARIO'!$D$2:$D$397)*p_horas_productivas_dia*E17)) -> 0.025217992 | N17: =IF(COUNTIF('05_RUTAS'!$E$2:$E$407,A17)>0,1,0) -> 1 | O17: ESTIMADO
A18: Sala acondicionada para pintura electrostática | B18: SAL-PIN | C18: Sala acondicionada para pintura electrostática | D18: AREA | E18: 1 | G18: 3 | H18: 0.5 | I18: Pintura y curado | J18: 0 | K18: =SUMPRODUCT(('06B_HABILIDADES'!$B$1:$Q$1=A18)*('06B_HABILIDADES'!$B$2:$Q$26)) -> 4 | L18: =SUMIF('09_CARGA_ORDEN'!$E$2:$E$1153,A18,'09_CARGA_ORDEN'!$J$2:$J$1153) -> 0 | M18: =IF(N(E18)=0,"",L18/(SUMPRODUCT((YEAR('07_CALENDARIO'!$A$2:$A$397)=p_anio_base)*'07_CALENDARIO'!$D$2:$D$397)*p_horas_productivas_dia*E18)) -> 0 | N18: =IF(COUNTIF('05_RUTAS'!$E$2:$E$407,A18)>0,1,0) -> 0 | O18: ESTIMADO

Sheet 05_RUTAS
A1: Producto | B1: Familia | C1: Paso | D1: Operación | E1: Equipo principal | F1: Min fijos por lote | G1: Minutos por unidad | H1: Precedencia | I1: Tratamiento del tiempo | J1: Min ciclo horno (incluidos) | K1: Origen de duración | L1: Equipo válido (1/0) | M1: Naturaleza
A2: Minirack metálico con bandejas | B2: Racks industriales | C2: 1 | D2: Corte de planchas de acero | E2: Guillotina hidráulica para corte de planchas de acero | F2: 8 | G2: 34.62 | H2: Inicio | I2: POR_UNIDAD | J2: 0 | K2: VALOR HEREDADO SIN CRONOMETRAJE | L2: =IF(COUNTIF('04_MAQUINAS'!$A$2:$A$18,E2)>0,1,0) -> 1 | M2: ESTIMADO
A3: Minirack metálico con bandejas | B3: Racks industriales | C3: 2 | D3: Corte de tubos y perfiles | E3: Sierra de cinta para corte de tubos y perfiles | F3: 8 | G3: 43.52 | H3: 1 | I3: POR_UNIDAD | J3: 0 | K3: VALOR HEREDADO SIN CRONOMETRAJE | L3: =IF(COUNTIF('04_MAQUINAS'!$A$2:$A$18,E3)>0,1,0) -> 1 | M3: ESTIMADO
A4: Minirack metálico con bandejas | B4: Racks industriales | C4: 3 | D4: Perforación | E4: Taladro de banco para perforación de acero | F4: 10 | G4: 63.2 | H4: 2 | I4: POR_UNIDAD | J4: 0 | K4: VALOR HEREDADO SIN CRONOMETRAJE | L4: =IF(COUNTIF('04_MAQUINAS'!$A$2:$A$18,E4)>0,1,0) -> 1 | M4: ESTIMADO
A5: Minirack metálico con bandejas | B5: Racks industriales | C5: 4 | D5: Plegado | E5: Plegadora hidráulica de chapa metálica | F5: 12 | G5: 60 | H5: 3 | I5: POR_UNIDAD | J5: 0 | K5: VALOR HEREDADO SIN CRONOMETRAJE | L5: =IF(COUNTIF('04_MAQUINAS'!$A$2:$A$18,E5)>0,1,0) -> 1 | M5: ESTIMADO
A6: Minirack metálico con bandejas | B6: Racks industriales | C6: 5 | D6: Soldadura | E6: Máquina de soldadura por arco MIG/MAG | F6: 10 | G6: 78.4 | H6: 4 | I6: POR_UNIDAD | J6: 0 | K6: VALOR HEREDADO SIN CRONOMETRAJE | L6: =IF(COUNTIF('04_MAQUINAS'!$A$2:$A$18,E6)>0,1,0) -> 1 | M6: ESTIMADO
A7: Minirack metálico con bandejas | B7: Racks industriales | C7: 6 | D7: Desbarbado | E7: Mesa de desbarbado/esmerilado | F7: 3 | G7: 42 | H7: 5 | I7: POR_UNIDAD | J7: 0 | K7: VALOR HEREDADO SIN CRONOMETRAJE | L7: =IF(COUNTIF('04_MAQUINAS'!$A$2:$A$18,E7)>0,1,0) -> 1 | M7: ESTIMADO
A8: Minirack metálico con bandejas | B8: Racks industriales | C8: 7 | D8: Preparación superficial | E8: Zona de preparación superficial | F8: 6 | G8: 29.7248 | H8: 6 | I8: POR_UNIDAD | J8: 0 | K8: VALOR HEREDADO SIN CRONOMETRAJE | L8: =IF(COUNTIF('04_MAQUINAS'!$A$2:$A$18,E8)>0,1,0) -> 1 | M8: ESTIMADO
A9: Minirack metálico con bandejas | B9: Racks industriales | C9: 8 | D9: Aplicación electrostática de polvo | E9: Pistola manual de pintura electrostática en polvo | F9: 12 | G9: 8.02 | H9: 7 | I9: POR_UNIDAD | J9: 0 | K9: HIPOTESIS TECNICA | L9: =IF(COUNTIF('04_MAQUINAS'!$A$2:$A$18,E9)>0,1,0) -> 1 | M9: ESTIMADO
A10: Minirack metálico con bandejas | B10: Racks industriales | C10: 9 | D10: Curado térmico en horno | E10: Horno de curado de pintura electrostática por lotes | F10: 45 | G10: 0 | H10: 8 | I10: POR_LOTE | J10: 40 | K10: HIPOTESIS TECNICA | L10: =IF(COUNTIF('04_MAQUINAS'!$A$2:$A$18,E10)>0,1,0) -> 1 | M10: ESTIMADO
A11: Minirack metálico con bandejas | B11: Racks industriales | C11: 10 | D11: Colgado, traslado y enfriamiento | E11: Manipulación y enfriamiento de piezas | F11: 8 | G11: 2.69 | H11: 9 | I11: POR_UNIDAD | J11: 0 | K11: HIPOTESIS TECNICA | L11: =IF(COUNTIF('04_MAQUINAS'!$A$2:$A$18,E11)>0,1,0) -> 1 | M11: ESTIMADO
A12: Minirack metálico con bandejas | B12: Racks industriales | C12: 11 | D12: Ensamblaje | E12: Mesa de armado | F12: 6 | G12: 60 | H12: 10 | I12: POR_UNIDAD | J12: 0 | K12: VALOR HEREDADO SIN CRONOMETRAJE | L12: =IF(COUNTIF('04_MAQUINAS'!$A$2:$A$18,E12)>0,1,0) -> 1 | M12: ESTIMADO
A13: Minirack metálico con bandejas | B13: Racks industriales | C13: 12 | D13: Inspección de calidad | E13: Área de inspección | F13: 2 | G13: 3.86 | H13: 11 | I13: POR_UNIDAD | J13: 0 | K13: HIPOTESIS TECNICA | L13: =IF(COUNTIF('04_MAQUINAS'!$A$2:$A$18,E13)>0,1,0) -> 1 | M13: ESTIMADO
A14: Minirack metálico con bandejas | B14: Racks industriales | C14: 13 | D14: Embalaje | E14: Zona de protección y embalaje | F14: 2 | G14: 5.3 | H14: 12 | I14: POR_UNIDAD | J14: 0 | K14: HIPOTESIS TECNICA | L14: =IF(COUNTIF('04_MAQUINAS'!$A$2:$A$18,E14)>0,1,0) -> 1 | M14: ESTIMADO
A15: Estante reforzado modular | B15: Racks industriales | C15: 1 | D15: Corte de planchas de acero | E15: Guillotina hidráulica para corte de planchas de acero | F15: 8 | G15: 36.67 | H15: Inicio | I15: POR_UNIDAD | J15: 0 | K15: VALOR HEREDADO SIN CRONOMETRAJE | L15: =IF(COUNTIF('04_MAQUINAS'!$A$2:$A$18,E15)>0,1,0) -> 1 | M15: ESTIMADO
A16: Estante reforzado modular | B16: Racks industriales | C16: 2 | D16: Corte de tubos y perfiles | E16: Sierra de cinta para corte de tubos y perfiles | F16: 8 | G16: 52 | H16: 1 | I16: POR_UNIDAD | J16: 0 | K16: VALOR HEREDADO SIN CRONOMETRAJE | L16: =IF(COUNTIF('04_MAQUINAS'!$A$2:$A$18,E16)>0,1,0) -> 1 | M16: ESTIMADO
A17: Estante reforzado modular | B17: Racks industriales | C17: 3 | D17: Perforación | E17: Taladro de banco para perforación de acero | F17: 10 | G17: 82.1 | H17: 2 | I17: POR_UNIDAD | J17: 0 | K17: VALOR HEREDADO SIN CRONOMETRAJE | L17: =IF(COUNTIF('04_MAQUINAS'!$A$2:$A$18,E17)>0,1,0) -> 1 | M17: ESTIMADO
A18: Estante reforzado modular | B18: Racks industriales | C18: 4 | D18: Plegado | E18: Plegadora hidráulica de chapa metálica | F18: 12 | G18: 69 | H18: 3 | I18: POR_UNIDAD | J18: 0 | K18: VALOR HEREDADO SIN CRONOMETRAJE | L18: =IF(COUNTIF('04_MAQUINAS'!$A$2:$A$18,E18)>0,1,0) -> 1 | M18: ESTIMADO
A19: Estante reforzado modular | B19: Racks industriales | C19: 5 | D19: Soldadura | E19: Máquina de soldadura por arco MIG/MAG | F19: 10 | G19: 78.4 | H19: 4 | I19: POR_UNIDAD | J19: 0 | K19: VALOR HEREDADO SIN CRONOMETRAJE | L19: =IF(COUNTIF('04_MAQUINAS'!$A$2:$A$18,E19)>0,1,0) -> 1 | M19: ESTIMADO
A20: Estante reforzado modular | B20: Racks industriales | C20: 6 | D20: Desbarbado | E20: Mesa de desbarbado/esmerilado | F20: 3 | G20: 49.5 | H20: 5 | I20: POR_UNIDAD | J20: 0 | K20: VALOR HEREDADO SIN CRONOMETRAJE | L20: =IF(COUNTIF('04_MAQUINAS'!$A$2:$A$18,E20)>0,1,0) -> 1 | M20: ESTIMADO
A21: Estante reforzado modular | B21: Racks industriales | C21: 7 | D21: Preparación superficial | E21: Zona de preparación superficial | F21: 6 | G21: 32.064 | H21: 6 | I21: POR_UNIDAD | J21: 0 | K21: VALOR HEREDADO SIN CRONOMETRAJE | L21: =IF(COUNTIF('04_MAQUINAS'!$A$2:$A$18,E21)>0,1,0) -> 1 | M21: ESTIMADO
A22: Estante reforzado modular | B22: Racks industriales | C22: 8 | D22: Aplicación electrostática de polvo | E22: Pistola manual de pintura electrostática en polvo | F22: 12 | G22: 8.02 | H22: 7 | I22: POR_UNIDAD | J22: 0 | K22: HIPOTESIS TECNICA | L22: =IF(COUNTIF('04_MAQUINAS'!$A$2:$A$18,E22)>0,1,0) -> 1 | M22: ESTIMADO
A23: Estante reforzado modular | B23: Racks industriales | C23: 9 | D23: Curado térmico en horno | E23: Horno de curado de pintura electrostática por lotes | F23: 45 | G23: 0 | H23: 8 | I23: POR_LOTE | J23: 40 | K23: HIPOTESIS TECNICA | L23: =IF(COUNTIF('04_MAQUINAS'!$A$2:$A$18,E23)>0,1,0) -> 1 | M23: ESTIMADO
A24: Estante reforzado modular | B24: Racks industriales | C24: 10 | D24: Colgado, traslado y enfriamiento | E24: Manipulación y enfriamiento de piezas | F24: 8 | G24: 2.69 | H24: 9 | I24: POR_UNIDAD | J24: 0 | K24: HIPOTESIS TECNICA | L24: =IF(COUNTIF('04_MAQUINAS'!$A$2:$A$18,E24)>0,1,0) -> 1 | M24: ESTIMADO
A25: Estante reforzado modular | B25: Racks industriales | C25: 11 | D25: Ensamblaje | E25: Mesa de armado | F25: 6 | G25: 62.25 | H25: 10 | I25: POR_UNIDAD | J25: 0 | K25: VALOR HEREDADO SIN CRONOMETRAJE | L25: =IF(COUNTIF('04_MAQUINAS'!$A$2:$A$18,E25)>0,1,0) -> 1 | M25: ESTIMADO
A26: Estante reforzado modular | B26: Racks industriales | C26: 12 | D26: Inspección de calidad | E26: Área de inspección | F26: 2 | G26: 3.86 | H26: 11 | I26: POR_UNIDAD | J26: 0 | K26: HIPOTESIS TECNICA | L26: =IF(COUNTIF('04_MAQUINAS'!$A$2:$A$18,E26)>0,1,0) -> 1 | M26: ESTIMADO
A27: Estante reforzado modular | B27: Racks industriales | C27: 13 | D27: Embalaje | E27: Zona de protección y embalaje | F27: 2 | G27: 5.3 | H27: 12 | I27: POR_UNIDAD | J27: 0 | K27: HIPOTESIS TECNICA | L27: =IF(COUNTIF('04_MAQUINAS'!$A$2:$A$18,E27)>0,1,0) -> 1 | M27: ESTIMADO
A28: Góndola central comercial | B28: Góndolas comerciales | C28: 1 | D28: Corte de planchas de acero | E28: Guillotina hidráulica para corte de planchas de acero | F28: 8 | G28: 90.38 | H28: Inicio | I28: POR_UNIDAD | J28: 0 | K28: VALOR HEREDADO SIN CRONOMETRAJE | L28: =IF(COUNTIF('04_MAQUINAS'!$A$2:$A$18,E28)>0,1,0) -> 1 | M28: ESTIMADO
A29: Góndola central comercial | B29: Góndolas comerciales | C29: 2 | D29: Corte de tubos y perfiles | E29: Sierra de cinta para corte de tubos y perfiles | F29: 8 | G29: 5.98 | H29: 1 | I29: POR_UNIDAD | J29: 0 | K29: VALOR HEREDADO SIN CRONOMETRAJE | L29: =IF(COUNTIF('04_MAQUINAS'!$A$2:$A$18,E29)>0,1,0) -> 1 | M29: ESTIMADO
A30: Góndola central comercial | B30: Góndolas comerciales | C30: 3 | D30: Perforación | E30: Taladro de banco para perforación de acero | F30: 10 | G30: 97 | H30: 2 | I30: POR_UNIDAD | J30: 0 | K30: VALOR HEREDADO SIN CRONOMETRAJE | L30: =IF(COUNTIF('04_MAQUINAS'!$A$2:$A$18,E30)>0,1,0) -> 1 | M30: ESTIMADO
A31: Góndola central comercial | B31: Góndolas comerciales | C31: 4 | D31: Plegado | E31: Plegadora hidráulica de chapa metálica | F31: 12 | G31: 196 | H31: 3 | I31: POR_UNIDAD | J31: 0 | K31: VALOR HEREDADO SIN CRONOMETRAJE | L31: =IF(COUNTIF('04_MAQUINAS'!$A$2:$A$18,E31)>0,1,0) -> 1 | M31: ESTIMADO
A32: Góndola central comercial | B32: Góndolas comerciales | C32: 5 | D32: Desbarbado | E32: Mesa de desbarbado/esmerilado | F32: 3 | G32: 51 | H32: 4 | I32: POR_UNIDAD | J32: 0 | K32: VALOR HEREDADO SIN CRONOMETRAJE | L32: =IF(COUNTIF('04_MAQUINAS'!$A$2:$A$18,E32)>0,1,0) -> 1 | M32: ESTIMADO
A33: Góndola central comercial | B33: Góndolas comerciales | C33: 6 | D33: Preparación superficial | E33: Zona de preparación superficial | F33: 6 | G33: 40.5152 | H33: 5 | I33: POR_UNIDAD | J33: 0 | K33: VALOR HEREDADO SIN CRONOMETRAJE | L33: =IF(COUNTIF('04_MAQUINAS'!$A$2:$A$18,E33)>0,1,0) -> 1 | M33: ESTIMADO
A34: Góndola central comercial | B34: Góndolas comerciales | C34: 7 | D34: Aplicación electrostática de polvo | E34: Pistola manual de pintura electrostática en polvo | F34: 12 | G34: 7.76 | H34: 6 | I34: POR_UNIDAD | J34: 0 | K34: HIPOTESIS TECNICA | L34: =IF(COUNTIF('04_MAQUINAS'!$A$2:$A$18,E34)>0,1,0) -> 1 | M34: ESTIMADO
A35: Góndola central comercial | B35: Góndolas comerciales | C35: 8 | D35: Curado térmico en horno | E35: Horno de curado de pintura electrostática por lotes | F35: 45 | G35: 0 | H35: 7 | I35: POR_LOTE | J35: 40 | K35: HIPOTESIS TECNICA | L35: =IF(COUNTIF('04_MAQUINAS'!$A$2:$A$18,E35)>0,1,0) -> 1 | M35: ESTIMADO
A36: Góndola central comercial | B36: Góndolas comerciales | C36: 9 | D36: Colgado, traslado y enfriamiento | E36: Manipulación y enfriamiento de piezas | F36: 8 | G36: 2.63 | H36: 8 | I36: POR_UNIDAD | J36: 0 | K36: HIPOTESIS TECNICA | L36: =IF(COUNTIF('04_MAQUINAS'!$A$2:$A$18,E36)>0,1,0) -> 1 | M36: ESTIMADO
A37: Góndola central comercial | B37: Góndolas comerciales | C37: 10 | D37: Ensamblaje | E37: Mesa de armado | F37: 6 | G37: 69 | H37: 9 | I37: POR_UNIDAD | J37: 0 | K37: VALOR HEREDADO SIN CRONOMETRAJE | L37: =IF(COUNTIF('04_MAQUINAS'!$A$2:$A$18,E37)>0,1,0) -> 1 | M37: ESTIMADO
A38: Góndola central comercial | B38: Góndolas comerciales | C38: 11 | D38: Inspección de calidad | E38: Área de inspección | F38: 2 | G38: 3.79 | H38: 10 | I38: POR_UNIDAD | J38: 0 | K38: HIPOTESIS TECNICA | L38: =IF(COUNTIF('04_MAQUINAS'!$A$2:$A$18,E38)>0,1,0) -> 1 | M38: ESTIMADO
A39: Góndola central comercial | B39: Góndolas comerciales | C39: 12 | D39: Embalaje | E39: Zona de protección y embalaje | F39: 2 | G39: 5.18 | H39: 11 | I39: POR_UNIDAD | J39: 0 | K39: HIPOTESIS TECNICA | L39: =IF(COUNTIF('04_MAQUINAS'!$A$2:$A$18,E39)>0,1,0) -> 1 | M39: ESTIMADO
A40: Góndola mural | B40: Góndolas comerciales | C40: 1 | D40: Corte de planchas de acero | E40: Guillotina hidráulica para corte de planchas de acero | F40: 8 | G40: 56.975 | H40: Inicio | I40: POR_UNIDAD | J40: 0 | K40: VALOR HEREDADO SIN CRONOMETRAJE | L40: =IF(COUNTIF('04_MAQUINAS'!$A$2:$A$18,E40)>0,1,0) -> 1 | M40: ESTIMADO
A41: Góndola mural | B41: Góndolas comerciales | C41: 2 | D41: Corte de tubos y perfiles | E41: Sierra de cinta para corte de tubos y perfiles | F41: 8 | G41: 6.28 | H41: 1 | I41: POR_UNIDAD | J41: 0 | K41: VALOR HEREDADO SIN CRONOMETRAJE | L41: =IF(COUNTIF('04_MAQUINAS'!$A$2:$A$18,E41)>0,1,0) -> 1 | M41: ESTIMADO
A42: Góndola mural | B42: Góndolas comerciales | C42: 3 | D42: Perforación | E42: Taladro de banco para perforación de acero | F42: 10 | G42: 67 | H42: 2 | I42: POR_UNIDAD | J42: 0 | K42: VALOR HEREDADO SIN CRONOMETRAJE | L42: =IF(COUNTIF('04_MAQUINAS'!$A$2:$A$18,E42)>0,1,0) -> 1 | M42: ESTIMADO
A43: Góndola mural | B43: Góndolas comerciales | C43: 4 | D43: Plegado | E43: Plegadora hidráulica de chapa metálica | F43: 12 | G43: 124 | H43: 3 | I43: POR_UNIDAD | J43: 0 | K43: VALOR HEREDADO SIN CRONOMETRAJE | L43: =IF(COUNTIF('04_MAQUINAS'!$A$2:$A$18,E43)>0,1,0) -> 1 | M43: ESTIMADO
A44: Góndola mural | B44: Góndolas comerciales | C44: 5 | D44: Soldadura | E44: Máquina de soldadura por arco MIG/MAG | F44: 10 | G44: 5.6 | H44: 4 | I44: POR_UNIDAD | J44: 0 | K44: VALOR HEREDADO SIN CRONOMETRAJE | L44: =IF(COUNTIF('04_MAQUINAS'!$A$2:$A$18,E44)>0,1,0) -> 1 | M44: ESTIMADO
A45: Góndola mural | B45: Góndolas comerciales | C45: 6 | D45: Desbarbado | E45: Mesa de desbarbado/esmerilado | F45: 3 | G45: 33 | H45: 5 | I45: POR_UNIDAD | J45: 0 | K45: VALOR HEREDADO SIN CRONOMETRAJE | L45: =IF(COUNTIF('04_MAQUINAS'!$A$2:$A$18,E45)>0,1,0) -> 1 | M45: ESTIMADO
A46: Góndola mural | B46: Góndolas comerciales | C46: 7 | D46: Preparación superficial | E46: Zona de preparación superficial | F46: 6 | G46: 27.0712 | H46: 6 | I46: POR_UNIDAD | J46: 0 | K46: VALOR HEREDADO SIN CRONOMETRAJE | L46: =IF(COUNTIF('04_MAQUINAS'!$A$2:$A$18,E46)>0,1,0) -> 1 | M46: ESTIMADO
A47: Góndola mural | B47: Góndolas comerciales | C47: 8 | D47: Aplicación electrostática de polvo | E47: Pistola manual de pintura electrostática en polvo | F47: 12 | G47: 7.34 | H47: 7 | I47: POR_UNIDAD | J47: 0 | K47: HIPOTESIS TECNICA | L47: =IF(COUNTIF('04_MAQUINAS'!$A$2:$A$18,E47)>0,1,0) -> 1 | M47: ESTIMADO
A48: Góndola mural | B48: Góndolas comerciales | C48: 9 | D48: Curado térmico en horno | E48: Horno de curado de pintura electrostática por lotes | F48: 45 | G48: 0 | H48: 8 | I48: POR_LOTE | J48: 40 | K48: HIPOTESIS TECNICA | L48: =IF(COUNTIF('04_MAQUINAS'!$A$2:$A$18,E48)>0,1,0) -> 1 | M48: ESTIMADO
A49: Góndola mural | B49: Góndolas comerciales | C49: 10 | D49: Colgado, traslado y enfriamiento | E49: Manipulación y enfriamiento de piezas | F49: 8 | G49: 2.54 | H49: 9 | I49: POR_UNIDAD | J49: 0 | K49: HIPOTESIS TECNICA | L49: =IF(COUNTIF('04_MAQUINAS'!$A$2:$A$18,E49)>0,1,0) -> 1 | M49: ESTIMADO
A50: Góndola mural | B50: Góndolas comerciales | C50: 11 | D50: Ensamblaje | E50: Mesa de armado | F50: 6 | G50: 48.75 | H50: 10 | I50: POR_UNIDAD | J50: 0 | K50: VALOR HEREDADO SIN CRONOMETRAJE | L50: =IF(COUNTIF('04_MAQUINAS'!$A$2:$A$18,E50)>0,1,0) -> 1 | M50: ESTIMADO
A51: Góndola mural | B51: Góndolas comerciales | C51: 12 | D51: Inspección de calidad | E51: Área de inspección | F51: 2 | G51: 3.67 | H51: 11 | I51: POR_UNIDAD | J51: 0 | K51: HIPOTESIS TECNICA | L51: =IF(COUNTIF('04_MAQUINAS'!$A$2:$A$18,E51)>0,1,0) -> 1 | M51: ESTIMADO
A52: Góndola mural | B52: Góndolas comerciales | C52: 13 | D52: Embalaje | E52: Zona de protección y embalaje | F52: 2 | G52: 5 | H52: 12 | I52: POR_UNIDAD | J52: 0 | K52: HIPOTESIS TECNICA | L52: =IF(COUNTIF('04_MAQUINAS'!$A$2:$A$18,E52)>0,1,0) -> 1 | M52: ESTIMADO
A53: Locker de 4 puertas | B53: Lockers metálicos | C53: 1 | D53: Corte de planchas de acero | E53: Guillotina hidráulica para corte de planchas de acero | F53: 8 | G53: 40.245 | H53: Inicio | I53: POR_UNIDAD | J53: 0 | K53: VALOR HEREDADO SIN CRONOMETRAJE | L53: =IF(COUNTIF('04_MAQUINAS'!$A$2:$A$18,E53)>0,1,0) -> 1 | M53: ESTIMADO
A54: Locker de 4 puertas | B54: Lockers metálicos | C54: 2 | D54: Perforación | E54: Taladro de banco para perforación de acero | F54: 10 | G54: 14.8 | H54: 1 | I54: POR_UNIDAD | J54: 0 | K54: VALOR HEREDADO SIN CRONOMETRAJE | L54: =IF(COUNTIF('04_MAQUINAS'!$A$2:$A$18,E54)>0,1,0) -> 1 | M54: ESTIMADO
A55: Locker de 4 puertas | B55: Lockers metálicos | C55: 3 | D55: Plegado | E55: Plegadora hidráulica de chapa metálica | F55: 12 | G55: 104 | H55: 2 | I55: POR_UNIDAD | J55: 0 | K55: VALOR HEREDADO SIN CRONOMETRAJE | L55: =IF(COUNTIF('04_MAQUINAS'!$A$2:$A$18,E55)>0,1,0) -> 1 | M55: ESTIMADO
A56: Locker de 4 puertas | B56: Lockers metálicos | C56: 4 | D56: Desbarbado | E56: Mesa de desbarbado/esmerilado | F56: 3 | G56: 18 | H56: 3 | I56: POR_UNIDAD | J56: 0 | K56: VALOR HEREDADO SIN CRONOMETRAJE | L56: =IF(COUNTIF('04_MAQUINAS'!$A$2:$A$18,E56)>0,1,0) -> 1 | M56: ESTIMADO
A57: Locker de 4 puertas | B57: Lockers metálicos | C57: 5 | D57: Preparación superficial | E57: Zona de preparación superficial | F57: 6 | G57: 26.324 | H57: 4 | I57: POR_UNIDAD | J57: 0 | K57: VALOR HEREDADO SIN CRONOMETRAJE | L57: =IF(COUNTIF('04_MAQUINAS'!$A$2:$A$18,E57)>0,1,0) -> 1 | M57: ESTIMADO
A58: Locker de 4 puertas | B58: Lockers metálicos | C58: 6 | D58: Aplicación electrostática de polvo | E58: Pistola manual de pintura electrostática en polvo | F58: 12 | G58: 6.83 | H58: 5 | I58: POR_UNIDAD | J58: 0 | K58: HIPOTESIS TECNICA | L58: =IF(COUNTIF('04_MAQUINAS'!$A$2:$A$18,E58)>0,1,0) -> 1 | M58: ESTIMADO
A59: Locker de 4 puertas | B59: Lockers metálicos | C59: 7 | D59: Curado térmico en horno | E59: Horno de curado de pintura electrostática por lotes | F59: 45 | G59: 0 | H59: 6 | I59: POR_LOTE | J59: 40 | K59: HIPOTESIS TECNICA | L59: =IF(COUNTIF('04_MAQUINAS'!$A$2:$A$18,E59)>0,1,0) -> 1 | M59: ESTIMADO
A60: Locker de 4 puertas | B60: Lockers metálicos | C60: 8 | D60: Colgado, traslado y enfriamiento | E60: Manipulación y enfriamiento de piezas | F60: 8 | G60: 2.42 | H60: 7 | I60: POR_UNIDAD | J60: 0 | K60: HIPOTESIS TECNICA | L60: =IF(COUNTIF('04_MAQUINAS'!$A$2:$A$18,E60)>0,1,0) -> 1 | M60: ESTIMADO
A61: Locker de 4 puertas | B61: Lockers metálicos | C61: 9 | D61: Ensamblaje | E61: Mesa de armado | F61: 6 | G61: 42 | H61: 8 | I61: POR_UNIDAD | J61: 0 | K61: VALOR HEREDADO SIN CRONOMETRAJE | L61: =IF(COUNTIF('04_MAQUINAS'!$A$2:$A$18,E61)>0,1,0) -> 1 | M61: ESTIMADO
A62: Locker de 4 puertas | B62: Lockers metálicos | C62: 10 | D62: Inspección de calidad | E62: Área de inspección | F62: 2 | G62: 3.52 | H62: 9 | I62: POR_UNIDAD | J62: 0 | K62: HIPOTESIS TECNICA | L62: =IF(COUNTIF('04_MAQUINAS'!$A$2:$A$18,E62)>0,1,0) -> 1 | M62: ESTIMADO
A63: Locker de 4 puertas | B63: Lockers metálicos | C63: 11 | D63: Embalaje | E63: Zona de protección y embalaje | F63: 2 | G63: 4.78 | H63: 10 | I63: POR_UNIDAD | J63: 0 | K63: HIPOTESIS TECNICA | L63: =IF(COUNTIF('04_MAQUINAS'!$A$2:$A$18,E63)>0,1,0) -> 1 | M63: ESTIMADO
A64: Locker de 6 puertas | B64: Lockers metálicos | C64: 1 | D64: Corte de planchas de acero | E64: Guillotina hidráulica para corte de planchas de acero | F64: 8 | G64: 57.14 | H64: Inicio | I64: POR_UNIDAD | J64: 0 | K64: VALOR HEREDADO SIN CRONOMETRAJE | L64: =IF(COUNTIF('04_MAQUINAS'!$A$2:$A$18,E64)>0,1,0) -> 1 | M64: ESTIMADO
A65: Locker de 6 puertas | B65: Lockers metálicos | C65: 2 | D65: Perforación | E65: Taladro de banco para perforación de acero | F65: 10 | G65: 27 | H65: 1 | I65: POR_UNIDAD | J65: 0 | K65: VALOR HEREDADO SIN CRONOMETRAJE | L65: =IF(COUNTIF('04_MAQUINAS'!$A$2:$A$18,E65)>0,1,0) -> 1 | M65: ESTIMADO
A66: Locker de 6 puertas | B66: Lockers metálicos | C66: 3 | D66: Plegado | E66: Plegadora hidráulica de chapa metálica | F66: 12 | G66: 149 | H66: 2 | I66: POR_UNIDAD | J66: 0 | K66: VALOR HEREDADO SIN CRONOMETRAJE | L66: =IF(COUNTIF('04_MAQUINAS'!$A$2:$A$18,E66)>0,1,0) -> 1 | M66: ESTIMADO
A67: Locker de 6 puertas | B67: Lockers metálicos | C67: 4 | D67: Desbarbado | E67: Mesa de desbarbado/esmerilado | F67: 3 | G67: 25.5 | H67: 3 | I67: POR_UNIDAD | J67: 0 | K67: VALOR HEREDADO SIN CRONOMETRAJE | L67: =IF(COUNTIF('04_MAQUINAS'!$A$2:$A$18,E67)>0,1,0) -> 1 | M67: ESTIMADO
A68: Locker de 6 puertas | B68: Lockers metálicos | C68: 5 | D68: Preparación superficial | E68: Zona de preparación superficial | F68: 6 | G68: 37.528 | H68: 4 | I68: POR_UNIDAD | J68: 0 | K68: VALOR HEREDADO SIN CRONOMETRAJE | L68: =IF(COUNTIF('04_MAQUINAS'!$A$2:$A$18,E68)>0,1,0) -> 1 | M68: ESTIMADO
A69: Locker de 6 puertas | B69: Lockers metálicos | C69: 6 | D69: Aplicación electrostática de polvo | E69: Pistola manual de pintura electrostática en polvo | F69: 12 | G69: 6.83 | H69: 5 | I69: POR_UNIDAD | J69: 0 | K69: HIPOTESIS TECNICA | L69: =IF(COUNTIF('04_MAQUINAS'!$A$2:$A$18,E69)>0,1,0) -> 1 | M69: ESTIMADO
A70: Locker de 6 puertas | B70: Lockers metálicos | C70: 7 | D70: Curado térmico en horno | E70: Horno de curado de pintura electrostática por lotes | F70: 45 | G70: 0 | H70: 6 | I70: POR_LOTE | J70: 40 | K70: HIPOTESIS TECNICA | L70: =IF(COUNTIF('04_MAQUINAS'!$A$2:$A$18,E70)>0,1,0) -> 1 | M70: ESTIMADO
A71: Locker de 6 puertas | B71: Lockers metálicos | C71: 8 | D71: Colgado, traslado y enfriamiento | E71: Manipulación y enfriamiento de piezas | F71: 8 | G71: 2.42 | H71: 7 | I71: POR_UNIDAD | J71: 0 | K71: HIPOTESIS TECNICA | L71: =IF(COUNTIF('04_MAQUINAS'!$A$2:$A$18,E71)>0,1,0) -> 1 | M71: ESTIMADO
A72: Locker de 6 puertas | B72: Lockers metálicos | C72: 9 | D72: Ensamblaje | E72: Mesa de armado | F72: 6 | G72: 56.25 | H72: 8 | I72: POR_UNIDAD | J72: 0 | K72: VALOR HEREDADO SIN CRONOMETRAJE | L72: =IF(COUNTIF('04_MAQUINAS'!$A$2:$A$18,E72)>0,1,0) -> 1 | M72: ESTIMADO
A73: Locker de 6 puertas | B73: Lockers metálicos | C73: 10 | D73: Inspección de calidad | E73: Área de inspección | F73: 2 | G73: 3.52 | H73: 9 | I73: POR_UNIDAD | J73: 0 | K73: HIPOTESIS TECNICA | L73: =IF(COUNTIF('04_MAQUINAS'!$A$2:$A$18,E73)>0,1,0) -> 1 | M73: ESTIMADO
A74: Locker de 6 puertas | B74: Lockers metálicos | C74: 11 | D74: Embalaje | E74: Zona de protección y embalaje | F74: 2 | G74: 4.78 | H74: 10 | I74: POR_UNIDAD | J74: 0 | K74: HIPOTESIS TECNICA | L74: =IF(COUNTIF('04_MAQUINAS'!$A$2:$A$18,E74)>0,1,0) -> 1 | M74: ESTIMADO
A75: Armario metálico | B75: Otros productos metalmecánicos | C75: 1 | D75: Corte de planchas de acero | E75: Guillotina hidráulica para corte de planchas de acero | F75: 8 | G75: 35.56 | H75: Inicio | I75: POR_UNIDAD | J75: 0 | K75: VALOR HEREDADO SIN CRONOMETRAJE | L75: =IF(COUNTIF('04_MAQUINAS'!$A$2:$A$18,E75)>0,1,0) -> 1 | M75: ESTIMADO
A76: Armario metálico | B76: Otros productos metalmecánicos | C76: 2 | D76: Perforación | E76: Taladro de banco para perforación de acero | F76: 10 | G76: 5.8 | H76: 1 | I76: POR_UNIDAD | J76: 0 | K76: VALOR HEREDADO SIN CRONOMETRAJE | L76: =IF(COUNTIF('04_MAQUINAS'!$A$2:$A$18,E76)>0,1,0) -> 1 | M76: ESTIMADO
A77: Armario metálico | B77: Otros productos metalmecánicos | C77: 3 | D77: Plegado | E77: Plegadora hidráulica de chapa metálica | F77: 12 | G77: 86 | H77: 2 | I77: POR_UNIDAD | J77: 0 | K77: VALOR HEREDADO SIN CRONOMETRAJE | L77: =IF(COUNTIF('04_MAQUINAS'!$A$2:$A$18,E77)>0,1,0) -> 1 | M77: ESTIMADO
A78: Armario metálico | B78: Otros productos metalmecánicos | C78: 4 | D78: Desbarbado | E78: Mesa de desbarbado/esmerilado | F78: 3 | G78: 15 | H78: 3 | I78: POR_UNIDAD | J78: 0 | K78: VALOR HEREDADO SIN CRONOMETRAJE | L78: =IF(COUNTIF('04_MAQUINAS'!$A$2:$A$18,E78)>0,1,0) -> 1 | M78: ESTIMADO
A79: Armario metálico | B79: Otros productos metalmecánicos | C79: 5 | D79: Preparación superficial | E79: Zona de preparación superficial | F79: 6 | G79: 25.712 | H79: 4 | I79: POR_UNIDAD | J79: 0 | K79: VALOR HEREDADO SIN CRONOMETRAJE | L79: =IF(COUNTIF('04_MAQUINAS'!$A$2:$A$18,E79)>0,1,0) -> 1 | M79: ESTIMADO
A80: Armario metálico | B80: Otros productos metalmecánicos | C80: 6 | D80: Aplicación electrostática de polvo | E80: Pistola manual de pintura electrostática en polvo | F80: 12 | G80: 6.58 | H80: 5 | I80: POR_UNIDAD | J80: 0 | K80: HIPOTESIS TECNICA | L80: =IF(COUNTIF('04_MAQUINAS'!$A$2:$A$18,E80)>0,1,0) -> 1 | M80: ESTIMADO
A81: Armario metálico | B81: Otros productos metalmecánicos | C81: 7 | D81: Curado térmico en horno | E81: Horno de curado de pintura electrostática por lotes | F81: 45 | G81: 0 | H81: 6 | I81: POR_LOTE | J81: 40 | K81: HIPOTESIS TECNICA | L81: =IF(COUNTIF('04_MAQUINAS'!$A$2:$A$18,E81)>0,1,0) -> 1 | M81: ESTIMADO
A82: Armario metálico | B82: Otros productos metalmecánicos | C82: 8 | D82: Colgado, traslado y enfriamiento | E82: Manipulación y enfriamiento de piezas | F82: 8 | G82: 2.36 | H82: 7 | I82: POR_UNIDAD | J82: 0 | K82: HIPOTESIS TECNICA | L82: =IF(COUNTIF('04_MAQUINAS'!$A$2:$A$18,E82)>0,1,0) -> 1 | M82: ESTIMADO
A83: Armario metálico | B83: Otros productos metalmecánicos | C83: 9 | D83: Ensamblaje | E83: Mesa de armado | F83: 6 | G83: 27 | H83: 8 | I83: POR_UNIDAD | J83: 0 | K83: VALOR HEREDADO SIN CRONOMETRAJE | L83: =IF(COUNTIF('04_MAQUINAS'!$A$2:$A$18,E83)>0,1,0) -> 1 | M83: ESTIMADO
A84: Armario metálico | B84: Otros productos metalmecánicos | C84: 10 | D84: Inspección de calidad | E84: Área de inspección | F84: 2 | G84: 3.45 | H84: 9 | I84: POR_UNIDAD | J84: 0 | K84: HIPOTESIS TECNICA | L84: =IF(COUNTIF('04_MAQUINAS'!$A$2:$A$18,E84)>0,1,0) -> 1 | M84: ESTIMADO
A85: Armario metálico | B85: Otros productos metalmecánicos | C85: 11 | D85: Embalaje | E85: Zona de protección y embalaje | F85: 2 | G85: 4.67 | H85: 10 | I85: POR_UNIDAD | J85: 0 | K85: HIPOTESIS TECNICA | L85: =IF(COUNTIF('04_MAQUINAS'!$A$2:$A$18,E85)>0,1,0) -> 1 | M85: ESTIMADO
A86: Estantería liviana metálica | B86: Otros productos metalmecánicos | C86: 1 | D86: Corte de planchas de acero | E86: Guillotina hidráulica para corte de planchas de acero | F86: 8 | G86: 35.92 | H86: Inicio | I86: POR_UNIDAD | J86: 0 | K86: VALOR HEREDADO SIN CRONOMETRAJE | L86: =IF(COUNTIF('04_MAQUINAS'!$A$2:$A$18,E86)>0,1,0) -> 1 | M86: ESTIMADO
A87: Estantería liviana metálica | B87: Otros productos metalmecánicos | C87: 2 | D87: Corte de tubos y perfiles | E87: Sierra de cinta para corte de tubos y perfiles | F87: 8 | G87: 32.28 | H87: 1 | I87: POR_UNIDAD | J87: 0 | K87: VALOR HEREDADO SIN CRONOMETRAJE | L87: =IF(COUNTIF('04_MAQUINAS'!$A$2:$A$18,E87)>0,1,0) -> 1 | M87: ESTIMADO
A88: Estantería liviana metálica | B88: Otros productos metalmecánicos | C88: 3 | D88: Perforación | E88: Taladro de banco para perforación de acero | F88: 10 | G88: 54.8 | H88: 2 | I88: POR_UNIDAD | J88: 0 | K88: VALOR HEREDADO SIN CRONOMETRAJE | L88: =IF(COUNTIF('04_MAQUINAS'!$A$2:$A$18,E88)>0,1,0) -> 1 | M88: ESTIMADO
A89: Estantería liviana metálica | B89: Otros productos metalmecánicos | C89: 4 | D89: Plegado | E89: Plegadora hidráulica de chapa metálica | F89: 12 | G89: 85 | H89: 3 | I89: POR_UNIDAD | J89: 0 | K89: VALOR HEREDADO SIN CRONOMETRAJE | L89: =IF(COUNTIF('04_MAQUINAS'!$A$2:$A$18,E89)>0,1,0) -> 1 | M89: ESTIMADO
A90: Estantería liviana metálica | B90: Otros productos metalmecánicos | C90: 5 | D90: Desbarbado | E90: Mesa de desbarbado/esmerilado | F90: 3 | G90: 37.5 | H90: 4 | I90: POR_UNIDAD | J90: 0 | K90: VALOR HEREDADO SIN CRONOMETRAJE | L90: =IF(COUNTIF('04_MAQUINAS'!$A$2:$A$18,E90)>0,1,0) -> 1 | M90: ESTIMADO
A91: Estantería liviana metálica | B91: Otros productos metalmecánicos | C91: 6 | D91: Preparación superficial | E91: Zona de preparación superficial | F91: 6 | G91: 24.4752 | H91: 5 | I91: POR_UNIDAD | J91: 0 | K91: VALOR HEREDADO SIN CRONOMETRAJE | L91: =IF(COUNTIF('04_MAQUINAS'!$A$2:$A$18,E91)>0,1,0) -> 1 | M91: ESTIMADO
A92: Estantería liviana metálica | B92: Otros productos metalmecánicos | C92: 7 | D92: Aplicación electrostática de polvo | E92: Pistola manual de pintura electrostática en polvo | F92: 12 | G92: 6.58 | H92: 6 | I92: POR_UNIDAD | J92: 0 | K92: HIPOTESIS TECNICA | L92: =IF(COUNTIF('04_MAQUINAS'!$A$2:$A$18,E92)>0,1,0) -> 1 | M92: ESTIMADO
A93: Estantería liviana metálica | B93: Otros productos metalmecánicos | C93: 8 | D93: Curado térmico en horno | E93: Horno de curado de pintura electrostática por lotes | F93: 45 | G93: 0 | H93: 7 | I93: POR_LOTE | J93: 40 | K93: HIPOTESIS TECNICA | L93: =IF(COUNTIF('04_MAQUINAS'!$A$2:$A$18,E93)>0,1,0) -> 1 | M93: ESTIMADO
A94: Estantería liviana metálica | B94: Otros productos metalmecánicos | C94: 9 | D94: Colgado, traslado y enfriamiento | E94: Manipulación y enfriamiento de piezas | F94: 8 | G94: 2.36 | H94: 8 | I94: POR_UNIDAD | J94: 0 | K94: HIPOTESIS TECNICA | L94: =IF(COUNTIF('04_MAQUINAS'!$A$2:$A$18,E94)>0,1,0) -> 1 | M94: ESTIMADO
A95: Estantería liviana metálica | B95: Otros productos metalmecánicos | C95: 10 | D95: Ensamblaje | E95: Mesa de armado | F95: 6 | G95: 61.5 | H95: 9 | I95: POR_UNIDAD | J95: 0 | K95: VALOR HEREDADO SIN CRONOMETRAJE | L95: =IF(COUNTIF('04_MAQUINAS'!$A$2:$A$18,E95)>0,1,0) -> 1 | M95: ESTIMADO
A96: Estantería liviana metálica | B96: Otros productos metalmecánicos | C96: 11 | D96: Inspección de calidad | E96: Área de inspección | F96: 2 | G96: 3.45 | H96: 10 | I96: POR_UNIDAD | J96: 0 | K96: HIPOTESIS TECNICA | L96: =IF(COUNTIF('04_MAQUINAS'!$A$2:$A$18,E96)>0,1,0) -> 1 | M96: ESTIMADO
A97: Estantería liviana metálica | B97: Otros productos metalmecánicos | C97: 12 | D97: Embalaje | E97: Zona de protección y embalaje | F97: 2 | G97: 4.67 | H97: 11 | I97: POR_UNIDAD | J97: 0 | K97: HIPOTESIS TECNICA | L97: =IF(COUNTIF('04_MAQUINAS'!$A$2:$A$18,E97)>0,1,0) -> 1 | M97: ESTIMADO
A98: Rack selectivo para pallets | B98: Racks industriales | C98: 1 | D98: Corte de tubos y perfiles | E98: Sierra de cinta para corte de tubos y perfiles | F98: 8 | G98: 68.56 | H98: Inicio | I98: POR_UNIDAD | J98: 0 | K98: VALOR HEREDADO SIN CRONOMETRAJE | L98: =IF(COUNTIF('04_MAQUINAS'!$A$2:$A$18,E98)>0,1,0) -> 1 | M98: ESTIMADO
A99: Rack selectivo para pallets | B99: Racks industriales | C99: 2 | D99: Perforación | E99: Segundo taladro (alternativo) | F99: 10 | G99: 35.6 | H99: 1 | I99: POR_UNIDAD | J99: 0 | K99: VALOR HEREDADO SIN CRONOMETRAJE | L99: =IF(COUNTIF('04_MAQUINAS'!$A$2:$A$18,E99)>0,1,0) -> 1 | M99: ESTIMADO
A100: Rack selectivo para pallets | B100: Racks industriales | C100: 3 | D100: Soldadura | E100: Segunda estación soldadura (alternativa) | F100: 10 | G100: 89.6 | H100: 2 | I100: POR_UNIDAD | J100: 0 | K100: VALOR HEREDADO SIN CRONOMETRAJE | L100: =IF(COUNTIF('04_MAQUINAS'!$A$2:$A$18,E100)>0,1,0) -> 1 | M100: ESTIMADO
...

Sheet 06B_HABILIDADES
A1: Operario (seudónimo) | B1: Guillotina hidráulica para corte de planchas de acero | C1: Sierra de cinta para corte de tubos y perfiles | D1: Taladro de banco para perforación de acero | E1: Plegadora hidráulica de chapa metálica | F1: Máquina de soldadura por arco MIG/MAG | G1: Mesa de desbarbado/esmerilado | H1: Zona de preparación superficial | I1: Pistola manual de pintura electrostática en polvo | J1: Mesa de armado | K1: Área de inspección | L1: Zona de protección y embalaje | M1: Segundo taladro (alternativo) | N1: Segunda estación soldadura (alternativa) | O1: Horno de curado de pintura electrostática por lotes | P1: Manipulación y enfriamiento de piezas | Q1: Sala acondicionada para pintura electrostática | R1: Naturaleza
A2: OP-01 | B2: 1 | C2: 1 | D2: 0 | E2: 0 | F2: 0 | G2: 0 | H2: 0 | I2: 0 | J2: 0 | K2: 0 | L2: 0 | M2: 0 | N2: 0 | O2: 0 | P2: 0 | Q2: 0 | R2: SIMULADO
A3: OP-02 | B3: 1 | C3: 1 | D3: 0 | E3: 0 | F3: 0 | G3: 0 | H3: 0 | I3: 0 | J3: 0 | K3: 0 | L3: 0 | M3: 0 | N3: 0 | O3: 0 | P3: 0 | Q3: 0 | R3: SIMULADO
A4: OP-03 | B4: 0 | C4: 0 | D4: 1 | E4: 0 | F4: 0 | G4: 0 | H4: 0 | I4: 0 | J4: 0 | K4: 0 | L4: 0 | M4: 1 | N4: 0 | O4: 0 | P4: 0 | Q4: 0 | R4: SIMULADO
A5: OP-04 | B5: 1 | C5: 0 | D5: 0 | E5: 1 | F5: 0 | G5: 0 | H5: 0 | I5: 0 | J5: 0 | K5: 0 | L5: 0 | M5: 0 | N5: 0 | O5: 0 | P5: 0 | Q5: 0 | R5: SIMULADO
A6: OP-05 | B6: 0 | C6: 0 | D6: 0 | E6: 0 | F6: 1 | G6: 1 | H6: 0 | I6: 0 | J6: 0 | K6: 0 | L6: 0 | M6: 0 | N6: 1 | O6: 0 | P6: 0 | Q6: 0 | R6: SIMULADO
A7: OP-06 | B7: 0 | C7: 0 | D7: 0 | E7: 0 | F7: 1 | G7: 1 | H7: 0 | I7: 0 | J7: 0 | K7: 0 | L7: 0 | M7: 0 | N7: 1 | O7: 0 | P7: 0 | Q7: 0 | R7: SIMULADO
A8: OP-07 | B8: 0 | C8: 0 | D8: 0 | E8: 0 | F8: 0 | G8: 0 | H8: 1 | I8: 1 | J8: 0 | K8: 0 | L8: 0 | M8: 0 | N8: 0 | O8: 0 | P8: 0 | Q8: 1 | R8: SIMULADO
A9: OP-08 | B9: 0 | C9: 0 | D9: 0 | E9: 0 | F9: 0 | G9: 0 | H9: 1 | I9: 1 | J9: 0 | K9: 0 | L9: 0 | M9: 0 | N9: 0 | O9: 0 | P9: 0 | Q9: 1 | R9: SIMULADO
A10: OP-09 | B10: 0 | C10: 0 | D10: 0 | E10: 0 | F10: 0 | G10: 0 | H10: 0 | I10: 0 | J10: 1 | K10: 1 | L10: 1 | M10: 0 | N10: 0 | O10: 0 | P10: 0 | Q10: 0 | R10: SIMULADO
A11: OP-10 | B11: 0 | C11: 0 | D11: 0 | E11: 0 | F11: 0 | G11: 0 | H11: 0 | I11: 0 | J11: 1 | K11: 1 | L11: 1 | M11: 0 | N11: 0 | O11: 0 | P11: 0 | Q11: 0 | R11: SIMULADO
A12: OP-11 | B12: 0 | C12: 0 | D12: 0 | E12: 0 | F12: 0 | G12: 0 | H12: 0 | I12: 0 | J12: 1 | K12: 1 | L12: 1 | M12: 0 | N12: 0 | O12: 0 | P12: 0 | Q12: 0 | R12: SIMULADO
A13: OP-12 | B13: 0 | C13: 0 | D13: 1 | E13: 0 | F13: 0 | G13: 0 | H13: 0 | I13: 0 | J13: 0 | K13: 0 | L13: 0 | M13: 1 | N13: 0 | O13: 0 | P13: 0 | Q13: 0 | R13: SIMULADO
... A26: OP-25 | B26: 0 | C26: 0 | D26: 1 | E26: 0 | F26: 0 | G26: 0 | H26: 0 | I26: 0 | J26: 0 | K26: 0 | L26: 0 | M26: 1 | N26: 0 | O26: 0 | P26: 0 | Q26: 0 | R26: SIMULADO

Sheet 06_OPERARIOS
A1: Operario (seudónimo) | B1: Especialidad (simulada) | C1: Turnos | D1: Horas netas / día | E1: Naturaleza
A2: OP-01 | B2: Corte | C2: 1 | D2: 8 | E2: REAL (cantidad y jornada); especialidad SIMULADA
A3: OP-02 | B3: Corte | C3: 1 | D3: 8 | E3: REAL (cantidad y jornada); especialidad SIMULADA
A4: OP-03 | B4: Perforación | C4: 1 | D4: 8 | E4: REAL (cantidad y jornada); especialidad SIMULADA
A5: OP-04 | B5: Plegado | C5: 1 | D5: 8 | E5: REAL (cantidad y jornada); especialidad SIMULADA
A6: OP-05 | B6: Soldadura | C6: 1 | D6: 8 | E6: REAL (cantidad y jornada); especialidad SIMULADA
A7: OP-06 | B7: Desbarbado | C7: 1 | D7: 8 | E7: REAL (cantidad y jornada); especialidad SIMULADA
A8: OP-07 | B8: Preparación superficial | C8: 1 | D8: 8 | E8: REAL (cantidad y jornada); especialidad SIMULADA
A9: OP-08 | B9: Pintura | C9: 1 | D9: 8 | E9: REAL (cantidad y jornada); especialidad SIMULADA
A10: OP-09 | B10: Armado | C10: 1 | D10: 8 | E10: REAL (cantidad y jornada); especialidad SIMULADA
A11: OP-10 | B11: Inspección | C11: 1 | D11: 8 | E11: REAL (cantidad y jornada); especialidad SIMULADA
A12: OP-11 | B12: Embalaje | C12: 1 | D12: 8 | E12: REAL (cantidad y jornada); especialidad SIMULADA
A13: OP-12 | B13: Perforación | C13: 1 | D13: 8 | E13: REAL (cantidad y jornada); especialidad SIMULADA
... A26: OP-25 | B26: Perforación | C26: 1 | D26: 8 | E26: REAL (cantidad y jornada); especialidad SIMULADA

Sheet 07_CALENDARIO
A1: Fecha | B1: Productivo (1/0) | C1: Feriado nacional Perú | D1: Productivo efectivo (1/0) | E1: Naturaleza
A2: 45658 | B2: 1 | C2: Año Nuevo | D2: =IF(AND(p_aplicar_feriados=1,C2<>""),0,B2) -> 1 | E2: ESTIMADO
A3: 45659 | B3: 1 | D3: =IF(AND(p_aplicar_feriados=1,C3<>""),0,B3) -> 1 | E3: ESTIMADO
A4: 45660 | B4: 1 | D4: =IF(AND(p_aplicar_feriados=1,C4<>""),0,B4) -> 1 | E4: ESTIMADO
A5: 45661 | B5: 0 | D5: =IF(AND(p_aplicar_feriados=1,C5<>""),0,B5) -> 0 | E5: ESTIMADO
A6: 45662 | B6: 0 | D6: =IF(AND(p_aplicar_feriados=1,C6<>""),0,B6) -> 0 | E6: ESTIMADO
A7: 45663 | B7: 1 | D7: =IF(AND(p_aplicar_feriados=1,C7<>""),0,B7) -> 1 | E7: ESTIMADO
A8: 45664 | B8: 1 | D8: =IF(AND(p_aplicar_feriados=1,C8<>""),0,B8) -> 1 | E8: ESTIMADO
A9: 45665 | B9: 1 | D9: =IF(AND(p_aplicar_feriados=1,C9<>""),0,B9) -> 1 | E9: ESTIMADO
A10: 45666 | B10: 1 | D10: =IF(AND(p_aplicar_feriados=1,C10<>""),0,B10) -> 1 | E10: ESTIMADO
A11: 45667 | B11: 1 | D11: =IF(AND(p_aplicar_feriados=1,C11<>""),0,B11) -> 1 | E11: ESTIMADO
A12: 45668 | B12: 0 | D12: =IF(AND(p_aplicar_feriados=1,C12<>""),0,B12) -> 0 | E12: ESTIMADO
A13: 45669 | B13: 0 | D13: =IF(AND(p_aplicar_feriados=1,C13<>""),0,B13) -> 0 | E13: ESTIMADO
A14: 45670 | B14: 1 | D14: =IF(AND(p_aplicar_feriados=1,C14<>""),0,B14) -> 1 | E14: ESTIMADO
... A107: 45763 | B107: 1 | D107: =IF(AND(p_aplicar_feriados=1,C107<>""),0,B107) -> 1 | E107: ESTIMADO
A108: 45764 | B108: 1 | C108: Jueves Santo | D108: =IF(AND(p_aplicar_feriados=1,C108<>""),0,B108) -> 1 | E108: ESTIMADO
A109: 45765 | B109: 1 | C109: Viernes Santo | D109: =IF(AND(p_aplicar_feriados=1,C109<>""),0,B109) -> 1 | E109: ESTIMADO
A110: 45766 | B110: 0 | D110: =IF(AND(p_aplicar_feriados=1,C110<>""),0,B110) -> 0 | E110: ESTIMADO
A111: 45767 | B111: 0 | D111: =IF(AND(p_aplicar_feriados=1,C111<>""),0,B111) -> 0 | E111: ESTIMADO
A112: 45768 | B112: 1 | D112: =IF(AND(p_aplicar_feriados=1,C112<>""),0,B112) -> 1 | E112: ESTIMADO
A113: 45769 | B113: 1 | D113: =IF(AND(p_aplicar_feriados=1,C113<>""),0,B113) -> 1 | E113: ESTIMADO
A114: 45770 | B114: 1 | D114: =IF(AND(p_aplicar_feriados=1,C114<>""),0,B114) -> 1 | E114: ESTIMADO
A115: 45771 | B115: 1 | D115: =IF(AND(p_aplicar_feriados=1,C115<>""),0,B115) -> 1 | E115: ESTIMADO
A116: 45772 | B116: 1 | D116: =IF(AND(p_aplicar_feriados=1,C116<>""),0,B116) -> 1 | E116: ESTIMADO
A117: 45773 | B117: 0 | D117: =IF(AND(p_aplicar_feriados=1,C117<>""),0,B117) -> 0 | E117: ESTIMADO
A118: 45774 | B118: 0 | D118: =IF(AND(p_aplicar_feriados=1,C118<>""),0,B118) -> 0 | E118: ESTIMADO
A119: 45775 | B119: 1 | D119: =IF(AND(p_aplicar_feriados=1,C119<>""),0,B119) -> 1 | E119: ESTIMADO
A120: 45776 | B120: 1 | D120: =IF(AND(p_aplicar_feriados=1,C120<>""),0,B120) -> 1 | E120: ESTIMADO
A121: 45777 | B121: 1 | D121: =IF(AND(p_aplicar_feriados=1,C121<>""),0,B121) -> 1 | E121: ESTIMADO
A122: 45778 | B122: 1 | C122: Día del Trabajo | D122: =IF(AND(p_aplicar_feriados=1,C122<>""),0,B122) -> 1 | E122: ESTIMADO
A123: 45779 | B123: 1 | D123: =IF(AND(p_aplicar_feriados=1,C123<>""),0,B123) -> 1 | E123: ESTIMADO
A124: 45780 | B124: 0 | D124: =IF(AND(p_aplicar_feriados=1,C124<>""),0,B124) -> 0 | E124: ESTIMADO
A125: 45781 | B125: 0 | D125: =IF(AND(p_aplicar_feriados=1,C125<>""),0,B125) -> 0 | E125: ESTIMADO
A126: 45782 | B126: 1 | D126: =IF(AND(p_aplicar_feriados=1,C126<>""),0,B126) -> 1 | E126: ESTIMADO
A127: 45783 | B127: 1 | D127: =IF(AND(p_aplicar_feriados=1,C127<>""),0,B127) -> 1 | E127: ESTIMADO
A128: 45784 | B128: 1 | D128: =IF(AND(p_aplicar_feriados=1,C128<>""),0,B128) -> 1 | E128: ESTIMADO
A129: 45785 | B129: 1 | D129: =IF(AND(p_aplicar_feriados=1,C129<>""),0,B129) -> 1 | E129: ESTIMADO
A130: 45786 | B130: 1 | D130: =IF(AND(p_aplicar_feriados=1,C130<>""),0,B130) -> 1 | E130: ESTIMADO
A131: 45787 | B131: 0 | D131: =IF(AND(p_aplicar_feriados=1,C131<>""),0,B131) -> 0 | E131: ESTIMADO
A132: 45788 | B132: 0 | D132: =IF(AND(p_aplicar_feriados=1,C132<>""),0,B132) -> 0 | E132: ESTIMADO
A133: 45789 | B133: 1 | D133: =IF(AND(p_aplicar_feriados=1,C133<>""),0,B133) -> 1 | E133: ESTIMADO
A134: 45790 | B134: 1 | D134: =IF(AND(p_aplicar_feriados=1,C134<>""),0,B134) -> 1 | E134: ESTIMADO
... A158: 45814 | B158: 1 | D158: =IF(AND(p_aplicar_feriados=1,C158<>""),0,B158) -> 1 | E158: ESTIMADO
A159: 45815 | B159: 0 | C159: Batalla de Arica y Día de la Bandera | D159: =IF(AND(p_aplicar_feriados=1,C159<>""),0,B159) -> 0 | E159: ESTIMADO
A160: 45816 | B160: 0 | D160: =IF(AND(p_aplicar_feriados=1,C160<>""),0,B160) -> 0 | E160: ESTIMADO
A161: 45817 | B161: 1 | D161: =IF(AND(p_aplicar_feriados=1,C161<>""),0,B161) -> 1 | E161: ESTIMADO
A162: 45818 | B162: 1 | D162: =IF(AND(p_aplicar_feriados=1,C162<>""),0,B162) -> 1 | E162: ESTIMADO
A163: 45819 | B163: 1 | D163: =IF(AND(p_aplicar_feriados=1,C163<>""),0,B163) -> 1 | E163: ESTIMADO
A164: 45820 | B164: 1 | D164: =IF(AND(p_aplicar_feriados=1,C164<>""),0,B164) -> 1 | E164: ESTIMADO
A165: 45821 | B165: 1 | D165: =IF(AND(p_aplicar_feriados=1,C165<>""),0,B165) -> 1 | E165: ESTIMADO
A166: 45822 | B166: 0 | D166: =IF(AND(p_aplicar_feriados=1,C166<>""),0,B166) -> 0 | E166: ESTIMADO
A167: 45823 | B167: 0 | D167: =IF(AND(p_aplicar_feriados=1,C167<>""),0,B167) -> 0 | E167: ESTIMADO
A168: 45824 | B168: 1 | D168: =IF(AND(p_aplicar_feriados=1,C168<>""),0,B168) -> 1 | E168: ESTIMADO
A169: 45825 | B169: 1 | D169: =IF(AND(p_aplicar_feriados=1,C169<>""),0,B169) -> 1 | E169: ESTIMADO
A170: 45826 | B170: 1 | D170: =IF(AND(p_aplicar_feriados=1,C170<>""),0,B170) -> 1 | E170: ESTIMADO
A171: 45827 | B171: 1 | D171: =IF(AND(p_aplicar_feriados=1,C171<>""),0,B171) -> 1 | E171: ESTIMADO
... A180: 45836 | B180: 0 | D180: =IF(AND(p_aplicar_feriados=1,C180<>""),0,B180) -> 0 | E180: ESTIMADO
A181: 45837 | B181: 0 | C181: San Pedro y San Pablo | D181: =IF(AND(p_aplicar_feriados=1,C181<>""),0,B181) -> 0 | E181: ESTIMADO
A182: 45838 | B182: 1 | D182: =IF(AND(p_aplicar_feriados=1,C182<>""),0,B182) -> 1 | E182: ESTIMADO
A183: 45839 | B183: 1 | D183: =IF(AND(p_aplicar_feriados=1,C183<>""),0,B183) -> 1 | E183: ESTIMADO
A184: 45840 | B184: 1 | D184: =IF(AND(p_aplicar_feriados=1,C184<>""),0,B184) -> 1 | E184: ESTIMADO
A185: 45841 | B185: 1 | D185: =IF(AND(p_aplicar_feriados=1,C185<>""),0,B185) -> 1 | E185: ESTIMADO
A186: 45842 | B186: 1 | D186: =IF(AND(p_aplicar_feriados=1,C186<>""),0,B186) -> 1 | E186: ESTIMADO
A187: 45843 | B187: 0 | D187: =IF(AND(p_aplicar_feriados=1,C187<>""),0,B187) -> 0 | E187: ESTIMADO
A188: 45844 | B188: 0 | D188: =IF(AND(p_aplicar_feriados=1,C188<>""),0,B188) -> 0 | E188: ESTIMADO
A189: 45845 | B189: 1 | D189: =IF(AND(p_aplicar_feriados=1,C189<>""),0,B189) -> 1 | E189: ESTIMADO
A190: 45846 | B190: 1 | D190: =IF(AND(p_aplicar_feriados=1,C190<>""),0,B190) -> 1 | E190: ESTIMADO
A191: 45847 | B191: 1 | D191: =IF(AND(p_aplicar_feriados=1,C191<>""),0,B191) -> 1 | E191: ESTIMADO
A192: 45848 | B192: 1 | D192: =IF(AND(p_aplicar_feriados=1,C192<>""),0,B192) -> 1 | E192: ESTIMADO
A193: 45849 | B193: 1 | D193: =IF(AND(p_aplicar_feriados=1,C193<>""),0,B193) -> 1 | E193: ESTIMADO
... A204: 45860 | B204: 1 | D204: =IF(AND(p_aplicar_feriados=1,C204<>""),0,B204) -> 1 | E204: ESTIMADO
A205: 45861 | B205: 1 | C205: Día de la Fuerza Aérea del Perú | D205: =IF(AND(p_aplicar_feriados=1,C205<>""),0,B205) -> 1 | E205: ESTIMADO
A206: 45862 | B206: 1 | D206: =IF(AND(p_aplicar_feriados=1,C206<>""),0,B206) -> 1 | E206: ESTIMADO
A207: 45863 | B207: 1 | D207: =IF(AND(p_aplicar_feriados=1,C207<>""),0,B207) -> 1 | E207: ESTIMADO
A208: 45864 | B208: 0 | D208: =IF(AND(p_aplicar_feriados=1,C208<>""),0,B208) -> 0 | E208: ESTIMADO
A209: 45865 | B209: 0 | D209: =IF(AND(p_aplicar_feriados=1,C209<>""),0,B209) -> 0 | E209: ESTIMADO
A210: 45866 | B210: 1 | C210: Fiestas Patrias | D210: =IF(AND(p_aplicar_feriados=1,C210<>""),0,B210) -> 1 | E210: ESTIMADO
A211: 45867 | B211: 1 | C211: Fiestas Patrias | D211: =IF(AND(p_aplicar_feriados=1,C211<>""),0,B211) -> 1 | E211: ESTIMADO
A212: 45868 | B212: 1 | D212: =IF(AND(p_aplicar_feriados=1,C212<>""),0,B212) -> 1 | E212: ESTIMADO
A213: 45869 | B213: 1 | D213: =IF(AND(p_aplicar_feriados=1,C213<>""),0,B213) -> 1 | E213: ESTIMADO
A214: 45870 | B214: 1 | D214: =IF(AND(p_aplicar_feriados=1,C214<>""),0,B214) -> 1 | E214: ESTIMADO
A215: 45871 | B215: 0 | D215: =IF(AND(p_aplicar_feriados=1,C215<>""),0,B215) -> 0 | E215: ESTIMADO
A216: 45872 | B216: 0 | D216: =IF(AND(p_aplicar_feriados=1,C216<>""),0,B216) -> 0 | E216: ESTIMADO
A217: 45873 | B217: 1 | D217: =IF(AND(p_aplicar_feriados=1,C217<>""),0,B217) -> 1 | E217: ESTIMADO
A218: 45874 | B218: 1 | D218: =IF(AND(p_aplicar_feriados=1,C218<>""),0,B218) -> 1 | E218: ESTIMADO
A219: 45875 | B219: 1 | C219: Batalla de Junín | D219: =IF(AND(p_aplicar_feriados=1,C219<>""),0,B219) -> 1 | E219: ESTIMADO
A220: 45876 | B220: 1 | D220: =IF(AND(p_aplicar_feriados=1,C220<>""),0,B220) -> 1 | E220: ESTIMADO
A221: 45877 | B221: 1 | D221: =IF(AND(p_aplicar_feriados=1,C221<>""),0,B221) -> 1 | E221: ESTIMADO
A222: 45878 | B222: 0 | D222: =IF(AND(p_aplicar_feriados=1,C222<>""),0,B222) -> 0 | E222: ESTIMADO
A223: 45879 | B223: 0 | D223: =IF(AND(p_aplicar_feriados=1,C223<>""),0,B223) -> 0 | E223: ESTIMADO
A224: 45880 | B224: 1 | D224: =IF(AND(p_aplicar_feriados=1,C224<>""),0,B224) -> 1 | E224: ESTIMADO
A225: 45881 | B225: 1 | D225: =IF(AND(p_aplicar_feriados=1,C225<>""),0,B225) -> 1 | E225: ESTIMADO
A226: 45882 | B226: 1 | D226: =IF(AND(p_aplicar_feriados=1,C226<>""),0,B226) -> 1 | E226: ESTIMADO
A227: 45883 | B227: 1 | D227: =IF(AND(p_aplicar_feriados=1,C227<>""),0,B227) -> 1 | E227: ESTIMADO
A228: 45884 | B228: 1 | D228: =IF(AND(p_aplicar_feriados=1,C228<>""),0,B228) -> 1 | E228: ESTIMADO
A229: 45885 | B229: 0 | D229: =IF(AND(p_aplicar_feriados=1,C229<>""),0,B229) -> 0 | E229: ESTIMADO
A230: 45886 | B230: 0 | D230: =IF(AND(p_aplicar_feriados=1,C230<>""),0,B230) -> 0 | E230: ESTIMADO
A231: 45887 | B231: 1 | D231: =IF(AND(p_aplicar_feriados=1,C231<>""),0,B231) -> 1 | E231: ESTIMADO
... A242: 45898 | B242: 1 | D242: =IF(AND(p_aplicar_feriados=1,C242<>""),0,B242) -> 1 | E242: ESTIMADO
A243: 45899 | B243: 0 | C243: Santa Rosa de Lima | D243: =IF(AND(p_aplicar_feriados=1,C243<>""),0,B243) -> 0 | E243: ESTIMADO
...

Sheet 08_PEDIDOS
A1: Pedido | B1: Producto | C1: Familia | D1: Unidades | E1: Recepción 2025 | F1: Liberación 2025 | G1: Compromiso 2025 | H1: Lote | I1: Clasificación | J1: Precio familiar S/ | K1: Valor pedido S/ | L1: Penalidad fija S/ | M1: Plazo días | N1: Horas de proceso (ruta principal) | O1: Horas productivas disponibles r→d | P1: Ruta excede ventana (1/0) | Q1: Fecha en fin de semana (1/0) | R1: Producto válido (1/0) | S1: Naturaleza
A2: P001 | B2: Minirack metálico con bandejas | C2: Racks industriales | D2: 12 | E2: 45660 | F2: 45660 | G2: 45677 | H2: 10 | I2: SIMULADO | J2: =INDEX('12_PRECIOS'!$D$2:$D$5,MATCH(C2,'12_PRECIOS'!$A$2:$A$5,0)) -> 2650.49 | K2: =J2*D2 -> 31805.88 | L2: =K2*INDEX('12_PRECIOS'!$E$2:$E$5,MATCH(C2,'12_PRECIOS'!$A$2:$A$5,0)) -> 3180.588 | M2: =G2-E2 -> 17 | N2: =SUMIF('09_CARGA_ORDEN'!$A$2:$A$1153,A2,'09_CARGA_ORDEN'!$J$2:$J$1153) -> 90.66696 | O2: =SUMPRODUCT(('07_CALENDARIO'!$A$2:$A$397>=F2)*('07_CALENDARIO'!$A$2:$A$397<=G2)*'07_CALENDARIO'!$D$2:$D$397)*p_horas_productivas_dia -> 96 | P2: =IF(N2>O2+0.000001,1,0) -> 0 | Q2: =IF(OR(WEEKDAY(F2,2)>5,WEEKDAY(G2,2)>5),1,0) -> 0 | R2: =IF(COUNTIF('01_PRODUCTOS'!$B$2:$B$51,B2)>0,1,0) -> 1 | S2: SIMULADO
A3: P002 | B3: Estante reforzado modular | C3: Racks industriales | D3: 12 | E3: 45673 | F3: 45673 | G3: 45691 | H3: 10 | I3: SIMULADO | J3: =INDEX('12_PRECIOS'!$D$2:$D$5,MATCH(C3,'12_PRECIOS'!$A$2:$A$5,0)) -> 2650.49 | K3: =J3*D3 -> 31805.88 | L3: =K3*INDEX('12_PRECIOS'!$E$2:$E$5,MATCH(C3,'12_PRECIOS'!$A$2:$A$5,0)) -> 3180.588 | M3: =G3-E3 -> 18 | N3: =SUMIF('09_CARGA_ORDEN'!$A$2:$A$1153,A3,'09_CARGA_ORDEN'!$J$2:$J$1153) -> 100.7708 | O3: =SUMPRODUCT(('07_CALENDARIO'!$A$2:$A$397>=F3)*('07_CALENDARIO'!$A$2:$A$397<=G3)*'07_CALENDARIO'!$D$2:$D$397)*p_horas_productivas_dia -> 104 | P3: =IF(N3>O3+0.000001,1,0) -> 0 | Q3: =IF(OR(WEEKDAY(F3,2)>5,WEEKDAY(G3,2)>5),1,0) -> 0 | R3: =IF(COUNTIF('01_PRODUCTOS'!$B$2:$B$51,B3)>0,1,0) -> 1 | S3: SIMULADO
A4: P003 | B4: Góndola central comercial | C4: Góndolas comerciales | D4: 7 | E4: 45660 | F4: 45660 | G4: 45675 | H4: 10 | I4: SIMULADO | J4: =INDEX('12_PRECIOS'!$D$2:$D$5,MATCH(C4,'12_PRECIOS'!$A$2:$A$5,0)) -> 2150.57 | K4: =J4*D4 -> 15053.99 | L4: =K4*INDEX('12_PRECIOS'!$E$2:$E$5,MATCH(C4,'12_PRECIOS'!$A$2:$A$5,0)) -> 1505.399 | M4: =G4-E4 -> 15 | N4: =SUMIF('09_CARGA_ORDEN'!$A$2:$A$1153,A4,'09_CARGA_ORDEN'!$J$2:$J$1153) -> 68.444107 | O4: =SUMPRODUCT(('07_CALENDARIO'!$A$2:$A$397>=F4)*('07_CALENDARIO'!$A$2:$A$397<=G4)*'07_CALENDARIO'!$D$2:$D$397)*p_horas_productivas_dia -> 88 | P4: =IF(N4>O4+0.000001,1,0) -> 0 | Q4: =IF(OR(WEEKDAY(F4,2)>5,WEEKDAY(G4,2)>5),1,0) -> 1 | R4: =IF(COUNTIF('01_PRODUCTOS'!$B$2:$B$51,B4)>0,1,0) -> 1 | S4: SIMULADO
A5: P004 | B5: Góndola mural | C5: Góndolas comerciales | D5: 7 | E5: 45673 | F5: 45673 | G5: 45689 | H5: 10 | I5: SIMULADO | J5: =INDEX('12_PRECIOS'!$D$2:$D$5,MATCH(C5,'12_PRECIOS'!$A$2:$A$5,0)) -> 2150.57 | K5: =J5*D5 -> 15053.99 | L5: =K5*INDEX('12_PRECIOS'!$E$2:$E$5,MATCH(C5,'12_PRECIOS'!$A$2:$A$5,0)) -> 1505.399 | M5: =G5-E5 -> 16 | N5: =SUMIF('09_CARGA_ORDEN'!$A$2:$A$1153,A5,'09_CARGA_ORDEN'!$J$2:$J$1153) -> 47.37639 | O5: =SUMPRODUCT(('07_CALENDARIO'!$A$2:$A$397>=F5)*('07_CALENDARIO'!$A$2:$A$397<=G5)*'07_CALENDARIO'!$D$2:$D$397)*p_horas_productivas_dia -> 96 | P5: =IF(N5>O5+0.000001,1,0) -> 0 | Q5: =IF(OR(WEEKDAY(F5,2)>5,WEEKDAY(G5,2)>5),1,0) -> 1 | R5: =IF(COUNTIF('01_PRODUCTOS'!$B$2:$B$51,B5)>0,1,0) -> 1 | S5: SIMULADO
A6: P005 | B6: Locker de 4 puertas | C6: Lockers metálicos | D6: 6 | E6: 45660 | F6: 45660 | G6: 45674 | H6: 10 | I6: SIMULADO | J6: =INDEX('12_PRECIOS'!$D$2:$D$5,MATCH(C6,'12_PRECIOS'!$A$2:$A$5,0)) -> 1800.81 | K6: =J6*D6 -> 10804.86 | L6: =K6*INDEX('12_PRECIOS'!$E$2:$E$5,MATCH(C6,'12_PRECIOS'!$A$2:$A$5,0)) -> 1080.486 | M6: =G6-E6 -> 14 | N6: =SUMIF('09_CARGA_ORDEN'!$A$2:$A$1153,A6,'09_CARGA_ORDEN'!$J$2:$J$1153) -> 28.1919 | O6: =SUMPRODUCT(('07_CALENDARIO'!$A$2:$A$397>=F6)*('07_CALENDARIO'!$A$2:$A$397<=G6)*'07_CALENDARIO'!$D$2:$D$397)*p_horas_productivas_dia -> 88 | P6: =IF(N6>O6+0.000001,1,0) -> 0 | Q6: =IF(OR(WEEKDAY(F6,2)>5,WEEKDAY(G6,2)>5),1,0) -> 0 | R6: =IF(COUNTIF('01_PRODUCTOS'!$B$2:$B$51,B6)>0,1,0) -> 1 | S6: SIMULADO
A7: P006 | B7: Locker de 6 puertas | C7: Lockers metálicos | D7: 6 | E7: 45673 | F7: 45673 | G7: 45688 | H7: 10 | I7: SIMULADO | J7: =INDEX('12_PRECIOS'!$D$2:$D$5,MATCH(C7,'12_PRECIOS'!$A$2:$A$5,0)) -> 1800.81 | K7: =J7*D7 -> 10804.86 | L7: =K7*INDEX('12_PRECIOS'!$E$2:$E$5,MATCH(C7,'12_PRECIOS'!$A$2:$A$5,0)) -> 1080.486 | M7: =G7-E7 -> 15 | N7: =SUMIF('09_CARGA_ORDEN'!$A$2:$A$1153,A7,'09_CARGA_ORDEN'!$J$2:$J$1153) -> 38.8968 | O7: =SUMPRODUCT(('07_CALENDARIO'!$A$2:$A$397>=F7)*('07_CALENDARIO'!$A$2:$A$397<=G7)*'07_CALENDARIO'!$D$2:$D$397)*p_horas_productivas_dia -> 96 | P7: =IF(N7>O7+0.000001,1,0) -> 0 | Q7: =IF(OR(WEEKDAY(F7,2)>5,WEEKDAY(G7,2)>5),1,0) -> 0 | R7: =IF(COUNTIF('01_PRODUCTOS'!$B$2:$B$51,B7)>0,1,0) -> 1 | S7: SIMULADO
A8: P007 | B8: Armario metálico | C8: Otros productos metalmecánicos | D8: 10 | E8: 45660 | F8: 45660 | G8: 45675 | H8: 10 | I8: SIMULADO | J8: =INDEX('12_PRECIOS'!$D$2:$D$5,MATCH(C8,'12_PRECIOS'!$A$2:$A$5,0)) -> 2322.4698 | K8: =J8*D8 -> 23224.698 | L8: =K8*INDEX('12_PRECIOS'!$E$2:$E$5,MATCH(C8,'12_PRECIOS'!$A$2:$A$5,0)) -> 2322.4698 | M8: =G8-E8 -> 15 | N8: =SUMIF('09_CARGA_ORDEN'!$A$2:$A$1153,A8,'09_CARGA_ORDEN'!$J$2:$J$1153) -> 37.255333 | O8: =SUMPRODUCT(('07_CALENDARIO'!$A$2:$A$397>=F8)*('07_CALENDARIO'!$A$2:$A$397<=G8)*'07_CALENDARIO'!$D$2:$D$397)*p_horas_productivas_dia -> 88 | P8: =IF(N8>O8+0.000001,1,0) -> 0 | Q8: =IF(OR(WEEKDAY(F8,2)>5,WEEKDAY(G8,2)>5),1,0) -> 1 | R8: =IF(COUNTIF('01_PRODUCTOS'!$B$2:$B$51,B8)>0,1,0) -> 1 | S8: SIMULADO
A9: P008 | B9: Estantería liviana metálica | C9: Otros productos metalmecánicos | D9: 10 | E9: 45673 | F9: 45673 | G9: 45689 | H9: 10 | I9: SIMULADO | J9: =INDEX('12_PRECIOS'!$D$2:$D$5,MATCH(C9,'12_PRECIOS'!$A$2:$A$5,0)) -> 2322.4698 | K9: =J9*D9 -> 23224.698 | L9: =K9*INDEX('12_PRECIOS'!$E$2:$E$5,MATCH(C9,'12_PRECIOS'!$A$2:$A$5,0)) -> 2322.4698 | M9: =G9-E9 -> 16 | N9: =SUMIF('09_CARGA_ORDEN'!$A$2:$A$1153,A9,'09_CARGA_ORDEN'!$J$2:$J$1153) -> 60.122533 | O9: =SUMPRODUCT(('07_CALENDARIO'!$A$2:$A$397>=F9)*('07_CALENDARIO'!$A$2:$A$397<=G9)*'07_CALENDARIO'!$D$2:$D$397)*p_horas_productivas_dia -> 96 | P9: =IF(N9>O9+0.000001,1,0) -> 0 | Q9: =IF(OR(WEEKDAY(F9,2)>5,WEEKDAY(G9,2)>5),1,0) -> 1 | R9: =IF(COUNTIF('01_PRODUCTOS'!$B$2:$B$51,B9)>0,1,0) -> 1 | S9: SIMULADO
A10: P009 | B10: Minirack metálico con bandejas | C10: Racks industriales | D10: 12 | E10: 45691 | F10: 45691 | G10: 45708 | H10: 10 | I10: SIMULADO | J10: =INDEX('12_PRECIOS'!$D$2:$D$5,MATCH(C10,'12_PRECIOS'!$A$2:$A$5,0)) -> 2650.49 | K10: =J10*D10 -> 31805.88 | L10: =K10*INDEX('12_PRECIOS'!$E$2:$E$5,MATCH(C10,'12_PRECIOS'!$A$2:$A$5,0)) -> 3180.588 | M10: =G10-E10 -> 17 | N10: =SUMIF('09_CARGA_ORDEN'!$A$2:$A$1153,A10,'09_CARGA_ORDEN'!$J$2:$J$1153) -> 90.66696 | O10: =SUMPRODUCT(('07_CALENDARIO'!$A$2:$A$397>=F10)*('07_CALENDARIO'!$A$2:$A$397<=G10)*'07_CALENDARIO'!$D$2:$D$397)*p_horas_productivas_dia -> 112 | P10: =IF(N10>O10+0.000001,1,0) -> 0 | Q10: =IF(OR(WEEKDAY(F10,2)>5,WEEKDAY(G10,2)>5),1,0) -> 0 | R10: =IF(COUNTIF('01_PRODUCTOS'!$B$2:$B$51,B10)>0,1,0) -> 1 | S10: SIMULADO
A11: P010 | B11: Estante reforzado modular | C11: Racks industriales | D11: 12 | E11: 45704 | F11: 45704 | G11: 45722 | H11: 10 | I11: SIMULADO | J11: =INDEX('12_PRECIOS'!$D$2:$D$5,MATCH(C11,'12_PRECIOS'!$A$2:$A$5,0)) -> 2650.49 | K11: =J11*D11 -> 31805.88 | L11: =K11*INDEX('12_PRECIOS'!$E$2:$E$5,MATCH(C11,'12_PRECIOS'!$A$2:$A$5,0)) -> 3180.588 | M11: =G11-E11 -> 18 | N11: =SUMIF('09_CARGA_ORDEN'!$A$2:$A$1153,A11,'09_CARGA_ORDEN'!$J$2:$J$1153) -> 100.7708 | O11: =SUMPRODUCT(('07_CALENDARIO'!$A$2:$A$397>=F11)*('07_CALENDARIO'!$A$2:$A$397<=G11)*'07_CALENDARIO'!$D$2:$D$397)*p_horas_productivas_dia -> 112 | P11: =IF(N11>O11+0.000001,1,0) -> 0 | Q11: =IF(OR(WEEKDAY(F11,2)>5,WEEKDAY(G11,2)>5),1,0) -> 1 | R11: =IF(COUNTIF('01_PRODUCTOS'!$B$2:$B$51,B11)>0,1,0) -> 1 | S11: SIMULADO
A12: P011 | B12: Góndola central comercial | C12: Góndolas comerciales | D12: 7 | E12: 45691 | F12: 45691 | G12: 45706 | H12: 10 | I12: SIMULADO | J12: =INDEX('12_PRECIOS'!$D$2:$D$5,MATCH(C12,'12_PRECIOS'!$A$2:$A$5,0)) -> 2150.57 | K12: =J12*D12 -> 15053.99 | L12: =K12*INDEX('12_PRECIOS'!$E$2:$E$5,MATCH(C12,'12_PRECIOS'!$A$2:$A$5,0)) -> 1505.399 | M12: =G12-E12 -> 15 | N12: =SUMIF('09_CARGA_ORDEN'!$A$2:$A$1153,A12,'09_CARGA_ORDEN'!$J$2:$J$1153) -> 68.444107 | O12: =SUMPRODUCT(('07_CALENDARIO'!$A$2:$A$397>=F12)*('07_CALENDARIO'!$A$2:$A$397<=G12)*'07_CALENDARIO'!$D$2:$D$397)*p_horas_productivas_dia -> 96 | P12: =IF(N12>O12+0.000001,1,0) -> 0 | Q12: =IF(OR(WEEKDAY(F12,2)>5,WEEKDAY(G12,2)>5),1,0) -> 0 | R12: =IF(COUNTIF('01_PRODUCTOS'!$B$2:$B$51,B12)>0,1,0) -> 1 | S12: SIMULADO
A13: P012 | B13: Góndola mural | C13: Góndolas comerciales | D13: 7 | E13: 45704 | F13: 45704 | G13: 45720 | H13: 10 | I13: SIMULADO | J13: =INDEX('12_PRECIOS'!$D$2:$D$5,MATCH(C13,'12_PRECIOS'!$A$2:$A$5,0)) -> 2150.57 | K13: =J13*D13 -> 15053.99 | L13: =K13*INDEX('12_PRECIOS'!$E$2:$E$5,MATCH(C13,'12_PRECIOS'!$A$2:$A$5,0)) -> 1505.399 | M13: =G13-E13 -> 16 | N13: =SUMIF('09_CARGA_ORDEN'!$A$2:$A$1153,A13,'09_CARGA_ORDEN'!$J$2:$J$1153) -> 47.37639 | O13: =SUMPRODUCT(('07_CALENDARIO'!$A$2:$A$397>=F13)*('07_CALENDARIO'!$A$2:$A$397<=G13)*'07_CALENDARIO'!$D$2:$D$397)*p_horas_productivas_dia -> 96 | P13: =IF(N13>O13+0.000001,1,0) -> 0 | Q13: =IF(OR(WEEKDAY(F13,2)>5,WEEKDAY(G13,2)>5),1,0) -> 1 | R13: =IF(COUNTIF('01_PRODUCTOS'!$B$2:$B$51,B13)>0,1,0) -> 1 | S13: SIMULADO
... A97: P096 | B97: Estantería liviana metálica | C97: Otros productos metalmecánicos | D97: 10 | E97: 46007 | F97: 46007 | G97: 46023 | H97: 10 | I97: SIMULADO | J97: =INDEX('12_PRECIOS'!$D$2:$D$5,MATCH(C97,'12_PRECIOS'!$A$2:$A$5,0)) -> 2322.4698 | K97: =J97*D97 -> 23224.698 | L97: =K97*INDEX('12_PRECIOS'!$E$2:$E$5,MATCH(C97,'12_PRECIOS'!$A$2:$A$5,0)) -> 2322.4698 | M97: =G97-E97 -> 16 | N97: =SUMIF('09_CARGA_ORDEN'!$A$2:$A$1153,A97,'09_CARGA_ORDEN'!$J$2:$J$1153) -> 60.122533 | O97: =SUMPRODUCT(('07_CALENDARIO'!$A$2:$A$397>=F97)*('07_CALENDARIO'!$A$2:$A$397<=G97)*'07_CALENDARIO'!$D$2:$D$397)*p_horas_productivas_dia -> 104 | P97: =IF(N97>O97+0.000001,1,0) -> 0 | Q97: =IF(OR(WEEKDAY(F97,2)>5,WEEKDAY(G97,2)>5),1,0) -> 0 | R97: =IF(COUNTIF('01_PRODUCTOS'!$B$2:$B$51,B97)>0,1,0) -> 1 | S97: SIMULADO

Sheet 09_CARGA_ORDEN
A1: Pedido | B1: Producto | C1: Paso | D1: Operación | E1: Equipo | F1: Cantidad | G1: Lote | H1: Min fijo/lote | I1: Min unidad | J1: Horas requeridas | K1: Mes | L1: Costo máquina S/ (tarifa 04) | M1: Energía kWh (04) | N1: Naturaleza
A2: P001 | B2: Minirack metálico con bandejas | C2: 1 | D2: Corte de planchas de acero | E2: Guillotina hidráulica para corte de planchas de acero | F2: =INDEX('08_PEDIDOS'!$D$2:$D$97,MATCH(A2,'08_PEDIDOS'!$A$2:$A$97,0)) -> 12 | G2: =INDEX('08_PEDIDOS'!$H$2:$H$97,MATCH(A2,'08_PEDIDOS'!$A$2:$A$97,0)) -> 10 | H2: =SUMIFS('05_RUTAS'!$F$2:$F$407,'05_RUTAS'!$A$2:$A$407,B2,'05_RUTAS'!$C$2:$C$407,C2) -> 8 | I2: =SUMIFS('05_RUTAS'!$G$2:$G$407,'05_RUTAS'!$A$2:$A$407,B2,'05_RUTAS'!$C$2:$C$407,C2) -> 34.62 | J2: =(ROUNDUP(F2/G2,0)*H2+F2*I2)/60 -> 7.1906667 | K2: =MONTH(INDEX('08_PEDIDOS'!$F$2:$F$97,MATCH(A2,'08_PEDIDOS'!$A$2:$A$97,0))) -> 1 | L2: =J2*N(INDEX('04_MAQUINAS'!$F$2:$F$18,MATCH(E2,'04_MAQUINAS'!$A$2:$A$18,0))) -> 172.576 | M2: =J2*INDEX('04_MAQUINAS'!$G$2:$G$18,MATCH(E2,'04_MAQUINAS'!$A$2:$A$18,0))*INDEX('04_MAQUINAS'!$H$2:$H$18,MATCH(E2,'04_MAQUINAS'!$A$2:$A$18,0)) -> 19.774333 | N2: CALCULADO
A3: P001 | B3: Minirack metálico con bandejas | C3: 2 | D3: Corte de tubos y perfiles | E3: Sierra de cinta para corte de tubos y perfiles | F3: =INDEX('08_PEDIDOS'!$D$2:$D$97,MATCH(A3,'08_PEDIDOS'!$A$2:$A$97,0)) -> 12 | G3: =INDEX('08_PEDIDOS'!$H$2:$H$97,MATCH(A3,'08_PEDIDOS'!$A$2:$A$97,0)) -> 10 | H3: =SUMIFS('05_RUTAS'!$F$2:$F$407,'05_RUTAS'!$A$2:$A$407,B3,'05_RUTAS'!$C$2:$C$407,C3) -> 8 | I3: =SUMIFS('05_RUTAS'!$G$2:$G$407,'05_RUTAS'!$A$2:$A$407,B3,'05_RUTAS'!$C$2:$C$407,C3) -> 43.52 | J3: =(ROUNDUP(F3/G3,0)*H3+F3*I3)/60 -> 8.9706667 | K3: =MONTH(INDEX('08_PEDIDOS'!$F$2:$F$97,MATCH(A3,'08_PEDIDOS'!$A$2:$A$97,0))) -> 1 | L3: =J3*N(INDEX('04_MAQUINAS'!$F$2:$F$18,MATCH(E3,'04_MAQUINAS'!$A$2:$A$18,0))) -> 197.35467 | M3: =J3*INDEX('04_MAQUINAS'!$G$2:$G$18,MATCH(E3,'04_MAQUINAS'!$A$2:$A$18,0))*INDEX('04_MAQUINAS'!$H$2:$H$18,MATCH(E3,'04_MAQUINAS'!$A$2:$A$18,0)) -> 4.0368 | N3: CALCULADO
A4: P001 | B4: Minirack metálico con bandejas | C4: 3 | D4: Perforación | E4: Taladro de banco para perforación de acero | F4: =INDEX('08_PEDIDOS'!$D$2:$D$97,MATCH(A4,'08_PEDIDOS'!$A$2:$A$97,0)) -> 12 | G4: =INDEX('08_PEDIDOS'!$H$2:$H$97,MATCH(A4,'08_PEDIDOS'!$A$2:$A$97,0)) -> 10 | H4: =SUMIFS('05_RUTAS'!$F$2:$F$407,'05_RUTAS'!$A$2:$A$407,B4,'05_RUTAS'!$C$2:$C$407,C4) -> 10 | I4: =SUMIFS('05_RUTAS'!$G$2:$G$407,'05_RUTAS'!$A$2:$A$407,B4,'05_RUTAS'!$C$2:$C$407,C4) -> 63.2 | J4: =(ROUNDUP(F4/G4,0)*H4+F4*I4)/60 -> 12.973333 | K4: =MONTH(INDEX('08_PEDIDOS'!$F$2:$F$97,MATCH(A4,'08_PEDIDOS'!$A$2:$A$97,0))) -> 1 | L4: =J4*N(INDEX('04_MAQUINAS'!$F$2:$F$18,MATCH(E4,'04_MAQUINAS'!$A$2:$A$18,0))) -> 285.41333 | M4: =J4*INDEX('04_MAQUINAS'!$G$2:$G$18,MATCH(E4,'04_MAQUINAS'!$A$2:$A$18,0))*INDEX('04_MAQUINAS'!$H$2:$H$18,MATCH(E4,'04_MAQUINAS'!$A$2:$A$18,0)) -> 3.5676667 | N4: CALCULADO
A5: P001 | B5: Minirack metálico con bandejas | C5: 4 | D5: Plegado | E5: Plegadora hidráulica de chapa metálica | F5: =INDEX('08_PEDIDOS'!$D$2:$D$97,MATCH(A5,'08_PEDIDOS'!$A$2:$A$97,0)) -> 12 | G5: =INDEX('08_PEDIDOS'!$H$2:$H$97,MATCH(A5,'08_PEDIDOS'!$A$2:$A$97,0)) -> 10 | H5: =SUMIFS('05_RUTAS'!$F$2:$F$407,'05_RUTAS'!$A$2:$A$407,B5,'05_RUTAS'!$C$2:$C$407,C5) -> 12 | I5: =SUMIFS('05_RUTAS'!$G$2:$G$407,'05_RUTAS'!$A$2:$A$407,B5,'05_RUTAS'!$C$2:$C$407,C5) -> 60 | J5: =(ROUNDUP(F5/G5,0)*H5+F5*I5)/60 -> 12.4 | K5: =MONTH(INDEX('08_PEDIDOS'!$F$2:$F$97,MATCH(A5,'08_PEDIDOS'!$A$2:$A$97,0))) -> 1 | L5: =J5*N(INDEX('04_MAQUINAS'!$F$2:$F$18,MATCH(E5,'04_MAQUINAS'!$A$2:$A$18,0))) -> 347.2 | M5: =J5*INDEX('04_MAQUINAS'!$G$2:$G$18,MATCH(E5,'04_MAQUINAS'!$A$2:$A$18,0))*INDEX('04_MAQUINAS'!$H$2:$H$18,MATCH(E5,'04_MAQUINAS'!$A$2:$A$18,0)) -> 30.69 | N5: CALCULADO
A6: P001 | B6: Minirack metálico con bandejas | C6: 5 | D6: Soldadura | E6: Máquina de soldadura por arco MIG/MAG | F6: =INDEX('08_PEDIDOS'!$D$2:$D$97,MATCH(A6,'08_PEDIDOS'!$A$2:$A$97,0)) -> 12 | G6: =INDEX('08_PEDIDOS'!$H$2:$H$97,MATCH(A6,'08_PEDIDOS'!$A$2:$A$97,0)) -> 10 | H6: =SUMIFS('05_RUTAS'!$F$2:$F$407,'05_RUTAS'!$A$2:$A$407,B6,'05_RUTAS'!$C$2:$C$407,C6) -> 10 | I6: =SUMIFS('05_RUTAS'!$G$2:$G$407,'05_RUTAS'!$A$2:$A$407,B6,'05_RUTAS'!$C$2:$C$407,C6) -> 78.4 | J6: =(ROUNDUP(F6/G6,0)*H6+F6*I6)/60 -> 16.013333 | K6: =MONTH(INDEX('08_PEDIDOS'!$F$2:$F$97,MATCH(A6,'08_PEDIDOS'!$A$2:$A$97,0))) -> 1 | L6: =J6*N(INDEX('04_MAQUINAS'!$F$2:$F$18,MATCH(E6,'04_MAQUINAS'!$A$2:$A$18,0))) -> 512.42667 | M6: =J6*INDEX('04_MAQUINAS'!$G$2:$G$18,MATCH(E6,'04_MAQUINAS'!$A$2:$A$18,0))*INDEX('04_MAQUINAS'!$H$2:$H$18,MATCH(E6,'04_MAQUINAS'!$A$2:$A$18,0)) -> 28.023333 | N6: CALCULADO
A7: P001 | B7: Minirack metálico con bandejas | C7: 6 | D7: Desbarbado | E7: Mesa de desbarbado/esmerilado | F7: =INDEX('08_PEDIDOS'!$D$2:$D$97,MATCH(A7,'08_PEDIDOS'!$A$2:$A$97,0)) -> 12 | G7: =INDEX('08_PEDIDOS'!$H$2:$H$97,MATCH(A7,'08_PEDIDOS'!$A$2:$A$97,0)) -> 10 | H7: =SUMIFS('05_RUTAS'!$F$2:$F$407,'05_RUTAS'!$A$2:$A$407,B7,'05_RUTAS'!$C$2:$C$407,C7) -> 3 | I7: =SUMIFS('05_RUTAS'!$G$2:$G$407,'05_RUTAS'!$A$2:$A$407,B7,'05_RUTAS'!$C$2:$C$407,C7) -> 42 | J7: =(ROUNDUP(F7/G7,0)*H7+F7*I7)/60 -> 8.5 | K7: =MONTH(INDEX('08_PEDIDOS'!$F$2:$F$97,MATCH(A7,'08_PEDIDOS'!$A$2:$A$97,0))) -> 1 | L7: =J7*N(INDEX('04_MAQUINAS'!$F$2:$F$18,MATCH(E7,'04_MAQUINAS'!$A$2:$A$18,0))) -> 178.5 | M7: =J7*INDEX('04_MAQUINAS'!$G$2:$G$18,MATCH(E7,'04_MAQUINAS'!$A$2:$A$18,0))*INDEX('04_MAQUINAS'!$H$2:$H$18,MATCH(E7,'04_MAQUINAS'!$A$2:$A$18,0)) -> 6.375 | N7: CALCULADO
A8: P001 | B8: Minirack metálico con bandejas | C8: 7 | D8: Preparación superficial | E8: Zona de preparación superficial | F8: =INDEX('08_PEDIDOS'!$D$2:$D$97,MATCH(A8,'08_PEDIDOS'!$A$2:$A$97,0)) -> 12 | G8: =INDEX('08_PEDIDOS'!$H$2:$H$97,MATCH(A8,'08_PEDIDOS'!$A$2:$A$97,0)) -> 10 | H8: =SUMIFS('05_RUTAS'!$F$2:$F$407,'05_RUTAS'!$A$2:$A$407,B8,'05_RUTAS'!$C$2:$C$407,C8) -> 6 | I8: =SUMIFS('05_RUTAS'!$G$2:$G$407,'05_RUTAS'!$A$2:$A$407,B8,'05_RUTAS'!$C$2:$C$407,C8) -> 29.7248 | J8: =(ROUNDUP(F8/G8,0)*H8+F8*I8)/60 -> 6.14496 | K8: =MONTH(INDEX('08_PEDIDOS'!$F$2:$F$97,MATCH(A8,'08_PEDIDOS'!$A$2:$A$97,0))) -> 1 | L8: =J8*N(INDEX('04_MAQUINAS'!$F$2:$F$18,MATCH(E8,'04_MAQUINAS'!$A$2:$A$18,0))) -> 116.75424 | M8: =J8*INDEX('04_MAQUINAS'!$G$2:$G$18,MATCH(E8,'04_MAQUINAS'!$A$2:$A$18,0))*INDEX('04_MAQUINAS'!$H$2:$H$18,MATCH(E8,'04_MAQUINAS'!$A$2:$A$18,0)) -> 5.4075648 | N8: CALCULADO
A9: P001 | B9: Minirack metálico con bandejas | C9: 8 | D9: Aplicación electrostática de polvo | E9: Pistola manual de pintura electrostática en polvo | F9: =INDEX('08_PEDIDOS'!$D$2:$D$97,MATCH(A9,'08_PEDIDOS'!$A$2:$A$97,0)) -> 12 | G9: =INDEX('08_PEDIDOS'!$H$2:$H$97,MATCH(A9,'08_PEDIDOS'!$A$2:$A$97,0)) -> 10 | H9: =SUMIFS('05_RUTAS'!$F$2:$F$407,'05_RUTAS'!$A$2:$A$407,B9,'05_RUTAS'!$C$2:$C$407,C9) -> 12 | I9: =SUMIFS('05_RUTAS'!$G$2:$G$407,'05_RUTAS'!$A$2:$A$407,B9,'05_RUTAS'!$C$2:$C$407,C9) -> 8.02 | J9: =(ROUNDUP(F9/G9,0)*H9+F9*I9)/60 -> 2.004 | K9: =MONTH(INDEX('08_PEDIDOS'!$F$2:$F$97,MATCH(A9,'08_PEDIDOS'!$A$2:$A$97,0))) -> 1 | L9: =J9*N(INDEX('04_MAQUINAS'!$F$2:$F$18,MATCH(E9,'04_MAQUINAS'!$A$2:$A$18,0))) -> 64.128 | M9: =J9*INDEX('04_MAQUINAS'!$G$2:$G$18,MATCH(E9,'04_MAQUINAS'!$A$2:$A$18,0))*INDEX('04_MAQUINAS'!$H$2:$H$18,MATCH(E9,'04_MAQUINAS'!$A$2:$A$18,0)) -> 2.1042 | N9: CALCULADO
A10: P001 | B10: Minirack metálico con bandejas | C10: 9 | D10: Curado térmico en horno | E10: Horno de curado de pintura electrostática por lotes | F10: =INDEX('08_PEDIDOS'!$D$2:$D$97,MATCH(A10,'08_PEDIDOS'!$A$2:$A$97,0)) -> 12 | G10: =INDEX('08_PEDIDOS'!$H$2:$H$97,MATCH(A10,'08_PEDIDOS'!$A$2:$A$97,0)) -> 10 | H10: =SUMIFS('05_RUTAS'!$F$2:$F$407,'05_RUTAS'!$A$2:$A$407,B10,'05_RUTAS'!$C$2:$C$407,C10) -> 45 | I10: =SUMIFS('05_RUTAS'!$G$2:$G$407,'05_RUTAS'!$A$2:$A$407,B10,'05_RUTAS'!$C$2:$C$407,C10) -> 0 | J10: =(ROUNDUP(F10/G10,0)*H10+F10*I10)/60 -> 1.5 | K10: =MONTH(INDEX('08_PEDIDOS'!$F$2:$F$97,MATCH(A10,'08_PEDIDOS'!$A$2:$A$97,0))) -> 1 | L10: =J10*N(INDEX('04_MAQUINAS'!$F$2:$F$18,MATCH(E10,'04_MAQUINAS'!$A$2:$A$18,0))) -> 39 | M10: =J10*INDEX('04_MAQUINAS'!$G$2:$G$18,MATCH(E10,'04_MAQUINAS'!$A$2:$A$18,0))*INDEX('04_MAQUINAS'!$H$2:$H$18,MATCH(E10,'04_MAQUINAS'!$A$2:$A$18,0)) -> 21.6 | N10: CALCULADO
A11: P001 | B11: Minirack metálico con bandejas | C11: 10 | D11: Colgado, traslado y enfriamiento | E11: Manipulación y enfriamiento de piezas | F11: =INDEX('08_PEDIDOS'!$D$2:$D$97,MATCH(A11,'08_PEDIDOS'!$A$2:$A$97,0)) -> 12 | G11: =INDEX('08_PEDIDOS'!$H$2:$H$97,MATCH(A11,'08_PEDIDOS'!$A$2:$A$97,0)) -> 10 | H11: =SUMIFS('05_RUTAS'!$F$2:$F$407,'05_RUTAS'!$A$2:$A$407,B11,'05_RUTAS'!$C$2:$C$407,C11) -> 8 | I11: =SUMIFS('05_RUTAS'!$G$2:$G$407,'05_RUTAS'!$A$2:$A$407,B11,'05_RUTAS'!$C$2:$C$407,C11) -> 2.69 | J11: =(ROUNDUP(F11/G11,0)*H11+F11*I11)/60 -> 0.80466667 | K11: =MONTH(INDEX('08_PEDIDOS'!$F$2:$F$97,MATCH(A11,'08_PEDIDOS'!$A$2:$A$97,0))) -> 1 | L11: =J11*N(INDEX('04_MAQUINAS'!$F$2:$F$18,MATCH(E11,'04_MAQUINAS'!$A$2:$A$18,0))) -> 12.874667 | M11: =J11*INDEX('04_MAQUINAS'!$G$2:$G$18,MATCH(E11,'04_MAQUINAS'!$A$2:$A$18,0))*INDEX('04_MAQUINAS'!$H$2:$H$18,MATCH(E11,'04_MAQUINAS'!$A$2:$A$18,0)) -> 0.20116667 | N11: CALCULADO
A12: P001 | B12: Minirack metálico con bandejas | C12: 11 | D12: Ensamblaje | E12: Mesa de armado | F12: =INDEX('08_PEDIDOS'!$D$2:$D$97,MATCH(A12,'08_PEDIDOS'!$A$2:$A$97,0)) -> 12 | G12: =INDEX('08_PEDIDOS'!$H$2:$H$97,MATCH(A12,'08_PEDIDOS'!$A$2:$A$97,0)) -> 10 | H12: =SUMIFS('05_RUTAS'!$F$2:$F$407,'05_RUTAS'!$A$2:$A$407,B12,'05_RUTAS'!$C$2:$C$407,C12) -> 6 | I12: =SUMIFS('05_RUTAS'!$G$2:$G$407,'05_RUTAS'!$A$2:$A$407,B12,'05_RUTAS'!$C$2:$C$407,C12) -> 60 | J12: =(ROUNDUP(F12/G12,0)*H12+F12*I12)/60 -> 12.2 | K12: =MONTH(INDEX('08_PEDIDOS'!$F$2:$F$97,MATCH(A12,'08_PEDIDOS'!$A$2:$A$97,0))) -> 1 | L12: =J12*N(INDEX('04_MAQUINAS'!$F$2:$F$18,MATCH(E12,'04_MAQUINAS'!$A$2:$A$18,0))) -> 231.8 | M12: =J12*INDEX('04_MAQUINAS'!$G$2:$G$18,MATCH(E12,'04_MAQUINAS'!$A$2:$A$18,0))*INDEX('04_MAQUINAS'!$H$2:$H$18,MATCH(E12,'04_MAQUINAS'!$A$2:$A$18,0)) -> 3.66 | N12: CALCULADO
A13: P001 | B13: Minirack metálico con bandejas | C13: 12 | D13: Inspección de calidad | E13: Área de inspección | F13: =INDEX('08_PEDIDOS'!$D$2:$D$97,MATCH(A13,'08_PEDIDOS'!$A$2:$A$97,0)) -> 12 | G13: =INDEX('08_PEDIDOS'!$H$2:$H$97,MATCH(A13,'08_PEDIDOS'!$A$2:$A$97,0)) -> 10 | H13: =SUMIFS('05_RUTAS'!$F$2:$F$407,'05_RUTAS'!$A$2:$A$407,B13,'05_RUTAS'!$C$2:$C$407,C13) -> 2 | I13: =SUMIFS('05_RUTAS'!$G$2:$G$407,'05_RUTAS'!$A$2:$A$407,B13,'05_RUTAS'!$C$2:$C$407,C13) -> 3.86 | J13: =(ROUNDUP(F13/G13,0)*H13+F13*I13)/60 -> 0.83866667 | K13: =MONTH(INDEX('08_PEDIDOS'!$F$2:$F$97,MATCH(A13,'08_PEDIDOS'!$A$2:$A$97,0))) -> 1 | L13: =J13*N(INDEX('04_MAQUINAS'!$F$2:$F$18,MATCH(E13,'04_MAQUINAS'!$A$2:$A$18,0))) -> 16.773333 | M13: =J13*INDEX('04_MAQUINAS'!$G$2:$G$18,MATCH(E13,'04_MAQUINAS'!$A$2:$A$18,0))*INDEX('04_MAQUINAS'!$H$2:$H$18,MATCH(E13,'04_MAQUINAS'!$A$2:$A$18,0)) -> 0.083866667 | N13: CALCULADO
... A1153: P096 | B1153: Estantería liviana metálica | C1153: 12 | D1153: Embalaje | E1153: Zona de protección y embalaje | F1153: =INDEX('08_PEDIDOS'!$D$2:$D$97,MATCH(A1153,'08_PEDIDOS'!$A$2:$A$97,0)) -> 10 | G1153: =INDEX('08_PEDIDOS'!$H$2:$H$97,MATCH(A1153,'08_PEDIDOS'!$A$2:$A$97,0)) -> 10 | H1153: =SUMIFS('05_RUTAS'!$F$2:$F$407,'05_RUTAS'!$A$2:$A$407,B1153,'05_RUTAS'!$C$2:$C$407,C1153) -> 2 | I1153: =SUMIFS('05_RUTAS'!$G$2:$G$407,'05_RUTAS'!$A$2:$A$407,B1153,'05_RUTAS'!$C$2:$C$407,C1153) -> 4.67 | J1153: =(ROUNDUP(F1153/G1153,0)*H1153+F1153*I1153)/60 -> 0.81166667 | K1153: =MONTH(INDEX('08_PEDIDOS'!$F$2:$F$97,MATCH(A1153,'08_PEDIDOS'!$A$2:$A$97,0))) -> 12 | L1153: =J1153*N(INDEX('04_MAQUINAS'!$F$2:$F$18,MATCH(E1153,'04_MAQUINAS'!$A$2:$A$18,0))) -> 14.61 | M1153: =J1153*INDEX('04_MAQUINAS'!$G$2:$G$18,MATCH(E1153,'04_MAQUINAS'!$A$2:$A$18,0))*INDEX('04_MAQUINAS'!$H$2:$H$18,MATCH(E1153,'04_MAQUINAS'!$A$2:$A$18,0)) -> 0.07305 | N1153: CALCULADO

Sheet 10_MATERIALES_ORDEN
A1: Pedido | B1: Producto | C1: Componente | D1: Material | E1: Cantidad pedida | F1: Piezas / unidad | G1: Piezas requeridas | H1: Costo componente por producto S/ | I1: Costo pedido S/ | J1: Masa de material del pedido kg | K1: Planchas equivalentes del pedido | L1: Costo disponible (1/0) | M1: Naturaleza
A2: P001 | B2: Minirack metálico con bandejas | C2: Parante vertical | D2: Tubo o perfil de acero (sección por definir) | E2: =INDEX('08_PEDIDOS'!$D$2:$D$97,MATCH(A2,'08_PEDIDOS'!$A$2:$A$97,0)) -> 12 | F2: =SUMIFS('03_DESPIECE'!$D$2:$D$225,'03_DESPIECE'!$A$2:$A$225,B2,'03_DESPIECE'!$B$2:$B$225,C2) -> 4 | G2: =E2*F2 -> 48 | H2: =SUMIFS('03_DESPIECE'!$J$2:$J$225,'03_DESPIECE'!$A$2:$A$225,B2,'03_DESPIECE'!$B$2:$B$225,C2) -> 68.625 | I2: =E2*H2 -> 823.5 | J2: =E2*SUMIFS('03_DESPIECE'!$I$2:$I$225,'03_DESPIECE'!$A$2:$A$225,B2,'03_DESPIECE'!$B$2:$B$225,C2) -> 129.6 | K2: =E2*SUMIFS('03_DESPIECE'!$K$2:$K$225,'03_DESPIECE'!$A$2:$A$225,B2,'03_DESPIECE'!$B$2:$B$225,C2) -> 0 | L2: =SUMIFS('03_DESPIECE'!$L$2:$L$225,'03_DESPIECE'!$A$2:$A$225,B2,'03_DESPIECE'!$B$2:$B$225,C2) -> 1 | M2: CALCULADO
A3: P001 | B3: Minirack metálico con bandejas | C3: Larguero horizontal | D3: Tubo o perfil de acero (sección por definir) | E3: =INDEX('08_PEDIDOS'!$D$2:$D$97,MATCH(A3,'08_PEDIDOS'!$A$2:$A$97,0)) -> 12 | F3: =SUMIFS('03_DESPIECE'!$D$2:$D$225,'03_DESPIECE'!$A$2:$A$225,B3,'03_DESPIECE'!$B$2:$B$225,C3) -> 8 | G3: =E3*F3 -> 96 | H3: =SUMIFS('03_DESPIECE'!$J$2:$J$225,'03_DESPIECE'!$A$2:$A$225,B3,'03_DESPIECE'!$B$2:$B$225,C3) -> 91.5 | I3: =E3*H3 -> 1098 | J3: =E3*SUMIFS('03_DESPIECE'!$I$2:$I$225,'03_DESPIECE'!$A$2:$A$225,B3,'03_DESPIECE'!$B$2:$B$225,C3) -> 172.8 | K3: =E3*SUMIFS('03_DESPIECE'!$K$2:$K$225,'03_DESPIECE'!$A$2:$A$225,B3,'03_DESPIECE'!$B$2:$B$225,C3) -> 0 | L3: =SUMIFS('03_DESPIECE'!$L$2:$L$225,'03_DESPIECE'!$A$2:$A$225,B3,'03_DESPIECE'!$B$2:$B$225,C3) -> 1 | M3: CALCULADO
A4: P001 | B4: Minirack metálico con bandejas | C4: Refuerzo transversal | D4: Tubo o perfil de acero (sección por definir) | E4: =INDEX('08_PEDIDOS'!$D$2:$D$97,MATCH(A4,'08_PEDIDOS'!$A$2:$A$97,0)) -> 12 | F4: =SUMIFS('03_DESPIECE'!$D$2:$D$225,'03_DESPIECE'!$A$2:$A$225,B4,'03_DESPIECE'!$B$2:$B$225,C4) -> 4 | G4: =E4*F4 -> 48 | H4: =SUMIFS('03_DESPIECE'!$J$2:$J$225,'03_DESPIECE'!$A$2:$A$225,B4,'03_DESPIECE'!$B$2:$B$225,C4) -> 22.875 | I4: =E4*H4 -> 274.5 | J4: =E4*SUMIFS('03_DESPIECE'!$I$2:$I$225,'03_DESPIECE'!$A$2:$A$225,B4,'03_DESPIECE'!$B$2:$B$225,C4) -> 43.2 | K4: =E4*SUMIFS('03_DESPIECE'!$K$2:$K$225,'03_DESPIECE'!$A$2:$A$225,B4,'03_DESPIECE'!$B$2:$B$225,C4) -> 0 | L4: =SUMIFS('03_DESPIECE'!$L$2:$L$225,'03_DESPIECE'!$A$2:$A$225,B4,'03_DESPIECE'!$B$2:$B$225,C4) -> 1 | M4: CALCULADO
A5: P001 | B5: Minirack metálico con bandejas | C5: Bandeja acero | D5: Plancha de acero laminado en caliente de 2 mm, 1.20 × 2.40 m | E5: =INDEX('08_PEDIDOS'!$D$2:$D$97,MATCH(A5,'08_PEDIDOS'!$A$2:$A$97,0)) -> 12 | F5: =SUMIFS('03_DESPIECE'!$D$2:$D$225,'03_DESPIECE'!$A$2:$A$225,B5,'03_DESPIECE'!$B$2:$B$225,C5) -> 4 | G5: =E5*F5 -> 48 | H5: =SUMIFS('03_DESPIECE'!$J$2:$J$225,'03_DESPIECE'!$A$2:$A$225,B5,'03_DESPIECE'!$B$2:$B$225,C5) -> 334.20522 | I5: =E5*H5 -> 4010.4626 | J5: =E5*SUMIFS('03_DESPIECE'!$I$2:$I$225,'03_DESPIECE'!$A$2:$A$225,B5,'03_DESPIECE'!$B$2:$B$225,C5) -> 542.592 | K5: =E5*SUMIFS('03_DESPIECE'!$K$2:$K$225,'03_DESPIECE'!$A$2:$A$225,B5,'03_DESPIECE'!$B$2:$B$225,C5) -> 12 | L5: =SUMIFS('03_DESPIECE'!$L$2:$L$225,'03_DESPIECE'!$A$2:$A$225,B5,'03_DESPIECE'!$B$2:$B$225,C5) -> 1 | M5: CALCULADO
A6: P001 | B6: Minirack metálico con bandejas | C6: Cartela unión | D6: Plancha de acero laminado en caliente de 2 mm, 1.20 × 2.40 m | E6: =INDEX('08_PEDIDOS'!$D$2:$D$97,MATCH(A6,'08_PEDIDOS'!$A$2:$A$97,0)) -> 12 | F6: =SUMIFS('03_DESPIECE'!$D$2:$D$225,'03_DESPIECE'!$A$2:$A$225,B6,'03_DESPIECE'!$B$2:$B$225,C6) -> 8 | G6: =E6*F6 -> 96 | H6: =SUMIFS('03_DESPIECE'!$J$2:$J$225,'03_DESPIECE'!$A$2:$A$225,B6,'03_DESPIECE'!$B$2:$B$225,C6) -> 23.208696 | I6: =E6*H6 -> 278.50435 | J6: =E6*SUMIFS('03_DESPIECE'!$I$2:$I$225,'03_DESPIECE'!$A$2:$A$225,B6,'03_DESPIECE'!$B$2:$B$225,C6) -> 37.68 | K6: =E6*SUMIFS('03_DESPIECE'!$K$2:$K$225,'03_DESPIECE'!$A$2:$A$225,B6,'03_DESPIECE'!$B$2:$B$225,C6) -> 0.83333333 | L6: =SUMIFS('03_DESPIECE'!$L$2:$L$225,'03_DESPIECE'!$A$2:$A$225,B6,'03_DESPIECE'!$B$2:$B$225,C6) -> 1 | M6: CALCULADO
A7: P001 | B7: Minirack metálico con bandejas | C7: Tornillería sujeción | D7: Elementos de fijación metálica (tipo por desagregar) | E7: =INDEX('08_PEDIDOS'!$D$2:$D$97,MATCH(A7,'08_PEDIDOS'!$A$2:$A$97,0)) -> 12 | F7: =SUMIFS('03_DESPIECE'!$D$2:$D$225,'03_DESPIECE'!$A$2:$A$225,B7,'03_DESPIECE'!$B$2:$B$225,C7) -> 24 | G7: =E7*F7 -> 288 | H7: =SUMIFS('03_DESPIECE'!$J$2:$J$225,'03_DESPIECE'!$A$2:$A$225,B7,'03_DESPIECE'!$B$2:$B$225,C7) -> 21.6 | I7: =E7*H7 -> 259.2 | J7: =E7*SUMIFS('03_DESPIECE'!$I$2:$I$225,'03_DESPIECE'!$A$2:$A$225,B7,'03_DESPIECE'!$B$2:$B$225,C7) -> 0 | K7: =E7*SUMIFS('03_DESPIECE'!$K$2:$K$225,'03_DESPIECE'!$A$2:$A$225,B7,'03_DESPIECE'!$B$2:$B$225,C7) -> 0 | L7: =SUMIFS('03_DESPIECE'!$L$2:$L$225,'03_DESPIECE'!$A$2:$A$225,B7,'03_DESPIECE'!$B$2:$B$225,C7) -> 1 | M7: CALCULADO
A8: P001 | B8: Minirack metálico con bandejas | C8: Tapa protectora | D8: Elementos de fijación metálica (tipo por desagregar) | E8: =INDEX('08_PEDIDOS'!$D$2:$D$97,MATCH(A8,'08_PEDIDOS'!$A$2:$A$97,0)) -> 12 | F8: =SUMIFS('03_DESPIECE'!$D$2:$D$225,'03_DESPIECE'!$A$2:$A$225,B8,'03_DESPIECE'!$B$2:$B$225,C8) -> 4 | G8: =E8*F8 -> 48 | H8: =SUMIFS('03_DESPIECE'!$J$2:$J$225,'03_DESPIECE'!$A$2:$A$225,B8,'03_DESPIECE'!$B$2:$B$225,C8) -> 3.6 | I8: =E8*H8 -> 43.2 | J8: =E8*SUMIFS('03_DESPIECE'!$I$2:$I$225,'03_DESPIECE'!$A$2:$A$225,B8,'03_DESPIECE'!$B$2:$B$225,C8) -> 0 | K8: =E8*SUMIFS('03_DESPIECE'!$K$2:$K$225,'03_DESPIECE'!$A$2:$A$225,B8,'03_DESPIECE'!$B$2:$B$225,C8) -> 0 | L8: =SUMIFS('03_DESPIECE'!$L$2:$L$225,'03_DESPIECE'!$A$2:$A$225,B8,'03_DESPIECE'!$B$2:$B$225,C8) -> 1 | M8: CALCULADO
A9: P002 | B9: Estante reforzado modular | C9: Parante perfil | D9: Tubo o perfil de acero (sección por definir) | E9: =INDEX('08_PEDIDOS'!$D$2:$D$97,MATCH(A9,'08_PEDIDOS'!$A$2:$A$97,0)) -> 12 | F9: =SUMIFS('03_DESPIECE'!$D$2:$D$225,'03_DESPIECE'!$A$2:$A$225,B9,'03_DESPIECE'!$B$2:$B$225,C9) -> 4 | G9: =E9*F9 -> 48 | H9: =SUMIFS('03_DESPIECE'!$J$2:$J$225,'03_DESPIECE'!$A$2:$A$225,B9,'03_DESPIECE'!$B$2:$B$225,C9) -> 76.25 | I9: =E9*H9 -> 915 | J9: =E9*SUMIFS('03_DESPIECE'!$I$2:$I$225,'03_DESPIECE'!$A$2:$A$225,B9,'03_DESPIECE'!$B$2:$B$225,C9) -> 144 | K9: =E9*SUMIFS('03_DESPIECE'!$K$2:$K$225,'03_DESPIECE'!$A$2:$A$225,B9,'03_DESPIECE'!$B$2:$B$225,C9) -> 0 | L9: =SUMIFS('03_DESPIECE'!$L$2:$L$225,'03_DESPIECE'!$A$2:$A$225,B9,'03_DESPIECE'!$B$2:$B$225,C9) -> 1 | M9: CALCULADO
A10: P002 | B10: Estante reforzado modular | C10: Travesaño frontal | D10: Tubo o perfil de acero (sección por definir) | E10: =INDEX('08_PEDIDOS'!$D$2:$D$97,MATCH(A10,'08_PEDIDOS'!$A$2:$A$97,0)) -> 12 | F10: =SUMIFS('03_DESPIECE'!$D$2:$D$225,'03_DESPIECE'!$A$2:$A$225,B10,'03_DESPIECE'!$B$2:$B$225,C10) -> 8 | G10: =E10*F10 -> 96 | H10: =SUMIFS('03_DESPIECE'!$J$2:$J$225,'03_DESPIECE'!$A$2:$A$225,B10,'03_DESPIECE'!$B$2:$B$225,C10) -> 76.25 | I10: =E10*H10 -> 915 | J10: =E10*SUMIFS('03_DESPIECE'!$I$2:$I$225,'03_DESPIECE'!$A$2:$A$225,B10,'03_DESPIECE'!$B$2:$B$225,C10) -> 144 | K10: =E10*SUMIFS('03_DESPIECE'!$K$2:$K$225,'03_DESPIECE'!$A$2:$A$225,B10,'03_DESPIECE'!$B$2:$B$225,C10) -> 0 | L10: =SUMIFS('03_DESPIECE'!$L$2:$L$225,'03_DESPIECE'!$A$2:$A$225,B10,'03_DESPIECE'!$B$2:$B$225,C10) -> 1 | M10: CALCULADO
A11: P002 | B11: Estante reforzado modular | C11: Travesaño lateral | D11: Tubo o perfil de acero (sección por definir) | E11: =INDEX('08_PEDIDOS'!$D$2:$D$97,MATCH(A11,'08_PEDIDOS'!$A$2:$A$97,0)) -> 12 | F11: =SUMIFS('03_DESPIECE'!$D$2:$D$225,'03_DESPIECE'!$A$2:$A$225,B11,'03_DESPIECE'!$B$2:$B$225,C11) -> 8 | G11: =E11*F11 -> 96 | H11: =SUMIFS('03_DESPIECE'!$J$2:$J$225,'03_DESPIECE'!$A$2:$A$225,B11,'03_DESPIECE'!$B$2:$B$225,C11) -> 38.125 | I11: =E11*H11 -> 457.5 | J11: =E11*SUMIFS('03_DESPIECE'!$I$2:$I$225,'03_DESPIECE'!$A$2:$A$225,B11,'03_DESPIECE'!$B$2:$B$225,C11) -> 72 | K11: =E11*SUMIFS('03_DESPIECE'!$K$2:$K$225,'03_DESPIECE'!$A$2:$A$225,B11,'03_DESPIECE'!$B$2:$B$225,C11) -> 0 | L11: =SUMIFS('03_DESPIECE'!$L$2:$L$225,'03_DESPIECE'!$A$2:$A$225,B11,'03_DESPIECE'!$B$2:$B$225,C11) -> 1 | M11: CALCULADO
A12: P002 | B12: Estante reforzado modular | C12: Bandeja reforzada | D12: Plancha de acero laminado en caliente de 2 mm, 1.20 × 2.40 m | E12: =INDEX('08_PEDIDOS'!$D$2:$D$97,MATCH(A12,'08_PEDIDOS'!$A$2:$A$97,0)) -> 12 | F12: =SUMIFS('03_DESPIECE'!$D$2:$D$225,'03_DESPIECE'!$A$2:$A$225,B12,'03_DESPIECE'!$B$2:$B$225,C12) -> 5 | G12: =E12*F12 -> 60 | H12: =SUMIFS('03_DESPIECE'!$J$2:$J$225,'03_DESPIECE'!$A$2:$A$225,B12,'03_DESPIECE'!$B$2:$B$225,C12) -> 290.1087 | I12: =E12*H12 -> 3481.3043 | J12: =E12*SUMIFS('03_DESPIECE'!$I$2:$I$225,'03_DESPIECE'!$A$2:$A$225,B12,'03_DESPIECE'!$B$2:$B$225,C12) -> 471 | K12: =E12*SUMIFS('03_DESPIECE'!$K$2:$K$225,'03_DESPIECE'!$A$2:$A$225,B12,'03_DESPIECE'!$B$2:$B$225,C12) -> 10.416667 | L12: =SUMIFS('03_DESPIECE'!$L$2:$L$225,'03_DESPIECE'!$A$2:$A$225,B12,'03_DESPIECE'!$B$2:$B$225,C12) -> 1 | M12: CALCULADO
A13: P002 | B13: Estante reforzado modular | C13: Cartela | D13: Plancha de acero laminado en caliente de 2 mm, 1.20 × 2.40 m | E13: =INDEX('08_PEDIDOS'!$D$2:$D$97,MATCH(A13,'08_PEDIDOS'!$A$2:$A$97,0)) -> 12 | F13: =SUMIFS('03_DESPIECE'!$D$2:$D$225,'03_DESPIECE'!$A$2:$A$225,B13,'03_DESPIECE'!$B$2:$B$225,C13) -> 8 | G13: =E13*F13 -> 96 | H13: =SUMIFS('03_DESPIECE'!$J$2:$J$225,'03_DESPIECE'!$A$2:$A$225,B13,'03_DESPIECE'!$B$2:$B$225,C13) -> 32.492174 | I13: =E13*H13 -> 389.90609 | J13: =E13*SUMIFS('03_DESPIECE'!$I$2:$I$225,'03_DESPIECE'!$A$2:$A$225,B13,'03_DESPIECE'!$B$2:$B$225,C13) -> 52.752 | K13: =E13*SUMIFS('03_DESPIECE'!$K$2:$K$225,'03_DESPIECE'!$A$2:$A$225,B13,'03_DESPIECE'!$B$2:$B$225,C13) -> 1.1666667 | L13: =SUMIFS('03_DESPIECE'!$L$2:$L$225,'03_DESPIECE'!$A$2:$A$225,B13,'03_DESPIECE'!$B$2:$B$225,C13) -> 1 | M13: CALCULADO
... A637: P096 | B637: Estantería liviana metálica | C637: Tornillería | D637: Elementos de fijación metálica (tipo por desagregar) | E637: =INDEX('08_PEDIDOS'!$D$2:$D$97,MATCH(A637,'08_PEDIDOS'!$A$2:$A$97,0)) -> 10 | F637: =SUMIFS('03_DESPIECE'!$D$2:$D$225,'03_DESPIECE'!$A$2:$A$225,B637,'03_DESPIECE'!$B$2:$B$225,C637) -> 32 | G637: =E637*F637 -> 320 | H637: =SUMIFS('03_DESPIECE'!$J$2:$J$225,'03_DESPIECE'!$A$2:$A$225,B637,'03_DESPIECE'!$B$2:$B$225,C637) -> 28.8 | I637: =E637*H637 -> 288 | J637: =E637*SUMIFS('03_DESPIECE'!$I$2:$I$225,'03_DESPIECE'!$A$2:$A$225,B637,'03_DESPIECE'!$B$2:$B$225,C637) -> 0 | K637: =E637*SUMIFS('03_DESPIECE'!$K$2:$K$225,'03_DESPIECE'!$A$2:$A$225,B637,'03_DESPIECE'!$B$2:$B$225,C637) -> 0 | L637: =SUMIFS('03_DESPIECE'!$L$2:$L$225,'03_DESPIECE'!$A$2:$A$225,B637,'03_DESPIECE'!$B$2:$B$225,C637) -> 1 | M637: CALCULADO

Sheet 11_CAPACIDAD
A1: Recurso | B1: Mes | C1: Días | D1: Horas/día | E1: Cantidad | F1: Horas programadas | G1: Carga requerida h | H1: Carga / capacidad | I1: Naturaleza
A2: Guillotina hidráulica para corte de planchas de acero | B2: 1 | C2: =SUMPRODUCT((MONTH('07_CALENDARIO'!$A$2:$A$397)=B2)*(YEAR('07_CALENDARIO'!$A$2:$A$397)=p_anio_base)*'07_CALENDARIO'!$D$2:$D$397) -> 23 | D2: =p_horas_productivas_dia -> 8 | E2: =INDEX('04_MAQUINAS'!$E$2:$E$18,MATCH(A2,'04_MAQUINAS'!$A$2:$A$18,0)) -> 1 | F2: =C2*D2*E2 -> 184 | G2: =SUMIFS('09_CARGA_ORDEN'!$J$2:$J$1153,'09_CARGA_ORDEN'!$E$2:$E$1153,A2,'09_CARGA_ORDEN'!$K$2:$K$1153,B2) -> 54.434583 | H2: =IF(F2=0,"",G2/F2) -> 0.29584013 | I2: CALCULADO
A3: Guillotina hidráulica para corte de planchas de acero | B3: 2 | C3: =SUMPRODUCT((MONTH('07_CALENDARIO'!$A$2:$A$397)=B3)*(YEAR('07_CALENDARIO'!$A$2:$A$397)=p_anio_base)*'07_CALENDARIO'!$D$2:$D$397) -> 20 | D3: =p_horas_productivas_dia -> 8 | E3: =INDEX('04_MAQUINAS'!$E$2:$E$18,MATCH(A3,'04_MAQUINAS'!$A$2:$A$18,0)) -> 1 | F3: =C3*D3*E3 -> 160 | G3: =SUMIFS('09_CARGA_ORDEN'!$J$2:$J$1153,'09_CARGA_ORDEN'!$E$2:$E$1153,A3,'09_CARGA_ORDEN'!$K$2:$K$1153,B3) -> 53.763833 | H3: =IF(F3=0,"",G3/F3) -> 0.33602396 | I3: CALCULADO
A4: Guillotina hidráulica para corte de planchas de acero | B4: 3 | C4: =SUMPRODUCT((MONTH('07_CALENDARIO'!$A$2:$A$397)=B4)*(YEAR('07_CALENDARIO'!$A$2:$A$397)=p_anio_base)*'07_CALENDARIO'!$D$2:$D$397) -> 21 | D4: =p_horas_productivas_dia -> 8 | E4: =INDEX('04_MAQUINAS'!$E$2:$E$18,MATCH(A4,'04_MAQUINAS'!$A$2:$A$18,0)) -> 1 | F4: =C4*D4*E4 -> 168 | G4: =SUMIFS('09_CARGA_ORDEN'!$J$2:$J$1153,'09_CARGA_ORDEN'!$E$2:$E$1153,A4,'09_CARGA_ORDEN'!$K$2:$K$1153,B4) -> 52.2575 | H4: =IF(F4=0,"",G4/F4) -> 0.31105655 | I4: CALCULADO
A5: Guillotina hidráulica para corte de planchas de acero | B5: 4 | C5: =SUMPRODUCT((MONTH('07_CALENDARIO'!$A$2:$A$397)=B5)*(YEAR('07_CALENDARIO'!$A$2:$A$397)=p_anio_base)*'07_CALENDARIO'!$D$2:$D$397) -> 22 | D5: =p_horas_productivas_dia -> 8 | E5: =INDEX('04_MAQUINAS'!$E$2:$E$18,MATCH(A5,'04_MAQUINAS'!$A$2:$A$18,0)) -> 1 | F5: =C5*D5*E5 -> 176 | G5: =SUMIFS('09_CARGA_ORDEN'!$J$2:$J$1153,'09_CARGA_ORDEN'!$E$2:$E$1153,A5,'09_CARGA_ORDEN'!$K$2:$K$1153,B5) -> 52.2575 | H5: =IF(F5=0,"",G5/F5) -> 0.29691761 | I5: CALCULADO
A6: Guillotina hidráulica para corte de planchas de acero | B6: 5 | C6: =SUMPRODUCT((MONTH('07_CALENDARIO'!$A$2:$A$397)=B6)*(YEAR('07_CALENDARIO'!$A$2:$A$397)=p_anio_base)*'07_CALENDARIO'!$D$2:$D$397) -> 22 | D6: =p_horas_productivas_dia -> 8 | E6: =INDEX('04_MAQUINAS'!$E$2:$E$18,MATCH(A6,'04_MAQUINAS'!$A$2:$A$18,0)) -> 1 | F6: =C6*D6*E6 -> 176 | G6: =SUMIFS('09_CARGA_ORDEN'!$J$2:$J$1153,'09_CARGA_ORDEN'!$E$2:$E$1153,A6,'09_CARGA_ORDEN'!$K$2:$K$1153,B6) -> 52.2575 | H6: =IF(F6=0,"",G6/F6) -> 0.29691761 | I6: CALCULADO
A7: Guillotina hidráulica para corte de planchas de acero | B7: 6 | C7: =SUMPRODUCT((MONTH('07_CALENDARIO'!$A$2:$A$397)=B7)*(YEAR('07_CALENDARIO'!$A$2:$A$397)=p_anio_base)*'07_CALENDARIO'!$D$2:$D$397) -> 21 | D7: =p_horas_productivas_dia -> 8 | E7: =INDEX('04_MAQUINAS'!$E$2:$E$18,MATCH(A7,'04_MAQUINAS'!$A$2:$A$18,0)) -> 1 | F7: =C7*D7*E7 -> 168 | G7: =SUMIFS('09_CARGA_ORDEN'!$J$2:$J$1153,'09_CARGA_ORDEN'!$E$2:$E$1153,A7,'09_CARGA_ORDEN'!$K$2:$K$1153,B7) -> 62.2915 | H7: =IF(F7=0,"",G7/F7) -> 0.37078274 | I7: CALCULADO
A8: Guillotina hidráulica para corte de planchas de acero | B8: 7 | C8: =SUMPRODUCT((MONTH('07_CALENDARIO'!$A$2:$A$397)=B8)*(YEAR('07_CALENDARIO'!$A$2:$A$397)=p_anio_base)*'07_CALENDARIO'!$D$2:$D$397) -> 23 | D8: =p_horas_productivas_dia -> 8 | E8: =INDEX('04_MAQUINAS'!$E$2:$E$18,MATCH(A8,'04_MAQUINAS'!$A$2:$A$18,0)) -> 1 | F8: =C8*D8*E8 -> 184 | G8: =SUMIFS('09_CARGA_ORDEN'!$J$2:$J$1153,'09_CARGA_ORDEN'!$E$2:$E$1153,A8,'09_CARGA_ORDEN'!$K$2:$K$1153,B8) -> 61.698833 | H8: =IF(F8=0,"",G8/F8) -> 0.33531975 | I8: CALCULADO
A9: Guillotina hidráulica para corte de planchas de acero | B9: 8 | C9: =SUMPRODUCT((MONTH('07_CALENDARIO'!$A$2:$A$397)=B9)*(YEAR('07_CALENDARIO'!$A$2:$A$397)=p_anio_base)*'07_CALENDARIO'!$D$2:$D$397) -> 21 | D9: =p_horas_productivas_dia -> 8 | E9: =INDEX('04_MAQUINAS'!$E$2:$E$18,MATCH(A9,'04_MAQUINAS'!$A$2:$A$18,0)) -> 1 | F9: =C9*D9*E9 -> 168 | G9: =SUMIFS('09_CARGA_ORDEN'!$J$2:$J$1153,'09_CARGA_ORDEN'!$E$2:$E$1153,A9,'09_CARGA_ORDEN'!$K$2:$K$1153,B9) -> 61.698833 | H9: =IF(F9=0,"",G9/F9) -> 0.36725496 | I9: CALCULADO
A10: Guillotina hidráulica para corte de planchas de acero | B10: 9 | C10: =SUMPRODUCT((MONTH('07_CALENDARIO'!$A$2:$A$397)=B10)*(YEAR('07_CALENDARIO'!$A$2:$A$397)=p_anio_base)*'07_CALENDARIO'!$D$2:$D$397) -> 22 | D10: =p_horas_productivas_dia -> 8 | E10: =INDEX('04_MAQUINAS'!$E$2:$E$18,MATCH(A10,'04_MAQUINAS'!$A$2:$A$18,0)) -> 1 | F10: =C10*D10*E10 -> 176 | G10: =SUMIFS('09_CARGA_ORDEN'!$J$2:$J$1153,'09_CARGA_ORDEN'!$E$2:$E$1153,A10,'09_CARGA_ORDEN'!$K$2:$K$1153,B10) -> 52.2575 | H10: =IF(F10=0,"",G10/F10) -> 0.29691761 | I10: CALCULADO
A11: Guillotina hidráulica para corte de planchas de acero | B11: 10 | C11: =SUMPRODUCT((MONTH('07_CALENDARIO'!$A$2:$A$397)=B11)*(YEAR('07_CALENDARIO'!$A$2:$A$397)=p_anio_base)*'07_CALENDARIO'!$D$2:$D$397) -> 23 | D11: =p_horas_productivas_dia -> 8 | E11: =INDEX('04_MAQUINAS'!$E$2:$E$18,MATCH(A11,'04_MAQUINAS'!$A$2:$A$18,0)) -> 1 | F11: =C11*D11*E11 -> 184 | G11: =SUMIFS('09_CARGA_ORDEN'!$J$2:$J$1153,'09_CARGA_ORDEN'!$E$2:$E$1153,A11,'09_CARGA_ORDEN'!$K$2:$K$1153,B11) -> 52.2575 | H11: =IF(F11=0,"",G11/F11) -> 0.28400815 | I11: CALCULADO
A12: Guillotina hidráulica para corte de planchas de acero | B12: 11 | C12: =SUMPRODUCT((MONTH('07_CALENDARIO'!$A$2:$A$397)=B12)*(YEAR('07_CALENDARIO'!$A$2:$A$397)=p_anio_base)*'07_CALENDARIO'!$D$2:$D$397) -> 20 | D12: =p_horas_productivas_dia -> 8 | E12: =INDEX('04_MAQUINAS'!$E$2:$E$18,MATCH(A12,'04_MAQUINAS'!$A$2:$A$18,0)) -> 1 | F12: =C12*D12*E12 -> 160 | G12: =SUMIFS('09_CARGA_ORDEN'!$J$2:$J$1153,'09_CARGA_ORDEN'!$E$2:$E$1153,A12,'09_CARGA_ORDEN'!$K$2:$K$1153,B12) -> 51.6805 | H12: =IF(F12=0,"",G12/F12) -> 0.32300313 | I12: CALCULADO
A13: Guillotina hidráulica para corte de planchas de acero | B13: 12 | C13: =SUMPRODUCT((MONTH('07_CALENDARIO'!$A$2:$A$397)=B13)*(YEAR('07_CALENDARIO'!$A$2:$A$397)=p_anio_base)*'07_CALENDARIO'!$D$2:$D$397) -> 23 | D13: =p_horas_productivas_dia -> 8 | E13: =INDEX('04_MAQUINAS'!$E$2:$E$18,MATCH(A13,'04_MAQUINAS'!$A$2:$A$18,0)) -> 1 | F13: =C13*D13*E13 -> 184 | G13: =SUMIFS('09_CARGA_ORDEN'!$J$2:$J$1153,'09_CARGA_ORDEN'!$E$2:$E$1153,A13,'09_CARGA_ORDEN'!$K$2:$K$1153,B13) -> 51.6805 | H13: =IF(F13=0,"",G13/F13) -> 0.28087228 | I13: CALCULADO
... A205: Sala acondicionada para pintura electrostática | B205: 12 | C205: =SUMPRODUCT((MONTH('07_CALENDARIO'!$A$2:$A$397)=B205)*(YEAR('07_CALENDARIO'!$A$2:$A$397)=p_anio_base)*'07_CALENDARIO'!$D$2:$D$397) -> 23 | D205: =p_horas_productivas_dia -> 8 | E205: =INDEX('04_MAQUINAS'!$E$2:$E$18,MATCH(A205,'04_MAQUINAS'!$A$2:$A$18,0)) -> 1 | F205: =C205*D205*E205 -> 184 | G205: =SUMIFS('09_CARGA_ORDEN'!$J$2:$J$1153,'09_CARGA_ORDEN'!$E$2:$E$1153,A205,'09_CARGA_ORDEN'!$K$2:$K$1153,B205) -> 0 | H205: =IF(F205=0,"",G205/F205) -> 0 | I205: CALCULADO

Sheet 12_PRECIOS
A1: Familia | B1: Unidades agregadas 2025 | C1: Ventas agregadas S/ | D1: Precio promedio S/ | E1: Penalidad fija % | F1: Penalidad diaria % | G1: Naturaleza
A2: Racks industriales | B2: 295 | C2: 781894.55 | D2: =C2/B2 -> 2650.49 | E2: 0.1 | F2: 0 | G2: REAL (ventas); ESTIMADO (penalidades)
A3: Góndolas comerciales | B3: 167 | C3: 359145.19 | D3: =C3/B3 -> 2150.57 | E3: 0.1 | F3: 0 | G3: REAL (ventas); ESTIMADO (penalidades)
A4: Lockers metálicos | B4: 139 | C4: 250312.59 | D4: =C4/B4 -> 1800.81 | E4: 0.1 | F4: 0 | G4: REAL (ventas); ESTIMADO (penalidades)
A5: Otros productos metalmecánicos | B5: 250 | C5: 580617.45 | D5: =C5/B5 -> 2322.4698 | E5: 0.1 | F5: 0 | G5: REAL (ventas); ESTIMADO (penalidades)

Sheet 13_ELEGIBILIDAD
A1: Producto | B1: Paso | C1: Operación | D1: Máquina elegible | E1: Tipo de asignación | F1: Elegible 1/0 | G1: Factor de tiempo relativo | H1: Naturaleza
A2: Minirack metálico con bandejas | B2: 1 | C2: Corte de planchas de acero | D2: Guillotina hidráulica para corte de planchas de acero | E2: PRINCIPAL | F2: 1 | G2: 1 | H2: CALCULADO
A3: Minirack metálico con bandejas | B3: 2 | C3: Corte de tubos y perfiles | D3: Sierra de cinta para corte de tubos y perfiles | E3: PRINCIPAL | F3: 1 | G3: 1 | H3: CALCULADO
A4: Minirack metálico con bandejas | B4: 3 | C4: Perforación | D4: Taladro de banco para perforación de acero | E4: PRINCIPAL | F4: 1 | G4: 1 | H4: CALCULADO
A5: Minirack metálico con bandejas | B5: 3 | C5: Perforación | D5: Segundo taladro (alternativo) | E5: ALTERNATIVA CON UTILLAJE COMPATIBLE | F5: 1 | G5: 1.1 | H5: ESTIMADO
A6: Minirack metálico con bandejas | B6: 4 | C6: Plegado | D6: Plegadora hidráulica de chapa metálica | E6: PRINCIPAL | F6: 1 | G6: 1 | H6: CALCULADO
A7: Minirack metálico con bandejas | B7: 5 | C7: Soldadura | D7: Máquina de soldadura por arco MIG/MAG | E7: PRINCIPAL | F7: 1 | G7: 1 | H7: CALCULADO
A8: Minirack metálico con bandejas | B8: 5 | C8: Soldadura | D8: Segunda estación soldadura (alternativa) | E8: ALTERNATIVA MISMO PROCESO | F8: 1 | G8: 1 | H8: ESTIMADO
A9: Minirack metálico con bandejas | B9: 6 | C9: Desbarbado | D9: Mesa de desbarbado/esmerilado | E9: PRINCIPAL | F9: 1 | G9: 1 | H9: CALCULADO
A10: Minirack metálico con bandejas | B10: 7 | C10: Preparación superficial | D10: Zona de preparación superficial | E10: PRINCIPAL | F10: 1 | G10: 1 | H10: CALCULADO
A11: Minirack metálico con bandejas | B11: 8 | C11: Aplicación electrostática de polvo | D11: Pistola manual de pintura electrostática en polvo | E11: PRINCIPAL | F11: 1 | G11: 1 | H11: CALCULADO
A12: Minirack metálico con bandejas | B12: 9 | C12: Curado térmico en horno | D12: Horno de curado de pintura electrostática por lotes | E12: PRINCIPAL | F12: 1 | G12: 1 | H12: CALCULADO
A13: Minirack metálico con bandejas | B13: 10 | C13: Colgado, traslado y enfriamiento | D13: Manipulación y enfriamiento de piezas | E13: PRINCIPAL | F13: 1 | G13: 1 | H13: CALCULADO
... A474: Silla terraza New Bistro | B474: 8 | C474: Inspección final de integridad del producto | D474: Mesa de armado | E474: PRINCIPAL | F474: 1 | G474: 1 | H474: CALCULADO

Sheet 14_FALLAS_ESC
A1: Evento | B1: Inicio | C1: Fin | D1: Horas de reloj | E1: Equipo | F1: Motivo hipotético | G1: Pedido potencialmente afectado | H1: Paso | I1: Tipo de dato | J1: Horas de turno afectadas | K1: Naturaleza
A2: F01 | B2: 45817.333 | C2: =B2+D2/24 -> 45817.417 | D2: 2 | E2: Plegadora hidráulica de chapa metálica | F2: Interrupción hidráulica hipotética | G2: P041 | H2: 4 | I2: SIMULADO | J2: 2 | K2: SIMULADO
A3: F02 | B3: 45825.427 | C3: =B3+D3/24 -> 45825.552 | D3: 3 | E3: Plegadora hidráulica de chapa metálica | F3: Falla de sensor de seguridad | G3: P047 | H3: 3 | I3: SIMULADO | J3: 2 | K3: SIMULADO
A4: F03 | B4: 45839.498 | C4: =B4+D4/24 -> 45839.664 | D4: 4 | E4: Plegadora hidráulica de chapa metálica | F4: Desajuste del tope posterior | G4: P048 | H4: 4 | I4: SIMULADO | J4: 3 | K4: SIMULADO
A5: F04 | B5: 45855.427 | C5: =B5+D5/24 -> 45855.677 | D5: 6 | E5: Plegadora hidráulica de chapa metálica | F5: Corte eléctrico local | G5: P055 | H5: 3 | I5: SIMULADO | J5: 5 | K5: SIMULADO
A6: F05 | B6: 45877.375 | C6: =B6+D6/24 -> 45877.479 | D6: 2.5 | E6: Plegadora hidráulica de chapa metálica | F6: Ajuste de herramienta | G6: P057 | H6: 4 | I6: SIMULADO | J6: 2.5 | K6: SIMULADO
A7: F06 | B7: 45887.427 | C7: =B7+D7/24 -> 45887.635 | D7: 5 | E7: Plegadora hidráulica de chapa metálica | F7: Descenso de presión | G7: P063 | H7: 3 | I7: SIMULADO | J7: 4 | K7: SIMULADO
A8: F07 | B8: 45902.498 | C8: =B8+D8/24 -> 45902.644 | D8: 3.5 | E8: Plegadora hidráulica de chapa metálica | F8: Interrupción hidráulica hipotética | G8: P064 | H8: 4 | I8: SIMULADO | J8: 2.5 | K8: SIMULADO
A9: F08 | B9: 45916.375 | C9: =B9+D9/24 -> 45916.562 | D9: 4.5 | E9: Plegadora hidráulica de chapa metálica | F9: Falla de sensor de seguridad | G9: P071 | H9: 3 | I9: SIMULADO | J9: 3.5 | K9: SIMULADO
A10: F09 | B10: 45939.375 | C10: =B10+D10/24 -> 45939.458 | D10: 2 | E10: Plegadora hidráulica de chapa metálica | F10: Desajuste del tope posterior | G10: P073 | H10: 4 | I10: SIMULADO | J10: 2 | K10: SIMULADO
A11: F10 | B11: 45952.477 | C11: =B11+D11/24 -> 45952.727 | D11: 6 | E11: Plegadora hidráulica de chapa metálica | F11: Corte eléctrico local | G11: P074 | H11: 4 | I11: SIMULADO | J11: 4.5626667 | K11: SIMULADO
A12: F11 | B12: 45967.466 | C12: =B12+D12/24 -> 45967.591 | D12: 3 | E12: Plegadora hidráulica de chapa metálica | F12: Ajuste de herramienta | G12: P081 | H12: 4 | I12: SIMULADO | J12: 2 | K12: SIMULADO
A13: F12 | B13: 45982.477 | C13: =B13+D13/24 -> 45982.643 | D13: 4 | E13: Plegadora hidráulica de chapa metálica | F13: Descenso de presión | G13: P082 | H13: 4 | I13: SIMULADO | J13: 3 | K13: SIMULADO
... A22: F21 | B22: 45854.333 | C22: =B22+D22/24 -> 45854.5 | D22: 4 | E22: Plegadora hidráulica de chapa metálica | F22: Mantenimiento preventivo programado: cambio de aceite hidráulico y calibración de topes | G22: P053 | H22: 3 | I22: SIMULADO (mantenimiento planificado) | J22: 4 | K22: SIMULADO

Sheet 15_RECUPERACION
A1: Producto | B1: Paso | C1: Operación | D1: Política | E1: Conserva piezas | F1: Reinicia lote | G1: Repite setup | H1: Piezas a repetir por interrupción | I1: Min de verificación tras reparación | J1: Naturaleza
A2: Minirack metálico con bandejas | B2: 4 | C2: Plegado | D2: A - reanudar | E2: 1 | F2: 0 | G2: 0 | H2: 1 | I2: 10 | J2: ESTIMADO
A3: Minirack metálico con bandejas | B3: 4 | C3: Plegado | D3: B - reiniciar lote | E3: 0 | F3: 1 | G3: 1 | I3: 0 | J3: ESTIMADO
A4: Estante reforzado modular | B4: 4 | C4: Plegado | D4: A - reanudar | E4: 1 | F4: 0 | G4: 0 | H4: 1 | I4: 10 | J4: ESTIMADO
A5: Estante reforzado modular | B5: 4 | C5: Plegado | D5: B - reiniciar lote | E5: 0 | F5: 1 | G5: 1 | I5: 0 | J5: ESTIMADO
A6: Góndola central comercial | B6: 4 | C6: Plegado | D6: A - reanudar | E6: 1 | F6: 0 | G6: 0 | H6: 1 | I6: 10 | J6: ESTIMADO
A7: Góndola central comercial | B7: 4 | C7: Plegado | D7: B - reiniciar lote | E7: 0 | F7: 1 | G7: 1 | I7: 0 | J7: ESTIMADO
A8: Góndola mural | B8: 4 | C8: Plegado | D8: A - reanudar | E8: 1 | F8: 0 | G8: 0 | H8: 1 | I8: 10 | J8: ESTIMADO
A9: Góndola mural | B9: 4 | C9: Plegado | D9: B - reiniciar lote | E9: 0 | F9: 1 | G9: 1 | I9: 0 | J9: ESTIMADO
A10: Locker de 4 puertas | B10: 3 | C10: Plegado | D10: A - reanudar | E10: 1 | F10: 0 | G10: 0 | H10: 1 | I10: 10 | J10: ESTIMADO
A11: Locker de 4 puertas | B11: 3 | C11: Plegado | D11: B - reiniciar lote | E11: 0 | F11: 1 | G11: 1 | I11: 0 | J11: ESTIMADO
A12: Locker de 6 puertas | B12: 3 | C12: Plegado | D12: A - reanudar | E12: 1 | F12: 0 | G12: 0 | H12: 1 | I12: 10 | J12: ESTIMADO
A13: Locker de 6 puertas | B13: 3 | C13: Plegado | D13: B - reiniciar lote | E13: 0 | F13: 1 | G13: 1 | I13: 0 | J13: ESTIMADO
A14: Armario metálico | B14: 3 | C14: Plegado | D14: A - reanudar | E14: 1 | F14: 0 | G14: 0 | H14: 1 | I14: 10 | J14: ESTIMADO
A15: Armario metálico | B15: 3 | C15: Plegado | D15: B - reiniciar lote | E15: 0 | F15: 1 | G15: 1 | I15: 0 | J15: ESTIMADO
A16: Estantería liviana metálica | B16: 4 | C16: Plegado | D16: A - reanudar | E16: 1 | F16: 0 | G16: 0 | H16: 1 | I16: 10 | J16: ESTIMADO
A17: Estantería liviana metálica | B17: 4 | C17: Plegado | D17: B - reiniciar lote | E17: 0 | F17: 1 | G17: 1 | I17: 0 | J17: ESTIMADO
A18: Estantería metálica K45 5 niveles | B18: 4 | C18: Plegado | D18: A - reanudar | E18: 1 | F18: 0 | G18: 0 | H18: 1 | I18: 10 | J18: ESTIMADO
A19: Estantería metálica K45 5 niveles | B19: 4 | C19: Plegado | D19: B - reiniciar lote | E19: 0 | F19: 1 | G19: 1 | I19: 0 | J19: ESTIMADO
A20: Góndola central doble forro liso | B20: 4 | C20: Plegado | D20: A - reanudar | E20: 1 | F20: 0 | G20: 0 | H20: 1 | I20: 10 | J20: ESTIMADO
A21: Góndola central doble forro liso | B21: 4 | C21: Plegado | D21: B - reiniciar lote | E21: 0 | F21: 1 | G21: 1 | I21: 0 | J21: ESTIMADO
A22: Góndola mural de forro liso | B22: 4 | C22: Plegado | D22: A - reanudar | E22: 1 | F22: 0 | G22: 0 | H22: 1 | I22: 10 | J22: ESTIMADO
A23: Góndola mural de forro liso | B23: 4 | C23: Plegado | D23: B - reiniciar lote | E23: 0 | F23: 1 | G23: 1 | I23: 0 | J23: ESTIMADO
A24: Góndola de cabecera liso | B24: 4 | C24: Plegado | D24: A - reanudar | E24: 1 | F24: 0 | G24: 0 | H24: 1 | I24: 10 | J24: ESTIMADO
A25: Góndola de cabecera liso | B25: 4 | C25: Plegado | D25: B - reiniciar lote | E25: 0 | F25: 1 | G25: 1 | I25: 0 | J25: ESTIMADO
A26: Góndola isla modular | B26: 4 | C26: Plegado | D26: A - reanudar | E26: 1 | F26: 0 | G26: 0 | H26: 1 | I26: 10 | J26: ESTIMADO
A27: Góndola isla modular | B27: 4 | C27: Plegado | D27: B - reiniciar lote | E27: 0 | F27: 1 | G27: 1 | I27: 0 | J27: ESTIMADO
A28: Locker metálico simple MK1-01 | B28: 3 | C28: Plegado | D28: A - reanudar | E28: 1 | F28: 0 | G28: 0 | H28: 1 | I28: 10 | J28: ESTIMADO
A29: Locker metálico simple MK1-01 | B29: 3 | C29: Plegado | D29: B - reiniciar lote | E29: 0 | F29: 1 | G29: 1 | I29: 0 | J29: ESTIMADO
A30: Locker metálico simple MK2-01 | B30: 3 | C30: Plegado | D30: A - reanudar | E30: 1 | F30: 0 | G30: 0 | H30: 1 | I30: 10 | J30: ESTIMADO
A31: Locker metálico simple MK2-01 | B31: 3 | C31: Plegado | D31: B - reiniciar lote | E31: 0 | F31: 1 | G31: 1 | I31: 0 | J31: ESTIMADO
A32: Locker metálico simple MK3-01 | B32: 3 | C32: Plegado | D32: A - reanudar | E32: 1 | F32: 0 | G32: 0 | H32: 1 | I32: 10 | J32: ESTIMADO
A33: Locker metálico simple MK3-01 | B33: 3 | C33: Plegado | D33: B - reiniciar lote | E33: 0 | F33: 1 | G33: 1 | I33: 0 | J33: ESTIMADO
A34: Locker metálico simple MK4-01 | B34: 3 | C34: Plegado | D34: A - reanudar | E34: 1 | F34: 0 | G34: 0 | H34: 1 | I34: 10 | J34: ESTIMADO
A35: Locker metálico simple MK4-01 | B35: 3 | C35: Plegado | D35: B - reiniciar lote | E35: 0 | F35: 1 | G35: 1 | I35: 0 | J35: ESTIMADO
A36: Cajonera metálica P1019 | B36: 3 | C36: Plegado | D36: A - reanudar | E36: 1 | F36: 0 | G36: 0 | H36: 1 | I36: 10 | J36: ESTIMADO
A37: Cajonera metálica P1019 | B37: 3 | C37: Plegado | D37: B - reiniciar lote | E37: 0 | F37: 1 | G37: 1 | I37: 0 | J37: ESTIMADO
A38: Archivador metálico 3 cajones | B38: 3 | C38: Plegado | D38: A - reanudar | E38: 1 | F38: 0 | G38: 0 | H38: 1 | I38: 10 | J38: ESTIMADO
A39: Archivador metálico 3 cajones | B39: 3 | C39: Plegado | D39: B - reiniciar lote | E39: 0 | F39: 1 | G39: 1 | I39: 0 | J39: ESTIMADO
A40: Archivador metálico 4 cajones | B40: 3 | C40: Plegado | D40: A - reanudar | E40: 1 | F40: 0 | G40: 0 | H40: 1 | I40: 10 | J40: ESTIMADO
A41: Archivador metálico 4 cajones | B41: 3 | C41: Plegado | D41: B - reiniciar lote | E41: 0 | F41: 1 | G41: 1 | I41: 0 | J41: ESTIMADO
A42: Armario metálico KD-034 | B42: 3 | C42: Plegado | D42: A - reanudar | E42: 1 | F42: 0 | G42: 0 | H42: 1 | I42: 10 | J42: ESTIMADO
A43: Armario metálico KD-034 | B43: 3 | C43: Plegado | D43: B - reiniciar lote | E43: 0 | F43: 1 | G43: 1 | I43: 0 | J43: ESTIMADO
A44: Armario herramientas MY-TC-03 | B44: 3 | C44: Plegado | D44: A - reanudar | E44: 1 | F44: 0 | G44: 0 | H44: 1 | I44: 10 | J44: ESTIMADO
A45: Armario herramientas MY-TC-03 | B45: 3 | C45: Plegado | D45: B - reiniciar lote | E45: 0 | F45: 1 | G45: 1 | I45: 0 | J45: ESTIMADO
A46: Armario herramientas MY-TC-04 | B46: 3 | C46: Plegado | D46: A - reanudar | E46: 1 | F46: 0 | G46: 0 | H46: 1 | I46: 10 | J46: ESTIMADO
A47: Armario herramientas MY-TC-04 | B47: 3 | C47: Plegado | D47: B - reiniciar lote | E47: 0 | F47: 1 | G47: 1 | I47: 0 | J47: ESTIMADO
A48: Armario herramientas MY-TC-05 | B48: 3 | C48: Plegado | D48: A - reanudar | E48: 1 | F48: 0 | G48: 0 | H48: 1 | I48: 10 | J48: ESTIMADO
A49: Armario herramientas MY-TC-05 | B49: 3 | C49: Plegado | D49: B - reiniciar lote | E49: 0 | F49: 1 | G49: 1 | I49: 0 | J49: ESTIMADO
A50: Armario herramientas MY-TC-06 | B50: 3 | C50: Plegado | D50: A - reanudar | E50: 1 | F50: 0 | G50: 0 | H50: 1 | I50: 10 | J50: ESTIMADO
A51: Armario herramientas MY-TC-06 | B51: 3 | C51: Plegado | D51: B - reiniciar lote | E51: 0 | F51: 1 | G51: 1 | I51: 0 | J51: ESTIMADO
A52: Carro taller MY-STC-15 (5 cajones) | B52: 3 | C52: Plegado | D52: A - reanudar | E52: 1 | F52: 0 | G52: 0 | H52: 1 | I52: 10 | J52: ESTIMADO
A53: Carro taller MY-STC-15 (5 cajones) | B53: 3 | C53: Plegado | D53: B - reiniciar lote | E53: 0 | F53: 1 | G53: 1 | I53: 0 | J53: ESTIMADO
A54: Carro taller MY-STC-13 (7 cajones) | B54: 3 | C54: Plegado | D54: A - reanudar | E54: 1 | F54: 0 | G54: 0 | H54: 1 | I54: 10 | J54: ESTIMADO
A55: Carro taller MY-STC-13 (7 cajones) | B55: 3 | C55: Plegado | D55: B - reiniciar lote | E55: 0 | F55: 1 | G55: 1 | I55: 0 | J55: ESTIMADO
A56: Carro taller MY-STC-26 (7 cajones) | B56: 3 | C56: Plegado | D56: A - reanudar | E56: 1 | F56: 0 | G56: 0 | H56: 1 | I56: 10 | J56: ESTIMADO
A57: Carro taller MY-STC-26 (7 cajones) | B57: 3 | C57: Plegado | D57: B - reiniciar lote | E57: 0 | F57: 1 | G57: 1 | I57: 0 | J57: ESTIMADO
A58: Estantería metálica K45 | B58: 3 | C58: Plegado | D58: A - reanudar | E58: 1 | F58: 0 | G58: 0 | H58: 1 | I58: 10 | J58: ESTIMADO
A59: Estantería metálica K45 | B59: 3 | C59: Plegado | D59: B - reiniciar lote | E59: 0 | F59: 1 | G59: 1 | I59: 0 | J59: ESTIMADO
A60: (Genérico) operaciones POR_UNIDAD | C60: operaciones POR_UNIDAD | D60: A - reanudar | E60: 1 | F60: 0 | G60: 0 | H60: 0 | I60: 0 | J60: ESTIMADO
A61: (Genérico) operaciones POR_UNIDAD | C61: operaciones POR_UNIDAD | D61: B - reiniciar lote | E61: 0 | F61: 1 | G61: 1 | I61: 0 | J61: ESTIMADO
A62: (Genérico) Curado térmico POR_LOTE | C62: Curado térmico POR_LOTE | D62: A - reanudar | E62: 0 | F62: 1 | G62: 1 | I62: 0 | J62: ESTIMADO
A63: (Genérico) Curado térmico POR_LOTE | C63: Curado térmico POR_LOTE | D63: B - reiniciar lote | E63: 0 | F63: 1 | G63: 1 | I63: 0 | J63: ESTIMADO

Sheet 16_PROGRAMA_BASE
A1: Pedido | B1: Producto | C1: Paso | D1: Operación | E1: Máquina | F1: Inicio | G1: Fin | H1: Duración h | I1: Fecha compromiso | J1: Naturaleza
A2: P001 | B2: Minirack metálico con bandejas | C2: 1 | D2: Corte de planchas de acero | E2: Guillotina hidráulica para corte de planchas de acero | F2: 45660.333 | G2: 45660.675 | H2: 7.1906667 | I2: 45677 | J2: CALCULADO
A3: P001 | B3: Minirack metálico con bandejas | C3: 2 | D3: Corte de tubos y perfiles | E3: Sierra de cinta para corte de tubos y perfiles | F3: 45660.675 | G3: 45664.34 | H3: 8.9706667 | I3: 45677 | J3: CALCULADO
A4: P001 | B4: Minirack metálico con bandejas | C4: 3 | D4: Perforación | E4: Taladro de banco para perforación de acero | F4: 45664.34 | G4: 45665.589 | H4: 12.973333 | I4: 45677 | J4: CALCULADO
A5: P001 | B5: Minirack metálico con bandejas | C5: 4 | D5: Plegado | E5: Plegadora hidráulica de chapa metálica | F5: 45665.589 | G5: 45667.397 | H5: 12.4 | I5: 45677 | J5: CALCULADO
A6: P001 | B6: Minirack metálico con bandejas | C6: 5 | D6: Soldadura | E6: Máquina de soldadura por arco MIG/MAG | F6: 45667.397 | G6: 45671.398 | H6: 16.013333 | I6: 45677 | J6: CALCULADO
A7: P001 | B7: Minirack metálico con bandejas | C7: 6 | D7: Desbarbado | E7: Mesa de desbarbado/esmerilado | F7: 45671.398 | G7: 45672.419 | H7: 8.5 | I7: 45677 | J7: CALCULADO
A8: P001 | B8: Minirack metálico con bandejas | C8: 7 | D8: Preparación superficial | E8: Zona de preparación superficial | F8: 45672.419 | G8: 45673.341 | H8: 6.14496 | I8: 45677 | J8: CALCULADO
A9: P001 | B9: Minirack metálico con bandejas | C9: 8 | D9: Aplicación electrostática de polvo | E9: Pistola manual de pintura electrostática en polvo | F9: 45673.341 | G9: 45673.425 | H9: 2.004 | I9: 45677 | J9: CALCULADO
A10: P001 | B10: Minirack metálico con bandejas | C10: 9 | D10: Curado térmico en horno | E10: Horno de curado de pintura electrostática por lotes | F10: 45673.425 | G10: 45673.487 | H10: 1.5 | I10: 45677 | J10: CALCULADO
A11: P001 | B11: Minirack metálico con bandejas | C11: 10 | D11: Colgado, traslado y enfriamiento | E11: Manipulación y enfriamiento de piezas | F11: 45673.487 | G11: 45673.563 | H11: 0.80466667 | I11: 45677 | J11: CALCULADO
A12: P001 | B12: Minirack metálico con bandejas | C12: 11 | D12: Ensamblaje | E12: Mesa de armado | F12: 45673.563 | G12: 45677.363 | H12: 12.2 | I12: 45677 | J12: CALCULADO
A13: P001 | B13: Minirack metálico con bandejas | C13: 12 | D13: Inspección de calidad | E13: Área de inspección | F13: 45677.363 | G13: 45677.398 | H13: 0.83866667 | I13: 45677 | J13: CALCULADO
... A1153: P096 | B1153: Estantería liviana metálica | C1153: 12 | D1153: Embalaje | E1153: Zona de protección y embalaje | F1153: 46028.387 | G1153: 46028.42 | H1153: 0.81166667 | I1153: 46023 | J1153: CALCULADO

Sheet 18_ESCENARIOS
A1: Escenario | B1: Caso | C1: Momento de falla | D1: Duración (h) | E1: Evento | F1: Recuperación | G1: Semilla | H1: Clasificación | I1: Naturaleza
A2: S00 | B2: Sin falla | D2: 0 | E2: Ninguna | F2: FIFO | G2: 20251000 | H2: BASE | I2: CONFIGURACION
A3: S01A | B3: Parada plegadora | C3: 45817.333 | D3: 2 | E3: F01 | F3: A - reanudar | G3: 20251001 | H3: SIMULADO | I3: SIMULADO
A4: S01B | B4: Parada plegadora | C4: 45817.333 | D4: 2 | E4: F01 | F4: B - reiniciar lote | G4: 20251001 | H4: SIMULADO | I4: SIMULADO
A5: S02A | B5: Parada plegadora | C5: 45825.427 | D5: 3 | E5: F02 | F5: A - reanudar | G5: 20251002 | H5: SIMULADO | I5: SIMULADO
A6: S02B | B6: Parada plegadora | C6: 45825.427 | D6: 3 | E6: F02 | F6: B - reiniciar lote | G6: 20251002 | H6: SIMULADO | I6: SIMULADO
A7: S03A | B7: Parada plegadora | C7: 45839.498 | D7: 4 | E7: F03 | F7: A - reanudar | G7: 20251003 | H7: SIMULADO | I7: SIMULADO
A8: S03B | B8: Parada plegadora | C8: 45839.498 | D8: 4 | E8: F03 | F8: B - reiniciar lote | G8: 20251003 | H8: SIMULADO | I8: SIMULADO
A9: S04A | B9: Parada plegadora | C9: 45855.427 | D9: 6 | E9: F04 | F9: A - reanudar | G9: 20251004 | H9: SIMULADO | I9: SIMULADO
A10: S04B | B10: Parada plegadora | C10: 45855.427 | D10: 6 | E10: F04 | F10: B - reiniciar lote | G10: 20251004 | H10: SIMULADO | I10: SIMULADO
A11: S05A | B11: Parada plegadora | C11: 45877.375 | D11: 2.5 | E11: F05 | F11: A - reanudar | G11: 20251005 | H11: SIMULADO | I11: SIMULADO
A12: S05B | B12: Parada plegadora | C12: 45877.375 | D12: 2.5 | E12: F05 | F12: B - reiniciar lote | G12: 20251005 | H12: SIMULADO | I12: SIMULADO
A13: S06A | B13: Parada plegadora | C13: 45887.427 | D13: 5 | E13: F06 | F13: A - reanudar | G13: 20251006 | H13: SIMULADO | I13: SIMULADO
A14: S06B | B14: Parada plegadora | C14: 45887.427 | D14: 5 | E14: F06 | F14: B - reiniciar lote | G14: 20251006 | H14: SIMULADO | I14: SIMULADO
... A41: S20A | B41: Año 2025 completo con F01-F12 (horizonte rodante) | C41: 45817.333 | D41: 45.5 | E41: F01+F02+F03+F04+F05+F06+F07+F08+F09+F10+F11+F12 | F41: A - reanudar | G41: 20251020 | H41: SIMULADO | I41: SIMULADO

Sheet 19_PARAMETROS
A1: Parámetro | B1: Valor | C1: Unidad | D1: Naturaleza | E1: Nota | F1: Leído por Python (1/0)
A2: Número total de trabajadores de producción | B2: 25 | C2: personas | D2: REAL | E2: Confirmado por la empresa (06C v1.2). | F2: 0
A3: Turnos diarios | B3: 1 | C3: turnos | D3: REAL | E3: Confirmado por la empresa. | F3: 0
A4: Horas productivas por día | B4: 8 | C4: h/día | D4: REAL | E4: Jornada neta confirmada; el modelo la deriva de 'Jornada productiva'. | F4: 0
A5: Jornada productiva | B5: 08:00-12:00 y 13:00-17:00 | C5: hora | D5: ESTIMADO | E5: Horario no confirmado por la empresa; define el eje de horas productivas. | F5: 1
A6: Refrigerio | B6: 12:00-13:00 | C6: hora | D6: ESTIMADO | E6: Horario no confirmado. | F6: 0
A7: Aplicar feriados nacionales (1/0) | B7: 0 | C7: 1/0 | D7: CONFIGURACION | E7: 0 = calendario v1.2 (feriados laborables). Práctica real de SAGAPI pendiente de confirmación. | F7: 1
A8: Año base del estudio | B8: 2025 | C8: año | D8: CONFIGURACION | F8: 0
A9: Hora de liberación | B9: 08:00 | C9: hora | D9: ESTIMADO | E9: Fijada en el código (instancia.py); el valor aquí es informativo. | F9: 0
A10: Hora de vencimiento d_j | B10: 17:00 | C10: hora | D10: ESTIMADO | E10: Cierre del día comprometido o del último día productivo previo (calendario.py). | F10: 0
A11: Densidad del acero | B11: 7850 | C11: kg/m³ | D11: REFERENCIA | E11: Constante física; reproduce exactamente la masa de chapa de v1.2. | F11: 0
A12: Masa lineal del perfil genérico | B12: 1.5 | C12: kg/m | D12: ESTIMADO | E12: Implícito en v1.2 (masa = piezas × longitud × 1,5); sección del perfil por definir. | F12: 0
A13: Factor de aprovechamiento de chapa | B13: 0.92 | C13: fracción | D13: ESTIMADO | E13: Implícito en v1.2 (costo = masa × precio / 0,92); sin medición de merma. | F13: 0
A14: Factor de aprovechamiento de perfil | B14: 0.96 | C14: fracción | D14: ESTIMADO | E14: Implícito en v1.2 (costo = masa × precio / 0,96). | F14: 0
A15: Área de plancha estándar 1,20 × 2,40 m | B15: 2.88 | C15: m² | D15: ESTIMADO | E15: Formato del material MAT-LAC2; no confirma que todas las chapas se compren en ese formato. | F15: 0
A16: Costo hora-hombre | B16: 13 | C16: S/ por h | D16: ESTIMADO | E16: Supuesto económico sin planilla. | F16: 0
A17: Tarifa eléctrica | B17: 0.65 | C17: S/ por kWh | D17: ESTIMADO | E17: Verificar con recibo eléctrico. | F17: 0
A18: Factor de emisión de la red | C18: kg CO2/kWh | D18: PENDIENTE | E18: Sin dato oficial cargado; el programa no calcula CO2. | F18: 0
A19: Ventas anuales aproximadas | B19: 2000000 | C19: S/ | D19: REAL | E19: Declarado por la empresa. | F19: 0
A20: UIT 2025 | B20: 5350 | C20: S/ | D20: REFERENCIA | E20: Valor oficial 2025. | F20: 0
A21: Ciclo horno | B21: 40 | C21: min por carga | D21: ESTIMADO | E21: Incluido en el tiempo fijo (45 min) del curado en 06_RUTAS. | F21: 0
A22: Capacidad horno por lote | B22: 10 | C22: piezas por carga (declarado) | D22: ESTIMADO | E22: Conflicto de unidades: el lote del modelo es de 10 UNIDADES de producto, no 10 piezas. | F22: 0
A23: Máquina de la avería | B23: Plegadora hidráulica de chapa metálica | C23: - | D23: CONFIGURACION | E23: Recurso crítico de los experimentos de Monte Carlo. | F23: 1
A24: Costo equivalente reasignación | B24: 8 | C24: h equivalentes | D24: CONFIGURACION | E24: Peso β de f2 (inestabilidad). | F24: 1
A25: Réplicas Monte Carlo de fallas de la plegadora | B25: 40 | C25: réplicas | D25: CONFIGURACION | F25: 1
A26: Semilla Monte Carlo | B26: 2025200 | C26: - | D26: CONFIGURACION | F26: 1
A27: Regla de penalidad del modelo | B27: FIJA | C27: - | D27: CONFIGURACION | E27: FIJA = penalidad fija de 01_FAMILIAS si hay atraso; DIARIA_CON_TOPE solo en sensibilidad. | F27: 0
A28: Penalidad diaria (sensibilidad) | B28: 0,10·valor/(F·plazo); F=0,40 si plazo ≤ 60 d; 0,25 si > 60 d | C28: S/ por día | D28: ESTIMADO | E28: Referencia de contratación pública peruana; no es cláusula de SAGAPI. Fórmula fija en datos.py. | F28: 0
A29: Tolerancia lexicográfica τ | B29: 1e-06 | C29: proporción | D29: CONFIGURACION | E29: Valor fijo en el código (optimizacion.py). | F29: 0
A30: Tolerancia de verificación | B30: 1e-06 | C30: h | D30: CONFIGURACION | E30: Valor fijo en el código (verificacion.py). | F30: 0
A31: Coeficiente de aumentación ε (ρ) | B31: 0.0001 | C31: - | D31: CONFIGURACION | F31: 0
A32: Límite de cómputo por fase | B32: 60 | C32: s | D32: CONFIGURACION | E32: Se fija con --tl en la línea de comandos. | F32: 0
A33: Brecha relativa máxima | B33: 1e-05 | C33: proporción | D33: CONFIGURACION | F33: 0
A34: Niveles para epsilon | B34: 7 | C34: niveles | D34: CONFIGURACION | F34: 0
A35: Solucionador | B35: HiGHS vía scipy.optimize.milp (API pública); una resolución por fase lexicográfica; sin votación | C35: - | D35: CONFIGURACION | E35: Corrige el texto de v1.2 (cartera de 3 configuraciones), obsoleto en el código 1.4.0. | F35: 0

Sheet 20_COSTOS
A1: Pedido | B1: Producto | C1: Unidades | D1: Materiales S/ | E1: Mano de obra S/ | F1: Máquinas S/ | G1: Costo total S/ | H1: Valor pedido S/ | I1: Margen bruto % | J1: Costo de materiales completo (1/0) | K1: Naturaleza
A2: P001 | B2: Minirack metálico con bandejas | C2: =INDEX('08_PEDIDOS'!$D$2:$D$97,MATCH(A2,'08_PEDIDOS'!$A$2:$A$97,0)) -> 12 | D2: =SUMIF('10_MATERIALES_ORDEN'!$A$2:$A$637,A2,'10_MATERIALES_ORDEN'!$I$2:$I$637) -> 6787.367 | E2: =SUMIF('09_CARGA_ORDEN'!$A$2:$A$1153,A2,'09_CARGA_ORDEN'!$J$2:$J$1153)*p_costo_hora_hombre -> 1178.6705 | F2: =SUMIF('09_CARGA_ORDEN'!$A$2:$A$1153,A2,'09_CARGA_ORDEN'!$L$2:$L$1153) -> 2195.0809 | G2: =SUM(D2:F2) -> 10161.118 | H2: =INDEX('08_PEDIDOS'!$K$2:$K$97,MATCH(A2,'08_PEDIDOS'!$A$2:$A$97,0)) -> 31805.88 | I2: =IF(H2=0,"",(H2-G2)/H2) -> 0.68052705 | J2: =IF(COUNTIFS('10_MATERIALES_ORDEN'!$A$2:$A$637,A2,'10_MATERIALES_ORDEN'!$L$2:$L$637,0)=0,1,0) -> 1 | K2: CALCULADO
A3: P002 | B3: Estante reforzado modular | C3: =INDEX('08_PEDIDOS'!$D$2:$D$97,MATCH(A3,'08_PEDIDOS'!$A$2:$A$97,0)) -> 12 | D3: =SUMIF('10_MATERIALES_ORDEN'!$A$2:$A$637,A3,'10_MATERIALES_ORDEN'!$I$2:$I$637) -> 6461.1104 | E3: =SUMIF('09_CARGA_ORDEN'!$A$2:$A$1153,A3,'09_CARGA_ORDEN'!$J$2:$J$1153)*p_costo_hora_hombre -> 1310.0204 | F3: =SUMIF('09_CARGA_ORDEN'!$A$2:$A$1153,A3,'09_CARGA_ORDEN'!$L$2:$L$1153) -> 2424.7319 | G3: =SUM(D3:F3) -> 10195.863 | H3: =INDEX('08_PEDIDOS'!$K$2:$K$97,MATCH(A3,'08_PEDIDOS'!$A$2:$A$97,0)) -> 31805.88 | I3: =IF(H3=0,"",(H3-G3)/H3) -> 0.67943466 | J3: =IF(COUNTIFS('10_MATERIALES_ORDEN'!$A$2:$A$637,A3,'10_MATERIALES_ORDEN'!$L$2:$L$637,0)=0,1,0) -> 1 | K3: CALCULADO
A4: P003 | B4: Góndola central comercial | C4: =INDEX('08_PEDIDOS'!$D$2:$D$97,MATCH(A4,'08_PEDIDOS'!$A$2:$A$97,0)) -> 7 | D4: =SUMIF('10_MATERIALES_ORDEN'!$A$2:$A$637,A4,'10_MATERIALES_ORDEN'!$I$2:$I$637) -> 3257.5449 | E4: =SUMIF('09_CARGA_ORDEN'!$A$2:$A$1153,A4,'09_CARGA_ORDEN'!$J$2:$J$1153)*p_costo_hora_hombre -> 889.77339 | F4: =SUMIF('09_CARGA_ORDEN'!$A$2:$A$1153,A4,'09_CARGA_ORDEN'!$L$2:$L$1153) -> 1628.506 | G4: =SUM(D4:F4) -> 5775.8243 | H4: =INDEX('08_PEDIDOS'!$K$2:$K$97,MATCH(A4,'08_PEDIDOS'!$A$2:$A$97,0)) -> 15053.99 | I4: =IF(H4=0,"",(H4-G4)/H4) -> 0.61632602 | J4: =IF(COUNTIFS('10_MATERIALES_ORDEN'!$A$2:$A$637,A4,'10_MATERIALES_ORDEN'!$L$2:$L$637,0)=0,1,0) -> 1 | K4: CALCULADO
A5: P004 | B5: Góndola mural | C5: =INDEX('08_PEDIDOS'!$D$2:$D$97,MATCH(A5,'08_PEDIDOS'!$A$2:$A$97,0)) -> 7 | D5: =SUMIF('10_MATERIALES_ORDEN'!$A$2:$A$637,A5,'10_MATERIALES_ORDEN'!$I$2:$I$637) -> 2305.9389 | E5: =SUMIF('09_CARGA_ORDEN'!$A$2:$A$1153,A5,'09_CARGA_ORDEN'!$J$2:$J$1153)*p_costo_hora_hombre -> 615.89307 | F5: =SUMIF('09_CARGA_ORDEN'!$A$2:$A$1153,A5,'09_CARGA_ORDEN'!$L$2:$L$1153) -> 1128.5997 | G5: =SUM(D5:F5) -> 4050.4316 | H5: =INDEX('08_PEDIDOS'!$K$2:$K$97,MATCH(A5,'08_PEDIDOS'!$A$2:$A$97,0)) -> 15053.99 | I5: =IF(H5=0,"",(H5-G5)/H5) -> 0.73093967 | J5: =IF(COUNTIFS('10_MATERIALES_ORDEN'!$A$2:$A$637,A5,'10_MATERIALES_ORDEN'!$L$2:$L$637,0)=0,1,0) -> 1 | K5: CALCULADO
A6: P005 | B6: Locker de 4 puertas | C6: =INDEX('08_PEDIDOS'!$D$2:$D$97,MATCH(A6,'08_PEDIDOS'!$A$2:$A$97,0)) -> 6 | D6: =SUMIF('10_MATERIALES_ORDEN'!$A$2:$A$637,A6,'10_MATERIALES_ORDEN'!$I$2:$I$637) -> 3631.3963 | E6: =SUMIF('09_CARGA_ORDEN'!$A$2:$A$1153,A6,'09_CARGA_ORDEN'!$J$2:$J$1153)*p_costo_hora_hombre -> 366.4947 | F6: =SUMIF('09_CARGA_ORDEN'!$A$2:$A$1153,A6,'09_CARGA_ORDEN'!$L$2:$L$1153) -> 675.95227 | G6: =SUM(D6:F6) -> 4673.8433 | H6: =INDEX('08_PEDIDOS'!$K$2:$K$97,MATCH(A6,'08_PEDIDOS'!$A$2:$A$97,0)) -> 10804.86 | I6: =IF(H6=0,"",(H6-G6)/H6) -> 0.56743139 | J6: =IF(COUNTIFS('10_MATERIALES_ORDEN'!$A$2:$A$637,A6,'10_MATERIALES_ORDEN'!$L$2:$L$637,0)=0,1,0) -> 1 | K6: CALCULADO
A7: P006 | B7: Locker de 6 puertas | C7: =INDEX('08_PEDIDOS'!$D$2:$D$97,MATCH(A7,'08_PEDIDOS'!$A$2:$A$97,0)) -> 6 | D7: =SUMIF('10_MATERIALES_ORDEN'!$A$2:$A$637,A7,'10_MATERIALES_ORDEN'!$I$2:$I$637) -> 5193.8296 | E7: =SUMIF('09_CARGA_ORDEN'!$A$2:$A$1153,A7,'09_CARGA_ORDEN'!$J$2:$J$1153)*p_costo_hora_hombre -> 505.6584 | F7: =SUMIF('09_CARGA_ORDEN'!$A$2:$A$1153,A7,'09_CARGA_ORDEN'!$L$2:$L$1153) -> 933.45287 | G7: =SUM(D7:F7) -> 6632.9408 | H7: =INDEX('08_PEDIDOS'!$K$2:$K$97,MATCH(A7,'08_PEDIDOS'!$A$2:$A$97,0)) -> 10804.86 | I7: =IF(H7=0,"",(H7-G7)/H7) -> 0.38611506 | J7: =IF(COUNTIFS('10_MATERIALES_ORDEN'!$A$2:$A$637,A7,'10_MATERIALES_ORDEN'!$L$2:$L$637,0)=0,1,0) -> 1 | K7: CALCULADO
A8: P007 | B8: Armario metálico | C8: =INDEX('08_PEDIDOS'!$D$2:$D$97,MATCH(A8,'08_PEDIDOS'!$A$2:$A$97,0)) -> 10 | D8: =SUMIF('10_MATERIALES_ORDEN'!$A$2:$A$637,A8,'10_MATERIALES_ORDEN'!$I$2:$I$637) -> 4138.7304 | E8: =SUMIF('09_CARGA_ORDEN'!$A$2:$A$1153,A8,'09_CARGA_ORDEN'!$J$2:$J$1153)*p_costo_hora_hombre -> 484.31933 | F8: =SUMIF('09_CARGA_ORDEN'!$A$2:$A$1153,A8,'09_CARGA_ORDEN'!$L$2:$L$1153) -> 897.77467 | G8: =SUM(D8:F8) -> 5520.8244 | H8: =INDEX('08_PEDIDOS'!$K$2:$K$97,MATCH(A8,'08_PEDIDOS'!$A$2:$A$97,0)) -> 23224.698 | I8: =IF(H8=0,"",(H8-G8)/H8) -> 0.76228649 | J8: =IF(COUNTIFS('10_MATERIALES_ORDEN'!$A$2:$A$637,A8,'10_MATERIALES_ORDEN'!$L$2:$L$637,0)=0,1,0) -> 1 | K8: CALCULADO
A9: P008 | B9: Estantería liviana metálica | C9: =INDEX('08_PEDIDOS'!$D$2:$D$97,MATCH(A9,'08_PEDIDOS'!$A$2:$A$97,0)) -> 10 | D9: =SUMIF('10_MATERIALES_ORDEN'!$A$2:$A$637,A9,'10_MATERIALES_ORDEN'!$I$2:$I$637) -> 2926.2082 | E9: =SUMIF('09_CARGA_ORDEN'!$A$2:$A$1153,A9,'09_CARGA_ORDEN'!$J$2:$J$1153)*p_costo_hora_hombre -> 781.59293 | F9: =SUMIF('09_CARGA_ORDEN'!$A$2:$A$1153,A9,'09_CARGA_ORDEN'!$L$2:$L$1153) -> 1379.5915 | G9: =SUM(D9:F9) -> 5087.3926 | H9: =INDEX('08_PEDIDOS'!$K$2:$K$97,MATCH(A9,'08_PEDIDOS'!$A$2:$A$97,0)) -> 23224.698 | I9: =IF(H9=0,"",(H9-G9)/H9) -> 0.78094903 | J9: =IF(COUNTIFS('10_MATERIALES_ORDEN'!$A$2:$A$637,A9,'10_MATERIALES_ORDEN'!$L$2:$L$637,0)=0,1,0) -> 1 | K9: CALCULADO
A10: P009 | B10: Minirack metálico con bandejas | C10: =INDEX('08_PEDIDOS'!$D$2:$D$97,MATCH(A10,'08_PEDIDOS'!$A$2:$A$97,0)) -> 12 | D10: =SUMIF('10_MATERIALES_ORDEN'!$A$2:$A$637,A10,'10_MATERIALES_ORDEN'!$I$2:$I$637) -> 6787.367 | E10: =SUMIF('09_CARGA_ORDEN'!$A$2:$A$1153,A10,'09_CARGA_ORDEN'!$J$2:$J$1153)*p_costo_hora_hombre -> 1178.6705 | F10: =SUMIF('09_CARGA_ORDEN'!$A$2:$A$1153,A10,'09_CARGA_ORDEN'!$L$2:$L$1153) -> 2195.0809 | G10: =SUM(D10:F10) -> 10161.118 | H10: =INDEX('08_PEDIDOS'!$K$2:$K$97,MATCH(A10,'08_PEDIDOS'!$A$2:$A$97,0)) -> 31805.88 | I10: =IF(H10=0,"",(H10-G10)/H10) -> 0.68052705 | J10: =IF(COUNTIFS('10_MATERIALES_ORDEN'!$A$2:$A$637,A10,'10_MATERIALES_ORDEN'!$L$2:$L$637,0)=0,1,0) -> 1 | K10: CALCULADO
A11: P010 | B11: Estante reforzado modular | C11: =INDEX('08_PEDIDOS'!$D$2:$D$97,MATCH(A11,'08_PEDIDOS'!$A$2:$A$97,0)) -> 12 | D11: =SUMIF('10_MATERIALES_ORDEN'!$A$2:$A$637,A11,'10_MATERIALES_ORDEN'!$I$2:$I$637) -> 6461.1104 | E11: =SUMIF('09_CARGA_ORDEN'!$A$2:$A$1153,A11,'09_CARGA_ORDEN'!$J$2:$J$1153)*p_costo_hora_hombre -> 1310.0204 | F11: =SUMIF('09_CARGA_ORDEN'!$A$2:$A$1153,A11,'09_CARGA_ORDEN'!$L$2:$L$1153) -> 2424.7319 | G11: =SUM(D11:F11) -> 10195.863 | H11: =INDEX('08_PEDIDOS'!$K$2:$K$97,MATCH(A11,'08_PEDIDOS'!$A$2:$A$97,0)) -> 31805.88 | I11: =IF(H11=0,"",(H11-G11)/H11) -> 0.67943466 | J11: =IF(COUNTIFS('10_MATERIALES_ORDEN'!$A$2:$A$637,A11,'10_MATERIALES_ORDEN'!$L$2:$L$637,0)=0,1,0) -> 1 | K11: CALCULADO
A12: P011 | B12: Góndola central comercial | C12: =INDEX('08_PEDIDOS'!$D$2:$D$97,MATCH(A12,'08_PEDIDOS'!$A$2:$A$97,0)) -> 7 | D12: =SUMIF('10_MATERIALES_ORDEN'!$A$2:$A$637,A12,'10_MATERIALES_ORDEN'!$I$2:$I$637) -> 3257.5449 | E12: =SUMIF('09_CARGA_ORDEN'!$A$2:$A$1153,A12,'09_CARGA_ORDEN'!$J$2:$J$1153)*p_costo_hora_hombre -> 889.77339 | F12: =SUMIF('09_CARGA_ORDEN'!$A$2:$A$1153,A12,'09_CARGA_ORDEN'!$L$2:$L$1153) -> 1628.506 | G12: =SUM(D12:F12) -> 5775.8243 | H12: =INDEX('08_PEDIDOS'!$K$2:$K$97,MATCH(A12,'08_PEDIDOS'!$A$2:$A$97,0)) -> 15053.99 | I12: =IF(H12=0,"",(H12-G12)/H12) -> 0.61632602 | J12: =IF(COUNTIFS('10_MATERIALES_ORDEN'!$A$2:$A$637,A12,'10_MATERIALES_ORDEN'!$L$2:$L$637,0)=0,1,0) -> 1 | K12: CALCULADO
A13: P012 | B13: Góndola mural | C13: =INDEX('08_PEDIDOS'!$D$2:$D$97,MATCH(A13,'08_PEDIDOS'!$A$2:$A$97,0)) -> 7 | D13: =SUMIF('10_MATERIALES_ORDEN'!$A$2:$A$637,A13,'10_MATERIALES_ORDEN'!$I$2:$I$637) -> 2305.9389 | E13: =SUMIF('09_CARGA_ORDEN'!$A$2:$A$1153,A13,'09_CARGA_ORDEN'!$J$2:$J$1153)*p_costo_hora_hombre -> 615.89307 | F13: =SUMIF('09_CARGA_ORDEN'!$A$2:$A$1153,A13,'09_CARGA_ORDEN'!$L$2:$L$1153) -> 1128.5997 | G13: =SUM(D13:F13) -> 4050.4316 | H13: =INDEX('08_PEDIDOS'!$K$2:$K$97,MATCH(A13,'08_PEDIDOS'!$A$2:$A$97,0)) -> 15053.99 | I13: =IF(H13=0,"",(H13-G13)/H13) -> 0.73093967 | J13: =IF(COUNTIFS('10_MATERIALES_ORDEN'!$A$2:$A$637,A13,'10_MATERIALES_ORDEN'!$L$2:$L$637,0)=0,1,0) -> 1 | K13: CALCULADO
... A97: P096 | B97: Estantería liviana metálica | C97: =INDEX('08_PEDIDOS'!$D$2:$D$97,MATCH(A97,'08_PEDIDOS'!$A$2:$A$97,0)) -> 10 | D97: =SUMIF('10_MATERIALES_ORDEN'!$A$2:$A$637,A97,'10_MATERIALES_ORDEN'!$I$2:$I$637) -> 2926.2082 | E97: =SUMIF('09_CARGA_ORDEN'!$A$2:$A$1153,A97,'09_CARGA_ORDEN'!$J$2:$J$1153)*p_costo_hora_hombre -> 781.59293 | F97: =SUMIF('09_CARGA_ORDEN'!$A$2:$A$1153,A97,'09_CARGA_ORDEN'!$L$2:$L$1153) -> 1379.5915 | G97: =SUM(D97:F97) -> 5087.3926 | H97: =INDEX('08_PEDIDOS'!$K$2:$K$97,MATCH(A97,'08_PEDIDOS'!$A$2:$A$97,0)) -> 23224.698 | I97: =IF(H97=0,"",(H97-G97)/H97) -> 0.78094903 | J97: =IF(COUNTIFS('10_MATERIALES_ORDEN'!$A$2:$A$637,A97,'10_MATERIALES_ORDEN'!$L$2:$L$637,0)=0,1,0) -> 1 | K97: CALCULADO

Sheet 24_VALIDACIONES
A1: Control | B1: Resultado calculado | C1: Objetivo | D1: Estado | E1: Interpretación
A2: Pedidos | B2: =COUNTA('08_PEDIDOS'!$A$2:$A$97) -> 96 | C2: 96 | D2: =IF(ROUND(N(B2)-N(C2),6)=0,"OK","REVISAR") -> OK | E2: Estructura (pedidos SIMULADOS)
A3: Unidades pedidas = unidades vendidas 2025 (12_PRECIOS) | B3: =SUM('08_PEDIDOS'!$D$2:$D$97)-SUM('12_PRECIOS'!$B$2:$B$5) -> 0 | C3: 0 | D3: =IF(ROUND(N(B3)-N(C3),6)=0,"OK","REVISAR") -> OK | E3: Los pedidos simulados reparten exactamente las unidades REALES agregadas
A4: Operaciones pedido × ruta | B4: =COUNTA('09_CARGA_ORDEN'!$A$2:$A$1153) -> 1152 | C4: 1152 | D4: =IF(ROUND(N(B4)-N(C4),6)=0,"OK","REVISAR") -> OK | E4: Instancia de cálculo
A5: Horas de proceso 08 = 09 | B5: =ROUND(SUM('08_PEDIDOS'!$N$2:$N$97)-SUM('09_CARGA_ORDEN'!$J$2:$J$1153),6) -> 0 | C5: 0 | D5: =IF(ROUND(N(B5)-N(C5),6)=0,"OK","REVISAR") -> OK | E5: Consistencia de cargas
A6: Carga 11 = 09 | B6: =ROUND(SUM('11_CAPACIDAD'!$G$2:$G$205)-SUM('09_CARGA_ORDEN'!$J$2:$J$1153),6) -> 0 | C6: 0 | D6: =IF(ROUND(N(B6)-N(C6),6)=0,"OK","REVISAR") -> OK | E6: Consistencia de capacidad
A7: Días productivos del año base | B7: =SUMPRODUCT((YEAR('07_CALENDARIO'!$A$2:$A$397)=p_anio_base)*'07_CALENDARIO'!$D$2:$D$397) -> 261 | C7: 261 | D7: =IF(ROUND(N(B7)-N(C7),6)=0,"OK","REVISAR") -> OK | E7: 261 sin feriados (interruptor = 0); 249 con feriados
A8: Productos con familia inválida | B8: =COUNTIF('01_PRODUCTOS'!$K$2:$K$51,0) -> 0 | C8: 0 | D8: =IF(ROUND(N(B8)-N(C8),6)=0,"OK","REVISAR") -> OK | E8: Integridad 01 ↔ 12
A9: Rutas con equipo inexistente | B9: =COUNTIF('05_RUTAS'!$L$2:$L$407,0) -> 0 | C9: 0 | D9: =IF(ROUND(N(B9)-N(C9),6)=0,"OK","REVISAR") -> OK | E9: Integridad 05 ↔ 04
A10: Pedidos con producto inexistente | B10: =COUNTIF('08_PEDIDOS'!$R$2:$R$97,0) -> 0 | C10: 0 | D10: =IF(ROUND(N(B10)-N(C10),6)=0,"OK","REVISAR") -> OK | E10: Integridad 08 ↔ 01
A11: Recursos usados en rutas sin operario habilitado (simulado) | B11: =COUNTIFS('04_MAQUINAS'!$N$2:$N$18,1,'04_MAQUINAS'!$K$2:$K$18,0) -> 0 | C11: 0 | D11: =IF(ROUND(N(B11)-N(C11),6)=0,"OK","REVISAR") -> OK | E11: Matriz de habilidades SIMULADA
A12: Pedidos cuya ruta excede la ventana r→d (ALERTA) | B12: =SUM('08_PEDIDOS'!$P$2:$P$97) -> 3 | C12: INFO | D12: ="INFO" -> INFO | E12: Infactibles por construcción aun con planta vacía (precedencia lineal, sin traslape)
A13: Pedidos con liberación o compromiso en fin de semana (ALERTA) | B13: =SUM('08_PEDIDOS'!$Q$2:$Q$97) -> 43 | C13: INFO | D13: ="INFO" -> INFO | E13: El modelo los desplaza al día productivo; fechas SIMULADAS
A14: Pedidos con costo de materiales incompleto (ALERTA) | B14: =COUNTIF('20_COSTOS'!$J$2:$J$97,0) -> 0 | C14: INFO | D14: ="INFO" -> INFO | E14: Componentes comprados sin precio (MAT-OTR, MAT-MEL18)
A15: Margen bruto medio implícito (ALERTA) | B15: =AVERAGE('20_COSTOS'!$I$2:$I$97) -> 0.65028496 | C15: INFO | D15: ="INFO" -> INFO | E15: Un margen > 50 % sugiere costos incompletos (sin planilla completa de 25 trabajadores ni gastos)
A16: Python reproduce 16_PROGRAMA_BASE | B16: Ver entrega_v2_0/verificacion | C16: Sí | D16: ="VER E5" -> VER E5 | E16: Lo actualiza el comando 'reportes --escribir-excel'; la verificación v2 está en E5

Sheet 25_PERDIDA_CAPACIDAD_ESC
A1: Escenario | B1: Eventos | C1: Guillotina hidráulica para corte de planchas de acero | D1: Taladro de banco para perforación de acero | E1: Plegadora hidráulica de chapa metálica | F1: Máquina de soldadura por arco MIG/MAG | G1: Horno de curado de pintura electrostática por lotes | H1: Total horas de turno perdidas | I1: Naturaleza
A2: S01A | B2: F01 | C2: =SUMPRODUCT(ISNUMBER(SEARCH("+"&'14_FALLAS_ESC'!$A$2:$A$22&"+","+"&$B2&"+"))*('14_FALLAS_ESC'!$E$2:$E$22=C$1)*'14_FALLAS_ESC'!$J$2:$J$22) -> 0 | D2: =SUMPRODUCT(ISNUMBER(SEARCH("+"&'14_FALLAS_ESC'!$A$2:$A$22&"+","+"&$B2&"+"))*('14_FALLAS_ESC'!$E$2:$E$22=D$1)*'14_FALLAS_ESC'!$J$2:$J$22) -> 0 | E2: =SUMPRODUCT(ISNUMBER(SEARCH("+"&'14_FALLAS_ESC'!$A$2:$A$22&"+","+"&$B2&"+"))*('14_FALLAS_ESC'!$E$2:$E$22=E$1)*'14_FALLAS_ESC'!$J$2:$J$22) -> 2 | F2: =SUMPRODUCT(ISNUMBER(SEARCH("+"&'14_FALLAS_ESC'!$A$2:$A$22&"+","+"&$B2&"+"))*('14_FALLAS_ESC'!$E$2:$E$22=F$1)*'14_FALLAS_ESC'!$J$2:$J$22) -> 0 | G2: =SUMPRODUCT(ISNUMBER(SEARCH("+"&'14_FALLAS_ESC'!$A$2:$A$22&"+","+"&$B2&"+"))*('14_FALLAS_ESC'!$E$2:$E$22=G$1)*'14_FALLAS_ESC'!$J$2:$J$22) -> 0 | H2: =SUM(C2:G2) -> 2 | I2: CALCULADO
A3: S01B | B3: F01 | C3: =SUMPRODUCT(ISNUMBER(SEARCH("+"&'14_FALLAS_ESC'!$A$2:$A$22&"+","+"&$B3&"+"))*('14_FALLAS_ESC'!$E$2:$E$22=C$1)*'14_FALLAS_ESC'!$J$2:$J$22) -> 0 | D3: =SUMPRODUCT(ISNUMBER(SEARCH("+"&'14_FALLAS_ESC'!$A$2:$A$22&"+","+"&$B3&"+"))*('14_FALLAS_ESC'!$E$2:$E$22=D$1)*'14_FALLAS_ESC'!$J$2:$J$22) -> 0 | E3: =SUMPRODUCT(ISNUMBER(SEARCH("+"&'14_FALLAS_ESC'!$A$2:$A$22&"+","+"&$B3&"+"))*('14_FALLAS_ESC'!$E$2:$E$22=E$1)*'14_FALLAS_ESC'!$J$2:$J$22) -> 2 | F3: =SUMPRODUCT(ISNUMBER(SEARCH("+"&'14_FALLAS_ESC'!$A$2:$A$22&"+","+"&$B3&"+"))*('14_FALLAS_ESC'!$E$2:$E$22=F$1)*'14_FALLAS_ESC'!$J$2:$J$22) -> 0 | G3: =SUMPRODUCT(ISNUMBER(SEARCH("+"&'14_FALLAS_ESC'!$A$2:$A$22&"+","+"&$B3&"+"))*('14_FALLAS_ESC'!$E$2:$E$22=G$1)*'14_FALLAS_ESC'!$J$2:$J$22) -> 0 | H3: =SUM(C3:G3) -> 2 | I3: CALCULADO
A4: S02A | B4: F02 | C4: =SUMPRODUCT(ISNUMBER(SEARCH("+"&'14_FALLAS_ESC'!$A$2:$A$22&"+","+"&$B4&"+"))*('14_FALLAS_ESC'!$E$2:$E$22=C$1)*'14_FALLAS_ESC'!$J$2:$J$22) -> 0 | D4: =SUMPRODUCT(ISNUMBER(SEARCH("+"&'14_FALLAS_ESC'!$A$2:$A$22&"+","+"&$B4&"+"))*('14_FALLAS_ESC'!$E$2:$E$22=D$1)*'14_FALLAS_ESC'!$J$2:$J$22) -> 0 | E4: =SUMPRODUCT(ISNUMBER(SEARCH("+"&'14_FALLAS_ESC'!$A$2:$A$22&"+","+"&$B4&"+"))*('14_FALLAS_ESC'!$E$2:$E$22=E$1)*'14_FALLAS_ESC'!$J$2:$J$22) -> 2 | F4: =SUMPRODUCT(ISNUMBER(SEARCH("+"&'14_FALLAS_ESC'!$A$2:$A$22&"+","+"&$B4&"+"))*('14_FALLAS_ESC'!$E$2:$E$22=F$1)*'14_FALLAS_ESC'!$J$2:$J$22) -> 0 | G4: =SUMPRODUCT(ISNUMBER(SEARCH("+"&'14_FALLAS_ESC'!$A$2:$A$22&"+","+"&$B4&"+"))*('14_FALLAS_ESC'!$E$2:$E$22=G$1)*'14_FALLAS_ESC'!$J$2:$J$22) -> 0 | H4: =SUM(C4:G4) -> 2 | I4: CALCULADO
A5: S02B | B5: F02 | C5: =SUMPRODUCT(ISNUMBER(SEARCH("+"&'14_FALLAS_ESC'!$A$2:$A$22&"+","+"&$B5&"+"))*('14_FALLAS_ESC'!$E$2:$E$22=C$1)*'14_FALLAS_ESC'!$J$2:$J$22) -> 0 | D5: =SUMPRODUCT(ISNUMBER(SEARCH("+"&'14_FALLAS_ESC'!$A$2:$A$22&"+","+"&$B5&"+"))*('14_FALLAS_ESC'!$E$2:$E$22=D$1)*'14_FALLAS_ESC'!$J$2:$J$22) -> 0 | E5: =SUMPRODUCT(ISNUMBER(SEARCH("+"&'14_FALLAS_ESC'!$A$2:$A$22&"+","+"&$B5&"+"))*('14_FALLAS_ESC'!$E$2:$E$22=E$1)*'14_FALLAS_ESC'!$J$2:$J$22) -> 2 | F5: =SUMPRODUCT(ISNUMBER(SEARCH("+"&'14_FALLAS_ESC'!$A$2:$A$22&"+","+"&$B5&"+"))*('14_FALLAS_ESC'!$E$2:$E$22=F$1)*'14_FALLAS_ESC'!$J$2:$J$22) -> 0 | G5: =SUMPRODUCT(ISNUMBER(SEARCH("+"&'14_FALLAS_ESC'!$A$2:$A$22&"+","+"&$B5&"+"))*('14_FALLAS_ESC'!$E$2:$E$22=G$1)*'14_FALLAS_ESC'!$J$2:$J$22) -> 0 | H5: =SUM(C5:G5) -> 2 | I5: CALCULADO
A6: S03A | B6: F03 | C6: =SUMPRODUCT(ISNUMBER(SEARCH("+"&'14_FALLAS_ESC'!$A$2:$A$22&"+","+"&$B6&"+"))*('14_FALLAS_ESC'!$E$2:$E$22=C$1)*'14_FALLAS_ESC'!$J$2:$J$22) -> 0 | D6: =SUMPRODUCT(ISNUMBER(SEARCH("+"&'14_FALLAS_ESC'!$A$2:$A$22&"+","+"&$B6&"+"))*('14_FALLAS_ESC'!$E$2:$E$22=D$1)*'14_FALLAS_ESC'!$J$2:$J$22) -> 0 | E6: =SUMPRODUCT(ISNUMBER(SEARCH("+"&'14_FALLAS_ESC'!$A$2:$A$22&"+","+"&$B6&"+"))*('14_FALLAS_ESC'!$E$2:$E$22=E$1)*'14_FALLAS_ESC'!$J$2:$J$22) -> 3 | F6: =SUMPRODUCT(ISNUMBER(SEARCH("+"&'14_FALLAS_ESC'!$A$2:$A$22&"+","+"&$B6&"+"))*('14_FALLAS_ESC'!$E$2:$E$22=F$1)*'14_FALLAS_ESC'!$J$2:$J$22) -> 0 | G6: =SUMPRODUCT(ISNUMBER(SEARCH("+"&'14_FALLAS_ESC'!$A$2:$A$22&"+","+"&$B6&"+"))*('14_FALLAS_ESC'!$E$2:$E$22=G$1)*'14_FALLAS_ESC'!$J$2:$J$22) -> 0 | H6: =SUM(C6:G6) -> 3 | I6: CALCULADO
A7: S03B | B7: F03 | C7: =SUMPRODUCT(ISNUMBER(SEARCH("+"&'14_FALLAS_ESC'!$A$2:$A$22&"+","+"&$B7&"+"))*('14_FALLAS_ESC'!$E$2:$E$22=C$1)*'14_FALLAS_ESC'!$J$2:$J$22) -> 0 | D7: =SUMPRODUCT(ISNUMBER(SEARCH("+"&'14_FALLAS_ESC'!$A$2:$A$22&"+","+"&$B7&"+"))*('14_FALLAS_ESC'!$E$2:$E$22=D$1)*'14_FALLAS_ESC'!$J$2:$J$22) -> 0 | E7: =SUMPRODUCT(ISNUMBER(SEARCH("+"&'14_FALLAS_ESC'!$A$2:$A$22&"+","+"&$B7&"+"))*('14_FALLAS_ESC'!$E$2:$E$22=E$1)*'14_FALLAS_ESC'!$J$2:$J$22) -> 3 | F7: =SUMPRODUCT(ISNUMBER(SEARCH("+"&'14_FALLAS_ESC'!$A$2:$A$22&"+","+"&$B7&"+"))*('14_FALLAS_ESC'!$E$2:$E$22=F$1)*'14_FALLAS_ESC'!$J$2:$J$22) -> 0 | G7: =SUMPRODUCT(ISNUMBER(SEARCH("+"&'14_FALLAS_ESC'!$A$2:$A$22&"+","+"&$B7&"+"))*('14_FALLAS_ESC'!$E$2:$E$22=G$1)*'14_FALLAS_ESC'!$J$2:$J$22) -> 0 | H7: =SUM(C7:G7) -> 3 | I7: CALCULADO
A8: S04A | B8: F04 | C8: =SUMPRODUCT(ISNUMBER(SEARCH("+"&'14_FALLAS_ESC'!$A$2:$A$22&"+","+"&$B8&"+"))*('14_FALLAS_ESC'!$E$2:$E$22=C$1)*'14_FALLAS_ESC'!$J$2:$J$22) -> 0 | D8: =SUMPRODUCT(ISNUMBER(SEARCH("+"&'14_FALLAS_ESC'!$A$2:$A$22&"+","+"&$B8&"+"))*('14_FALLAS_ESC'!$E$2:$E$22=D$1)*'14_FALLAS_ESC'!$J$2:$J$22) -> 0 | E8: =SUMPRODUCT(ISNUMBER(SEARCH("+"&'14_FALLAS_ESC'!$A$2:$A$22&"+","+"&$B8&"+"))*('14_FALLAS_ESC'!$E$2:$E$22=E$1)*'14_FALLAS_ESC'!$J$2:$J$22) -> 5 | F8: =SUMPRODUCT(ISNUMBER(SEARCH("+"&'14_FALLAS_ESC'!$A$2:$A$22&"+","+"&$B8&"+"))*('14_FALLAS_ESC'!$E$2:$E$22=F$1)*'14_FALLAS_ESC'!$J$2:$J$22) -> 0 | G8: =SUMPRODUCT(ISNUMBER(SEARCH("+"&'14_FALLAS_ESC'!$A$2:$A$22&"+","+"&$B8&"+"))*('14_FALLAS_ESC'!$E$2:$E$22=G$1)*'14_FALLAS_ESC'!$J$2:$J$22) -> 0 | H8: =SUM(C8:G8) -> 5 | I8: CALCULADO
A9: S04B | B9: F04 | C9: =SUMPRODUCT(ISNUMBER(SEARCH("+"&'14_FALLAS_ESC'!$A$2:$A$22&"+","+"&$B9&"+"))*('14_FALLAS_ESC'!$E$2:$E$22=C$1)*'14_FALLAS_ESC'!$J$2:$J$22) -> 0 | D9: =SUMPRODUCT(ISNUMBER(SEARCH("+"&'14_FALLAS_ESC'!$A$2:$A$22&"+","+"&$B9&"+"))*('14_FALLAS_ESC'!$E$2:$E$22=D$1)*'14_FALLAS_ESC'!$J$2:$J$22) -> 0 | E9: =SUMPRODUCT(ISNUMBER(SEARCH("+"&'14_FALLAS_ESC'!$A$2:$A$22&"+","+"&$B9&"+"))*('14_FALLAS_ESC'!$E$2:$E$22=E$1)*'14_FALLAS_ESC'!$J$2:$J$22) -> 5 | F9: =SUMPRODUCT(ISNUMBER(SEARCH("+"&'14_FALLAS_ESC'!$A$2:$A$22&"+","+"&$B9&"+"))*('14_FALLAS_ESC'!$E$2:$E$22=F$1)*'14_FALLAS_ESC'!$J$2:$J$22) -> 0 | G9: =SUMPRODUCT(ISNUMBER(SEARCH("+"&'14_FALLAS_ESC'!$A$2:$A$22&"+","+"&$B9&"+"))*('14_FALLAS_ESC'!$E$2:$E$22=G$1)*'14_FALLAS_ESC'!$J$2:$J$22) -> 0 | H9: =SUM(C9:G9) -> 5 | I9: CALCULADO
A10: S05A | B10: F05 | C10: =SUMPRODUCT(ISNUMBER(SEARCH("+"&'14_FALLAS_ESC'!$A$2:$A$22&"+","+"&$B10&"+"))*('14_FALLAS_ESC'!$E$2:$E$22=C$1)*'14_FALLAS_ESC'!$J$2:$J$22) -> 0 | D10: =SUMPRODUCT(ISNUMBER(SEARCH("+"&'14_FALLAS_ESC'!$A$2:$A$22&"+","+"&$B10&"+"))*('14_FALLAS_ESC'!$E$2:$E$22=D$1)*'14_FALLAS_ESC'!$J$2:$J$22) -> 0 | E10: =SUMPRODUCT(ISNUMBER(SEARCH("+"&'14_FALLAS_ESC'!$A$2:$A$22&"+","+"&$B10&"+"))*('14_FALLAS_ESC'!$E$2:$E$22=E$1)*'14_FALLAS_ESC'!$J$2:$J$22) -> 2.5 | F10: =SUMPRODUCT(ISNUMBER(SEARCH("+"&'14_FALLAS_ESC'!$A$2:$A$22&"+","+"&$B10&"+"))*('14_FALLAS_ESC'!$E$2:$E$22=F$1)*'14_FALLAS_ESC'!$J$2:$J$22) -> 0 | G10: =SUMPRODUCT(ISNUMBER(SEARCH("+"&'14_FALLAS_ESC'!$A$2:$A$22&"+","+"&$B10&"+"))*('14_FALLAS_ESC'!$E$2:$E$22=G$1)*'14_FALLAS_ESC'!$J$2:$J$22) -> 0 | H10: =SUM(C10:G10) -> 2.5 | I10: CALCULADO
A11: S05B | B11: F05 | C11: =SUMPRODUCT(ISNUMBER(SEARCH("+"&'14_FALLAS_ESC'!$A$2:$A$22&"+","+"&$B11&"+"))*('14_FALLAS_ESC'!$E$2:$E$22=C$1)*'14_FALLAS_ESC'!$J$2:$J$22) -> 0 | D11: =SUMPRODUCT(ISNUMBER(SEARCH("+"&'14_FALLAS_ESC'!$A$2:$A$22&"+","+"&$B11&"+"))*('14_FALLAS_ESC'!$E$2:$E$22=D$1)*'14_FALLAS_ESC'!$J$2:$J$22) -> 0 | E11: =SUMPRODUCT(ISNUMBER(SEARCH("+"&'14_FALLAS_ESC'!$A$2:$A$22&"+","+"&$B11&"+"))*('14_FALLAS_ESC'!$E$2:$E$22=E$1)*'14_FALLAS_ESC'!$J$2:$J$22) -> 2.5 | F11: =SUMPRODUCT(ISNUMBER(SEARCH("+"&'14_FALLAS_ESC'!$A$2:$A$22&"+","+"&$B11&"+"))*('14_FALLAS_ESC'!$E$2:$E$22=F$1)*'14_FALLAS_ESC'!$J$2:$J$22) -> 0 | G11: =SUMPRODUCT(ISNUMBER(SEARCH("+"&'14_FALLAS_ESC'!$A$2:$A$22&"+","+"&$B11&"+"))*('14_FALLAS_ESC'!$E$2:$E$22=G$1)*'14_FALLAS_ESC'!$J$2:$J$22) -> 0 | H11: =SUM(C11:G11) -> 2.5 | I11: CALCULADO
A12: S06A | B12: F06 | C12: =SUMPRODUCT(ISNUMBER(SEARCH("+"&'14_FALLAS_ESC'!$A$2:$A$22&"+","+"&$B12&"+"))*('14_FALLAS_ESC'!$E$2:$E$22=C$1)*'14_FALLAS_ESC'!$J$2:$J$22) -> 0 | D12: =SUMPRODUCT(ISNUMBER(SEARCH("+"&'14_FALLAS_ESC'!$A$2:$A$22&"+","+"&$B12&"+"))*('14_FALLAS_ESC'!$E$2:$E$22=D$1)*'14_FALLAS_ESC'!$J$2:$J$22) -> 0 | E12: =SUMPRODUCT(ISNUMBER(SEARCH("+"&'14_FALLAS_ESC'!$A$2:$A$22&"+","+"&$B12&"+"))*('14_FALLAS_ESC'!$E$2:$E$22=E$1)*'14_FALLAS_ESC'!$J$2:$J$22) -> 4 | F12: =SUMPRODUCT(ISNUMBER(SEARCH("+"&'14_FALLAS_ESC'!$A$2:$A$22&"+","+"&$B12&"+"))*('14_FALLAS_ESC'!$E$2:$E$22=F$1)*'14_FALLAS_ESC'!$J$2:$J$22) -> 0 | G12: =SUMPRODUCT(ISNUMBER(SEARCH("+"&'14_FALLAS_ESC'!$A$2:$A$22&"+","+"&$B12&"+"))*('14_FALLAS_ESC'!$E$2:$E$22=G$1)*'14_FALLAS_ESC'!$J$2:$J$22) -> 0 | H12: =SUM(C12:G12) -> 4 | I12: CALCULADO
A13: S06B | B13: F06 | C13: =SUMPRODUCT(ISNUMBER(SEARCH("+"&'14_FALLAS_ESC'!$A$2:$A$22&"+","+"&$B13&"+"))*('14_FALLAS_ESC'!$E$2:$E$22=C$1)*'14_FALLAS_ESC'!$J$2:$J$22) -> 0 | D13: =SUMPRODUCT(ISNUMBER(SEARCH("+"&'14_FALLAS_ESC'!$A$2:$A$22&"+","+"&$B13&"+"))*('14_FALLAS_ESC'!$E$2:$E$22=D$1)*'14_FALLAS_ESC'!$J$2:$J$22) -> 0 | E13: =SUMPRODUCT(ISNUMBER(SEARCH("+"&'14_FALLAS_ESC'!$A$2:$A$22&"+","+"&$B13&"+"))*('14_FALLAS_ESC'!$E$2:$E$22=E$1)*'14_FALLAS_ESC'!$J$2:$J$22) -> 4 | F13: =SUMPRODUCT(ISNUMBER(SEARCH("+"&'14_FALLAS_ESC'!$A$2:$A$22&"+","+"&$B13&"+"))*('14_FALLAS_ESC'!$E$2:$E$22=F$1)*'14_FALLAS_ESC'!$J$2:$J$22) -> 0 | G13: =SUMPRODUCT(ISNUMBER(SEARCH("+"&'14_FALLAS_ESC'!$A$2:$A$22&"+","+"&$B13&"+"))*('14_FALLAS_ESC'!$E$2:$E$22=G$1)*'14_FALLAS_ESC'!$J$2:$J$22) -> 0 | H13: =SUM(C13:G13) -> 4 | I13: CALCULADO
... A40: S20A | B40: F01+F02+F03+F04+F05+F06+F07+F08+F09+F10+F11+F12 | C40: =SUMPRODUCT(ISNUMBER(SEARCH("+"&'14_FALLAS_ESC'!$A$2:$A$22&"+","+"&$B40&"+"))*('14_FALLAS_ESC'!$E$2:$E$22=C$1)*'14_FALLAS_ESC'!$J$2:$J$22) -> 0 | D40: =SUMPRODUCT(ISNUMBER(SEARCH("+"&'14_FALLAS_ESC'!$A$2:$A$22&"+","+"&$B40&"+"))*('14_FALLAS_ESC'!$E$2:$E$22=D$1)*'14_FALLAS_ESC'!$J$2:$J$22) -> 0 | E40: =SUMPRODUCT(ISNUMBER(SEARCH("+"&'14_FALLAS_ESC'!$A$2:$A$22&"+","+"&$B40&"+"))*('14_FALLAS_ESC'!$E$2:$E$22=E$1)*'14_FALLAS_ESC'!$J$2:$J$22) -> 36.062667 | F40: =SUMPRODUCT(ISNUMBER(SEARCH("+"&'14_FALLAS_ESC'!$A$2:$A$22&"+","+"&$B40&"+"))*('14_FALLAS_ESC'!$E$2:$E$22=F$1)*'14_FALLAS_ESC'!$J$2:$J$22) -> 0 | G40: =SUMPRODUCT(ISNUMBER(SEARCH("+"&'14_FALLAS_ESC'!$A$2:$A$22&"+","+"&$B40&"+"))*('14_FALLAS_ESC'!$E$2:$E$22=G$1)*'14_FALLAS_ESC'!$J$2:$J$22) -> 0 | H40: =SUM(C40:G40) -> 36.062667 | I40: CALCULADO

Sheet 27_SENSIBILIDAD
A1: Factor | B1: Niveles | C1: Aplicado a | D1: Propósito | E1: Naturaleza
A2: Multiplicador de duración de la avería | B2: 0.5;1;2;4 | C2: F01–F12, política A | D2: Robustez ante averías más cortas o más largas | E2: CONFIGURACION
A3: Peso de reasignación β (h) | B3: 0;8;24 | C3: F01–F12, política A | D3: Efecto del criterio humano de estabilidad | E3: CONFIGURACION
A4: Regla de penalidad | B4: FIJA;DIARIA_CON_TOPE | C4: Año 2025 y F01–F12 | D4: Cambio de la regla económica | E4: CONFIGURACION
A5: Factor de tiempo en máquina alternativa | B5: 1.0;1.1;1.25 | C5: S15 y S16 | D5: Valor de la flexibilidad de asignación | E5: CONFIGURACION
A6: Aplicar feriados nacionales | B6: 0;1 | C6: Año 2025 | D6: Calendario sin y con feriados | E6: CONFIGURACION
