Workbook

Sheet 00_DICCIONARIO
A1: hoja | B1: columna | C1: tipo | D1: unidad | E1: obligatorio_1_0 | F1: naturaleza | G1: descripcion | H1: usado_por_python
A2: 01_FAMILIAS | B2: familia_id | C2: texto | E2: 1 | F2: REAL | G2: Clave de familia.
A3: 01_FAMILIAS | B3: familia | C3: texto | E3: 1 | F3: REAL | G3: Familia productiva declarada por la empresa.
A4: 01_FAMILIAS | B4: unidades_vendidas_2025 | C4: entero | D4: und | E4: 1 | F4: REAL | G4: Unidades agregadas 2025 del archivo de la empresa. | H4: datos.leer → 12_PRECIOS (precio medio)
A5: 01_FAMILIAS | B5: ventas_2025_soles | C5: moneda S/ | D5: S/ | E5: 1 | F5: REAL | G5: Ventas agregadas 2025 del archivo de la empresa. | H5: datos.leer → 12_PRECIOS (precio medio)
A6: 01_FAMILIAS | B6: precio_promedio_soles | C6: moneda S/ | D6: S/ por und | E6: 1 | F6: CALCULADO | G6: Fórmula: ventas / unidades.
A7: 01_FAMILIAS | B7: penalidad_fija_frac | C7: fracción | D7: fracción | E7: 1 | F7: ESTIMADO | G7: Fracción del valor del pedido si se entrega tarde. | H7: Objetivo f1 (P_j)
A8: 01_FAMILIAS | B8: penalidad_diaria_frac | C8: fracción | D8: fracción/día | E8: 1 | F8: ESTIMADO | G8: Fracción diaria (0 = no se usa). | H8: datos.leer (no interviene en f1)
A9: 01_FAMILIAS | B9: naturaleza | C9: texto | E9: 1 | G9: Naturaleza principal de la fila.
A10: 02_PRODUCTOS | B10: producto_id | C10: texto | E10: 1 | G10: Clave de producto.
A11: 02_PRODUCTOS | B11: familia_id | C11: texto | E11: 1 | G11: Familia (01_FAMILIAS).
A12: 02_PRODUCTOS | B12: producto | C12: texto | E12: 1 | G12: Nombre del producto (clave que usa Python). | H12: datos.leer → 01_PRODUCTOS
A13: 02_PRODUCTOS | B13: tipo | C13: texto | E13: 1 | G13: Tipo comercial.
A14: 02_PRODUCTOS | B14: alto_cm | C14: decimal | D14: cm | E14: 1 | F14: ESTIMADO | G14: Alto exterior.
A15: 02_PRODUCTOS | B15: ancho_cm | C15: decimal | D15: cm | E15: 1 | F15: ESTIMADO | G15: Ancho exterior.
A16: 02_PRODUCTOS | B16: fondo_cm | C16: decimal | D16: cm | E16: 1 | F16: ESTIMADO | G16: Fondo exterior.
A17: 02_PRODUCTOS | B17: puertas | C17: entero | D17: und | E17: 0 | G17: Número de puertas (vacío = no aplica).
A18: 02_PRODUCTOS | B18: lote_guia_und | C18: entero | D18: und | E18: 1 | F18: ESTIMADO | G18: Tamaño de lote de fabricación. | H18: Lote por defecto del pedido; duración (ROUNDUP(q/lote)·setup)
A19: 02_PRODUCTOS | B19: n_componentes | C19: entero | E19: 1 | F19: CALCULADO | G19: Líneas de despiece (fórmula).
A20: 02_PRODUCTOS | B20: n_pasos_ruta | C20: entero | E20: 1 | F20: CALCULADO | G20: Pasos de ruta (fórmula).
A21: 02_PRODUCTOS | B21: dimensiones_genericas | C21: binario 0/1 | E21: 1 | F21: CALCULADO | G21: 1 si ≥5 productos comparten exactamente las mismas dimensiones (indicio de plantilla, no de medición).
A22: 02_PRODUCTOS | B22: naturaleza | C22: texto | E22: 1 | G22: Naturaleza principal de la fila.
A23: 03_MATERIALES | B23: material_id | C23: texto | E23: 1 | G23: Clave técnica del material.
A24: 03_MATERIALES | B24: material | C24: texto | E24: 1 | G24: Descripción.
A25: 03_MATERIALES | B25: grupo | C25: texto | E25: 1 | G25: Grupo normalizado.
A26: 03_MATERIALES | B26: unidad_costo | C26: texto | E26: 1 | G26: Unidad del costo unitario.
A27: 03_MATERIALES | B27: espesor_mm | C27: decimal | D27: mm | E27: 0 | G27: Espesor nominal (vacío = no especificado).
A28: 03_MATERIALES | B28: ancho_m | C28: decimal | D28: m | E28: 0 | G28: Ancho del formato de compra.
A29: 03_MATERIALES | B29: largo_m | C29: decimal | D29: m | E29: 0 | G29: Largo del formato de compra.
A30: 03_MATERIALES | B30: costo_unitario_soles | C30: moneda S/ | D30: S/ | E30: 0 | F30: ESTIMADO | G30: Costo por unidad de costo (vacío = sin cotización).
A31: 03_MATERIALES | B31: material_generico | C31: binario 0/1 | E31: 1 | G31: 1 = material genérico (sección o tipo por definir).
A32: 03_MATERIALES | B32: naturaleza | C32: texto | E32: 1 | G32: ESTIMADO si tiene costo; PENDIENTE si falta el costo.
A33: 04_DESPIECE | B33: bom_id | C33: texto | E33: 1 | G33: Clave de línea de despiece.
A34: 04_DESPIECE | B34: producto_id | C34: texto | E34: 1 | G34: Producto.
A35: 04_DESPIECE | B35: componente | C35: texto | E35: 1 | G35: Componente.
A36: 04_DESPIECE | B36: material_id | C36: texto | E36: 1 | G36: Material (03_MATERIALES).
A37: 04_DESPIECE | B37: tipo_calculo | C37: texto | E37: 1 | G37: CHAPA_AREA | PERFIL_LONGITUD | UNIDAD | SIN_PRECIO.
A38: 04_DESPIECE | B38: piezas_por_unidad | C38: entero | D38: pzas | E38: 1 | F38: ESTIMADO | G38: Piezas por unidad de producto.
A39: 04_DESPIECE | B39: ancho_pieza_mm | C39: decimal | D39: mm | E39: 0 | G39: Desarrollo de la pieza de chapa.
A40: 04_DESPIECE | B40: alto_pieza_mm | C40: decimal | D40: mm | E40: 0 | G40: Desarrollo de la pieza de chapa.
A41: 04_DESPIECE | B41: longitud_pieza_m | C41: decimal | D41: m | E41: 0 | G41: Longitud de perfil por pieza.
A42: 04_DESPIECE | B42: area_chapa_m2_pieza | C42: decimal | D42: m² | E42: 0 | G42: Área por PIEZA (fórmula ancho×alto si hay medidas).
A43: 04_DESPIECE | B43: masa_kg_producto | C43: decimal | D43: kg | E43: 0 | F43: CALCULADO | G43: Masa por unidad de producto (fórmula; vacío si no es calculable). | H43: 03_DESPIECE → masa de chapa (reprocesos)
A44: 04_DESPIECE | B44: costo_soles_producto | C44: moneda S/ | D44: S/ | E44: 0 | F44: CALCULADO | G44: Costo de la línea por unidad de producto (fórmula).
A45: 04_DESPIECE | B45: planchas_equiv_producto | C45: decimal | D45: planchas | E45: 0 | F45: CALCULADO | G45: Piezas × área / área de plancha (corregido en v2).
A46: 04_DESPIECE | B46: naturaleza | C46: texto | E46: 1 | G46: Naturaleza de la fila.
A47: 05_RECURSOS | B47: recurso_id | C47: texto | E47: 1 | G47: Clave del recurso.
A48: 05_RECURSOS | B48: recurso | C48: texto | E48: 1 | G48: Nombre (clave que usa Python). | H48: datos.leer → 04_MAQUINAS
A49: 05_RECURSOS | B49: tipo_tecnico | C49: texto | E49: 1 | G49: Descripción técnica.
A50: 05_RECURSOS | B50: tipo_recurso | C50: texto | E50: 1 | F50: ESTIMADO | G50: MAQUINA | EQUIPO_MANUAL | PUESTO_MANUAL | AREA | EXTERNO.
A51: 05_RECURSOS | B51: cantidad | C51: entero | D51: und | E51: 1 | F51: ESTIMADO | G51: Unidades del recurso en el escenario. | H51: Validación: recurso disponible si ≥ 1 (el MILP trata cada recurso con capacidad 1)
A52: 05_RECURSOS | B52: costo_uso_soles_h | C52: moneda S/ | D52: S/ por h | E52: 0 | F52: ESTIMADO | G52: Tarifa de uso (vacío = sin dato).
A53: 05_RECURSOS | B53: potencia_kw_ref | C53: decimal | D53: kW | E53: 1 | F53: ESTIMADO | G53: Potencia de catálogo. | H53: Energía (indicador)
A54: 05_RECURSOS | B54: factor_carga | C54: decimal | D54: fracción | E54: 1 | F54: ESTIMADO | G54: Factor medio de carga eléctrica. | H54: Energía (indicador)
A55: 05_RECURSOS | B55: grupo_operarios | C55: texto | E55: 1 | F55: ESTIMADO | G55: Grupo de personal.
A56: 05_RECURSOS | B56: recurso_critico | C56: binario 0/1 | E56: 1 | G56: 1 = recurso de estudio (plegadora).
A57: 05_RECURSOS | B57: inventario_verificado | C57: binario 0/1 | E57: 1 | F57: PENDIENTE | G57: 1 solo cuando la empresa confirme la existencia física.
A58: 05_RECURSOS | B58: naturaleza | C58: texto | E58: 1 | G58: Naturaleza de la fila.
A59: 06_RUTAS | B59: producto_id | C59: texto | E59: 1 | G59: Producto.
A60: 06_RUTAS | B60: paso | C60: entero | E60: 1 | G60: Número de paso (1..n).
A61: 06_RUTAS | B61: operacion | C61: texto | E61: 1 | G61: Operación.
A62: 06_RUTAS | B62: recurso_id | C62: texto | E62: 1 | G62: Recurso principal.
A63: 06_RUTAS | B63: paso_predecesor | C63: entero | E63: 0 | G63: Paso anterior (vacío = primera operación).
A64: 06_RUTAS | B64: min_fijos_lote | C64: decimal | D64: min por lote | E64: 1 | F64: ESTIMADO | G64: Preparación por lote. | H64: p_om = (ROUNDUP(q/lote)·setup + q·u)/60
A65: 06_RUTAS | B65: min_por_unidad | C65: decimal | D65: min por und | E65: 1 | F65: ESTIMADO | G65: Tiempo por unidad de producto. | H65: p_om
A66: 06_RUTAS | B66: tratamiento_tiempo | C66: texto | E66: 1 | G66: POR_UNIDAD | POR_LOTE. | H66: Recuperación tras avería
A67: 06_RUTAS | B67: min_ciclo_horno_incluido | C67: decimal | D67: min | E67: 0 | G67: Minutos de ciclo de horno ya incluidos en min_fijos_lote.
A68: 06_RUTAS | B68: origen_tiempo | C68: texto | E68: 1 | G68: HEREDADO_SIN_CRONOMETRAJE | HIPOTESIS_TECNICA.
A69: 06_RUTAS | B69: naturaleza | C69: texto | E69: 1 | G69: Naturaleza de la fila.
A70: 07_ELEGIBILIDAD | B70: producto_id | C70: texto | E70: 1 | G70: Producto.
A71: 07_ELEGIBILIDAD | B71: paso | C71: entero | E71: 1 | G71: Paso.
A72: 07_ELEGIBILIDAD | B72: recurso_id | C72: texto | E72: 1 | G72: Recurso elegible. | H72: Conjunto M_o del MILP
A73: 07_ELEGIBILIDAD | B73: tipo_asignacion | C73: texto | E73: 1 | G73: PRINCIPAL | ALT_UTILLAJE | ALT_MISMO_PROCESO.
A74: 07_ELEGIBILIDAD | B74: elegible | C74: binario 0/1 | E74: 1 | G74: 1 = elegible.
A75: 07_ELEGIBILIDAD | B75: factor_tiempo | C75: decimal | D75: × | E75: 1 | F75: ESTIMADO | G75: Multiplicador del tiempo de ruta en ese recurso. | H75: p_om en máquina alternativa
A76: 07_ELEGIBILIDAD | B76: naturaleza | C76: texto | E76: 1 | G76: CALCULADO (principal) / ESTIMADO (alternativa).
A77: 08_PERSONAL | B77: operario_id | C77: texto | E77: 1 | F77: REAL | G77: Seudónimo del trabajador (25 confirmados). | H77: 06_OPERARIOS (lista de trabajadores)
A78: 08_PERSONAL | B78: turno | C78: entero | E78: 1 | F78: REAL | G78: Turno asignado.
A79: 08_PERSONAL | B79: hora_entrada | C79: hora | E79: 1 | F79: ESTIMADO | G79: Entrada.
A80: 08_PERSONAL | B80: hora_salida | C80: hora | E80: 1 | F80: ESTIMADO | G80: Salida.
A81: 08_PERSONAL | B81: descanso_h | C81: decimal | D81: h | E81: 1 | F81: ESTIMADO | G81: Descanso no productivo.
A82: 08_PERSONAL | B82: horas_netas_dia | C82: decimal | D82: h | E82: 1 | F82: REAL | G82: Horas netas confirmadas.
A83: 08_PERSONAL | B83: control_horario_h | C83: decimal | D83: h | E83: 1 | F83: CALCULADO | G83: (salida − entrada) − descanso; debe igualar horas netas.
A84: 08_PERSONAL | B84: naturaleza | C84: texto | E84: 1 | G84: Naturaleza principal (existencia y jornada).
A85: 09_CALENDARIO | B85: fecha | C85: fecha | E85: 1 | G85: Fecha. | H85: 07_CALENDARIO
A86: 09_CALENDARIO | B86: dia_semana | C86: entero | E86: 1 | F86: CALCULADO | G86: 1 = lunes … 7 = domingo (fórmula).
A87: 09_CALENDARIO | B87: laborable_base | C87: binario 0/1 | E87: 1 | F87: ESTIMADO | G87: Día laborable del calendario base (lunes-viernes). | H87: Productivo (1/0)
A88: 09_CALENDARIO | B88: feriado_nacional | C88: texto | E88: 0 | F88: REFERENCIA | G88: Nombre del feriado nacional (vacío = no feriado). | H88: Feriado nacional Perú
A89: 09_CALENDARIO | B89: productivo_efectivo | C89: binario 0/1 | E89: 1 | F89: CALCULADO | G89: Fórmula: aplica feriados si p_aplicar_feriados = 1.
A90: 09_CALENDARIO | B90: horas_productivas | C90: decimal | D90: h | E90: 1 | F90: CALCULADO | G90: productivo_efectivo × horas por día.
A91: 09_CALENDARIO | B91: naturaleza | C91: texto | E91: 1 | G91: Naturaleza principal.
A92: 10_CAPACIDAD_MENSUAL | B92: recurso_id | C92: texto | E92: 1 | G92: Recurso.
A93: 10_CAPACIDAD_MENSUAL | B93: mes | C93: entero | E93: 1 | G93: Mes del año base.
A94: 10_CAPACIDAD_MENSUAL | B94: dias_productivos | C94: entero | D94: días | E94: 1 | F94: CALCULADO | G94: Días productivos efectivos del mes (fórmula).
A95: 10_CAPACIDAD_MENSUAL | B95: horas_dia | C95: decimal | D95: h | E95: 1 | F95: REAL | G95: Horas productivas por día.
A96: 10_CAPACIDAD_MENSUAL | B96: cantidad | C96: entero | E96: 1 | F96: ESTIMADO | G96: Unidades del recurso.
A97: 10_CAPACIDAD_MENSUAL | B97: horas_disponibles | C97: decimal | D97: h | E97: 1 | F97: CALCULADO | G97: días × horas × cantidad (sin descontar paradas: no hay historial).
A98: 10_CAPACIDAD_MENSUAL | B98: naturaleza | C98: texto | E98: 1
A99: 11_PARAMETROS | B99: parametro_id | C99: texto | E99: 1 | G99: Clave única del parámetro (nombre definido p_<id>).
A100: 11_PARAMETROS | B100: parametro | C100: texto | E100: 1 | G100: Nombre descriptivo; coincide con el nombre que lee Python cuando aplica.
...

Sheet 00_CODIGOS
A1: codigo_naturaleza | B1: definicion
A2: REAL | B2: Dato declarado o respaldado por la empresa (p. ej. 25 trabajadores, 1 turno, ventas agregadas).
A3: REFERENCIA | B3: Dato público verificable ajeno a la empresa (ley, constante física, UIT, feriados oficiales).
A4: CALCULADO | B4: Resultado de una operación reproducible a partir de otros datos de la base.
A5: ESTIMADO | B5: Aproximación justificada (heredada, de catálogo o de ingeniería) que requiere validación en planta.
A6: SIMULADO | B6: Dato artificial creado para probar el modelo. No es historial ni registro de SAGAPI.
A7: CONFIGURACION | B7: Parámetro de ejecución del modelo o del experimento; no describe la planta.
A8: PENDIENTE | B8: Dato necesario que no existe en la base; se deja vacío a propósito (ver pendientes).
A10: LIBRO | B10: SAGAPI — Base de datos OPERATIVA v2.0 (datos reales, de referencia, calculados y estimados; sin datos simulados).
A11: VERSION_BD | B11: 2.0.0
A12: COLORES | B12: Texto azul = dato introducido; texto negro = fórmula; encabezado azul oscuro.
A13: FECHAS | B13: AAAA-MM-DD (fecha) y AAAA-MM-DD hh:mm:ss (fecha-hora).

Sheet 01_FAMILIAS
A1: familia_id | B1: familia | C1: unidades_vendidas_2025 | D1: ventas_2025_soles | E1: precio_promedio_soles | F1: penalidad_fija_frac | G1: penalidad_diaria_frac | H1: naturaleza
A2: FAM-RAC | B2: Racks industriales | C2: 295 | D2: 781894.55 | E2: =D2/C2 -> 2650.49 | F2: 0.1 | G2: 0 | H2: REAL
A3: FAM-GON | B3: Góndolas comerciales | C3: 167 | D3: 359145.19 | E3: =D3/C3 -> 2150.57 | F3: 0.1 | G3: 0 | H3: REAL
A4: FAM-LOC | B4: Lockers metálicos | C4: 139 | D4: 250312.59 | E4: =D4/C4 -> 1800.81 | F4: 0.1 | G4: 0 | H4: REAL
A5: FAM-OTR | B5: Otros productos metalmecánicos | C5: 250 | D5: 580617.45 | E5: =D5/C5 -> 2322.4698 | F5: 0.1 | G5: 0 | H5: REAL

Sheet 02_PRODUCTOS
A1: producto_id | B1: familia_id | C1: producto | D1: tipo | E1: alto_cm | F1: ancho_cm | G1: fondo_cm | H1: puertas | I1: lote_guia_und | J1: n_componentes | K1: n_pasos_ruta | L1: dimensiones_genericas | M1: naturaleza
A2: PRD-001 | B2: FAM-RAC | C2: Minirack metálico con bandejas | D2: Estantería liviana | E2: 200 | F2: 120 | G2: 60 | I2: 10 | J2: =COUNTIF('04_DESPIECE'!$B$2:$B$225,A2) -> 7 | K2: =COUNTIF('06_RUTAS'!$A$2:$A$407,A2) -> 13 | L2: =IF(COUNTIFS($E$2:$E$51,E2,$F$2:$F$51,F2,$G$2:$G$51,G2)>=5,1,0) -> 0 | M2: ESTIMADO
A3: PRD-002 | B3: FAM-RAC | C3: Estante reforzado modular | D3: Estantería reforzada | E3: 200 | F3: 120 | G3: 60 | I3: 10 | J3: =COUNTIF('04_DESPIECE'!$B$2:$B$225,A3) -> 6 | K3: =COUNTIF('06_RUTAS'!$A$2:$A$407,A3) -> 13 | L3: =IF(COUNTIFS($E$2:$E$51,E3,$F$2:$F$51,F3,$G$2:$G$51,G3)>=5,1,0) -> 0 | M3: ESTIMADO
A4: PRD-003 | B4: FAM-RAC | C4: Rack selectivo para pallets | D4: Selectivo | E4: 400 | F4: 270 | G4: 110 | I4: 10 | J4: =COUNTIF('04_DESPIECE'!$B$2:$B$225,A4) -> 4 | K4: =COUNTIF('06_RUTAS'!$A$2:$A$407,A4) -> 8 | L4: =IF(COUNTIFS($E$2:$E$51,E4,$F$2:$F$51,F4,$G$2:$G$51,G4)>=5,1,0) -> 0 | M4: ESTIMADO
A5: PRD-004 | B5: FAM-RAC | C5: Rack cantilever 3 niveles | D5: Cantilever | E5: 300 | F5: 150 | G5: 100 | I5: 10 | J5: =COUNTIF('04_DESPIECE'!$B$2:$B$225,A5) -> 4 | K5: =COUNTIF('06_RUTAS'!$A$2:$A$407,A5) -> 8 | L5: =IF(COUNTIFS($E$2:$E$51,E5,$F$2:$F$51,F5,$G$2:$G$51,G5)>=5,1,0) -> 0 | M5: ESTIMADO
A6: PRD-005 | B6: FAM-RAC | C6: Estantería metálica K45 5 niveles | D6: Picking | E6: 200 | F6: 120 | G6: 60 | I6: 10 | J6: =COUNTIF('04_DESPIECE'!$B$2:$B$225,A6) -> 4 | K6: =COUNTIF('06_RUTAS'!$A$2:$A$407,A6) -> 10 | L6: =IF(COUNTIFS($E$2:$E$51,E6,$F$2:$F$51,F6,$G$2:$G$51,G6)>=5,1,0) -> 0 | M6: ESTIMADO
A7: PRD-006 | B7: FAM-RAC | C7: Rack Mecano Strong MY-075-1 | D7: Semindustrial | E7: 200 | F7: 120 | G7: 60 | I7: 10 | J7: =COUNTIF('04_DESPIECE'!$B$2:$B$225,A7) -> 4 | K7: =COUNTIF('06_RUTAS'!$A$2:$A$407,A7) -> 8 | L7: =IF(COUNTIFS($E$2:$E$51,E7,$F$2:$F$51,F7,$G$2:$G$51,G7)>=5,1,0) -> 0 | M7: ESTIMADO
A8: PRD-007 | B8: FAM-GON | C8: Góndola central comercial | D8: Góndola central | E8: 160 | F8: 100 | G8: 90 | I8: 10 | J8: =COUNTIF('04_DESPIECE'!$B$2:$B$225,A8) -> 7 | K8: =COUNTIF('06_RUTAS'!$A$2:$A$407,A8) -> 12 | L8: =IF(COUNTIFS($E$2:$E$51,E8,$F$2:$F$51,F8,$G$2:$G$51,G8)>=5,1,0) -> 0 | M8: ESTIMADO
A9: PRD-008 | B9: FAM-GON | C9: Góndola mural | D9: Góndola mural | E9: 200 | F9: 100 | G9: 45 | I9: 10 | J9: =COUNTIF('04_DESPIECE'!$B$2:$B$225,A9) -> 6 | K9: =COUNTIF('06_RUTAS'!$A$2:$A$407,A9) -> 13 | L9: =IF(COUNTIFS($E$2:$E$51,E9,$F$2:$F$51,F9,$G$2:$G$51,G9)>=5,1,0) -> 0 | M9: ESTIMADO
A10: PRD-009 | B10: FAM-GON | C10: Góndola central doble forro liso | D10: Central | E10: 160 | F10: 100 | G10: 90 | I10: 10 | J10: =COUNTIF('04_DESPIECE'!$B$2:$B$225,A10) -> 5 | K10: =COUNTIF('06_RUTAS'!$A$2:$A$407,A10) -> 10 | L10: =IF(COUNTIFS($E$2:$E$51,E10,$F$2:$F$51,F10,$G$2:$G$51,G10)>=5,1,0) -> 0 | M10: ESTIMADO
A11: PRD-010 | B11: FAM-GON | C11: Góndola mural de forro liso | D11: Pared | E11: 200 | F11: 100 | G11: 45 | I11: 10 | J11: =COUNTIF('04_DESPIECE'!$B$2:$B$225,A11) -> 5 | K11: =COUNTIF('06_RUTAS'!$A$2:$A$407,A11) -> 10 | L11: =IF(COUNTIFS($E$2:$E$51,E11,$F$2:$F$51,F11,$G$2:$G$51,G11)>=5,1,0) -> 0 | M11: ESTIMADO
A12: PRD-011 | B12: FAM-GON | C12: Góndola de cabecera liso | D12: Cabecera | E12: 150 | F12: 90 | G12: 45 | I12: 10 | J12: =COUNTIF('04_DESPIECE'!$B$2:$B$225,A12) -> 5 | K12: =COUNTIF('06_RUTAS'!$A$2:$A$407,A12) -> 10 | L12: =IF(COUNTIFS($E$2:$E$51,E12,$F$2:$F$51,F12,$G$2:$G$51,G12)>=5,1,0) -> 0 | M12: ESTIMADO
A13: PRD-012 | B13: FAM-GON | C13: Góndola isla modular | D13: Isla | E13: 160 | F13: 100 | G13: 90 | I13: 10 | J13: =COUNTIF('04_DESPIECE'!$B$2:$B$225,A13) -> 5 | K13: =COUNTIF('06_RUTAS'!$A$2:$A$407,A13) -> 10 | L13: =IF(COUNTIFS($E$2:$E$51,E13,$F$2:$F$51,F13,$G$2:$G$51,G13)>=5,1,0) -> 0 | M13: ESTIMADO
A14: PRD-013 | B14: FAM-LOC | C14: Locker de 4 puertas | D14: Locker de 4 compartimentos | E14: 180 | F14: 80 | G14: 45 | H14: 4 | I14: 10 | J14: =COUNTIF('04_DESPIECE'!$B$2:$B$225,A14) -> 7 | K14: =COUNTIF('06_RUTAS'!$A$2:$A$407,A14) -> 11 | L14: =IF(COUNTIFS($E$2:$E$51,E14,$F$2:$F$51,F14,$G$2:$G$51,G14)>=5,1,0) -> 0 | M14: ESTIMADO
A15: PRD-014 | B15: FAM-LOC | C15: Locker de 6 puertas | D15: Locker de 6 compartimentos | E15: 180 | F15: 80 | G15: 45 | H15: 6 | I15: 10 | J15: =COUNTIF('04_DESPIECE'!$B$2:$B$225,A15) -> 8 | K15: =COUNTIF('06_RUTAS'!$A$2:$A$407,A15) -> 11 | L15: =IF(COUNTIFS($E$2:$E$51,E15,$F$2:$F$51,F15,$G$2:$G$51,G15)>=5,1,0) -> 0 | M15: ESTIMADO
A16: PRD-015 | B16: FAM-LOC | C16: Locker metálico simple MK1-01 | D16: 1 puertas | E16: 180 | F16: 40 | G16: 45 | H16: 1 | I16: 10 | J16: =COUNTIF('04_DESPIECE'!$B$2:$B$225,A16) -> 5 | K16: =COUNTIF('06_RUTAS'!$A$2:$A$407,A16) -> 8 | L16: =IF(COUNTIFS($E$2:$E$51,E16,$F$2:$F$51,F16,$G$2:$G$51,G16)>=5,1,0) -> 0 | M16: ESTIMADO
A17: PRD-016 | B17: FAM-LOC | C17: Locker metálico simple MK2-01 | D17: 2 puertas | E17: 180 | F17: 40 | G17: 45 | H17: 2 | I17: 10 | J17: =COUNTIF('04_DESPIECE'!$B$2:$B$225,A17) -> 5 | K17: =COUNTIF('06_RUTAS'!$A$2:$A$407,A17) -> 8 | L17: =IF(COUNTIFS($E$2:$E$51,E17,$F$2:$F$51,F17,$G$2:$G$51,G17)>=5,1,0) -> 0 | M17: ESTIMADO
A18: PRD-017 | B18: FAM-LOC | C18: Locker metálico simple MK3-01 | D18: 3 puertas | E18: 180 | F18: 40 | G18: 45 | H18: 3 | I18: 10 | J18: =COUNTIF('04_DESPIECE'!$B$2:$B$225,A18) -> 5 | K18: =COUNTIF('06_RUTAS'!$A$2:$A$407,A18) -> 8 | L18: =IF(COUNTIFS($E$2:$E$51,E18,$F$2:$F$51,F18,$G$2:$G$51,G18)>=5,1,0) -> 0 | M18: ESTIMADO
A19: PRD-018 | B19: FAM-LOC | C19: Locker metálico simple MK4-01 | D19: 4 puertas | E19: 180 | F19: 40 | G19: 45 | H19: 4 | I19: 10 | J19: =COUNTIF('04_DESPIECE'!$B$2:$B$225,A19) -> 5 | K19: =COUNTIF('06_RUTAS'!$A$2:$A$407,A19) -> 8 | L19: =IF(COUNTIFS($E$2:$E$51,E19,$F$2:$F$51,F19,$G$2:$G$51,G19)>=5,1,0) -> 0 | M19: ESTIMADO
A20: PRD-019 | B20: FAM-OTR | C20: Armario metálico | D20: Gabinete metálico | E20: 85 | F20: 120 | G20: 60 | I20: 10 | J20: =COUNTIF('04_DESPIECE'!$B$2:$B$225,A20) -> 7 | K20: =COUNTIF('06_RUTAS'!$A$2:$A$407,A20) -> 11 | L20: =IF(COUNTIFS($E$2:$E$51,E20,$F$2:$F$51,F20,$G$2:$G$51,G20)>=5,1,0) -> 1 | M20: ESTIMADO
A21: PRD-020 | B21: FAM-OTR | C21: Estantería liviana metálica | D21: Estantería liviana | E21: 85 | F21: 120 | G21: 60 | I21: 10 | J21: =COUNTIF('04_DESPIECE'!$B$2:$B$225,A21) -> 5 | K21: =COUNTIF('06_RUTAS'!$A$2:$A$407,A21) -> 12 | L21: =IF(COUNTIFS($E$2:$E$51,E21,$F$2:$F$51,F21,$G$2:$G$51,G21)>=5,1,0) -> 1 | M21: ESTIMADO
A22: PRD-021 | B22: FAM-OTR | C22: Silla fija PC0173 | D22: Silla | E22: 85 | F22: 45 | G22: 50 | I22: 10 | J22: =COUNTIF('04_DESPIECE'!$B$2:$B$225,A22) -> 3 | K22: =COUNTIF('06_RUTAS'!$A$2:$A$407,A22) -> 8 | L22: =IF(COUNTIFS($E$2:$E$51,E22,$F$2:$F$51,F22,$G$2:$G$51,G22)>=5,1,0) -> 1 | M22: ESTIMADO
A23: PRD-022 | B23: FAM-OTR | C23: Silla capacitación 105 | D23: Silla | E23: 85 | F23: 45 | G23: 50 | I23: 10 | J23: =COUNTIF('04_DESPIECE'!$B$2:$B$225,A23) -> 3 | K23: =COUNTIF('06_RUTAS'!$A$2:$A$407,A23) -> 2 | L23: =IF(COUNTIFS($E$2:$E$51,E23,$F$2:$F$51,F23,$G$2:$G$51,G23)>=5,1,0) -> 1 | M23: ESTIMADO
A24: PRD-023 | B24: FAM-OTR | C24: Cajonera metálica P1019 | D24: Archivador | E24: 85 | F24: 120 | G24: 60 | I24: 10 | J24: =COUNTIF('04_DESPIECE'!$B$2:$B$225,A24) -> 4 | K24: =COUNTIF('06_RUTAS'!$A$2:$A$407,A24) -> 8 | L24: =IF(COUNTIFS($E$2:$E$51,E24,$F$2:$F$51,F24,$G$2:$G$51,G24)>=5,1,0) -> 1 | M24: ESTIMADO
A25: PRD-024 | B25: FAM-OTR | C25: Archivador metálico 3 cajones | D25: Archivador | E25: 85 | F25: 120 | G25: 60 | I25: 10 | J25: =COUNTIF('04_DESPIECE'!$B$2:$B$225,A25) -> 4 | K25: =COUNTIF('06_RUTAS'!$A$2:$A$407,A25) -> 8 | L25: =IF(COUNTIFS($E$2:$E$51,E25,$F$2:$F$51,F25,$G$2:$G$51,G25)>=5,1,0) -> 1 | M25: ESTIMADO
A26: PRD-025 | B26: FAM-OTR | C26: Archivador metálico 4 cajones | D26: Archivador | E26: 85 | F26: 120 | G26: 60 | I26: 10 | J26: =COUNTIF('04_DESPIECE'!$B$2:$B$225,A26) -> 4 | K26: =COUNTIF('06_RUTAS'!$A$2:$A$407,A26) -> 8 | L26: =IF(COUNTIFS($E$2:$E$51,E26,$F$2:$F$51,F26,$G$2:$G$51,G26)>=5,1,0) -> 1 | M26: ESTIMADO
A27: PRD-026 | B27: FAM-OTR | C27: Armario metálico KD-034 | D27: Gabinete | E27: 85 | F27: 120 | G27: 60 | I27: 10 | J27: =COUNTIF('04_DESPIECE'!$B$2:$B$225,A27) -> 4 | K27: =COUNTIF('06_RUTAS'!$A$2:$A$407,A27) -> 8 | L27: =IF(COUNTIFS($E$2:$E$51,E27,$F$2:$F$51,F27,$G$2:$G$51,G27)>=5,1,0) -> 1 | M27: ESTIMADO
A28: PRD-027 | B28: FAM-OTR | C28: Banqueta con patas metálicas | D28: Banco | E28: 85 | F28: 120 | G28: 60 | I28: 10 | J28: =COUNTIF('04_DESPIECE'!$B$2:$B$225,A28) -> 4 | K28: =COUNTIF('06_RUTAS'!$A$2:$A$407,A28) -> 8 | L28: =IF(COUNTIFS($E$2:$E$51,E28,$F$2:$F$51,F28,$G$2:$G$51,G28)>=5,1,0) -> 1 | M28: ESTIMADO
A29: PRD-028 | B29: FAM-OTR | C29: Armario herramientas MY-TC-03 | D29: Gabinete | E29: 85 | F29: 120 | G29: 60 | I29: 10 | J29: =COUNTIF('04_DESPIECE'!$B$2:$B$225,A29) -> 4 | K29: =COUNTIF('06_RUTAS'!$A$2:$A$407,A29) -> 8 | L29: =IF(COUNTIFS($E$2:$E$51,E29,$F$2:$F$51,F29,$G$2:$G$51,G29)>=5,1,0) -> 1 | M29: ESTIMADO
A30: PRD-029 | B30: FAM-OTR | C30: Armario herramientas MY-TC-04 | D30: Gabinete | E30: 85 | F30: 120 | G30: 60 | I30: 10 | J30: =COUNTIF('04_DESPIECE'!$B$2:$B$225,A30) -> 4 | K30: =COUNTIF('06_RUTAS'!$A$2:$A$407,A30) -> 8 | L30: =IF(COUNTIFS($E$2:$E$51,E30,$F$2:$F$51,F30,$G$2:$G$51,G30)>=5,1,0) -> 1 | M30: ESTIMADO
A31: PRD-030 | B31: FAM-OTR | C31: Armario herramientas MY-TC-05 | D31: Gabinete | E31: 85 | F31: 120 | G31: 60 | I31: 10 | J31: =COUNTIF('04_DESPIECE'!$B$2:$B$225,A31) -> 4 | K31: =COUNTIF('06_RUTAS'!$A$2:$A$407,A31) -> 8 | L31: =IF(COUNTIFS($E$2:$E$51,E31,$F$2:$F$51,F31,$G$2:$G$51,G31)>=5,1,0) -> 1 | M31: ESTIMADO
... A51: PRD-050 | B51: FAM-OTR | C51: Silla terraza New Bistro | D51: Silla | E51: 85 | F51: 45 | G51: 50 | I51: 10 | J51: =COUNTIF('04_DESPIECE'!$B$2:$B$225,A51) -> 3 | K51: =COUNTIF('06_RUTAS'!$A$2:$A$407,A51) -> 8 | L51: =IF(COUNTIFS($E$2:$E$51,E51,$F$2:$F$51,F51,$G$2:$G$51,G51)>=5,1,0) -> 1 | M51: ESTIMADO

Sheet 03_MATERIALES
A1: material_id | B1: material | C1: grupo | D1: unidad_costo | E1: espesor_mm | F1: ancho_m | G1: largo_m | H1: costo_unitario_soles | I1: material_generico | J1: naturaleza
A2: MAT-LAC2 | B2: Plancha de acero laminado en caliente de 2 mm, 1.20 × 2.40 m | C2: CHAPA | D2: kg | E2: 2 | F2: 1.2 | G2: 2.4 | H2: 6.8 | I2: 0 | J2: ESTIMADO
A3: MAT-CH-1.0 | B3: Lámina LAF o acero 1.0 mm (alternativa V4) | C3: CHAPA | D3: kg | E3: 1 | H3: 6.8 | I3: 0 | J3: ESTIMADO
A4: MAT-CH-1.5 | B4: Lámina LAF o acero 1.5 mm (alternativa V4) | C4: CHAPA | D4: kg | E4: 1.5 | H4: 6.8 | I4: 0 | J4: ESTIMADO
A5: MAT-LAF06 | B5: Lámina LAF 0.6 mm (catálogo lockers) | C5: CHAPA | D5: kg | E5: 0.6 | H5: 6.8 | I5: 0 | J5: ESTIMADO
A6: MAT-LAF08 | B6: Lámina LAF 0.8 mm (catálogo góndolas) | C6: CHAPA | D6: kg | E6: 0.8 | H6: 6.8 | I6: 0 | J6: ESTIMADO
A7: MAT-LAF12 | B7: Lámina LAF 1.2 mm (taller) | C7: CHAPA | D7: kg | E7: 1.2 | H7: 6.8 | I7: 0 | J7: ESTIMADO
A8: MAT-PR-1 | B8: Tubo o perfil de acero (sección por definir) | C8: PERFIL | D8: m | H8: 6.1 | I8: 1 | J8: ESTIMADO
A9: MAT-FIJ | B9: Elementos de fijación metálica (tipo por desagregar) | C9: HERRAJE | D9: und | H9: 0.9 | I9: 1 | J9: ESTIMADO
A10: MAT-MEL18 | B10: Tablero melamina/MDP 18 mm comprado | C10: OTRO | D10: und | E10: 18 | I10: 0 | J10: PENDIENTE
A11: MAT-OTR | B11: Asiento, ruedas, vidrio, PVC o mecanismos comprados | C11: OTRO | D11: und | I11: 1 | J11: PENDIENTE
A12: COM-001 | B12: Pintura electrostática en polvo poliéster | C12: PINTURA | D12: kg | I12: 0 | J12: PENDIENTE
A13: COM-002 | B13: Pintura en polvo epoxi-poliéster | C13: PINTURA | D13: kg | I13: 0 | J13: PENDIENTE
A14: COM-003 | B14: Desengrasante industrial | C14: PREPARACION_SUPERFICIAL | D14: l | I14: 0 | J14: PENDIENTE
A15: COM-004 | B15: Disco abrasivo de corte | C15: CONSUMIBLE | D15: und | I15: 0 | J15: PENDIENTE
A16: COM-005 | B16: Disco abrasivo para desbarbado | C16: CONSUMIBLE | D16: und | I16: 0 | J16: PENDIENTE
A17: COM-006 | B17: Alambre para soldadura MIG/MAG | C17: SOLDADURA | D17: kg | I17: 0 | J17: PENDIENTE
A18: COM-007 | B18: Electrodo revestido para soldadura | C18: SOLDADURA | D18: kg | I18: 0 | J18: PENDIENTE
A19: COM-008 | B19: Gas protector para soldadura MIG/MAG | C19: SOLDADURA | D19: m3 | I19: 0 | J19: PENDIENTE
A20: COM-009 | B20: Tubo cuadrado de acero 30 × 30 mm | C20: PERFIL | D20: m | I20: 0 | J20: PENDIENTE
A21: COM-010 | B21: Tubo cuadrado de acero 40 × 40 mm | C21: PERFIL | D21: m | I21: 0 | J21: PENDIENTE
A22: COM-011 | B22: Ángulo de acero estructural | C22: PERFIL | D22: m | I22: 0 | J22: PENDIENTE
... A42: COM-031 | B42: Guante anticorte reutilizable | C42: SEGURIDAD | D42: par | I42: 0 | J42: PENDIENTE

Sheet 04_DESPIECE
A1: bom_id | B1: producto_id | C1: componente | D1: material_id | E1: tipo_calculo | F1: piezas_por_unidad | G1: ancho_pieza_mm | H1: alto_pieza_mm | I1: longitud_pieza_m | J1: area_chapa_m2_pieza | K1: masa_kg_producto | L1: costo_soles_producto | M1: planchas_equiv_producto | N1: naturaleza
A2: BOM-0001 | B2: PRD-001 | C2: Parante vertical | D2: MAT-PR-1 | E2: PERFIL_LONGITUD | F2: 4 | I2: 1.8 | K2: =IF(E2="CHAPA_AREA",F2*J2*INDEX('03_MATERIALES'!$E$2:$E$42,MATCH(D2,'03_MATERIALES'!$A$2:$A$42,0))/1000*p_densidad_acero,IF(E2="PERFIL_LONGITUD",F2*I2*p_kg_por_m_perfil,"")) -> 10.8 | L2: =IF(E2="CHAPA_AREA",K2*INDEX('03_MATERIALES'!$H$2:$H$42,MATCH(D2,'03_MATERIALES'!$A$2:$A$42,0))/p_aprovechamiento_chapa,IF(E2="PERFIL_LONGITUD",K2*INDEX('03_MATERIALES'!$H$2:$H$42,MATCH(D2,'03_MATERIALES'!$A$2:$A$42,0))/p_aprovechamiento_perfil,IF(E2="UNIDAD",F2*INDEX('03_MATERIALES'!$H$2:$H$42,MATCH(D2,'03_MATERIALES'!$A$2:$A$42,0)),""))) -> 68.625 | M2: =IF(N(J2)>0,F2*J2/p_area_plancha_m2,"") | N2: ESTIMADO
A3: BOM-0002 | B3: PRD-001 | C3: Larguero horizontal | D3: MAT-PR-1 | E3: PERFIL_LONGITUD | F3: 8 | I3: 1.2 | K3: =IF(E3="CHAPA_AREA",F3*J3*INDEX('03_MATERIALES'!$E$2:$E$42,MATCH(D3,'03_MATERIALES'!$A$2:$A$42,0))/1000*p_densidad_acero,IF(E3="PERFIL_LONGITUD",F3*I3*p_kg_por_m_perfil,"")) -> 14.4 | L3: =IF(E3="CHAPA_AREA",K3*INDEX('03_MATERIALES'!$H$2:$H$42,MATCH(D3,'03_MATERIALES'!$A$2:$A$42,0))/p_aprovechamiento_chapa,IF(E3="PERFIL_LONGITUD",K3*INDEX('03_MATERIALES'!$H$2:$H$42,MATCH(D3,'03_MATERIALES'!$A$2:$A$42,0))/p_aprovechamiento_perfil,IF(E3="UNIDAD",F3*INDEX('03_MATERIALES'!$H$2:$H$42,MATCH(D3,'03_MATERIALES'!$A$2:$A$42,0)),""))) -> 91.5 | M3: =IF(N(J3)>0,F3*J3/p_area_plancha_m2,"") | N3: ESTIMADO
A4: BOM-0003 | B4: PRD-001 | C4: Refuerzo transversal | D4: MAT-PR-1 | E4: PERFIL_LONGITUD | F4: 4 | I4: 0.6 | K4: =IF(E4="CHAPA_AREA",F4*J4*INDEX('03_MATERIALES'!$E$2:$E$42,MATCH(D4,'03_MATERIALES'!$A$2:$A$42,0))/1000*p_densidad_acero,IF(E4="PERFIL_LONGITUD",F4*I4*p_kg_por_m_perfil,"")) -> 3.6 | L4: =IF(E4="CHAPA_AREA",K4*INDEX('03_MATERIALES'!$H$2:$H$42,MATCH(D4,'03_MATERIALES'!$A$2:$A$42,0))/p_aprovechamiento_chapa,IF(E4="PERFIL_LONGITUD",K4*INDEX('03_MATERIALES'!$H$2:$H$42,MATCH(D4,'03_MATERIALES'!$A$2:$A$42,0))/p_aprovechamiento_perfil,IF(E4="UNIDAD",F4*INDEX('03_MATERIALES'!$H$2:$H$42,MATCH(D4,'03_MATERIALES'!$A$2:$A$42,0)),""))) -> 22.875 | M4: =IF(N(J4)>0,F4*J4/p_area_plancha_m2,"") | N4: ESTIMADO
A5: BOM-0004 | B5: PRD-001 | C5: Bandeja acero | D5: MAT-LAC2 | E5: CHAPA_AREA | F5: 4 | J5: 0.72 | K5: =IF(E5="CHAPA_AREA",F5*J5*INDEX('03_MATERIALES'!$E$2:$E$42,MATCH(D5,'03_MATERIALES'!$A$2:$A$42,0))/1000*p_densidad_acero,IF(E5="PERFIL_LONGITUD",F5*I5*p_kg_por_m_perfil,"")) -> 45.216 | L5: =IF(E5="CHAPA_AREA",K5*INDEX('03_MATERIALES'!$H$2:$H$42,MATCH(D5,'03_MATERIALES'!$A$2:$A$42,0))/p_aprovechamiento_chapa,IF(E5="PERFIL_LONGITUD",K5*INDEX('03_MATERIALES'!$H$2:$H$42,MATCH(D5,'03_MATERIALES'!$A$2:$A$42,0))/p_aprovechamiento_perfil,IF(E5="UNIDAD",F5*INDEX('03_MATERIALES'!$H$2:$H$42,MATCH(D5,'03_MATERIALES'!$A$2:$A$42,0)),""))) -> 334.20522 | M5: =IF(N(J5)>0,F5*J5/p_area_plancha_m2,"") -> 1 | N5: ESTIMADO
A6: BOM-0005 | B6: PRD-001 | C6: Cartela unión | D6: MAT-LAC2 | E6: CHAPA_AREA | F6: 8 | J6: 0.025 | K6: =IF(E6="CHAPA_AREA",F6*J6*INDEX('03_MATERIALES'!$E$2:$E$42,MATCH(D6,'03_MATERIALES'!$A$2:$A$42,0))/1000*p_densidad_acero,IF(E6="PERFIL_LONGITUD",F6*I6*p_kg_por_m_perfil,"")) -> 3.14 | L6: =IF(E6="CHAPA_AREA",K6*INDEX('03_MATERIALES'!$H$2:$H$42,MATCH(D6,'03_MATERIALES'!$A$2:$A$42,0))/p_aprovechamiento_chapa,IF(E6="PERFIL_LONGITUD",K6*INDEX('03_MATERIALES'!$H$2:$H$42,MATCH(D6,'03_MATERIALES'!$A$2:$A$42,0))/p_aprovechamiento_perfil,IF(E6="UNIDAD",F6*INDEX('03_MATERIALES'!$H$2:$H$42,MATCH(D6,'03_MATERIALES'!$A$2:$A$42,0)),""))) -> 23.208696 | M6: =IF(N(J6)>0,F6*J6/p_area_plancha_m2,"") -> 0.069444444 | N6: ESTIMADO
A7: BOM-0006 | B7: PRD-001 | C7: Tornillería sujeción | D7: MAT-FIJ | E7: UNIDAD | F7: 24 | K7: =IF(E7="CHAPA_AREA",F7*J7*INDEX('03_MATERIALES'!$E$2:$E$42,MATCH(D7,'03_MATERIALES'!$A$2:$A$42,0))/1000*p_densidad_acero,IF(E7="PERFIL_LONGITUD",F7*I7*p_kg_por_m_perfil,"")) | L7: =IF(E7="CHAPA_AREA",K7*INDEX('03_MATERIALES'!$H$2:$H$42,MATCH(D7,'03_MATERIALES'!$A$2:$A$42,0))/p_aprovechamiento_chapa,IF(E7="PERFIL_LONGITUD",K7*INDEX('03_MATERIALES'!$H$2:$H$42,MATCH(D7,'03_MATERIALES'!$A$2:$A$42,0))/p_aprovechamiento_perfil,IF(E7="UNIDAD",F7*INDEX('03_MATERIALES'!$H$2:$H$42,MATCH(D7,'03_MATERIALES'!$A$2:$A$42,0)),""))) -> 21.6 | M7: =IF(N(J7)>0,F7*J7/p_area_plancha_m2,"") | N7: ESTIMADO
A8: BOM-0007 | B8: PRD-001 | C8: Tapa protectora | D8: MAT-FIJ | E8: UNIDAD | F8: 4 | K8: =IF(E8="CHAPA_AREA",F8*J8*INDEX('03_MATERIALES'!$E$2:$E$42,MATCH(D8,'03_MATERIALES'!$A$2:$A$42,0))/1000*p_densidad_acero,IF(E8="PERFIL_LONGITUD",F8*I8*p_kg_por_m_perfil,"")) | L8: =IF(E8="CHAPA_AREA",K8*INDEX('03_MATERIALES'!$H$2:$H$42,MATCH(D8,'03_MATERIALES'!$A$2:$A$42,0))/p_aprovechamiento_chapa,IF(E8="PERFIL_LONGITUD",K8*INDEX('03_MATERIALES'!$H$2:$H$42,MATCH(D8,'03_MATERIALES'!$A$2:$A$42,0))/p_aprovechamiento_perfil,IF(E8="UNIDAD",F8*INDEX('03_MATERIALES'!$H$2:$H$42,MATCH(D8,'03_MATERIALES'!$A$2:$A$42,0)),""))) -> 3.6 | M8: =IF(N(J8)>0,F8*J8/p_area_plancha_m2,"") | N8: ESTIMADO
A9: BOM-0008 | B9: PRD-002 | C9: Parante perfil | D9: MAT-PR-1 | E9: PERFIL_LONGITUD | F9: 4 | I9: 2 | K9: =IF(E9="CHAPA_AREA",F9*J9*INDEX('03_MATERIALES'!$E$2:$E$42,MATCH(D9,'03_MATERIALES'!$A$2:$A$42,0))/1000*p_densidad_acero,IF(E9="PERFIL_LONGITUD",F9*I9*p_kg_por_m_perfil,"")) -> 12 | L9: =IF(E9="CHAPA_AREA",K9*INDEX('03_MATERIALES'!$H$2:$H$42,MATCH(D9,'03_MATERIALES'!$A$2:$A$42,0))/p_aprovechamiento_chapa,IF(E9="PERFIL_LONGITUD",K9*INDEX('03_MATERIALES'!$H$2:$H$42,MATCH(D9,'03_MATERIALES'!$A$2:$A$42,0))/p_aprovechamiento_perfil,IF(E9="UNIDAD",F9*INDEX('03_MATERIALES'!$H$2:$H$42,MATCH(D9,'03_MATERIALES'!$A$2:$A$42,0)),""))) -> 76.25 | M9: =IF(N(J9)>0,F9*J9/p_area_plancha_m2,"") | N9: ESTIMADO
A10: BOM-0009 | B10: PRD-002 | C10: Travesaño frontal | D10: MAT-PR-1 | E10: PERFIL_LONGITUD | F10: 8 | I10: 1 | K10: =IF(E10="CHAPA_AREA",F10*J10*INDEX('03_MATERIALES'!$E$2:$E$42,MATCH(D10,'03_MATERIALES'!$A$2:$A$42,0))/1000*p_densidad_acero,IF(E10="PERFIL_LONGITUD",F10*I10*p_kg_por_m_perfil,"")) -> 12 | L10: =IF(E10="CHAPA_AREA",K10*INDEX('03_MATERIALES'!$H$2:$H$42,MATCH(D10,'03_MATERIALES'!$A$2:$A$42,0))/p_aprovechamiento_chapa,IF(E10="PERFIL_LONGITUD",K10*INDEX('03_MATERIALES'!$H$2:$H$42,MATCH(D10,'03_MATERIALES'!$A$2:$A$42,0))/p_aprovechamiento_perfil,IF(E10="UNIDAD",F10*INDEX('03_MATERIALES'!$H$2:$H$42,MATCH(D10,'03_MATERIALES'!$A$2:$A$42,0)),""))) -> 76.25 | M10: =IF(N(J10)>0,F10*J10/p_area_plancha_m2,"") | N10: ESTIMADO
A11: BOM-0010 | B11: PRD-002 | C11: Travesaño lateral | D11: MAT-PR-1 | E11: PERFIL_LONGITUD | F11: 8 | I11: 0.5 | K11: =IF(E11="CHAPA_AREA",F11*J11*INDEX('03_MATERIALES'!$E$2:$E$42,MATCH(D11,'03_MATERIALES'!$A$2:$A$42,0))/1000*p_densidad_acero,IF(E11="PERFIL_LONGITUD",F11*I11*p_kg_por_m_perfil,"")) -> 6 | L11: =IF(E11="CHAPA_AREA",K11*INDEX('03_MATERIALES'!$H$2:$H$42,MATCH(D11,'03_MATERIALES'!$A$2:$A$42,0))/p_aprovechamiento_chapa,IF(E11="PERFIL_LONGITUD",K11*INDEX('03_MATERIALES'!$H$2:$H$42,MATCH(D11,'03_MATERIALES'!$A$2:$A$42,0))/p_aprovechamiento_perfil,IF(E11="UNIDAD",F11*INDEX('03_MATERIALES'!$H$2:$H$42,MATCH(D11,'03_MATERIALES'!$A$2:$A$42,0)),""))) -> 38.125 | M11: =IF(N(J11)>0,F11*J11/p_area_plancha_m2,"") | N11: ESTIMADO
A12: BOM-0011 | B12: PRD-002 | C12: Bandeja reforzada | D12: MAT-LAC2 | E12: CHAPA_AREA | F12: 5 | J12: 0.5 | K12: =IF(E12="CHAPA_AREA",F12*J12*INDEX('03_MATERIALES'!$E$2:$E$42,MATCH(D12,'03_MATERIALES'!$A$2:$A$42,0))/1000*p_densidad_acero,IF(E12="PERFIL_LONGITUD",F12*I12*p_kg_por_m_perfil,"")) -> 39.25 | L12: =IF(E12="CHAPA_AREA",K12*INDEX('03_MATERIALES'!$H$2:$H$42,MATCH(D12,'03_MATERIALES'!$A$2:$A$42,0))/p_aprovechamiento_chapa,IF(E12="PERFIL_LONGITUD",K12*INDEX('03_MATERIALES'!$H$2:$H$42,MATCH(D12,'03_MATERIALES'!$A$2:$A$42,0))/p_aprovechamiento_perfil,IF(E12="UNIDAD",F12*INDEX('03_MATERIALES'!$H$2:$H$42,MATCH(D12,'03_MATERIALES'!$A$2:$A$42,0)),""))) -> 290.1087 | M12: =IF(N(J12)>0,F12*J12/p_area_plancha_m2,"") -> 0.86805556 | N12: ESTIMADO
A13: BOM-0012 | B13: PRD-002 | C13: Cartela | D13: MAT-LAC2 | E13: CHAPA_AREA | F13: 8 | J13: 0.035 | K13: =IF(E13="CHAPA_AREA",F13*J13*INDEX('03_MATERIALES'!$E$2:$E$42,MATCH(D13,'03_MATERIALES'!$A$2:$A$42,0))/1000*p_densidad_acero,IF(E13="PERFIL_LONGITUD",F13*I13*p_kg_por_m_perfil,"")) -> 4.396 | L13: =IF(E13="CHAPA_AREA",K13*INDEX('03_MATERIALES'!$H$2:$H$42,MATCH(D13,'03_MATERIALES'!$A$2:$A$42,0))/p_aprovechamiento_chapa,IF(E13="PERFIL_LONGITUD",K13*INDEX('03_MATERIALES'!$H$2:$H$42,MATCH(D13,'03_MATERIALES'!$A$2:$A$42,0))/p_aprovechamiento_perfil,IF(E13="UNIDAD",F13*INDEX('03_MATERIALES'!$H$2:$H$42,MATCH(D13,'03_MATERIALES'!$A$2:$A$42,0)),""))) -> 32.492174 | M13: =IF(N(J13)>0,F13*J13/p_area_plancha_m2,"") -> 0.097222222 | N13: ESTIMADO
A14: BOM-0013 | B14: PRD-002 | C14: Juego pernos | D14: MAT-FIJ | E14: UNIDAD | F14: 28 | K14: =IF(E14="CHAPA_AREA",F14*J14*INDEX('03_MATERIALES'!$E$2:$E$42,MATCH(D14,'03_MATERIALES'!$A$2:$A$42,0))/1000*p_densidad_acero,IF(E14="PERFIL_LONGITUD",F14*I14*p_kg_por_m_perfil,"")) | L14: =IF(E14="CHAPA_AREA",K14*INDEX('03_MATERIALES'!$H$2:$H$42,MATCH(D14,'03_MATERIALES'!$A$2:$A$42,0))/p_aprovechamiento_chapa,IF(E14="PERFIL_LONGITUD",K14*INDEX('03_MATERIALES'!$H$2:$H$42,MATCH(D14,'03_MATERIALES'!$A$2:$A$42,0))/p_aprovechamiento_perfil,IF(E14="UNIDAD",F14*INDEX('03_MATERIALES'!$H$2:$H$42,MATCH(D14,'03_MATERIALES'!$A$2:$A$42,0)),""))) -> 25.2 | M14: =IF(N(J14)>0,F14*J14/p_area_plancha_m2,"") | N14: ESTIMADO
A15: BOM-0014 | B15: PRD-007 | C15: Columna doble | D15: MAT-PR-1 | E15: PERFIL_LONGITUD | F15: 2 | I15: 1.65 | K15: =IF(E15="CHAPA_AREA",F15*J15*INDEX('03_MATERIALES'!$E$2:$E$42,MATCH(D15,'03_MATERIALES'!$A$2:$A$42,0))/1000*p_densidad_acero,IF(E15="PERFIL_LONGITUD",F15*I15*p_kg_por_m_perfil,"")) -> 4.95 | L15: =IF(E15="CHAPA_AREA",K15*INDEX('03_MATERIALES'!$H$2:$H$42,MATCH(D15,'03_MATERIALES'!$A$2:$A$42,0))/p_aprovechamiento_chapa,IF(E15="PERFIL_LONGITUD",K15*INDEX('03_MATERIALES'!$H$2:$H$42,MATCH(D15,'03_MATERIALES'!$A$2:$A$42,0))/p_aprovechamiento_perfil,IF(E15="UNIDAD",F15*INDEX('03_MATERIALES'!$H$2:$H$42,MATCH(D15,'03_MATERIALES'!$A$2:$A$42,0)),""))) -> 31.453125 | M15: =IF(N(J15)>0,F15*J15/p_area_plancha_m2,"") | N15: ESTIMADO
A16: BOM-0015 | B16: PRD-007 | C16: Base apoyo | D16: MAT-CH-1.0 | E16: CHAPA_AREA | F16: 2 | J16: 0.3 | K16: =IF(E16="CHAPA_AREA",F16*J16*INDEX('03_MATERIALES'!$E$2:$E$42,MATCH(D16,'03_MATERIALES'!$A$2:$A$42,0))/1000*p_densidad_acero,IF(E16="PERFIL_LONGITUD",F16*I16*p_kg_por_m_perfil,"")) -> 4.71 | L16: =IF(E16="CHAPA_AREA",K16*INDEX('03_MATERIALES'!$H$2:$H$42,MATCH(D16,'03_MATERIALES'!$A$2:$A$42,0))/p_aprovechamiento_chapa,IF(E16="PERFIL_LONGITUD",K16*INDEX('03_MATERIALES'!$H$2:$H$42,MATCH(D16,'03_MATERIALES'!$A$2:$A$42,0))/p_aprovechamiento_perfil,IF(E16="UNIDAD",F16*INDEX('03_MATERIALES'!$H$2:$H$42,MATCH(D16,'03_MATERIALES'!$A$2:$A$42,0)),""))) -> 34.813043 | M16: =IF(N(J16)>0,F16*J16/p_area_plancha_m2,"") -> 0.20833333 | N16: ESTIMADO
A17: BOM-0016 | B17: PRD-007 | C17: Panel trasero | D17: MAT-CH-1.0 | E17: CHAPA_AREA | F17: 4 | J17: 0.56 | K17: =IF(E17="CHAPA_AREA",F17*J17*INDEX('03_MATERIALES'!$E$2:$E$42,MATCH(D17,'03_MATERIALES'!$A$2:$A$42,0))/1000*p_densidad_acero,IF(E17="PERFIL_LONGITUD",F17*I17*p_kg_por_m_perfil,"")) -> 17.584 | L17: =IF(E17="CHAPA_AREA",K17*INDEX('03_MATERIALES'!$H$2:$H$42,MATCH(D17,'03_MATERIALES'!$A$2:$A$42,0))/p_aprovechamiento_chapa,IF(E17="PERFIL_LONGITUD",K17*INDEX('03_MATERIALES'!$H$2:$H$42,MATCH(D17,'03_MATERIALES'!$A$2:$A$42,0))/p_aprovechamiento_perfil,IF(E17="UNIDAD",F17*INDEX('03_MATERIALES'!$H$2:$H$42,MATCH(D17,'03_MATERIALES'!$A$2:$A$42,0)),""))) -> 129.9687 | M17: =IF(N(J17)>0,F17*J17/p_area_plancha_m2,"") -> 0.77777778 | N17: ESTIMADO
A18: BOM-0017 | B18: PRD-007 | C18: Estante de exposición | D18: MAT-CH-1.0 | E18: CHAPA_AREA | F18: 8 | J18: 0.4 | K18: =IF(E18="CHAPA_AREA",F18*J18*INDEX('03_MATERIALES'!$E$2:$E$42,MATCH(D18,'03_MATERIALES'!$A$2:$A$42,0))/1000*p_densidad_acero,IF(E18="PERFIL_LONGITUD",F18*I18*p_kg_por_m_perfil,"")) -> 25.12 | L18: =IF(E18="CHAPA_AREA",K18*INDEX('03_MATERIALES'!$H$2:$H$42,MATCH(D18,'03_MATERIALES'!$A$2:$A$42,0))/p_aprovechamiento_chapa,IF(E18="PERFIL_LONGITUD",K18*INDEX('03_MATERIALES'!$H$2:$H$42,MATCH(D18,'03_MATERIALES'!$A$2:$A$42,0))/p_aprovechamiento_perfil,IF(E18="UNIDAD",F18*INDEX('03_MATERIALES'!$H$2:$H$42,MATCH(D18,'03_MATERIALES'!$A$2:$A$42,0)),""))) -> 185.66957 | M18: =IF(N(J18)>0,F18*J18/p_area_plancha_m2,"") -> 1.1111111 | N18: ESTIMADO
A19: BOM-0018 | B19: PRD-007 | C19: Ménsula | D19: MAT-CH-1.0 | E19: CHAPA_AREA | F19: 16 | J19: 0.04 | K19: =IF(E19="CHAPA_AREA",F19*J19*INDEX('03_MATERIALES'!$E$2:$E$42,MATCH(D19,'03_MATERIALES'!$A$2:$A$42,0))/1000*p_densidad_acero,IF(E19="PERFIL_LONGITUD",F19*I19*p_kg_por_m_perfil,"")) -> 5.024 | L19: =IF(E19="CHAPA_AREA",K19*INDEX('03_MATERIALES'!$H$2:$H$42,MATCH(D19,'03_MATERIALES'!$A$2:$A$42,0))/p_aprovechamiento_chapa,IF(E19="PERFIL_LONGITUD",K19*INDEX('03_MATERIALES'!$H$2:$H$42,MATCH(D19,'03_MATERIALES'!$A$2:$A$42,0))/p_aprovechamiento_perfil,IF(E19="UNIDAD",F19*INDEX('03_MATERIALES'!$H$2:$H$42,MATCH(D19,'03_MATERIALES'!$A$2:$A$42,0)),""))) -> 37.133913 | M19: =IF(N(J19)>0,F19*J19/p_area_plancha_m2,"") -> 0.22222222 | N19: ESTIMADO
A20: BOM-0019 | B20: PRD-007 | C20: Zócalo frontal | D20: MAT-CH-1.0 | E20: CHAPA_AREA | F20: 2 | J20: 0.12 | K20: =IF(E20="CHAPA_AREA",F20*J20*INDEX('03_MATERIALES'!$E$2:$E$42,MATCH(D20,'03_MATERIALES'!$A$2:$A$42,0))/1000*p_densidad_acero,IF(E20="PERFIL_LONGITUD",F20*I20*p_kg_por_m_perfil,"")) -> 1.884 | L20: =IF(E20="CHAPA_AREA",K20*INDEX('03_MATERIALES'!$H$2:$H$42,MATCH(D20,'03_MATERIALES'!$A$2:$A$42,0))/p_aprovechamiento_chapa,IF(E20="PERFIL_LONGITUD",K20*INDEX('03_MATERIALES'!$H$2:$H$42,MATCH(D20,'03_MATERIALES'!$A$2:$A$42,0))/p_aprovechamiento_perfil,IF(E20="UNIDAD",F20*INDEX('03_MATERIALES'!$H$2:$H$42,MATCH(D20,'03_MATERIALES'!$A$2:$A$42,0)),""))) -> 13.925217 | M20: =IF(N(J20)>0,F20*J20/p_area_plancha_m2,"") -> 0.083333333 | N20: ESTIMADO
A21: BOM-0020 | B21: PRD-007 | C21: Pernos de ensamble | D21: MAT-FIJ | E21: UNIDAD | F21: 36 | K21: =IF(E21="CHAPA_AREA",F21*J21*INDEX('03_MATERIALES'!$E$2:$E$42,MATCH(D21,'03_MATERIALES'!$A$2:$A$42,0))/1000*p_densidad_acero,IF(E21="PERFIL_LONGITUD",F21*I21*p_kg_por_m_perfil,"")) | L21: =IF(E21="CHAPA_AREA",K21*INDEX('03_MATERIALES'!$H$2:$H$42,MATCH(D21,'03_MATERIALES'!$A$2:$A$42,0))/p_aprovechamiento_chapa,IF(E21="PERFIL_LONGITUD",K21*INDEX('03_MATERIALES'!$H$2:$H$42,MATCH(D21,'03_MATERIALES'!$A$2:$A$42,0))/p_aprovechamiento_perfil,IF(E21="UNIDAD",F21*INDEX('03_MATERIALES'!$H$2:$H$42,MATCH(D21,'03_MATERIALES'!$A$2:$A$42,0)),""))) -> 32.4 | M21: =IF(N(J21)>0,F21*J21/p_area_plancha_m2,"") | N21: ESTIMADO
A22: BOM-0021 | B22: PRD-008 | C22: Montante mural | D22: MAT-PR-1 | E22: PERFIL_LONGITUD | F22: 2 | I22: 1.9 | K22: =IF(E22="CHAPA_AREA",F22*J22*INDEX('03_MATERIALES'!$E$2:$E$42,MATCH(D22,'03_MATERIALES'!$A$2:$A$42,0))/1000*p_densidad_acero,IF(E22="PERFIL_LONGITUD",F22*I22*p_kg_por_m_perfil,"")) -> 5.7 | L22: =IF(E22="CHAPA_AREA",K22*INDEX('03_MATERIALES'!$H$2:$H$42,MATCH(D22,'03_MATERIALES'!$A$2:$A$42,0))/p_aprovechamiento_chapa,IF(E22="PERFIL_LONGITUD",K22*INDEX('03_MATERIALES'!$H$2:$H$42,MATCH(D22,'03_MATERIALES'!$A$2:$A$42,0))/p_aprovechamiento_perfil,IF(E22="UNIDAD",F22*INDEX('03_MATERIALES'!$H$2:$H$42,MATCH(D22,'03_MATERIALES'!$A$2:$A$42,0)),""))) -> 36.21875 | M22: =IF(N(J22)>0,F22*J22/p_area_plancha_m2,"") | N22: ESTIMADO
A23: BOM-0022 | B23: PRD-008 | C23: Panel de fondo | D23: MAT-CH-1.0 | E23: CHAPA_AREA | F23: 3 | J23: 0.55 | K23: =IF(E23="CHAPA_AREA",F23*J23*INDEX('03_MATERIALES'!$E$2:$E$42,MATCH(D23,'03_MATERIALES'!$A$2:$A$42,0))/1000*p_densidad_acero,IF(E23="PERFIL_LONGITUD",F23*I23*p_kg_por_m_perfil,"")) -> 12.9525 | L23: =IF(E23="CHAPA_AREA",K23*INDEX('03_MATERIALES'!$H$2:$H$42,MATCH(D23,'03_MATERIALES'!$A$2:$A$42,0))/p_aprovechamiento_chapa,IF(E23="PERFIL_LONGITUD",K23*INDEX('03_MATERIALES'!$H$2:$H$42,MATCH(D23,'03_MATERIALES'!$A$2:$A$42,0))/p_aprovechamiento_perfil,IF(E23="UNIDAD",F23*INDEX('03_MATERIALES'!$H$2:$H$42,MATCH(D23,'03_MATERIALES'!$A$2:$A$42,0)),""))) -> 95.73587 | M23: =IF(N(J23)>0,F23*J23/p_area_plancha_m2,"") -> 0.57291667 | N23: ESTIMADO
A24: BOM-0023 | B24: PRD-008 | C24: Bandeja | D24: MAT-CH-1.0 | E24: CHAPA_AREA | F24: 5 | J24: 0.42 | K24: =IF(E24="CHAPA_AREA",F24*J24*INDEX('03_MATERIALES'!$E$2:$E$42,MATCH(D24,'03_MATERIALES'!$A$2:$A$42,0))/1000*p_densidad_acero,IF(E24="PERFIL_LONGITUD",F24*I24*p_kg_por_m_perfil,"")) -> 16.485 | L24: =IF(E24="CHAPA_AREA",K24*INDEX('03_MATERIALES'!$H$2:$H$42,MATCH(D24,'03_MATERIALES'!$A$2:$A$42,0))/p_aprovechamiento_chapa,IF(E24="PERFIL_LONGITUD",K24*INDEX('03_MATERIALES'!$H$2:$H$42,MATCH(D24,'03_MATERIALES'!$A$2:$A$42,0))/p_aprovechamiento_perfil,IF(E24="UNIDAD",F24*INDEX('03_MATERIALES'!$H$2:$H$42,MATCH(D24,'03_MATERIALES'!$A$2:$A$42,0)),""))) -> 121.84565 | M24: =IF(N(J24)>0,F24*J24/p_area_plancha_m2,"") -> 0.72916667 | N24: ESTIMADO
A25: BOM-0024 | B25: PRD-008 | C25: Soporte bandeja | D25: MAT-CH-1.0 | E25: CHAPA_AREA | F25: 10 | J25: 0.04 | K25: =IF(E25="CHAPA_AREA",F25*J25*INDEX('03_MATERIALES'!$E$2:$E$42,MATCH(D25,'03_MATERIALES'!$A$2:$A$42,0))/1000*p_densidad_acero,IF(E25="PERFIL_LONGITUD",F25*I25*p_kg_por_m_perfil,"")) -> 3.14 | L25: =IF(E25="CHAPA_AREA",K25*INDEX('03_MATERIALES'!$H$2:$H$42,MATCH(D25,'03_MATERIALES'!$A$2:$A$42,0))/p_aprovechamiento_chapa,IF(E25="PERFIL_LONGITUD",K25*INDEX('03_MATERIALES'!$H$2:$H$42,MATCH(D25,'03_MATERIALES'!$A$2:$A$42,0))/p_aprovechamiento_perfil,IF(E25="UNIDAD",F25*INDEX('03_MATERIALES'!$H$2:$H$42,MATCH(D25,'03_MATERIALES'!$A$2:$A$42,0)),""))) -> 23.208696 | M25: =IF(N(J25)>0,F25*J25/p_area_plancha_m2,"") -> 0.13888889 | N25: ESTIMADO
A26: BOM-0025 | B26: PRD-008 | C26: Pie soporte | D26: MAT-CH-1.0 | E26: CHAPA_AREA | F26: 2 | J26: 0.25 | K26: =IF(E26="CHAPA_AREA",F26*J26*INDEX('03_MATERIALES'!$E$2:$E$42,MATCH(D26,'03_MATERIALES'!$A$2:$A$42,0))/1000*p_densidad_acero,IF(E26="PERFIL_LONGITUD",F26*I26*p_kg_por_m_perfil,"")) -> 3.925 | L26: =IF(E26="CHAPA_AREA",K26*INDEX('03_MATERIALES'!$H$2:$H$42,MATCH(D26,'03_MATERIALES'!$A$2:$A$42,0))/p_aprovechamiento_chapa,IF(E26="PERFIL_LONGITUD",K26*INDEX('03_MATERIALES'!$H$2:$H$42,MATCH(D26,'03_MATERIALES'!$A$2:$A$42,0))/p_aprovechamiento_perfil,IF(E26="UNIDAD",F26*INDEX('03_MATERIALES'!$H$2:$H$42,MATCH(D26,'03_MATERIALES'!$A$2:$A$42,0)),""))) -> 29.01087 | M26: =IF(N(J26)>0,F26*J26/p_area_plancha_m2,"") -> 0.17361111 | N26: ESTIMADO
A27: BOM-0026 | B27: PRD-008 | C27: Fijaciones | D27: MAT-FIJ | E27: UNIDAD | F27: 26 | K27: =IF(E27="CHAPA_AREA",F27*J27*INDEX('03_MATERIALES'!$E$2:$E$42,MATCH(D27,'03_MATERIALES'!$A$2:$A$42,0))/1000*p_densidad_acero,IF(E27="PERFIL_LONGITUD",F27*I27*p_kg_por_m_perfil,"")) | L27: =IF(E27="CHAPA_AREA",K27*INDEX('03_MATERIALES'!$H$2:$H$42,MATCH(D27,'03_MATERIALES'!$A$2:$A$42,0))/p_aprovechamiento_chapa,IF(E27="PERFIL_LONGITUD",K27*INDEX('03_MATERIALES'!$H$2:$H$42,MATCH(D27,'03_MATERIALES'!$A$2:$A$42,0))/p_aprovechamiento_perfil,IF(E27="UNIDAD",F27*INDEX('03_MATERIALES'!$H$2:$H$42,MATCH(D27,'03_MATERIALES'!$A$2:$A$42,0)),""))) -> 23.4 | M27: =IF(N(J27)>0,F27*J27/p_area_plancha_m2,"") | N27: ESTIMADO
A28: BOM-0027 | B28: PRD-013 | C28: Panel lateral | D28: MAT-CH-1.5 | E28: CHAPA_AREA | F28: 2 | J28: 0.95 | K28: =IF(E28="CHAPA_AREA",F28*J28*INDEX('03_MATERIALES'!$E$2:$E$42,MATCH(D28,'03_MATERIALES'!$A$2:$A$42,0))/1000*p_densidad_acero,IF(E28="PERFIL_LONGITUD",F28*I28*p_kg_por_m_perfil,"")) -> 22.3725 | L28: =IF(E28="CHAPA_AREA",K28*INDEX('03_MATERIALES'!$H$2:$H$42,MATCH(D28,'03_MATERIALES'!$A$2:$A$42,0))/p_aprovechamiento_chapa,IF(E28="PERFIL_LONGITUD",K28*INDEX('03_MATERIALES'!$H$2:$H$42,MATCH(D28,'03_MATERIALES'!$A$2:$A$42,0))/p_aprovechamiento_perfil,IF(E28="UNIDAD",F28*INDEX('03_MATERIALES'!$H$2:$H$42,MATCH(D28,'03_MATERIALES'!$A$2:$A$42,0)),""))) -> 165.36196 | M28: =IF(N(J28)>0,F28*J28/p_area_plancha_m2,"") -> 0.65972222 | N28: ESTIMADO
A29: BOM-0028 | B29: PRD-013 | C29: Techo/base | D29: MAT-CH-1.5 | E29: CHAPA_AREA | F29: 2 | J29: 0.35 | K29: =IF(E29="CHAPA_AREA",F29*J29*INDEX('03_MATERIALES'!$E$2:$E$42,MATCH(D29,'03_MATERIALES'!$A$2:$A$42,0))/1000*p_densidad_acero,IF(E29="PERFIL_LONGITUD",F29*I29*p_kg_por_m_perfil,"")) -> 8.2425 | L29: =IF(E29="CHAPA_AREA",K29*INDEX('03_MATERIALES'!$H$2:$H$42,MATCH(D29,'03_MATERIALES'!$A$2:$A$42,0))/p_aprovechamiento_chapa,IF(E29="PERFIL_LONGITUD",K29*INDEX('03_MATERIALES'!$H$2:$H$42,MATCH(D29,'03_MATERIALES'!$A$2:$A$42,0))/p_aprovechamiento_perfil,IF(E29="UNIDAD",F29*INDEX('03_MATERIALES'!$H$2:$H$42,MATCH(D29,'03_MATERIALES'!$A$2:$A$42,0)),""))) -> 60.922826 | M29: =IF(N(J29)>0,F29*J29/p_area_plancha_m2,"") -> 0.24305556 | N29: ESTIMADO
A30: BOM-0029 | B30: PRD-013 | C30: Panel posterior | D30: MAT-CH-1.5 | E30: CHAPA_AREA | F30: 1 | J30: 1.7 | K30: =IF(E30="CHAPA_AREA",F30*J30*INDEX('03_MATERIALES'!$E$2:$E$42,MATCH(D30,'03_MATERIALES'!$A$2:$A$42,0))/1000*p_densidad_acero,IF(E30="PERFIL_LONGITUD",F30*I30*p_kg_por_m_perfil,"")) -> 20.0175 | L30: =IF(E30="CHAPA_AREA",K30*INDEX('03_MATERIALES'!$H$2:$H$42,MATCH(D30,'03_MATERIALES'!$A$2:$A$42,0))/p_aprovechamiento_chapa,IF(E30="PERFIL_LONGITUD",K30*INDEX('03_MATERIALES'!$H$2:$H$42,MATCH(D30,'03_MATERIALES'!$A$2:$A$42,0))/p_aprovechamiento_perfil,IF(E30="UNIDAD",F30*INDEX('03_MATERIALES'!$H$2:$H$42,MATCH(D30,'03_MATERIALES'!$A$2:$A$42,0)),""))) -> 147.95543 | M30: =IF(N(J30)>0,F30*J30/p_area_plancha_m2,"") -> 0.59027778 | N30: ESTIMADO
A31: BOM-0030 | B31: PRD-013 | C31: Puerta individual | D31: MAT-CH-1.5 | E31: CHAPA_AREA | F31: 4 | J31: 0.37 | K31: =IF(E31="CHAPA_AREA",F31*J31*INDEX('03_MATERIALES'!$E$2:$E$42,MATCH(D31,'03_MATERIALES'!$A$2:$A$42,0))/1000*p_densidad_acero,IF(E31="PERFIL_LONGITUD",F31*I31*p_kg_por_m_perfil,"")) -> 17.427 | L31: =IF(E31="CHAPA_AREA",K31*INDEX('03_MATERIALES'!$H$2:$H$42,MATCH(D31,'03_MATERIALES'!$A$2:$A$42,0))/p_aprovechamiento_chapa,IF(E31="PERFIL_LONGITUD",K31*INDEX('03_MATERIALES'!$H$2:$H$42,MATCH(D31,'03_MATERIALES'!$A$2:$A$42,0))/p_aprovechamiento_perfil,IF(E31="UNIDAD",F31*INDEX('03_MATERIALES'!$H$2:$H$42,MATCH(D31,'03_MATERIALES'!$A$2:$A$42,0)),""))) -> 128.80826 | M31: =IF(N(J31)>0,F31*J31/p_area_plancha_m2,"") -> 0.51388889 | N31: ESTIMADO
A32: BOM-0031 | B32: PRD-013 | C32: Separador interior | D32: MAT-CH-1.5 | E32: CHAPA_AREA | F32: 3 | J32: 0.35 | K32: =IF(E32="CHAPA_AREA",F32*J32*INDEX('03_MATERIALES'!$E$2:$E$42,MATCH(D32,'03_MATERIALES'!$A$2:$A$42,0))/1000*p_densidad_acero,IF(E32="PERFIL_LONGITUD",F32*I32*p_kg_por_m_perfil,"")) -> 12.36375 | L32: =IF(E32="CHAPA_AREA",K32*INDEX('03_MATERIALES'!$H$2:$H$42,MATCH(D32,'03_MATERIALES'!$A$2:$A$42,0))/p_aprovechamiento_chapa,IF(E32="PERFIL_LONGITUD",K32*INDEX('03_MATERIALES'!$H$2:$H$42,MATCH(D32,'03_MATERIALES'!$A$2:$A$42,0))/p_aprovechamiento_perfil,IF(E32="UNIDAD",F32*INDEX('03_MATERIALES'!$H$2:$H$42,MATCH(D32,'03_MATERIALES'!$A$2:$A$42,0)),""))) -> 91.384239 | M32: =IF(N(J32)>0,F32*J32/p_area_plancha_m2,"") -> 0.36458333 | N32: ESTIMADO
A33: BOM-0032 | B33: PRD-013 | C33: Bisagra | D33: MAT-FIJ | E33: UNIDAD | F33: 8 | K33: =IF(E33="CHAPA_AREA",F33*J33*INDEX('03_MATERIALES'!$E$2:$E$42,MATCH(D33,'03_MATERIALES'!$A$2:$A$42,0))/1000*p_densidad_acero,IF(E33="PERFIL_LONGITUD",F33*I33*p_kg_por_m_perfil,"")) | L33: =IF(E33="CHAPA_AREA",K33*INDEX('03_MATERIALES'!$H$2:$H$42,MATCH(D33,'03_MATERIALES'!$A$2:$A$42,0))/p_aprovechamiento_chapa,IF(E33="PERFIL_LONGITUD",K33*INDEX('03_MATERIALES'!$H$2:$H$42,MATCH(D33,'03_MATERIALES'!$A$2:$A$42,0))/p_aprovechamiento_perfil,IF(E33="UNIDAD",F33*INDEX('03_MATERIALES'!$H$2:$H$42,MATCH(D33,'03_MATERIALES'!$A$2:$A$42,0)),""))) -> 7.2 | M33: =IF(N(J33)>0,F33*J33/p_area_plancha_m2,"") | N33: ESTIMADO
A34: BOM-0033 | B34: PRD-013 | C34: Cerradura | D34: MAT-FIJ | E34: UNIDAD | F34: 4 | K34: =IF(E34="CHAPA_AREA",F34*J34*INDEX('03_MATERIALES'!$E$2:$E$42,MATCH(D34,'03_MATERIALES'!$A$2:$A$42,0))/1000*p_densidad_acero,IF(E34="PERFIL_LONGITUD",F34*I34*p_kg_por_m_perfil,"")) | L34: =IF(E34="CHAPA_AREA",K34*INDEX('03_MATERIALES'!$H$2:$H$42,MATCH(D34,'03_MATERIALES'!$A$2:$A$42,0))/p_aprovechamiento_chapa,IF(E34="PERFIL_LONGITUD",K34*INDEX('03_MATERIALES'!$H$2:$H$42,MATCH(D34,'03_MATERIALES'!$A$2:$A$42,0))/p_aprovechamiento_perfil,IF(E34="UNIDAD",F34*INDEX('03_MATERIALES'!$H$2:$H$42,MATCH(D34,'03_MATERIALES'!$A$2:$A$42,0)),""))) -> 3.6 | M34: =IF(N(J34)>0,F34*J34/p_area_plancha_m2,"") | N34: ESTIMADO
A35: BOM-0034 | B35: PRD-014 | C35: Costado externo | D35: MAT-CH-1.5 | E35: CHAPA_AREA | F35: 2 | J35: 1.1 | K35: =IF(E35="CHAPA_AREA",F35*J35*INDEX('03_MATERIALES'!$E$2:$E$42,MATCH(D35,'03_MATERIALES'!$A$2:$A$42,0))/1000*p_densidad_acero,IF(E35="PERFIL_LONGITUD",F35*I35*p_kg_por_m_perfil,"")) -> 25.905 | L35: =IF(E35="CHAPA_AREA",K35*INDEX('03_MATERIALES'!$H$2:$H$42,MATCH(D35,'03_MATERIALES'!$A$2:$A$42,0))/p_aprovechamiento_chapa,IF(E35="PERFIL_LONGITUD",K35*INDEX('03_MATERIALES'!$H$2:$H$42,MATCH(D35,'03_MATERIALES'!$A$2:$A$42,0))/p_aprovechamiento_perfil,IF(E35="UNIDAD",F35*INDEX('03_MATERIALES'!$H$2:$H$42,MATCH(D35,'03_MATERIALES'!$A$2:$A$42,0)),""))) -> 191.47174 | M35: =IF(N(J35)>0,F35*J35/p_area_plancha_m2,"") -> 0.76388889 | N35: ESTIMADO
A36: BOM-0035 | B36: PRD-014 | C36: Panel techo/base | D36: MAT-CH-1.5 | E36: CHAPA_AREA | F36: 2 | J36: 0.48 | K36: =IF(E36="CHAPA_AREA",F36*J36*INDEX('03_MATERIALES'!$E$2:$E$42,MATCH(D36,'03_MATERIALES'!$A$2:$A$42,0))/1000*p_densidad_acero,IF(E36="PERFIL_LONGITUD",F36*I36*p_kg_por_m_perfil,"")) -> 11.304 | L36: =IF(E36="CHAPA_AREA",K36*INDEX('03_MATERIALES'!$H$2:$H$42,MATCH(D36,'03_MATERIALES'!$A$2:$A$42,0))/p_aprovechamiento_chapa,IF(E36="PERFIL_LONGITUD",K36*INDEX('03_MATERIALES'!$H$2:$H$42,MATCH(D36,'03_MATERIALES'!$A$2:$A$42,0))/p_aprovechamiento_perfil,IF(E36="UNIDAD",F36*INDEX('03_MATERIALES'!$H$2:$H$42,MATCH(D36,'03_MATERIALES'!$A$2:$A$42,0)),""))) -> 83.551304 | M36: =IF(N(J36)>0,F36*J36/p_area_plancha_m2,"") -> 0.33333333 | N36: ESTIMADO
A37: BOM-0036 | B37: PRD-014 | C37: Fondo | D37: MAT-CH-1.5 | E37: CHAPA_AREA | F37: 1 | J37: 1.8 | K37: =IF(E37="CHAPA_AREA",F37*J37*INDEX('03_MATERIALES'!$E$2:$E$42,MATCH(D37,'03_MATERIALES'!$A$2:$A$42,0))/1000*p_densidad_acero,IF(E37="PERFIL_LONGITUD",F37*I37*p_kg_por_m_perfil,"")) -> 21.195 | L37: =IF(E37="CHAPA_AREA",K37*INDEX('03_MATERIALES'!$H$2:$H$42,MATCH(D37,'03_MATERIALES'!$A$2:$A$42,0))/p_aprovechamiento_chapa,IF(E37="PERFIL_LONGITUD",K37*INDEX('03_MATERIALES'!$H$2:$H$42,MATCH(D37,'03_MATERIALES'!$A$2:$A$42,0))/p_aprovechamiento_perfil,IF(E37="UNIDAD",F37*INDEX('03_MATERIALES'!$H$2:$H$42,MATCH(D37,'03_MATERIALES'!$A$2:$A$42,0)),""))) -> 156.6587 | M37: =IF(N(J37)>0,F37*J37/p_area_plancha_m2,"") -> 0.625 | N37: ESTIMADO
A38: BOM-0037 | B38: PRD-014 | C38: Puerta con rejilla | D38: MAT-CH-1.5 | E38: CHAPA_AREA | F38: 6 | J38: 0.3 | K38: =IF(E38="CHAPA_AREA",F38*J38*INDEX('03_MATERIALES'!$E$2:$E$42,MATCH(D38,'03_MATERIALES'!$A$2:$A$42,0))/1000*p_densidad_acero,IF(E38="PERFIL_LONGITUD",F38*I38*p_kg_por_m_perfil,"")) -> 21.195 | L38: =IF(E38="CHAPA_AREA",K38*INDEX('03_MATERIALES'!$H$2:$H$42,MATCH(D38,'03_MATERIALES'!$A$2:$A$42,0))/p_aprovechamiento_chapa,IF(E38="PERFIL_LONGITUD",K38*INDEX('03_MATERIALES'!$H$2:$H$42,MATCH(D38,'03_MATERIALES'!$A$2:$A$42,0))/p_aprovechamiento_perfil,IF(E38="UNIDAD",F38*INDEX('03_MATERIALES'!$H$2:$H$42,MATCH(D38,'03_MATERIALES'!$A$2:$A$42,0)),""))) -> 156.6587 | M38: =IF(N(J38)>0,F38*J38/p_area_plancha_m2,"") -> 0.625 | N38: ESTIMADO
A39: BOM-0038 | B39: PRD-014 | C39: Separador vertical | D39: MAT-CH-1.5 | E39: CHAPA_AREA | F39: 2 | J39: 0.7 | K39: =IF(E39="CHAPA_AREA",F39*J39*INDEX('03_MATERIALES'!$E$2:$E$42,MATCH(D39,'03_MATERIALES'!$A$2:$A$42,0))/1000*p_densidad_acero,IF(E39="PERFIL_LONGITUD",F39*I39*p_kg_por_m_perfil,"")) -> 16.485 | L39: =IF(E39="CHAPA_AREA",K39*INDEX('03_MATERIALES'!$H$2:$H$42,MATCH(D39,'03_MATERIALES'!$A$2:$A$42,0))/p_aprovechamiento_chapa,IF(E39="PERFIL_LONGITUD",K39*INDEX('03_MATERIALES'!$H$2:$H$42,MATCH(D39,'03_MATERIALES'!$A$2:$A$42,0))/p_aprovechamiento_perfil,IF(E39="UNIDAD",F39*INDEX('03_MATERIALES'!$H$2:$H$42,MATCH(D39,'03_MATERIALES'!$A$2:$A$42,0)),""))) -> 121.84565 | M39: =IF(N(J39)>0,F39*J39/p_area_plancha_m2,"") -> 0.48611111 | N39: ESTIMADO
A40: BOM-0039 | B40: PRD-014 | C40: Entrepiso | D40: MAT-CH-1.5 | E40: CHAPA_AREA | F40: 4 | J40: 0.4 | K40: =IF(E40="CHAPA_AREA",F40*J40*INDEX('03_MATERIALES'!$E$2:$E$42,MATCH(D40,'03_MATERIALES'!$A$2:$A$42,0))/1000*p_densidad_acero,IF(E40="PERFIL_LONGITUD",F40*I40*p_kg_por_m_perfil,"")) -> 18.84 | L40: =IF(E40="CHAPA_AREA",K40*INDEX('03_MATERIALES'!$H$2:$H$42,MATCH(D40,'03_MATERIALES'!$A$2:$A$42,0))/p_aprovechamiento_chapa,IF(E40="PERFIL_LONGITUD",K40*INDEX('03_MATERIALES'!$H$2:$H$42,MATCH(D40,'03_MATERIALES'!$A$2:$A$42,0))/p_aprovechamiento_perfil,IF(E40="UNIDAD",F40*INDEX('03_MATERIALES'!$H$2:$H$42,MATCH(D40,'03_MATERIALES'!$A$2:$A$42,0)),""))) -> 139.25217 | M40: =IF(N(J40)>0,F40*J40/p_area_plancha_m2,"") -> 0.55555556 | N40: ESTIMADO
A41: BOM-0040 | B41: PRD-014 | C41: Bisagra | D41: MAT-FIJ | E41: UNIDAD | F41: 12 | K41: =IF(E41="CHAPA_AREA",F41*J41*INDEX('03_MATERIALES'!$E$2:$E$42,MATCH(D41,'03_MATERIALES'!$A$2:$A$42,0))/1000*p_densidad_acero,IF(E41="PERFIL_LONGITUD",F41*I41*p_kg_por_m_perfil,"")) | L41: =IF(E41="CHAPA_AREA",K41*INDEX('03_MATERIALES'!$H$2:$H$42,MATCH(D41,'03_MATERIALES'!$A$2:$A$42,0))/p_aprovechamiento_chapa,IF(E41="PERFIL_LONGITUD",K41*INDEX('03_MATERIALES'!$H$2:$H$42,MATCH(D41,'03_MATERIALES'!$A$2:$A$42,0))/p_aprovechamiento_perfil,IF(E41="UNIDAD",F41*INDEX('03_MATERIALES'!$H$2:$H$42,MATCH(D41,'03_MATERIALES'!$A$2:$A$42,0)),""))) -> 10.8 | M41: =IF(N(J41)>0,F41*J41/p_area_plancha_m2,"") | N41: ESTIMADO
A42: BOM-0041 | B42: PRD-014 | C42: Cerradura | D42: MAT-FIJ | E42: UNIDAD | F42: 6 | K42: =IF(E42="CHAPA_AREA",F42*J42*INDEX('03_MATERIALES'!$E$2:$E$42,MATCH(D42,'03_MATERIALES'!$A$2:$A$42,0))/1000*p_densidad_acero,IF(E42="PERFIL_LONGITUD",F42*I42*p_kg_por_m_perfil,"")) | L42: =IF(E42="CHAPA_AREA",K42*INDEX('03_MATERIALES'!$H$2:$H$42,MATCH(D42,'03_MATERIALES'!$A$2:$A$42,0))/p_aprovechamiento_chapa,IF(E42="PERFIL_LONGITUD",K42*INDEX('03_MATERIALES'!$H$2:$H$42,MATCH(D42,'03_MATERIALES'!$A$2:$A$42,0))/p_aprovechamiento_perfil,IF(E42="UNIDAD",F42*INDEX('03_MATERIALES'!$H$2:$H$42,MATCH(D42,'03_MATERIALES'!$A$2:$A$42,0)),""))) -> 5.4 | M42: =IF(N(J42)>0,F42*J42/p_area_plancha_m2,"") | N42: ESTIMADO
A43: BOM-0042 | B43: PRD-019 | C43: Lateral gabinete | D43: MAT-CH-1.0 | E43: CHAPA_AREA | F43: 2 | J43: 0.95 | K43: =IF(E43="CHAPA_AREA",F43*J43*INDEX('03_MATERIALES'!$E$2:$E$42,MATCH(D43,'03_MATERIALES'!$A$2:$A$42,0))/1000*p_densidad_acero,IF(E43="PERFIL_LONGITUD",F43*I43*p_kg_por_m_perfil,"")) -> 14.915 | L43: =IF(E43="CHAPA_AREA",K43*INDEX('03_MATERIALES'!$H$2:$H$42,MATCH(D43,'03_MATERIALES'!$A$2:$A$42,0))/p_aprovechamiento_chapa,IF(E43="PERFIL_LONGITUD",K43*INDEX('03_MATERIALES'!$H$2:$H$42,MATCH(D43,'03_MATERIALES'!$A$2:$A$42,0))/p_aprovechamiento_perfil,IF(E43="UNIDAD",F43*INDEX('03_MATERIALES'!$H$2:$H$42,MATCH(D43,'03_MATERIALES'!$A$2:$A$42,0)),""))) -> 110.2413 | M43: =IF(N(J43)>0,F43*J43/p_area_plancha_m2,"") -> 0.65972222 | N43: ESTIMADO
A44: BOM-0043 | B44: PRD-019 | C44: Panel posterior | D44: MAT-CH-1.0 | E44: CHAPA_AREA | F44: 1 | J44: 1.3 | K44: =IF(E44="CHAPA_AREA",F44*J44*INDEX('03_MATERIALES'!$E$2:$E$42,MATCH(D44,'03_MATERIALES'!$A$2:$A$42,0))/1000*p_densidad_acero,IF(E44="PERFIL_LONGITUD",F44*I44*p_kg_por_m_perfil,"")) -> 10.205 | L44: =IF(E44="CHAPA_AREA",K44*INDEX('03_MATERIALES'!$H$2:$H$42,MATCH(D44,'03_MATERIALES'!$A$2:$A$42,0))/p_aprovechamiento_chapa,IF(E44="PERFIL_LONGITUD",K44*INDEX('03_MATERIALES'!$H$2:$H$42,MATCH(D44,'03_MATERIALES'!$A$2:$A$42,0))/p_aprovechamiento_perfil,IF(E44="UNIDAD",F44*INDEX('03_MATERIALES'!$H$2:$H$42,MATCH(D44,'03_MATERIALES'!$A$2:$A$42,0)),""))) -> 75.428261 | M44: =IF(N(J44)>0,F44*J44/p_area_plancha_m2,"") -> 0.45138889 | N44: ESTIMADO
A45: BOM-0044 | B45: PRD-019 | C45: Panel techo/base | D45: MAT-CH-1.0 | E45: CHAPA_AREA | F45: 2 | J45: 0.5 | K45: =IF(E45="CHAPA_AREA",F45*J45*INDEX('03_MATERIALES'!$E$2:$E$42,MATCH(D45,'03_MATERIALES'!$A$2:$A$42,0))/1000*p_densidad_acero,IF(E45="PERFIL_LONGITUD",F45*I45*p_kg_por_m_perfil,"")) -> 7.85 | L45: =IF(E45="CHAPA_AREA",K45*INDEX('03_MATERIALES'!$H$2:$H$42,MATCH(D45,'03_MATERIALES'!$A$2:$A$42,0))/p_aprovechamiento_chapa,IF(E45="PERFIL_LONGITUD",K45*INDEX('03_MATERIALES'!$H$2:$H$42,MATCH(D45,'03_MATERIALES'!$A$2:$A$42,0))/p_aprovechamiento_perfil,IF(E45="UNIDAD",F45*INDEX('03_MATERIALES'!$H$2:$H$42,MATCH(D45,'03_MATERIALES'!$A$2:$A$42,0)),""))) -> 58.021739 | M45: =IF(N(J45)>0,F45*J45/p_area_plancha_m2,"") -> 0.34722222 | N45: ESTIMADO
A46: BOM-0045 | B46: PRD-019 | C46: Puerta | D46: MAT-CH-1.0 | E46: CHAPA_AREA | F46: 2 | J46: 0.7 | K46: =IF(E46="CHAPA_AREA",F46*J46*INDEX('03_MATERIALES'!$E$2:$E$42,MATCH(D46,'03_MATERIALES'!$A$2:$A$42,0))/1000*p_densidad_acero,IF(E46="PERFIL_LONGITUD",F46*I46*p_kg_por_m_perfil,"")) -> 10.99 | L46: =IF(E46="CHAPA_AREA",K46*INDEX('03_MATERIALES'!$H$2:$H$42,MATCH(D46,'03_MATERIALES'!$A$2:$A$42,0))/p_aprovechamiento_chapa,IF(E46="PERFIL_LONGITUD",K46*INDEX('03_MATERIALES'!$H$2:$H$42,MATCH(D46,'03_MATERIALES'!$A$2:$A$42,0))/p_aprovechamiento_perfil,IF(E46="UNIDAD",F46*INDEX('03_MATERIALES'!$H$2:$H$42,MATCH(D46,'03_MATERIALES'!$A$2:$A$42,0)),""))) -> 81.230435 | M46: =IF(N(J46)>0,F46*J46/p_area_plancha_m2,"") -> 0.48611111 | N46: ESTIMADO
A47: BOM-0046 | B47: PRD-019 | C47: Bandeja | D47: MAT-CH-1.0 | E47: CHAPA_AREA | F47: 3 | J47: 0.48 | K47: =IF(E47="CHAPA_AREA",F47*J47*INDEX('03_MATERIALES'!$E$2:$E$42,MATCH(D47,'03_MATERIALES'!$A$2:$A$42,0))/1000*p_densidad_acero,IF(E47="PERFIL_LONGITUD",F47*I47*p_kg_por_m_perfil,"")) -> 11.304 | L47: =IF(E47="CHAPA_AREA",K47*INDEX('03_MATERIALES'!$H$2:$H$42,MATCH(D47,'03_MATERIALES'!$A$2:$A$42,0))/p_aprovechamiento_chapa,IF(E47="PERFIL_LONGITUD",K47*INDEX('03_MATERIALES'!$H$2:$H$42,MATCH(D47,'03_MATERIALES'!$A$2:$A$42,0))/p_aprovechamiento_perfil,IF(E47="UNIDAD",F47*INDEX('03_MATERIALES'!$H$2:$H$42,MATCH(D47,'03_MATERIALES'!$A$2:$A$42,0)),""))) -> 83.551304 | M47: =IF(N(J47)>0,F47*J47/p_area_plancha_m2,"") -> 0.5 | N47: ESTIMADO
A48: BOM-0047 | B48: PRD-019 | C48: Bisagra | D48: MAT-FIJ | E48: UNIDAD | F48: 4 | K48: =IF(E48="CHAPA_AREA",F48*J48*INDEX('03_MATERIALES'!$E$2:$E$42,MATCH(D48,'03_MATERIALES'!$A$2:$A$42,0))/1000*p_densidad_acero,IF(E48="PERFIL_LONGITUD",F48*I48*p_kg_por_m_perfil,"")) | L48: =IF(E48="CHAPA_AREA",K48*INDEX('03_MATERIALES'!$H$2:$H$42,MATCH(D48,'03_MATERIALES'!$A$2:$A$42,0))/p_aprovechamiento_chapa,IF(E48="PERFIL_LONGITUD",K48*INDEX('03_MATERIALES'!$H$2:$H$42,MATCH(D48,'03_MATERIALES'!$A$2:$A$42,0))/p_aprovechamiento_perfil,IF(E48="UNIDAD",F48*INDEX('03_MATERIALES'!$H$2:$H$42,MATCH(D48,'03_MATERIALES'!$A$2:$A$42,0)),""))) -> 3.6 | M48: =IF(N(J48)>0,F48*J48/p_area_plancha_m2,"") | N48: ESTIMADO
A49: BOM-0048 | B49: PRD-019 | C49: Cerradura | D49: MAT-FIJ | E49: UNIDAD | F49: 2 | K49: =IF(E49="CHAPA_AREA",F49*J49*INDEX('03_MATERIALES'!$E$2:$E$42,MATCH(D49,'03_MATERIALES'!$A$2:$A$42,0))/1000*p_densidad_acero,IF(E49="PERFIL_LONGITUD",F49*I49*p_kg_por_m_perfil,"")) | L49: =IF(E49="CHAPA_AREA",K49*INDEX('03_MATERIALES'!$H$2:$H$42,MATCH(D49,'03_MATERIALES'!$A$2:$A$42,0))/p_aprovechamiento_chapa,IF(E49="PERFIL_LONGITUD",K49*INDEX('03_MATERIALES'!$H$2:$H$42,MATCH(D49,'03_MATERIALES'!$A$2:$A$42,0))/p_aprovechamiento_perfil,IF(E49="UNIDAD",F49*INDEX('03_MATERIALES'!$H$2:$H$42,MATCH(D49,'03_MATERIALES'!$A$2:$A$42,0)),""))) -> 1.8 | M49: =IF(N(J49)>0,F49*J49/p_area_plancha_m2,"") | N49: ESTIMADO
A50: BOM-0049 | B50: PRD-020 | C50: Parante | D50: MAT-PR-1 | E50: PERFIL_LONGITUD | F50: 4 | I50: 1.65 | K50: =IF(E50="CHAPA_AREA",F50*J50*INDEX('03_MATERIALES'!$E$2:$E$42,MATCH(D50,'03_MATERIALES'!$A$2:$A$42,0))/1000*p_densidad_acero,IF(E50="PERFIL_LONGITUD",F50*I50*p_kg_por_m_perfil,"")) -> 9.9 | L50: =IF(E50="CHAPA_AREA",K50*INDEX('03_MATERIALES'!$H$2:$H$42,MATCH(D50,'03_MATERIALES'!$A$2:$A$42,0))/p_aprovechamiento_chapa,IF(E50="PERFIL_LONGITUD",K50*INDEX('03_MATERIALES'!$H$2:$H$42,MATCH(D50,'03_MATERIALES'!$A$2:$A$42,0))/p_aprovechamiento_perfil,IF(E50="UNIDAD",F50*INDEX('03_MATERIALES'!$H$2:$H$42,MATCH(D50,'03_MATERIALES'!$A$2:$A$42,0)),""))) -> 62.90625 | M50: =IF(N(J50)>0,F50*J50/p_area_plancha_m2,"") | N50: ESTIMADO
A51: BOM-0050 | B51: PRD-020 | C51: Travesaño | D51: MAT-PR-1 | E51: PERFIL_LONGITUD | F51: 8 | I51: 0.9 | K51: =IF(E51="CHAPA_AREA",F51*J51*INDEX('03_MATERIALES'!$E$2:$E$42,MATCH(D51,'03_MATERIALES'!$A$2:$A$42,0))/1000*p_densidad_acero,IF(E51="PERFIL_LONGITUD",F51*I51*p_kg_por_m_perfil,"")) -> 10.8 | L51: =IF(E51="CHAPA_AREA",K51*INDEX('03_MATERIALES'!$H$2:$H$42,MATCH(D51,'03_MATERIALES'!$A$2:$A$42,0))/p_aprovechamiento_chapa,IF(E51="PERFIL_LONGITUD",K51*INDEX('03_MATERIALES'!$H$2:$H$42,MATCH(D51,'03_MATERIALES'!$A$2:$A$42,0))/p_aprovechamiento_perfil,IF(E51="UNIDAD",F51*INDEX('03_MATERIALES'!$H$2:$H$42,MATCH(D51,'03_MATERIALES'!$A$2:$A$42,0)),""))) -> 68.625 | M51: =IF(N(J51)>0,F51*J51/p_area_plancha_m2,"") | N51: ESTIMADO
A52: BOM-0051 | B52: PRD-020 | C52: Bandeja | D52: MAT-CH-1.0 | E52: CHAPA_AREA | F52: 5 | J52: 0.4 | K52: =IF(E52="CHAPA_AREA",F52*J52*INDEX('03_MATERIALES'!$E$2:$E$42,MATCH(D52,'03_MATERIALES'!$A$2:$A$42,0))/1000*p_densidad_acero,IF(E52="PERFIL_LONGITUD",F52*I52*p_kg_por_m_perfil,"")) -> 15.7 | L52: =IF(E52="CHAPA_AREA",K52*INDEX('03_MATERIALES'!$H$2:$H$42,MATCH(D52,'03_MATERIALES'!$A$2:$A$42,0))/p_aprovechamiento_chapa,IF(E52="PERFIL_LONGITUD",K52*INDEX('03_MATERIALES'!$H$2:$H$42,MATCH(D52,'03_MATERIALES'!$A$2:$A$42,0))/p_aprovechamiento_perfil,IF(E52="UNIDAD",F52*INDEX('03_MATERIALES'!$H$2:$H$42,MATCH(D52,'03_MATERIALES'!$A$2:$A$42,0)),""))) -> 116.04348 | M52: =IF(N(J52)>0,F52*J52/p_area_plancha_m2,"") -> 0.69444444 | N52: ESTIMADO
A53: BOM-0052 | B53: PRD-020 | C53: Escuadra | D53: MAT-CH-1.0 | E53: CHAPA_AREA | F53: 8 | J53: 0.035 | K53: =IF(E53="CHAPA_AREA",F53*J53*INDEX('03_MATERIALES'!$E$2:$E$42,MATCH(D53,'03_MATERIALES'!$A$2:$A$42,0))/1000*p_densidad_acero,IF(E53="PERFIL_LONGITUD",F53*I53*p_kg_por_m_perfil,"")) -> 2.198 | L53: =IF(E53="CHAPA_AREA",K53*INDEX('03_MATERIALES'!$H$2:$H$42,MATCH(D53,'03_MATERIALES'!$A$2:$A$42,0))/p_aprovechamiento_chapa,IF(E53="PERFIL_LONGITUD",K53*INDEX('03_MATERIALES'!$H$2:$H$42,MATCH(D53,'03_MATERIALES'!$A$2:$A$42,0))/p_aprovechamiento_perfil,IF(E53="UNIDAD",F53*INDEX('03_MATERIALES'!$H$2:$H$42,MATCH(D53,'03_MATERIALES'!$A$2:$A$42,0)),""))) -> 16.246087 | M53: =IF(N(J53)>0,F53*J53/p_area_plancha_m2,"") -> 0.097222222 | N53: ESTIMADO
A54: BOM-0053 | B54: PRD-020 | C54: Tornillería | D54: MAT-FIJ | E54: UNIDAD | F54: 32 | K54: =IF(E54="CHAPA_AREA",F54*J54*INDEX('03_MATERIALES'!$E$2:$E$42,MATCH(D54,'03_MATERIALES'!$A$2:$A$42,0))/1000*p_densidad_acero,IF(E54="PERFIL_LONGITUD",F54*I54*p_kg_por_m_perfil,"")) | L54: =IF(E54="CHAPA_AREA",K54*INDEX('03_MATERIALES'!$H$2:$H$42,MATCH(D54,'03_MATERIALES'!$A$2:$A$42,0))/p_aprovechamiento_chapa,IF(E54="PERFIL_LONGITUD",K54*INDEX('03_MATERIALES'!$H$2:$H$42,MATCH(D54,'03_MATERIALES'!$A$2:$A$42,0))/p_aprovechamiento_perfil,IF(E54="UNIDAD",F54*INDEX('03_MATERIALES'!$H$2:$H$42,MATCH(D54,'03_MATERIALES'!$A$2:$A$42,0)),""))) -> 28.8 | M54: =IF(N(J54)>0,F54*J54/p_area_plancha_m2,"") | N54: ESTIMADO
A55: BOM-0054 | B55: PRD-003 | C55: Montante estructural | D55: MAT-PR-1 | E55: PERFIL_LONGITUD | F55: 4 | I55: 4.5 | K55: =IF(E55="CHAPA_AREA",F55*J55*INDEX('03_MATERIALES'!$E$2:$E$42,MATCH(D55,'03_MATERIALES'!$A$2:$A$42,0))/1000*p_densidad_acero,IF(E55="PERFIL_LONGITUD",F55*I55*p_kg_por_m_perfil,"")) -> 27 | L55: =IF(E55="CHAPA_AREA",K55*INDEX('03_MATERIALES'!$H$2:$H$42,MATCH(D55,'03_MATERIALES'!$A$2:$A$42,0))/p_aprovechamiento_chapa,IF(E55="PERFIL_LONGITUD",K55*INDEX('03_MATERIALES'!$H$2:$H$42,MATCH(D55,'03_MATERIALES'!$A$2:$A$42,0))/p_aprovechamiento_perfil,IF(E55="UNIDAD",F55*INDEX('03_MATERIALES'!$H$2:$H$42,MATCH(D55,'03_MATERIALES'!$A$2:$A$42,0)),""))) -> 171.5625 | M55: =IF(N(J55)>0,F55*J55/p_area_plancha_m2,"") | N55: ESTIMADO
A56: BOM-0055 | B56: PRD-003 | C56: Viga longitudinal | D56: MAT-PR-1 | E56: PERFIL_LONGITUD | F56: 8 | I56: 2.7 | K56: =IF(E56="CHAPA_AREA",F56*J56*INDEX('03_MATERIALES'!$E$2:$E$42,MATCH(D56,'03_MATERIALES'!$A$2:$A$42,0))/1000*p_densidad_acero,IF(E56="PERFIL_LONGITUD",F56*I56*p_kg_por_m_perfil,"")) -> 32.4 | L56: =IF(E56="CHAPA_AREA",K56*INDEX('03_MATERIALES'!$H$2:$H$42,MATCH(D56,'03_MATERIALES'!$A$2:$A$42,0))/p_aprovechamiento_chapa,IF(E56="PERFIL_LONGITUD",K56*INDEX('03_MATERIALES'!$H$2:$H$42,MATCH(D56,'03_MATERIALES'!$A$2:$A$42,0))/p_aprovechamiento_perfil,IF(E56="UNIDAD",F56*INDEX('03_MATERIALES'!$H$2:$H$42,MATCH(D56,'03_MATERIALES'!$A$2:$A$42,0)),""))) -> 205.875 | M56: =IF(N(J56)>0,F56*J56/p_area_plancha_m2,"") | N56: ESTIMADO
A57: BOM-0056 | B57: PRD-003 | C57: Travesaño lateral | D57: MAT-PR-1 | E57: PERFIL_LONGITUD | F57: 8 | I57: 1 | K57: =IF(E57="CHAPA_AREA",F57*J57*INDEX('03_MATERIALES'!$E$2:$E$42,MATCH(D57,'03_MATERIALES'!$A$2:$A$42,0))/1000*p_densidad_acero,IF(E57="PERFIL_LONGITUD",F57*I57*p_kg_por_m_perfil,"")) -> 12 | L57: =IF(E57="CHAPA_AREA",K57*INDEX('03_MATERIALES'!$H$2:$H$42,MATCH(D57,'03_MATERIALES'!$A$2:$A$42,0))/p_aprovechamiento_chapa,IF(E57="PERFIL_LONGITUD",K57*INDEX('03_MATERIALES'!$H$2:$H$42,MATCH(D57,'03_MATERIALES'!$A$2:$A$42,0))/p_aprovechamiento_perfil,IF(E57="UNIDAD",F57*INDEX('03_MATERIALES'!$H$2:$H$42,MATCH(D57,'03_MATERIALES'!$A$2:$A$42,0)),""))) -> 76.25 | M57: =IF(N(J57)>0,F57*J57/p_area_plancha_m2,"") | N57: ESTIMADO
A58: BOM-0057 | B58: PRD-003 | C58: Anclajes/seguros | D58: MAT-FIJ | E58: UNIDAD | F58: 16 | K58: =IF(E58="CHAPA_AREA",F58*J58*INDEX('03_MATERIALES'!$E$2:$E$42,MATCH(D58,'03_MATERIALES'!$A$2:$A$42,0))/1000*p_densidad_acero,IF(E58="PERFIL_LONGITUD",F58*I58*p_kg_por_m_perfil,"")) | L58: =IF(E58="CHAPA_AREA",K58*INDEX('03_MATERIALES'!$H$2:$H$42,MATCH(D58,'03_MATERIALES'!$A$2:$A$42,0))/p_aprovechamiento_chapa,IF(E58="PERFIL_LONGITUD",K58*INDEX('03_MATERIALES'!$H$2:$H$42,MATCH(D58,'03_MATERIALES'!$A$2:$A$42,0))/p_aprovechamiento_perfil,IF(E58="UNIDAD",F58*INDEX('03_MATERIALES'!$H$2:$H$42,MATCH(D58,'03_MATERIALES'!$A$2:$A$42,0)),""))) -> 14.4 | M58: =IF(N(J58)>0,F58*J58/p_area_plancha_m2,"") | N58: ESTIMADO
A59: BOM-0058 | B59: PRD-004 | C59: Montante estructural | D59: MAT-PR-1 | E59: PERFIL_LONGITUD | F59: 4 | I59: 3 | K59: =IF(E59="CHAPA_AREA",F59*J59*INDEX('03_MATERIALES'!$E$2:$E$42,MATCH(D59,'03_MATERIALES'!$A$2:$A$42,0))/1000*p_densidad_acero,IF(E59="PERFIL_LONGITUD",F59*I59*p_kg_por_m_perfil,"")) -> 18 | L59: =IF(E59="CHAPA_AREA",K59*INDEX('03_MATERIALES'!$H$2:$H$42,MATCH(D59,'03_MATERIALES'!$A$2:$A$42,0))/p_aprovechamiento_chapa,IF(E59="PERFIL_LONGITUD",K59*INDEX('03_MATERIALES'!$H$2:$H$42,MATCH(D59,'03_MATERIALES'!$A$2:$A$42,0))/p_aprovechamiento_perfil,IF(E59="UNIDAD",F59*INDEX('03_MATERIALES'!$H$2:$H$42,MATCH(D59,'03_MATERIALES'!$A$2:$A$42,0)),""))) -> 114.375 | M59: =IF(N(J59)>0,F59*J59/p_area_plancha_m2,"") | N59: ESTIMADO
A60: BOM-0059 | B60: PRD-004 | C60: Viga longitudinal | D60: MAT-PR-1 | E60: PERFIL_LONGITUD | F60: 8 | I60: 2 | K60: =IF(E60="CHAPA_AREA",F60*J60*INDEX('03_MATERIALES'!$E$2:$E$42,MATCH(D60,'03_MATERIALES'!$A$2:$A$42,0))/1000*p_densidad_acero,IF(E60="PERFIL_LONGITUD",F60*I60*p_kg_por_m_perfil,"")) -> 24 | L60: =IF(E60="CHAPA_AREA",K60*INDEX('03_MATERIALES'!$H$2:$H$42,MATCH(D60,'03_MATERIALES'!$A$2:$A$42,0))/p_aprovechamiento_chapa,IF(E60="PERFIL_LONGITUD",K60*INDEX('03_MATERIALES'!$H$2:$H$42,MATCH(D60,'03_MATERIALES'!$A$2:$A$42,0))/p_aprovechamiento_perfil,IF(E60="UNIDAD",F60*INDEX('03_MATERIALES'!$H$2:$H$42,MATCH(D60,'03_MATERIALES'!$A$2:$A$42,0)),""))) -> 152.5 | M60: =IF(N(J60)>0,F60*J60/p_area_plancha_m2,"") | N60: ESTIMADO
A61: BOM-0060 | B61: PRD-004 | C61: Travesaño lateral | D61: MAT-PR-1 | E61: PERFIL_LONGITUD | F61: 8 | I61: 1.5 | K61: =IF(E61="CHAPA_AREA",F61*J61*INDEX('03_MATERIALES'!$E$2:$E$42,MATCH(D61,'03_MATERIALES'!$A$2:$A$42,0))/1000*p_densidad_acero,IF(E61="PERFIL_LONGITUD",F61*I61*p_kg_por_m_perfil,"")) -> 18 | L61: =IF(E61="CHAPA_AREA",K61*INDEX('03_MATERIALES'!$H$2:$H$42,MATCH(D61,'03_MATERIALES'!$A$2:$A$42,0))/p_aprovechamiento_chapa,IF(E61="PERFIL_LONGITUD",K61*INDEX('03_MATERIALES'!$H$2:$H$42,MATCH(D61,'03_MATERIALES'!$A$2:$A$42,0))/p_aprovechamiento_perfil,IF(E61="UNIDAD",F61*INDEX('03_MATERIALES'!$H$2:$H$42,MATCH(D61,'03_MATERIALES'!$A$2:$A$42,0)),""))) -> 114.375 | M61: =IF(N(J61)>0,F61*J61/p_area_plancha_m2,"") | N61: ESTIMADO
A62: BOM-0061 | B62: PRD-004 | C62: Anclajes/seguros | D62: MAT-FIJ | E62: UNIDAD | F62: 16 | K62: =IF(E62="CHAPA_AREA",F62*J62*INDEX('03_MATERIALES'!$E$2:$E$42,MATCH(D62,'03_MATERIALES'!$A$2:$A$42,0))/1000*p_densidad_acero,IF(E62="PERFIL_LONGITUD",F62*I62*p_kg_por_m_perfil,"")) | L62: =IF(E62="CHAPA_AREA",K62*INDEX('03_MATERIALES'!$H$2:$H$42,MATCH(D62,'03_MATERIALES'!$A$2:$A$42,0))/p_aprovechamiento_chapa,IF(E62="PERFIL_LONGITUD",K62*INDEX('03_MATERIALES'!$H$2:$H$42,MATCH(D62,'03_MATERIALES'!$A$2:$A$42,0))/p_aprovechamiento_perfil,IF(E62="UNIDAD",F62*INDEX('03_MATERIALES'!$H$2:$H$42,MATCH(D62,'03_MATERIALES'!$A$2:$A$42,0)),""))) -> 14.4 | M62: =IF(N(J62)>0,F62*J62/p_area_plancha_m2,"") | N62: ESTIMADO
A63: BOM-0062 | B63: PRD-005 | C63: Montante estructural | D63: MAT-PR-1 | E63: PERFIL_LONGITUD | F63: 4 | I63: 1.8 | K63: =IF(E63="CHAPA_AREA",F63*J63*INDEX('03_MATERIALES'!$E$2:$E$42,MATCH(D63,'03_MATERIALES'!$A$2:$A$42,0))/1000*p_densidad_acero,IF(E63="PERFIL_LONGITUD",F63*I63*p_kg_por_m_perfil,"")) -> 10.8 | L63: =IF(E63="CHAPA_AREA",K63*INDEX('03_MATERIALES'!$H$2:$H$42,MATCH(D63,'03_MATERIALES'!$A$2:$A$42,0))/p_aprovechamiento_chapa,IF(E63="PERFIL_LONGITUD",K63*INDEX('03_MATERIALES'!$H$2:$H$42,MATCH(D63,'03_MATERIALES'!$A$2:$A$42,0))/p_aprovechamiento_perfil,IF(E63="UNIDAD",F63*INDEX('03_MATERIALES'!$H$2:$H$42,MATCH(D63,'03_MATERIALES'!$A$2:$A$42,0)),""))) -> 68.625 | M63: =IF(N(J63)>0,F63*J63/p_area_plancha_m2,"") | N63: ESTIMADO
A64: BOM-0063 | B64: PRD-005 | C64: Viga longitudinal | D64: MAT-PR-1 | E64: PERFIL_LONGITUD | F64: 8 | I64: 0.9 | K64: =IF(E64="CHAPA_AREA",F64*J64*INDEX('03_MATERIALES'!$E$2:$E$42,MATCH(D64,'03_MATERIALES'!$A$2:$A$42,0))/1000*p_densidad_acero,IF(E64="PERFIL_LONGITUD",F64*I64*p_kg_por_m_perfil,"")) -> 10.8 | L64: =IF(E64="CHAPA_AREA",K64*INDEX('03_MATERIALES'!$H$2:$H$42,MATCH(D64,'03_MATERIALES'!$A$2:$A$42,0))/p_aprovechamiento_chapa,IF(E64="PERFIL_LONGITUD",K64*INDEX('03_MATERIALES'!$H$2:$H$42,MATCH(D64,'03_MATERIALES'!$A$2:$A$42,0))/p_aprovechamiento_perfil,IF(E64="UNIDAD",F64*INDEX('03_MATERIALES'!$H$2:$H$42,MATCH(D64,'03_MATERIALES'!$A$2:$A$42,0)),""))) -> 68.625 | M64: =IF(N(J64)>0,F64*J64/p_area_plancha_m2,"") | N64: ESTIMADO
A65: BOM-0064 | B65: PRD-005 | C65: Travesaño lateral | D65: MAT-PR-1 | E65: PERFIL_LONGITUD | F65: 8 | I65: 0.45 | K65: =IF(E65="CHAPA_AREA",F65*J65*INDEX('03_MATERIALES'!$E$2:$E$42,MATCH(D65,'03_MATERIALES'!$A$2:$A$42,0))/1000*p_densidad_acero,IF(E65="PERFIL_LONGITUD",F65*I65*p_kg_por_m_perfil,"")) -> 5.4 | L65: =IF(E65="CHAPA_AREA",K65*INDEX('03_MATERIALES'!$H$2:$H$42,MATCH(D65,'03_MATERIALES'!$A$2:$A$42,0))/p_aprovechamiento_chapa,IF(E65="PERFIL_LONGITUD",K65*INDEX('03_MATERIALES'!$H$2:$H$42,MATCH(D65,'03_MATERIALES'!$A$2:$A$42,0))/p_aprovechamiento_perfil,IF(E65="UNIDAD",F65*INDEX('03_MATERIALES'!$H$2:$H$42,MATCH(D65,'03_MATERIALES'!$A$2:$A$42,0)),""))) -> 34.3125 | M65: =IF(N(J65)>0,F65*J65/p_area_plancha_m2,"") | N65: ESTIMADO
A66: BOM-0065 | B66: PRD-005 | C66: Panel/bandeja desmontable segmento | D66: MAT-LAF08 | E66: CHAPA_AREA | F66: 4 | G66: 828 | H66: 423 | J66: =G66*H66/1000000 -> 0.350244 | K66: =IF(E66="CHAPA_AREA",F66*J66*INDEX('03_MATERIALES'!$E$2:$E$42,MATCH(D66,'03_MATERIALES'!$A$2:$A$42,0))/1000*p_densidad_acero,IF(E66="PERFIL_LONGITUD",F66*I66*p_kg_por_m_perfil,"")) -> 8.7981293 | L66: =IF(E66="CHAPA_AREA",K66*INDEX('03_MATERIALES'!$H$2:$H$42,MATCH(D66,'03_MATERIALES'!$A$2:$A$42,0))/p_aprovechamiento_chapa,IF(E66="PERFIL_LONGITUD",K66*INDEX('03_MATERIALES'!$H$2:$H$42,MATCH(D66,'03_MATERIALES'!$A$2:$A$42,0))/p_aprovechamiento_perfil,IF(E66="UNIDAD",F66*INDEX('03_MATERIALES'!$H$2:$H$42,MATCH(D66,'03_MATERIALES'!$A$2:$A$42,0)),""))) -> 65.029651 | M66: =IF(N(J66)>0,F66*J66/p_area_plancha_m2,"") -> 0.48645 | N66: ESTIMADO
A67: BOM-0066 | B67: PRD-006 | C67: Montante estructural | D67: MAT-PR-1 | E67: PERFIL_LONGITUD | F67: 4 | I67: 2 | K67: =IF(E67="CHAPA_AREA",F67*J67*INDEX('03_MATERIALES'!$E$2:$E$42,MATCH(D67,'03_MATERIALES'!$A$2:$A$42,0))/1000*p_densidad_acero,IF(E67="PERFIL_LONGITUD",F67*I67*p_kg_por_m_perfil,"")) -> 12 | L67: =IF(E67="CHAPA_AREA",K67*INDEX('03_MATERIALES'!$H$2:$H$42,MATCH(D67,'03_MATERIALES'!$A$2:$A$42,0))/p_aprovechamiento_chapa,IF(E67="PERFIL_LONGITUD",K67*INDEX('03_MATERIALES'!$H$2:$H$42,MATCH(D67,'03_MATERIALES'!$A$2:$A$42,0))/p_aprovechamiento_perfil,IF(E67="UNIDAD",F67*INDEX('03_MATERIALES'!$H$2:$H$42,MATCH(D67,'03_MATERIALES'!$A$2:$A$42,0)),""))) -> 76.25 | M67: =IF(N(J67)>0,F67*J67/p_area_plancha_m2,"") | N67: ESTIMADO
A68: BOM-0067 | B68: PRD-006 | C68: Viga longitudinal | D68: MAT-PR-1 | E68: PERFIL_LONGITUD | F68: 8 | I68: 2 | K68: =IF(E68="CHAPA_AREA",F68*J68*INDEX('03_MATERIALES'!$E$2:$E$42,MATCH(D68,'03_MATERIALES'!$A$2:$A$42,0))/1000*p_densidad_acero,IF(E68="PERFIL_LONGITUD",F68*I68*p_kg_por_m_perfil,"")) -> 24 | L68: =IF(E68="CHAPA_AREA",K68*INDEX('03_MATERIALES'!$H$2:$H$42,MATCH(D68,'03_MATERIALES'!$A$2:$A$42,0))/p_aprovechamiento_chapa,IF(E68="PERFIL_LONGITUD",K68*INDEX('03_MATERIALES'!$H$2:$H$42,MATCH(D68,'03_MATERIALES'!$A$2:$A$42,0))/p_aprovechamiento_perfil,IF(E68="UNIDAD",F68*INDEX('03_MATERIALES'!$H$2:$H$42,MATCH(D68,'03_MATERIALES'!$A$2:$A$42,0)),""))) -> 152.5 | M68: =IF(N(J68)>0,F68*J68/p_area_plancha_m2,"") | N68: ESTIMADO
A69: BOM-0068 | B69: PRD-006 | C69: Travesaño lateral | D69: MAT-PR-1 | E69: PERFIL_LONGITUD | F69: 8 | I69: 0.6 | K69: =IF(E69="CHAPA_AREA",F69*J69*INDEX('03_MATERIALES'!$E$2:$E$42,MATCH(D69,'03_MATERIALES'!$A$2:$A$42,0))/1000*p_densidad_acero,IF(E69="PERFIL_LONGITUD",F69*I69*p_kg_por_m_perfil,"")) -> 7.2 | L69: =IF(E69="CHAPA_AREA",K69*INDEX('03_MATERIALES'!$H$2:$H$42,MATCH(D69,'03_MATERIALES'!$A$2:$A$42,0))/p_aprovechamiento_chapa,IF(E69="PERFIL_LONGITUD",K69*INDEX('03_MATERIALES'!$H$2:$H$42,MATCH(D69,'03_MATERIALES'!$A$2:$A$42,0))/p_aprovechamiento_perfil,IF(E69="UNIDAD",F69*INDEX('03_MATERIALES'!$H$2:$H$42,MATCH(D69,'03_MATERIALES'!$A$2:$A$42,0)),""))) -> 45.75 | M69: =IF(N(J69)>0,F69*J69/p_area_plancha_m2,"") | N69: ESTIMADO
A70: BOM-0069 | B70: PRD-006 | C70: Anclajes/seguros | D70: MAT-FIJ | E70: UNIDAD | F70: 16 | K70: =IF(E70="CHAPA_AREA",F70*J70*INDEX('03_MATERIALES'!$E$2:$E$42,MATCH(D70,'03_MATERIALES'!$A$2:$A$42,0))/1000*p_densidad_acero,IF(E70="PERFIL_LONGITUD",F70*I70*p_kg_por_m_perfil,"")) | L70: =IF(E70="CHAPA_AREA",K70*INDEX('03_MATERIALES'!$H$2:$H$42,MATCH(D70,'03_MATERIALES'!$A$2:$A$42,0))/p_aprovechamiento_chapa,IF(E70="PERFIL_LONGITUD",K70*INDEX('03_MATERIALES'!$H$2:$H$42,MATCH(D70,'03_MATERIALES'!$A$2:$A$42,0))/p_aprovechamiento_perfil,IF(E70="UNIDAD",F70*INDEX('03_MATERIALES'!$H$2:$H$42,MATCH(D70,'03_MATERIALES'!$A$2:$A$42,0)),""))) -> 14.4 | M70: =IF(N(J70)>0,F70*J70/p_area_plancha_m2,"") | N70: ESTIMADO
A71: BOM-0070 | B71: PRD-009 | C71: Bastidor vertical tubular | D71: MAT-PR-1 | E71: PERFIL_LONGITUD | F71: 2 | I71: 1.5 | K71: =IF(E71="CHAPA_AREA",F71*J71*INDEX('03_MATERIALES'!$E$2:$E$42,MATCH(D71,'03_MATERIALES'!$A$2:$A$42,0))/1000*p_densidad_acero,IF(E71="PERFIL_LONGITUD",F71*I71*p_kg_por_m_perfil,"")) -> 4.5 | L71: =IF(E71="CHAPA_AREA",K71*INDEX('03_MATERIALES'!$H$2:$H$42,MATCH(D71,'03_MATERIALES'!$A$2:$A$42,0))/p_aprovechamiento_chapa,IF(E71="PERFIL_LONGITUD",K71*INDEX('03_MATERIALES'!$H$2:$H$42,MATCH(D71,'03_MATERIALES'!$A$2:$A$42,0))/p_aprovechamiento_perfil,IF(E71="UNIDAD",F71*INDEX('03_MATERIALES'!$H$2:$H$42,MATCH(D71,'03_MATERIALES'!$A$2:$A$42,0)),""))) -> 28.59375 | M71: =IF(N(J71)>0,F71*J71/p_area_plancha_m2,"") | N71: ESTIMADO
A72: BOM-0071 | B72: PRD-009 | C72: Panel trasero chapa | D72: MAT-LAF08 | E72: CHAPA_AREA | F72: 1 | G72: 1092.5 | H72: 1350 | J72: =G72*H72/1000000 -> 1.474875 | K72: =IF(E72="CHAPA_AREA",F72*J72*INDEX('03_MATERIALES'!$E$2:$E$42,MATCH(D72,'03_MATERIALES'!$A$2:$A$42,0))/1000*p_densidad_acero,IF(E72="PERFIL_LONGITUD",F72*I72*p_kg_por_m_perfil,"")) -> 9.262215 | L72: =IF(E72="CHAPA_AREA",K72*INDEX('03_MATERIALES'!$H$2:$H$42,MATCH(D72,'03_MATERIALES'!$A$2:$A$42,0))/p_aprovechamiento_chapa,IF(E72="PERFIL_LONGITUD",K72*INDEX('03_MATERIALES'!$H$2:$H$42,MATCH(D72,'03_MATERIALES'!$A$2:$A$42,0))/p_aprovechamiento_perfil,IF(E72="UNIDAD",F72*INDEX('03_MATERIALES'!$H$2:$H$42,MATCH(D72,'03_MATERIALES'!$A$2:$A$42,0)),""))) -> 68.45985 | M72: =IF(N(J72)>0,F72*J72/p_area_plancha_m2,"") -> 0.51210937 | N72: ESTIMADO
A73: BOM-0072 | B73: PRD-009 | C73: Bandeja de exhibición | D73: MAT-LAF08 | E73: CHAPA_AREA | F73: 5 | G73: 1058 | H73: 405 | J73: =G73*H73/1000000 -> 0.42849 | K73: =IF(E73="CHAPA_AREA",F73*J73*INDEX('03_MATERIALES'!$E$2:$E$42,MATCH(D73,'03_MATERIALES'!$A$2:$A$42,0))/1000*p_densidad_acero,IF(E73="PERFIL_LONGITUD",F73*I73*p_kg_por_m_perfil,"")) -> 13.454586 | L73: =IF(E73="CHAPA_AREA",K73*INDEX('03_MATERIALES'!$H$2:$H$42,MATCH(D73,'03_MATERIALES'!$A$2:$A$42,0))/p_aprovechamiento_chapa,IF(E73="PERFIL_LONGITUD",K73*INDEX('03_MATERIALES'!$H$2:$H$42,MATCH(D73,'03_MATERIALES'!$A$2:$A$42,0))/p_aprovechamiento_perfil,IF(E73="UNIDAD",F73*INDEX('03_MATERIALES'!$H$2:$H$42,MATCH(D73,'03_MATERIALES'!$A$2:$A$42,0)),""))) -> 99.44694 | M73: =IF(N(J73)>0,F73*J73/p_area_plancha_m2,"") -> 0.74390625 | N73: ESTIMADO
A74: BOM-0073 | B74: PRD-009 | C74: Base y refuerzo perfil | D74: MAT-PR-1 | E74: PERFIL_LONGITUD | F74: 2 | I74: 0.9 | K74: =IF(E74="CHAPA_AREA",F74*J74*INDEX('03_MATERIALES'!$E$2:$E$42,MATCH(D74,'03_MATERIALES'!$A$2:$A$42,0))/1000*p_densidad_acero,IF(E74="PERFIL_LONGITUD",F74*I74*p_kg_por_m_perfil,"")) -> 2.7 | L74: =IF(E74="CHAPA_AREA",K74*INDEX('03_MATERIALES'!$H$2:$H$42,MATCH(D74,'03_MATERIALES'!$A$2:$A$42,0))/p_aprovechamiento_chapa,IF(E74="PERFIL_LONGITUD",K74*INDEX('03_MATERIALES'!$H$2:$H$42,MATCH(D74,'03_MATERIALES'!$A$2:$A$42,0))/p_aprovechamiento_perfil,IF(E74="UNIDAD",F74*INDEX('03_MATERIALES'!$H$2:$H$42,MATCH(D74,'03_MATERIALES'!$A$2:$A$42,0)),""))) -> 17.15625 | M74: =IF(N(J74)>0,F74*J74/p_area_plancha_m2,"") | N74: ESTIMADO
A75: BOM-0074 | B75: PRD-009 | C75: Ménsula y herrajes | D75: MAT-FIJ | E75: UNIDAD | F75: 10 | K75: =IF(E75="CHAPA_AREA",F75*J75*INDEX('03_MATERIALES'!$E$2:$E$42,MATCH(D75,'03_MATERIALES'!$A$2:$A$42,0))/1000*p_densidad_acero,IF(E75="PERFIL_LONGITUD",F75*I75*p_kg_por_m_perfil,"")) | L75: =IF(E75="CHAPA_AREA",K75*INDEX('03_MATERIALES'!$H$2:$H$42,MATCH(D75,'03_MATERIALES'!$A$2:$A$42,0))/p_aprovechamiento_chapa,IF(E75="PERFIL_LONGITUD",K75*INDEX('03_MATERIALES'!$H$2:$H$42,MATCH(D75,'03_MATERIALES'!$A$2:$A$42,0))/p_aprovechamiento_perfil,IF(E75="UNIDAD",F75*INDEX('03_MATERIALES'!$H$2:$H$42,MATCH(D75,'03_MATERIALES'!$A$2:$A$42,0)),""))) -> 9 | M75: =IF(N(J75)>0,F75*J75/p_area_plancha_m2,"") | N75: ESTIMADO
A76: BOM-0075 | B76: PRD-010 | C76: Bastidor vertical tubular | D76: MAT-PR-1 | E76: PERFIL_LONGITUD | F76: 2 | I76: 1.85 | K76: =IF(E76="CHAPA_AREA",F76*J76*INDEX('03_MATERIALES'!$E$2:$E$42,MATCH(D76,'03_MATERIALES'!$A$2:$A$42,0))/1000*p_densidad_acero,IF(E76="PERFIL_LONGITUD",F76*I76*p_kg_por_m_perfil,"")) -> 5.55 | L76: =IF(E76="CHAPA_AREA",K76*INDEX('03_MATERIALES'!$H$2:$H$42,MATCH(D76,'03_MATERIALES'!$A$2:$A$42,0))/p_aprovechamiento_chapa,IF(E76="PERFIL_LONGITUD",K76*INDEX('03_MATERIALES'!$H$2:$H$42,MATCH(D76,'03_MATERIALES'!$A$2:$A$42,0))/p_aprovechamiento_perfil,IF(E76="UNIDAD",F76*INDEX('03_MATERIALES'!$H$2:$H$42,MATCH(D76,'03_MATERIALES'!$A$2:$A$42,0)),""))) -> 35.265625 | M76: =IF(N(J76)>0,F76*J76/p_area_plancha_m2,"") | N76: ESTIMADO
A77: BOM-0076 | B77: PRD-010 | C77: Panel trasero chapa | D77: MAT-LAF08 | E77: CHAPA_AREA | F77: 1 | G77: 1092.5 | H77: 1665 | J77: =G77*H77/1000000 -> 1.8190125 | K77: =IF(E77="CHAPA_AREA",F77*J77*INDEX('03_MATERIALES'!$E$2:$E$42,MATCH(D77,'03_MATERIALES'!$A$2:$A$42,0))/1000*p_densidad_acero,IF(E77="PERFIL_LONGITUD",F77*I77*p_kg_por_m_perfil,"")) -> 11.423398 | L77: =IF(E77="CHAPA_AREA",K77*INDEX('03_MATERIALES'!$H$2:$H$42,MATCH(D77,'03_MATERIALES'!$A$2:$A$42,0))/p_aprovechamiento_chapa,IF(E77="PERFIL_LONGITUD",K77*INDEX('03_MATERIALES'!$H$2:$H$42,MATCH(D77,'03_MATERIALES'!$A$2:$A$42,0))/p_aprovechamiento_perfil,IF(E77="UNIDAD",F77*INDEX('03_MATERIALES'!$H$2:$H$42,MATCH(D77,'03_MATERIALES'!$A$2:$A$42,0)),""))) -> 84.433815 | M77: =IF(N(J77)>0,F77*J77/p_area_plancha_m2,"") -> 0.63160156 | N77: ESTIMADO
A78: BOM-0077 | B78: PRD-010 | C78: Bandeja de exhibición | D78: MAT-LAF08 | E78: CHAPA_AREA | F78: 5 | G78: 1058 | H78: 180 | J78: =G78*H78/1000000 -> 0.19044 | K78: =IF(E78="CHAPA_AREA",F78*J78*INDEX('03_MATERIALES'!$E$2:$E$42,MATCH(D78,'03_MATERIALES'!$A$2:$A$42,0))/1000*p_densidad_acero,IF(E78="PERFIL_LONGITUD",F78*I78*p_kg_por_m_perfil,"")) -> 5.979816 | L78: =IF(E78="CHAPA_AREA",K78*INDEX('03_MATERIALES'!$H$2:$H$42,MATCH(D78,'03_MATERIALES'!$A$2:$A$42,0))/p_aprovechamiento_chapa,IF(E78="PERFIL_LONGITUD",K78*INDEX('03_MATERIALES'!$H$2:$H$42,MATCH(D78,'03_MATERIALES'!$A$2:$A$42,0))/p_aprovechamiento_perfil,IF(E78="UNIDAD",F78*INDEX('03_MATERIALES'!$H$2:$H$42,MATCH(D78,'03_MATERIALES'!$A$2:$A$42,0)),""))) -> 44.19864 | M78: =IF(N(J78)>0,F78*J78/p_area_plancha_m2,"") -> 0.330625 | N78: ESTIMADO
A79: BOM-0078 | B79: PRD-010 | C79: Base y refuerzo perfil | D79: MAT-PR-1 | E79: PERFIL_LONGITUD | F79: 2 | I79: 0.4 | K79: =IF(E79="CHAPA_AREA",F79*J79*INDEX('03_MATERIALES'!$E$2:$E$42,MATCH(D79,'03_MATERIALES'!$A$2:$A$42,0))/1000*p_densidad_acero,IF(E79="PERFIL_LONGITUD",F79*I79*p_kg_por_m_perfil,"")) -> 1.2 | L79: =IF(E79="CHAPA_AREA",K79*INDEX('03_MATERIALES'!$H$2:$H$42,MATCH(D79,'03_MATERIALES'!$A$2:$A$42,0))/p_aprovechamiento_chapa,IF(E79="PERFIL_LONGITUD",K79*INDEX('03_MATERIALES'!$H$2:$H$42,MATCH(D79,'03_MATERIALES'!$A$2:$A$42,0))/p_aprovechamiento_perfil,IF(E79="UNIDAD",F79*INDEX('03_MATERIALES'!$H$2:$H$42,MATCH(D79,'03_MATERIALES'!$A$2:$A$42,0)),""))) -> 7.625 | M79: =IF(N(J79)>0,F79*J79/p_area_plancha_m2,"") | N79: ESTIMADO
A80: BOM-0079 | B80: PRD-010 | C80: Ménsula y herrajes | D80: MAT-FIJ | E80: UNIDAD | F80: 10 | K80: =IF(E80="CHAPA_AREA",F80*J80*INDEX('03_MATERIALES'!$E$2:$E$42,MATCH(D80,'03_MATERIALES'!$A$2:$A$42,0))/1000*p_densidad_acero,IF(E80="PERFIL_LONGITUD",F80*I80*p_kg_por_m_perfil,"")) | L80: =IF(E80="CHAPA_AREA",K80*INDEX('03_MATERIALES'!$H$2:$H$42,MATCH(D80,'03_MATERIALES'!$A$2:$A$42,0))/p_aprovechamiento_chapa,IF(E80="PERFIL_LONGITUD",K80*INDEX('03_MATERIALES'!$H$2:$H$42,MATCH(D80,'03_MATERIALES'!$A$2:$A$42,0))/p_aprovechamiento_perfil,IF(E80="UNIDAD",F80*INDEX('03_MATERIALES'!$H$2:$H$42,MATCH(D80,'03_MATERIALES'!$A$2:$A$42,0)),""))) -> 9 | M80: =IF(N(J80)>0,F80*J80/p_area_plancha_m2,"") | N80: ESTIMADO
A81: BOM-0080 | B81: PRD-011 | C81: Bastidor vertical tubular | D81: MAT-PR-1 | E81: PERFIL_LONGITUD | F81: 2 | I81: 1.5 | K81: =IF(E81="CHAPA_AREA",F81*J81*INDEX('03_MATERIALES'!$E$2:$E$42,MATCH(D81,'03_MATERIALES'!$A$2:$A$42,0))/1000*p_densidad_acero,IF(E81="PERFIL_LONGITUD",F81*I81*p_kg_por_m_perfil,"")) -> 4.5 | L81: =IF(E81="CHAPA_AREA",K81*INDEX('03_MATERIALES'!$H$2:$H$42,MATCH(D81,'03_MATERIALES'!$A$2:$A$42,0))/p_aprovechamiento_chapa,IF(E81="PERFIL_LONGITUD",K81*INDEX('03_MATERIALES'!$H$2:$H$42,MATCH(D81,'03_MATERIALES'!$A$2:$A$42,0))/p_aprovechamiento_perfil,IF(E81="UNIDAD",F81*INDEX('03_MATERIALES'!$H$2:$H$42,MATCH(D81,'03_MATERIALES'!$A$2:$A$42,0)),""))) -> 28.59375 | M81: =IF(N(J81)>0,F81*J81/p_area_plancha_m2,"") | N81: ESTIMADO
A82: BOM-0081 | B82: PRD-011 | C82: Panel trasero chapa | D82: MAT-LAF08 | E82: CHAPA_AREA | F82: 1 | G82: 855 | H82: 1350 | J82: =G82*H82/1000000 -> 1.15425 | K82: =IF(E82="CHAPA_AREA",F82*J82*INDEX('03_MATERIALES'!$E$2:$E$42,MATCH(D82,'03_MATERIALES'!$A$2:$A$42,0))/1000*p_densidad_acero,IF(E82="PERFIL_LONGITUD",F82*I82*p_kg_por_m_perfil,"")) -> 7.24869 | L82: =IF(E82="CHAPA_AREA",K82*INDEX('03_MATERIALES'!$H$2:$H$42,MATCH(D82,'03_MATERIALES'!$A$2:$A$42,0))/p_aprovechamiento_chapa,IF(E82="PERFIL_LONGITUD",K82*INDEX('03_MATERIALES'!$H$2:$H$42,MATCH(D82,'03_MATERIALES'!$A$2:$A$42,0))/p_aprovechamiento_perfil,IF(E82="UNIDAD",F82*INDEX('03_MATERIALES'!$H$2:$H$42,MATCH(D82,'03_MATERIALES'!$A$2:$A$42,0)),""))) -> 53.577274 | M82: =IF(N(J82)>0,F82*J82/p_area_plancha_m2,"") -> 0.40078125 | N82: ESTIMADO
A83: BOM-0082 | B83: PRD-011 | C83: Bandeja de exhibición | D83: MAT-LAF08 | E83: CHAPA_AREA | F83: 5 | G83: 828 | H83: 180 | J83: =G83*H83/1000000 -> 0.14904 | K83: =IF(E83="CHAPA_AREA",F83*J83*INDEX('03_MATERIALES'!$E$2:$E$42,MATCH(D83,'03_MATERIALES'!$A$2:$A$42,0))/1000*p_densidad_acero,IF(E83="PERFIL_LONGITUD",F83*I83*p_kg_por_m_perfil,"")) -> 4.679856 | L83: =IF(E83="CHAPA_AREA",K83*INDEX('03_MATERIALES'!$H$2:$H$42,MATCH(D83,'03_MATERIALES'!$A$2:$A$42,0))/p_aprovechamiento_chapa,IF(E83="PERFIL_LONGITUD",K83*INDEX('03_MATERIALES'!$H$2:$H$42,MATCH(D83,'03_MATERIALES'!$A$2:$A$42,0))/p_aprovechamiento_perfil,IF(E83="UNIDAD",F83*INDEX('03_MATERIALES'!$H$2:$H$42,MATCH(D83,'03_MATERIALES'!$A$2:$A$42,0)),""))) -> 34.59024 | M83: =IF(N(J83)>0,F83*J83/p_area_plancha_m2,"") -> 0.25875 | N83: ESTIMADO
A84: BOM-0083 | B84: PRD-011 | C84: Base y refuerzo perfil | D84: MAT-PR-1 | E84: PERFIL_LONGITUD | F84: 2 | I84: 0.4 | K84: =IF(E84="CHAPA_AREA",F84*J84*INDEX('03_MATERIALES'!$E$2:$E$42,MATCH(D84,'03_MATERIALES'!$A$2:$A$42,0))/1000*p_densidad_acero,IF(E84="PERFIL_LONGITUD",F84*I84*p_kg_por_m_perfil,"")) -> 1.2 | L84: =IF(E84="CHAPA_AREA",K84*INDEX('03_MATERIALES'!$H$2:$H$42,MATCH(D84,'03_MATERIALES'!$A$2:$A$42,0))/p_aprovechamiento_chapa,IF(E84="PERFIL_LONGITUD",K84*INDEX('03_MATERIALES'!$H$2:$H$42,MATCH(D84,'03_MATERIALES'!$A$2:$A$42,0))/p_aprovechamiento_perfil,IF(E84="UNIDAD",F84*INDEX('03_MATERIALES'!$H$2:$H$42,MATCH(D84,'03_MATERIALES'!$A$2:$A$42,0)),""))) -> 7.625 | M84: =IF(N(J84)>0,F84*J84/p_area_plancha_m2,"") | N84: ESTIMADO
A85: BOM-0084 | B85: PRD-011 | C85: Ménsula y herrajes | D85: MAT-FIJ | E85: UNIDAD | F85: 10 | K85: =IF(E85="CHAPA_AREA",F85*J85*INDEX('03_MATERIALES'!$E$2:$E$42,MATCH(D85,'03_MATERIALES'!$A$2:$A$42,0))/1000*p_densidad_acero,IF(E85="PERFIL_LONGITUD",F85*I85*p_kg_por_m_perfil,"")) | L85: =IF(E85="CHAPA_AREA",K85*INDEX('03_MATERIALES'!$H$2:$H$42,MATCH(D85,'03_MATERIALES'!$A$2:$A$42,0))/p_aprovechamiento_chapa,IF(E85="PERFIL_LONGITUD",K85*INDEX('03_MATERIALES'!$H$2:$H$42,MATCH(D85,'03_MATERIALES'!$A$2:$A$42,0))/p_aprovechamiento_perfil,IF(E85="UNIDAD",F85*INDEX('03_MATERIALES'!$H$2:$H$42,MATCH(D85,'03_MATERIALES'!$A$2:$A$42,0)),""))) -> 9 | M85: =IF(N(J85)>0,F85*J85/p_area_plancha_m2,"") | N85: ESTIMADO
A86: BOM-0085 | B86: PRD-012 | C86: Bastidor vertical tubular | D86: MAT-PR-1 | E86: PERFIL_LONGITUD | F86: 2 | I86: 1.5 | K86: =IF(E86="CHAPA_AREA",F86*J86*INDEX('03_MATERIALES'!$E$2:$E$42,MATCH(D86,'03_MATERIALES'!$A$2:$A$42,0))/1000*p_densidad_acero,IF(E86="PERFIL_LONGITUD",F86*I86*p_kg_por_m_perfil,"")) -> 4.5 | L86: =IF(E86="CHAPA_AREA",K86*INDEX('03_MATERIALES'!$H$2:$H$42,MATCH(D86,'03_MATERIALES'!$A$2:$A$42,0))/p_aprovechamiento_chapa,IF(E86="PERFIL_LONGITUD",K86*INDEX('03_MATERIALES'!$H$2:$H$42,MATCH(D86,'03_MATERIALES'!$A$2:$A$42,0))/p_aprovechamiento_perfil,IF(E86="UNIDAD",F86*INDEX('03_MATERIALES'!$H$2:$H$42,MATCH(D86,'03_MATERIALES'!$A$2:$A$42,0)),""))) -> 28.59375 | M86: =IF(N(J86)>0,F86*J86/p_area_plancha_m2,"") | N86: ESTIMADO
A87: BOM-0086 | B87: PRD-012 | C87: Panel trasero chapa | D87: MAT-LAF08 | E87: CHAPA_AREA | F87: 1 | G87: 665 | H87: 1350 | J87: =G87*H87/1000000 -> 0.89775 | K87: =IF(E87="CHAPA_AREA",F87*J87*INDEX('03_MATERIALES'!$E$2:$E$42,MATCH(D87,'03_MATERIALES'!$A$2:$A$42,0))/1000*p_densidad_acero,IF(E87="PERFIL_LONGITUD",F87*I87*p_kg_por_m_perfil,"")) -> 5.63787 | L87: =IF(E87="CHAPA_AREA",K87*INDEX('03_MATERIALES'!$H$2:$H$42,MATCH(D87,'03_MATERIALES'!$A$2:$A$42,0))/p_aprovechamiento_chapa,IF(E87="PERFIL_LONGITUD",K87*INDEX('03_MATERIALES'!$H$2:$H$42,MATCH(D87,'03_MATERIALES'!$A$2:$A$42,0))/p_aprovechamiento_perfil,IF(E87="UNIDAD",F87*INDEX('03_MATERIALES'!$H$2:$H$42,MATCH(D87,'03_MATERIALES'!$A$2:$A$42,0)),""))) -> 41.671213 | M87: =IF(N(J87)>0,F87*J87/p_area_plancha_m2,"") -> 0.31171875 | N87: ESTIMADO
A88: BOM-0087 | B88: PRD-012 | C88: Bandeja de exhibición | D88: MAT-LAF08 | E88: CHAPA_AREA | F88: 5 | G88: 644 | H88: 315 | J88: =G88*H88/1000000 -> 0.20286 | K88: =IF(E88="CHAPA_AREA",F88*J88*INDEX('03_MATERIALES'!$E$2:$E$42,MATCH(D88,'03_MATERIALES'!$A$2:$A$42,0))/1000*p_densidad_acero,IF(E88="PERFIL_LONGITUD",F88*I88*p_kg_por_m_perfil,"")) -> 6.369804 | L88: =IF(E88="CHAPA_AREA",K88*INDEX('03_MATERIALES'!$H$2:$H$42,MATCH(D88,'03_MATERIALES'!$A$2:$A$42,0))/p_aprovechamiento_chapa,IF(E88="PERFIL_LONGITUD",K88*INDEX('03_MATERIALES'!$H$2:$H$42,MATCH(D88,'03_MATERIALES'!$A$2:$A$42,0))/p_aprovechamiento_perfil,IF(E88="UNIDAD",F88*INDEX('03_MATERIALES'!$H$2:$H$42,MATCH(D88,'03_MATERIALES'!$A$2:$A$42,0)),""))) -> 47.08116 | M88: =IF(N(J88)>0,F88*J88/p_area_plancha_m2,"") -> 0.3521875 | N88: ESTIMADO
A89: BOM-0088 | B89: PRD-012 | C89: Base y refuerzo perfil | D89: MAT-PR-1 | E89: PERFIL_LONGITUD | F89: 2 | I89: 0.7 | K89: =IF(E89="CHAPA_AREA",F89*J89*INDEX('03_MATERIALES'!$E$2:$E$42,MATCH(D89,'03_MATERIALES'!$A$2:$A$42,0))/1000*p_densidad_acero,IF(E89="PERFIL_LONGITUD",F89*I89*p_kg_por_m_perfil,"")) -> 2.1 | L89: =IF(E89="CHAPA_AREA",K89*INDEX('03_MATERIALES'!$H$2:$H$42,MATCH(D89,'03_MATERIALES'!$A$2:$A$42,0))/p_aprovechamiento_chapa,IF(E89="PERFIL_LONGITUD",K89*INDEX('03_MATERIALES'!$H$2:$H$42,MATCH(D89,'03_MATERIALES'!$A$2:$A$42,0))/p_aprovechamiento_perfil,IF(E89="UNIDAD",F89*INDEX('03_MATERIALES'!$H$2:$H$42,MATCH(D89,'03_MATERIALES'!$A$2:$A$42,0)),""))) -> 13.34375 | M89: =IF(N(J89)>0,F89*J89/p_area_plancha_m2,"") | N89: ESTIMADO
A90: BOM-0089 | B90: PRD-012 | C90: Ménsula y herrajes | D90: MAT-FIJ | E90: UNIDAD | F90: 10 | K90: =IF(E90="CHAPA_AREA",F90*J90*INDEX('03_MATERIALES'!$E$2:$E$42,MATCH(D90,'03_MATERIALES'!$A$2:$A$42,0))/1000*p_densidad_acero,IF(E90="PERFIL_LONGITUD",F90*I90*p_kg_por_m_perfil,"")) | L90: =IF(E90="CHAPA_AREA",K90*INDEX('03_MATERIALES'!$H$2:$H$42,MATCH(D90,'03_MATERIALES'!$A$2:$A$42,0))/p_aprovechamiento_chapa,IF(E90="PERFIL_LONGITUD",K90*INDEX('03_MATERIALES'!$H$2:$H$42,MATCH(D90,'03_MATERIALES'!$A$2:$A$42,0))/p_aprovechamiento_perfil,IF(E90="UNIDAD",F90*INDEX('03_MATERIALES'!$H$2:$H$42,MATCH(D90,'03_MATERIALES'!$A$2:$A$42,0)),""))) -> 9 | M90: =IF(N(J90)>0,F90*J90/p_area_plancha_m2,"") | N90: ESTIMADO
A91: BOM-0090 | B91: PRD-015 | C91: Costados chapa | D91: MAT-LAF06 | E91: CHAPA_AREA | F91: 2 | G91: 376 | H91: 1656 | J91: =G91*H91/1000000 -> 0.622656 | K91: =IF(E91="CHAPA_AREA",F91*J91*INDEX('03_MATERIALES'!$E$2:$E$42,MATCH(D91,'03_MATERIALES'!$A$2:$A$42,0))/1000*p_densidad_acero,IF(E91="PERFIL_LONGITUD",F91*I91*p_kg_por_m_perfil,"")) -> 5.8654195 | L91: =IF(E91="CHAPA_AREA",K91*INDEX('03_MATERIALES'!$H$2:$H$42,MATCH(D91,'03_MATERIALES'!$A$2:$A$42,0))/p_aprovechamiento_chapa,IF(E91="PERFIL_LONGITUD",K91*INDEX('03_MATERIALES'!$H$2:$H$42,MATCH(D91,'03_MATERIALES'!$A$2:$A$42,0))/p_aprovechamiento_perfil,IF(E91="UNIDAD",F91*INDEX('03_MATERIALES'!$H$2:$H$42,MATCH(D91,'03_MATERIALES'!$A$2:$A$42,0)),""))) -> 43.353101 | M91: =IF(N(J91)>0,F91*J91/p_area_plancha_m2,"") -> 0.4324 | N91: ESTIMADO
A92: BOM-0091 | B92: PRD-015 | C92: Panel posterior segmentado | D92: MAT-LAF06 | E92: CHAPA_AREA | F92: 1 | G92: 339.5 | H92: 1620 | J92: =G92*H92/1000000 -> 0.54999 | K92: =IF(E92="CHAPA_AREA",F92*J92*INDEX('03_MATERIALES'!$E$2:$E$42,MATCH(D92,'03_MATERIALES'!$A$2:$A$42,0))/1000*p_densidad_acero,IF(E92="PERFIL_LONGITUD",F92*I92*p_kg_por_m_perfil,"")) -> 2.5904529 | L92: =IF(E92="CHAPA_AREA",K92*INDEX('03_MATERIALES'!$H$2:$H$42,MATCH(D92,'03_MATERIALES'!$A$2:$A$42,0))/p_aprovechamiento_chapa,IF(E92="PERFIL_LONGITUD",K92*INDEX('03_MATERIALES'!$H$2:$H$42,MATCH(D92,'03_MATERIALES'!$A$2:$A$42,0))/p_aprovechamiento_perfil,IF(E92="UNIDAD",F92*INDEX('03_MATERIALES'!$H$2:$H$42,MATCH(D92,'03_MATERIALES'!$A$2:$A$42,0)),""))) -> 19.146826 | M92: =IF(N(J92)>0,F92*J92/p_area_plancha_m2,"") -> 0.19096875 | N92: ESTIMADO
A93: BOM-0092 | B93: PRD-015 | C93: Puerta con ventilación | D93: MAT-LAF06 | E93: CHAPA_AREA | F93: 1 | G93: 324.8 | H93: 1548 | J93: =G93*H93/1000000 -> 0.5027904 | K93: =IF(E93="CHAPA_AREA",F93*J93*INDEX('03_MATERIALES'!$E$2:$E$42,MATCH(D93,'03_MATERIALES'!$A$2:$A$42,0))/1000*p_densidad_acero,IF(E93="PERFIL_LONGITUD",F93*I93*p_kg_por_m_perfil,"")) -> 2.3681428 | L93: =IF(E93="CHAPA_AREA",K93*INDEX('03_MATERIALES'!$H$2:$H$42,MATCH(D93,'03_MATERIALES'!$A$2:$A$42,0))/p_aprovechamiento_chapa,IF(E93="PERFIL_LONGITUD",K93*INDEX('03_MATERIALES'!$H$2:$H$42,MATCH(D93,'03_MATERIALES'!$A$2:$A$42,0))/p_aprovechamiento_perfil,IF(E93="UNIDAD",F93*INDEX('03_MATERIALES'!$H$2:$H$42,MATCH(D93,'03_MATERIALES'!$A$2:$A$42,0)),""))) -> 17.503664 | M93: =IF(N(J93)>0,F93*J93/p_area_plancha_m2,"") -> 0.17458 | N93: ESTIMADO
A94: BOM-0093 | B94: PRD-015 | C94: Tapa superior/inferior | D94: MAT-LAF06 | E94: CHAPA_AREA | F94: 2 | G94: 328.5 | H94: 376 | J94: =G94*H94/1000000 -> 0.123516 | K94: =IF(E94="CHAPA_AREA",F94*J94*INDEX('03_MATERIALES'!$E$2:$E$42,MATCH(D94,'03_MATERIALES'!$A$2:$A$42,0))/1000*p_densidad_acero,IF(E94="PERFIL_LONGITUD",F94*I94*p_kg_por_m_perfil,"")) -> 1.1635207 | L94: =IF(E94="CHAPA_AREA",K94*INDEX('03_MATERIALES'!$H$2:$H$42,MATCH(D94,'03_MATERIALES'!$A$2:$A$42,0))/p_aprovechamiento_chapa,IF(E94="PERFIL_LONGITUD",K94*INDEX('03_MATERIALES'!$H$2:$H$42,MATCH(D94,'03_MATERIALES'!$A$2:$A$42,0))/p_aprovechamiento_perfil,IF(E94="UNIDAD",F94*INDEX('03_MATERIALES'!$H$2:$H$42,MATCH(D94,'03_MATERIALES'!$A$2:$A$42,0)),""))) -> 8.5999358 | M94: =IF(N(J94)>0,F94*J94/p_area_plancha_m2,"") -> 0.085775 | N94: ESTIMADO
A95: BOM-0094 | B95: PRD-015 | C95: Bisagras/cerraduras | D95: MAT-FIJ | E95: UNIDAD | F95: 3 | K95: =IF(E95="CHAPA_AREA",F95*J95*INDEX('03_MATERIALES'!$E$2:$E$42,MATCH(D95,'03_MATERIALES'!$A$2:$A$42,0))/1000*p_densidad_acero,IF(E95="PERFIL_LONGITUD",F95*I95*p_kg_por_m_perfil,"")) | L95: =IF(E95="CHAPA_AREA",K95*INDEX('03_MATERIALES'!$H$2:$H$42,MATCH(D95,'03_MATERIALES'!$A$2:$A$42,0))/p_aprovechamiento_chapa,IF(E95="PERFIL_LONGITUD",K95*INDEX('03_MATERIALES'!$H$2:$H$42,MATCH(D95,'03_MATERIALES'!$A$2:$A$42,0))/p_aprovechamiento_perfil,IF(E95="UNIDAD",F95*INDEX('03_MATERIALES'!$H$2:$H$42,MATCH(D95,'03_MATERIALES'!$A$2:$A$42,0)),""))) -> 2.7 | M95: =IF(N(J95)>0,F95*J95/p_area_plancha_m2,"") | N95: ESTIMADO
A96: BOM-0095 | B96: PRD-016 | C96: Costados chapa | D96: MAT-LAF06 | E96: CHAPA_AREA | F96: 2 | G96: 376 | H96: 1656 | J96: =G96*H96/1000000 -> 0.622656 | K96: =IF(E96="CHAPA_AREA",F96*J96*INDEX('03_MATERIALES'!$E$2:$E$42,MATCH(D96,'03_MATERIALES'!$A$2:$A$42,0))/1000*p_densidad_acero,IF(E96="PERFIL_LONGITUD",F96*I96*p_kg_por_m_perfil,"")) -> 5.8654195 | L96: =IF(E96="CHAPA_AREA",K96*INDEX('03_MATERIALES'!$H$2:$H$42,MATCH(D96,'03_MATERIALES'!$A$2:$A$42,0))/p_aprovechamiento_chapa,IF(E96="PERFIL_LONGITUD",K96*INDEX('03_MATERIALES'!$H$2:$H$42,MATCH(D96,'03_MATERIALES'!$A$2:$A$42,0))/p_aprovechamiento_perfil,IF(E96="UNIDAD",F96*INDEX('03_MATERIALES'!$H$2:$H$42,MATCH(D96,'03_MATERIALES'!$A$2:$A$42,0)),""))) -> 43.353101 | M96: =IF(N(J96)>0,F96*J96/p_area_plancha_m2,"") -> 0.4324 | N96: ESTIMADO
A97: BOM-0096 | B97: PRD-016 | C97: Panel posterior segmentado | D97: MAT-LAF06 | E97: CHAPA_AREA | F97: 1 | G97: 651 | H97: 1620 | J97: =G97*H97/1000000 -> 1.05462 | K97: =IF(E97="CHAPA_AREA",F97*J97*INDEX('03_MATERIALES'!$E$2:$E$42,MATCH(D97,'03_MATERIALES'!$A$2:$A$42,0))/1000*p_densidad_acero,IF(E97="PERFIL_LONGITUD",F97*I97*p_kg_por_m_perfil,"")) -> 4.9672602 | L97: =IF(E97="CHAPA_AREA",K97*INDEX('03_MATERIALES'!$H$2:$H$42,MATCH(D97,'03_MATERIALES'!$A$2:$A$42,0))/p_aprovechamiento_chapa,IF(E97="PERFIL_LONGITUD",K97*INDEX('03_MATERIALES'!$H$2:$H$42,MATCH(D97,'03_MATERIALES'!$A$2:$A$42,0))/p_aprovechamiento_perfil,IF(E97="UNIDAD",F97*INDEX('03_MATERIALES'!$H$2:$H$42,MATCH(D97,'03_MATERIALES'!$A$2:$A$42,0)),""))) -> 36.714532 | M97: =IF(N(J97)>0,F97*J97/p_area_plancha_m2,"") -> 0.3661875 | N97: ESTIMADO
A98: BOM-0097 | B98: PRD-016 | C98: Puerta con ventilación | D98: MAT-LAF06 | E98: CHAPA_AREA | F98: 2 | G98: 311.5 | H98: 1548 | J98: =G98*H98/1000000 -> 0.482202 | K98: =IF(E98="CHAPA_AREA",F98*J98*INDEX('03_MATERIALES'!$E$2:$E$42,MATCH(D98,'03_MATERIALES'!$A$2:$A$42,0))/1000*p_densidad_acero,IF(E98="PERFIL_LONGITUD",F98*I98*p_kg_por_m_perfil,"")) -> 4.5423428 | L98: =IF(E98="CHAPA_AREA",K98*INDEX('03_MATERIALES'!$H$2:$H$42,MATCH(D98,'03_MATERIALES'!$A$2:$A$42,0))/p_aprovechamiento_chapa,IF(E98="PERFIL_LONGITUD",K98*INDEX('03_MATERIALES'!$H$2:$H$42,MATCH(D98,'03_MATERIALES'!$A$2:$A$42,0))/p_aprovechamiento_perfil,IF(E98="UNIDAD",F98*INDEX('03_MATERIALES'!$H$2:$H$42,MATCH(D98,'03_MATERIALES'!$A$2:$A$42,0)),""))) -> 33.573838 | M98: =IF(N(J98)>0,F98*J98/p_area_plancha_m2,"") -> 0.3348625 | N98: ESTIMADO
A99: BOM-0098 | B99: PRD-016 | C99: Tapa superior/inferior | D99: MAT-LAF06 | E99: CHAPA_AREA | F99: 2 | G99: 630 | H99: 376 | J99: =G99*H99/1000000 -> 0.23688 | K99: =IF(E99="CHAPA_AREA",F99*J99*INDEX('03_MATERIALES'!$E$2:$E$42,MATCH(D99,'03_MATERIALES'!$A$2:$A$42,0))/1000*p_densidad_acero,IF(E99="PERFIL_LONGITUD",F99*I99*p_kg_por_m_perfil,"")) -> 2.2314096 | L99: =IF(E99="CHAPA_AREA",K99*INDEX('03_MATERIALES'!$H$2:$H$42,MATCH(D99,'03_MATERIALES'!$A$2:$A$42,0))/p_aprovechamiento_chapa,IF(E99="PERFIL_LONGITUD",K99*INDEX('03_MATERIALES'!$H$2:$H$42,MATCH(D99,'03_MATERIALES'!$A$2:$A$42,0))/p_aprovechamiento_perfil,IF(E99="UNIDAD",F99*INDEX('03_MATERIALES'!$H$2:$H$42,MATCH(D99,'03_MATERIALES'!$A$2:$A$42,0)),""))) -> 16.493027 | M99: =IF(N(J99)>0,F99*J99/p_area_plancha_m2,"") -> 0.1645 | N99: ESTIMADO
A100: BOM-0099 | B100: PRD-016 | C100: Bisagras/cerraduras | D100: MAT-FIJ | E100: UNIDAD | F100: 6 | K100: =IF(E100="CHAPA_AREA",F100*J100*INDEX('03_MATERIALES'!$E$2:$E$42,MATCH(D100,'03_MATERIALES'!$A$2:$A$42,0))/1000*p_densidad_acero,IF(E100="PERFIL_LONGITUD",F100*I100*p_kg_por_m_perfil,"")) | L100: =IF(E100="CHAPA_AREA",K100*INDEX('03_MATERIALES'!$H$2:$H$42,MATCH(D100,'03_MATERIALES'!$A$2:$A$42,0))/p_aprovechamiento_chapa,IF(E100="PERFIL_LONGITUD",K100*INDEX('03_MATERIALES'!$H$2:$H$42,MATCH(D100,'03_MATERIALES'!$A$2:$A$42,0))/p_aprovechamiento_perfil,IF(E100="UNIDAD",F100*INDEX('03_MATERIALES'!$H$2:$H$42,MATCH(D100,'03_MATERIALES'!$A$2:$A$42,0)),""))) -> 5.4 | M100: =IF(N(J100)>0,F100*J100/p_area_plancha_m2,"") | N100: ESTIMADO
...

Sheet 05_RECURSOS
A1: recurso_id | B1: recurso | C1: tipo_tecnico | D1: tipo_recurso | E1: cantidad | F1: costo_uso_soles_h | G1: potencia_kw_ref | H1: factor_carga | I1: grupo_operarios | J1: recurso_critico | K1: inventario_verificado | L1: naturaleza
A2: CCH-01 | B2: Guillotina hidráulica para corte de planchas de acero | C2: Guillotina hidráulica de chapa, hasta 4 mm | D2: MAQUINA | E2: 1 | F2: 24 | G2: 5.5 | H2: 0.5 | I2: Corte | J2: 0 | K2: 0 | L2: ESTIMADO
A3: CPR-01 | B3: Sierra de cinta para corte de tubos y perfiles | C3: Sierra de cinta para metal | D3: MAQUINA | E3: 1 | F3: 22 | G3: 0.75 | H3: 0.6 | I3: Corte | J3: 0 | K3: 0 | L3: ESTIMADO
A4: PER-01 | B4: Taladro de banco para perforación de acero | C4: Taladro de banco industrial | D4: MAQUINA | E4: 1 | F4: 22 | G4: 0.55 | H4: 0.5 | I4: Perforación | J4: 0 | K4: 0 | L4: ESTIMADO
A5: PLE-01 | B5: Plegadora hidráulica de chapa metálica | C5: Plegadora hidráulica compacta | D5: MAQUINA | E5: 1 | F5: 28 | G5: 5.5 | H5: 0.45 | I5: Plegado | J5: 1 | K5: 0 | L5: ESTIMADO
A6: SOL-01 | B6: Máquina de soldadura por arco MIG/MAG | C6: Soldadora inversora MIG/MAG | D6: MAQUINA | E6: 1 | F6: 32 | G6: 5 | H6: 0.35 | I6: Soldadura y armado | J6: 0 | K6: 0 | L6: ESTIMADO
A7: DES-01 | B7: Mesa de desbarbado/esmerilado | C7: Mesa de desbarbado/esmerilado | D7: PUESTO_MANUAL | E7: 1 | F7: 21 | G7: 1.5 | H7: 0.5 | I7: Acabado | J7: 0 | K7: 0 | L7: ESTIMADO
A8: PRE-01 | B8: Zona de preparación superficial | C8: Zona de preparación superficial | D8: AREA | E8: 1 | F8: 19 | G8: 2.2 | H8: 0.4 | I8: Acabado | J8: 0 | K8: 0 | L8: ESTIMADO
A9: PIN-01 | B9: Pistola manual de pintura electrostática en polvo | C9: Pistola manual de pintura electrostática en polvo | D9: EQUIPO_MANUAL | E9: 1 | F9: 32 | G9: 1.5 | H9: 0.7 | I9: Pintura y curado | J9: 0 | K9: 0 | L9: ESTIMADO
A10: ARM-01 | B10: Mesa de armado | C10: Mesa de armado | D10: PUESTO_MANUAL | E10: 1 | F10: 19 | G10: 1 | H10: 0.3 | I10: Soldadura y armado | J10: 0 | K10: 0 | L10: ESTIMADO
A11: CAL-01 | B11: Área de inspección | C11: Área de inspección | D11: AREA | E11: 1 | F11: 20 | G11: 0.2 | H11: 0.5 | I11: Calidad y despacho | J11: 0 | K11: 0 | L11: ESTIMADO
A12: EMP-01 | B12: Zona de protección y embalaje | C12: Zona de protección y embalaje | D12: AREA | E12: 1 | F12: 18 | G12: 0.3 | H12: 0.3 | I12: Calidad y despacho | J12: 0 | K12: 0 | L12: ESTIMADO
A13: PER-02 | B13: Segundo taladro (alternativo) | C13: Segundo taladro (alternativo) | D13: MAQUINA | E13: 1 | F13: 22 | G13: 0.75 | H13: 0.5 | I13: Perforación | J13: 0 | K13: 0 | L13: ESTIMADO
A14: SOL-02 | B14: Segunda estación soldadura (alternativa) | C14: Segunda estación soldadura (alternativa) | D14: MAQUINA | E14: 1 | F14: 32 | G14: 5 | H14: 0.35 | I14: Soldadura y armado | J14: 0 | K14: 0 | L14: ESTIMADO
A15: PIN-EXT | B15: Proveedor de pintura externo | C15: Proveedor de pintura externo | D15: EXTERNO | E15: 0 | G15: 0 | H15: 0 | I15: No aplica | J15: 0 | K15: 0 | L15: ESTIMADO
A16: HOR-01 | B16: Horno de curado de pintura electrostática por lotes | C16: Horno de curado de pintura electrostática por lotes | D16: MAQUINA | E16: 1 | F16: 26 | G16: 24 | H16: 0.6 | I16: Pintura y curado | J16: 0 | K16: 0 | L16: ESTIMADO
A17: MAN-01 | B17: Manipulación y enfriamiento de piezas | C17: Manipulación y enfriamiento de piezas | D17: PUESTO_MANUAL | E17: 1 | F17: 16 | G17: 0.5 | H17: 0.5 | I17: Pintura y curado | J17: 0 | K17: 0 | L17: ESTIMADO
A18: SAL-PIN | B18: Sala acondicionada para pintura electrostática | C18: Sala acondicionada para pintura electrostática | D18: AREA | E18: 1 | G18: 3 | H18: 0.5 | I18: Pintura y curado | J18: 0 | K18: 0 | L18: ESTIMADO

Sheet 06_RUTAS
A1: producto_id | B1: paso | C1: operacion | D1: recurso_id | E1: paso_predecesor | F1: min_fijos_lote | G1: min_por_unidad | H1: tratamiento_tiempo | I1: min_ciclo_horno_incluido | J1: origen_tiempo | K1: naturaleza
A2: PRD-001 | B2: 1 | C2: Corte de planchas de acero | D2: CCH-01 | F2: 8 | G2: 34.62 | H2: POR_UNIDAD | I2: 0 | J2: HEREDADO_SIN_CRONOMETRAJE | K2: ESTIMADO
A3: PRD-001 | B3: 2 | C3: Corte de tubos y perfiles | D3: CPR-01 | E3: 1 | F3: 8 | G3: 43.52 | H3: POR_UNIDAD | I3: 0 | J3: HEREDADO_SIN_CRONOMETRAJE | K3: ESTIMADO
A4: PRD-001 | B4: 3 | C4: Perforación | D4: PER-01 | E4: 2 | F4: 10 | G4: 63.2 | H4: POR_UNIDAD | I4: 0 | J4: HEREDADO_SIN_CRONOMETRAJE | K4: ESTIMADO
A5: PRD-001 | B5: 4 | C5: Plegado | D5: PLE-01 | E5: 3 | F5: 12 | G5: 60 | H5: POR_UNIDAD | I5: 0 | J5: HEREDADO_SIN_CRONOMETRAJE | K5: ESTIMADO
A6: PRD-001 | B6: 5 | C6: Soldadura | D6: SOL-01 | E6: 4 | F6: 10 | G6: 78.4 | H6: POR_UNIDAD | I6: 0 | J6: HEREDADO_SIN_CRONOMETRAJE | K6: ESTIMADO
A7: PRD-001 | B7: 6 | C7: Desbarbado | D7: DES-01 | E7: 5 | F7: 3 | G7: 42 | H7: POR_UNIDAD | I7: 0 | J7: HEREDADO_SIN_CRONOMETRAJE | K7: ESTIMADO
A8: PRD-001 | B8: 7 | C8: Preparación superficial | D8: PRE-01 | E8: 6 | F8: 6 | G8: 29.7248 | H8: POR_UNIDAD | I8: 0 | J8: HEREDADO_SIN_CRONOMETRAJE | K8: ESTIMADO
A9: PRD-001 | B9: 8 | C9: Aplicación electrostática de polvo | D9: PIN-01 | E9: 7 | F9: 12 | G9: 8.02 | H9: POR_UNIDAD | I9: 0 | J9: HIPOTESIS_TECNICA | K9: ESTIMADO
A10: PRD-001 | B10: 9 | C10: Curado térmico en horno | D10: HOR-01 | E10: 8 | F10: 45 | G10: 0 | H10: POR_LOTE | I10: 40 | J10: HIPOTESIS_TECNICA | K10: ESTIMADO
A11: PRD-001 | B11: 10 | C11: Colgado, traslado y enfriamiento | D11: MAN-01 | E11: 9 | F11: 8 | G11: 2.69 | H11: POR_UNIDAD | I11: 0 | J11: HIPOTESIS_TECNICA | K11: ESTIMADO
A12: PRD-001 | B12: 11 | C12: Ensamblaje | D12: ARM-01 | E12: 10 | F12: 6 | G12: 60 | H12: POR_UNIDAD | I12: 0 | J12: HEREDADO_SIN_CRONOMETRAJE | K12: ESTIMADO
A13: PRD-001 | B13: 12 | C13: Inspección de calidad | D13: CAL-01 | E13: 11 | F13: 2 | G13: 3.86 | H13: POR_UNIDAD | I13: 0 | J13: HIPOTESIS_TECNICA | K13: ESTIMADO
A14: PRD-001 | B14: 13 | C14: Embalaje | D14: EMP-01 | E14: 12 | F14: 2 | G14: 5.3 | H14: POR_UNIDAD | I14: 0 | J14: HIPOTESIS_TECNICA | K14: ESTIMADO
A15: PRD-002 | B15: 1 | C15: Corte de planchas de acero | D15: CCH-01 | F15: 8 | G15: 36.67 | H15: POR_UNIDAD | I15: 0 | J15: HEREDADO_SIN_CRONOMETRAJE | K15: ESTIMADO
A16: PRD-002 | B16: 2 | C16: Corte de tubos y perfiles | D16: CPR-01 | E16: 1 | F16: 8 | G16: 52 | H16: POR_UNIDAD | I16: 0 | J16: HEREDADO_SIN_CRONOMETRAJE | K16: ESTIMADO
A17: PRD-002 | B17: 3 | C17: Perforación | D17: PER-01 | E17: 2 | F17: 10 | G17: 82.1 | H17: POR_UNIDAD | I17: 0 | J17: HEREDADO_SIN_CRONOMETRAJE | K17: ESTIMADO
A18: PRD-002 | B18: 4 | C18: Plegado | D18: PLE-01 | E18: 3 | F18: 12 | G18: 69 | H18: POR_UNIDAD | I18: 0 | J18: HEREDADO_SIN_CRONOMETRAJE | K18: ESTIMADO
A19: PRD-002 | B19: 5 | C19: Soldadura | D19: SOL-01 | E19: 4 | F19: 10 | G19: 78.4 | H19: POR_UNIDAD | I19: 0 | J19: HEREDADO_SIN_CRONOMETRAJE | K19: ESTIMADO
A20: PRD-002 | B20: 6 | C20: Desbarbado | D20: DES-01 | E20: 5 | F20: 3 | G20: 49.5 | H20: POR_UNIDAD | I20: 0 | J20: HEREDADO_SIN_CRONOMETRAJE | K20: ESTIMADO
A21: PRD-002 | B21: 7 | C21: Preparación superficial | D21: PRE-01 | E21: 6 | F21: 6 | G21: 32.064 | H21: POR_UNIDAD | I21: 0 | J21: HEREDADO_SIN_CRONOMETRAJE | K21: ESTIMADO
A22: PRD-002 | B22: 8 | C22: Aplicación electrostática de polvo | D22: PIN-01 | E22: 7 | F22: 12 | G22: 8.02 | H22: POR_UNIDAD | I22: 0 | J22: HIPOTESIS_TECNICA | K22: ESTIMADO
A23: PRD-002 | B23: 9 | C23: Curado térmico en horno | D23: HOR-01 | E23: 8 | F23: 45 | G23: 0 | H23: POR_LOTE | I23: 40 | J23: HIPOTESIS_TECNICA | K23: ESTIMADO
A24: PRD-002 | B24: 10 | C24: Colgado, traslado y enfriamiento | D24: MAN-01 | E24: 9 | F24: 8 | G24: 2.69 | H24: POR_UNIDAD | I24: 0 | J24: HIPOTESIS_TECNICA | K24: ESTIMADO
A25: PRD-002 | B25: 11 | C25: Ensamblaje | D25: ARM-01 | E25: 10 | F25: 6 | G25: 62.25 | H25: POR_UNIDAD | I25: 0 | J25: HEREDADO_SIN_CRONOMETRAJE | K25: ESTIMADO
A26: PRD-002 | B26: 12 | C26: Inspección de calidad | D26: CAL-01 | E26: 11 | F26: 2 | G26: 3.86 | H26: POR_UNIDAD | I26: 0 | J26: HIPOTESIS_TECNICA | K26: ESTIMADO
A27: PRD-002 | B27: 13 | C27: Embalaje | D27: EMP-01 | E27: 12 | F27: 2 | G27: 5.3 | H27: POR_UNIDAD | I27: 0 | J27: HIPOTESIS_TECNICA | K27: ESTIMADO
A28: PRD-007 | B28: 1 | C28: Corte de planchas de acero | D28: CCH-01 | F28: 8 | G28: 90.38 | H28: POR_UNIDAD | I28: 0 | J28: HEREDADO_SIN_CRONOMETRAJE | K28: ESTIMADO
A29: PRD-007 | B29: 2 | C29: Corte de tubos y perfiles | D29: CPR-01 | E29: 1 | F29: 8 | G29: 5.98 | H29: POR_UNIDAD | I29: 0 | J29: HEREDADO_SIN_CRONOMETRAJE | K29: ESTIMADO
A30: PRD-007 | B30: 3 | C30: Perforación | D30: PER-01 | E30: 2 | F30: 10 | G30: 97 | H30: POR_UNIDAD | I30: 0 | J30: HEREDADO_SIN_CRONOMETRAJE | K30: ESTIMADO
A31: PRD-007 | B31: 4 | C31: Plegado | D31: PLE-01 | E31: 3 | F31: 12 | G31: 196 | H31: POR_UNIDAD | I31: 0 | J31: HEREDADO_SIN_CRONOMETRAJE | K31: ESTIMADO
A32: PRD-007 | B32: 5 | C32: Desbarbado | D32: DES-01 | E32: 4 | F32: 3 | G32: 51 | H32: POR_UNIDAD | I32: 0 | J32: HEREDADO_SIN_CRONOMETRAJE | K32: ESTIMADO
A33: PRD-007 | B33: 6 | C33: Preparación superficial | D33: PRE-01 | E33: 5 | F33: 6 | G33: 40.5152 | H33: POR_UNIDAD | I33: 0 | J33: HEREDADO_SIN_CRONOMETRAJE | K33: ESTIMADO
A34: PRD-007 | B34: 7 | C34: Aplicación electrostática de polvo | D34: PIN-01 | E34: 6 | F34: 12 | G34: 7.76 | H34: POR_UNIDAD | I34: 0 | J34: HIPOTESIS_TECNICA | K34: ESTIMADO
A35: PRD-007 | B35: 8 | C35: Curado térmico en horno | D35: HOR-01 | E35: 7 | F35: 45 | G35: 0 | H35: POR_LOTE | I35: 40 | J35: HIPOTESIS_TECNICA | K35: ESTIMADO
A36: PRD-007 | B36: 9 | C36: Colgado, traslado y enfriamiento | D36: MAN-01 | E36: 8 | F36: 8 | G36: 2.63 | H36: POR_UNIDAD | I36: 0 | J36: HIPOTESIS_TECNICA | K36: ESTIMADO
A37: PRD-007 | B37: 10 | C37: Ensamblaje | D37: ARM-01 | E37: 9 | F37: 6 | G37: 69 | H37: POR_UNIDAD | I37: 0 | J37: HEREDADO_SIN_CRONOMETRAJE | K37: ESTIMADO
A38: PRD-007 | B38: 11 | C38: Inspección de calidad | D38: CAL-01 | E38: 10 | F38: 2 | G38: 3.79 | H38: POR_UNIDAD | I38: 0 | J38: HIPOTESIS_TECNICA | K38: ESTIMADO
A39: PRD-007 | B39: 12 | C39: Embalaje | D39: EMP-01 | E39: 11 | F39: 2 | G39: 5.18 | H39: POR_UNIDAD | I39: 0 | J39: HIPOTESIS_TECNICA | K39: ESTIMADO
A40: PRD-008 | B40: 1 | C40: Corte de planchas de acero | D40: CCH-01 | F40: 8 | G40: 56.975 | H40: POR_UNIDAD | I40: 0 | J40: HEREDADO_SIN_CRONOMETRAJE | K40: ESTIMADO
A41: PRD-008 | B41: 2 | C41: Corte de tubos y perfiles | D41: CPR-01 | E41: 1 | F41: 8 | G41: 6.28 | H41: POR_UNIDAD | I41: 0 | J41: HEREDADO_SIN_CRONOMETRAJE | K41: ESTIMADO
A42: PRD-008 | B42: 3 | C42: Perforación | D42: PER-01 | E42: 2 | F42: 10 | G42: 67 | H42: POR_UNIDAD | I42: 0 | J42: HEREDADO_SIN_CRONOMETRAJE | K42: ESTIMADO
A43: PRD-008 | B43: 4 | C43: Plegado | D43: PLE-01 | E43: 3 | F43: 12 | G43: 124 | H43: POR_UNIDAD | I43: 0 | J43: HEREDADO_SIN_CRONOMETRAJE | K43: ESTIMADO
A44: PRD-008 | B44: 5 | C44: Soldadura | D44: SOL-01 | E44: 4 | F44: 10 | G44: 5.6 | H44: POR_UNIDAD | I44: 0 | J44: HEREDADO_SIN_CRONOMETRAJE | K44: ESTIMADO
A45: PRD-008 | B45: 6 | C45: Desbarbado | D45: DES-01 | E45: 5 | F45: 3 | G45: 33 | H45: POR_UNIDAD | I45: 0 | J45: HEREDADO_SIN_CRONOMETRAJE | K45: ESTIMADO
A46: PRD-008 | B46: 7 | C46: Preparación superficial | D46: PRE-01 | E46: 6 | F46: 6 | G46: 27.0712 | H46: POR_UNIDAD | I46: 0 | J46: HEREDADO_SIN_CRONOMETRAJE | K46: ESTIMADO
A47: PRD-008 | B47: 8 | C47: Aplicación electrostática de polvo | D47: PIN-01 | E47: 7 | F47: 12 | G47: 7.34 | H47: POR_UNIDAD | I47: 0 | J47: HIPOTESIS_TECNICA | K47: ESTIMADO
A48: PRD-008 | B48: 9 | C48: Curado térmico en horno | D48: HOR-01 | E48: 8 | F48: 45 | G48: 0 | H48: POR_LOTE | I48: 40 | J48: HIPOTESIS_TECNICA | K48: ESTIMADO
A49: PRD-008 | B49: 10 | C49: Colgado, traslado y enfriamiento | D49: MAN-01 | E49: 9 | F49: 8 | G49: 2.54 | H49: POR_UNIDAD | I49: 0 | J49: HIPOTESIS_TECNICA | K49: ESTIMADO
A50: PRD-008 | B50: 11 | C50: Ensamblaje | D50: ARM-01 | E50: 10 | F50: 6 | G50: 48.75 | H50: POR_UNIDAD | I50: 0 | J50: HEREDADO_SIN_CRONOMETRAJE | K50: ESTIMADO
A51: PRD-008 | B51: 12 | C51: Inspección de calidad | D51: CAL-01 | E51: 11 | F51: 2 | G51: 3.67 | H51: POR_UNIDAD | I51: 0 | J51: HIPOTESIS_TECNICA | K51: ESTIMADO
A52: PRD-008 | B52: 13 | C52: Embalaje | D52: EMP-01 | E52: 12 | F52: 2 | G52: 5 | H52: POR_UNIDAD | I52: 0 | J52: HIPOTESIS_TECNICA | K52: ESTIMADO
A53: PRD-013 | B53: 1 | C53: Corte de planchas de acero | D53: CCH-01 | F53: 8 | G53: 40.245 | H53: POR_UNIDAD | I53: 0 | J53: HEREDADO_SIN_CRONOMETRAJE | K53: ESTIMADO
A54: PRD-013 | B54: 2 | C54: Perforación | D54: PER-01 | E54: 1 | F54: 10 | G54: 14.8 | H54: POR_UNIDAD | I54: 0 | J54: HEREDADO_SIN_CRONOMETRAJE | K54: ESTIMADO
A55: PRD-013 | B55: 3 | C55: Plegado | D55: PLE-01 | E55: 2 | F55: 12 | G55: 104 | H55: POR_UNIDAD | I55: 0 | J55: HEREDADO_SIN_CRONOMETRAJE | K55: ESTIMADO
A56: PRD-013 | B56: 4 | C56: Desbarbado | D56: DES-01 | E56: 3 | F56: 3 | G56: 18 | H56: POR_UNIDAD | I56: 0 | J56: HEREDADO_SIN_CRONOMETRAJE | K56: ESTIMADO
A57: PRD-013 | B57: 5 | C57: Preparación superficial | D57: PRE-01 | E57: 4 | F57: 6 | G57: 26.324 | H57: POR_UNIDAD | I57: 0 | J57: HEREDADO_SIN_CRONOMETRAJE | K57: ESTIMADO
A58: PRD-013 | B58: 6 | C58: Aplicación electrostática de polvo | D58: PIN-01 | E58: 5 | F58: 12 | G58: 6.83 | H58: POR_UNIDAD | I58: 0 | J58: HIPOTESIS_TECNICA | K58: ESTIMADO
A59: PRD-013 | B59: 7 | C59: Curado térmico en horno | D59: HOR-01 | E59: 6 | F59: 45 | G59: 0 | H59: POR_LOTE | I59: 40 | J59: HIPOTESIS_TECNICA | K59: ESTIMADO
A60: PRD-013 | B60: 8 | C60: Colgado, traslado y enfriamiento | D60: MAN-01 | E60: 7 | F60: 8 | G60: 2.42 | H60: POR_UNIDAD | I60: 0 | J60: HIPOTESIS_TECNICA | K60: ESTIMADO
A61: PRD-013 | B61: 9 | C61: Ensamblaje | D61: ARM-01 | E61: 8 | F61: 6 | G61: 42 | H61: POR_UNIDAD | I61: 0 | J61: HEREDADO_SIN_CRONOMETRAJE | K61: ESTIMADO
A62: PRD-013 | B62: 10 | C62: Inspección de calidad | D62: CAL-01 | E62: 9 | F62: 2 | G62: 3.52 | H62: POR_UNIDAD | I62: 0 | J62: HIPOTESIS_TECNICA | K62: ESTIMADO
A63: PRD-013 | B63: 11 | C63: Embalaje | D63: EMP-01 | E63: 10 | F63: 2 | G63: 4.78 | H63: POR_UNIDAD | I63: 0 | J63: HIPOTESIS_TECNICA | K63: ESTIMADO
A64: PRD-014 | B64: 1 | C64: Corte de planchas de acero | D64: CCH-01 | F64: 8 | G64: 57.14 | H64: POR_UNIDAD | I64: 0 | J64: HEREDADO_SIN_CRONOMETRAJE | K64: ESTIMADO
A65: PRD-014 | B65: 2 | C65: Perforación | D65: PER-01 | E65: 1 | F65: 10 | G65: 27 | H65: POR_UNIDAD | I65: 0 | J65: HEREDADO_SIN_CRONOMETRAJE | K65: ESTIMADO
A66: PRD-014 | B66: 3 | C66: Plegado | D66: PLE-01 | E66: 2 | F66: 12 | G66: 149 | H66: POR_UNIDAD | I66: 0 | J66: HEREDADO_SIN_CRONOMETRAJE | K66: ESTIMADO
A67: PRD-014 | B67: 4 | C67: Desbarbado | D67: DES-01 | E67: 3 | F67: 3 | G67: 25.5 | H67: POR_UNIDAD | I67: 0 | J67: HEREDADO_SIN_CRONOMETRAJE | K67: ESTIMADO
A68: PRD-014 | B68: 5 | C68: Preparación superficial | D68: PRE-01 | E68: 4 | F68: 6 | G68: 37.528 | H68: POR_UNIDAD | I68: 0 | J68: HEREDADO_SIN_CRONOMETRAJE | K68: ESTIMADO
A69: PRD-014 | B69: 6 | C69: Aplicación electrostática de polvo | D69: PIN-01 | E69: 5 | F69: 12 | G69: 6.83 | H69: POR_UNIDAD | I69: 0 | J69: HIPOTESIS_TECNICA | K69: ESTIMADO
A70: PRD-014 | B70: 7 | C70: Curado térmico en horno | D70: HOR-01 | E70: 6 | F70: 45 | G70: 0 | H70: POR_LOTE | I70: 40 | J70: HIPOTESIS_TECNICA | K70: ESTIMADO
A71: PRD-014 | B71: 8 | C71: Colgado, traslado y enfriamiento | D71: MAN-01 | E71: 7 | F71: 8 | G71: 2.42 | H71: POR_UNIDAD | I71: 0 | J71: HIPOTESIS_TECNICA | K71: ESTIMADO
A72: PRD-014 | B72: 9 | C72: Ensamblaje | D72: ARM-01 | E72: 8 | F72: 6 | G72: 56.25 | H72: POR_UNIDAD | I72: 0 | J72: HEREDADO_SIN_CRONOMETRAJE | K72: ESTIMADO
A73: PRD-014 | B73: 10 | C73: Inspección de calidad | D73: CAL-01 | E73: 9 | F73: 2 | G73: 3.52 | H73: POR_UNIDAD | I73: 0 | J73: HIPOTESIS_TECNICA | K73: ESTIMADO
A74: PRD-014 | B74: 11 | C74: Embalaje | D74: EMP-01 | E74: 10 | F74: 2 | G74: 4.78 | H74: POR_UNIDAD | I74: 0 | J74: HIPOTESIS_TECNICA | K74: ESTIMADO
A75: PRD-019 | B75: 1 | C75: Corte de planchas de acero | D75: CCH-01 | F75: 8 | G75: 35.56 | H75: POR_UNIDAD | I75: 0 | J75: HEREDADO_SIN_CRONOMETRAJE | K75: ESTIMADO
A76: PRD-019 | B76: 2 | C76: Perforación | D76: PER-01 | E76: 1 | F76: 10 | G76: 5.8 | H76: POR_UNIDAD | I76: 0 | J76: HEREDADO_SIN_CRONOMETRAJE | K76: ESTIMADO
A77: PRD-019 | B77: 3 | C77: Plegado | D77: PLE-01 | E77: 2 | F77: 12 | G77: 86 | H77: POR_UNIDAD | I77: 0 | J77: HEREDADO_SIN_CRONOMETRAJE | K77: ESTIMADO
A78: PRD-019 | B78: 4 | C78: Desbarbado | D78: DES-01 | E78: 3 | F78: 3 | G78: 15 | H78: POR_UNIDAD | I78: 0 | J78: HEREDADO_SIN_CRONOMETRAJE | K78: ESTIMADO
A79: PRD-019 | B79: 5 | C79: Preparación superficial | D79: PRE-01 | E79: 4 | F79: 6 | G79: 25.712 | H79: POR_UNIDAD | I79: 0 | J79: HEREDADO_SIN_CRONOMETRAJE | K79: ESTIMADO
A80: PRD-019 | B80: 6 | C80: Aplicación electrostática de polvo | D80: PIN-01 | E80: 5 | F80: 12 | G80: 6.58 | H80: POR_UNIDAD | I80: 0 | J80: HIPOTESIS_TECNICA | K80: ESTIMADO
A81: PRD-019 | B81: 7 | C81: Curado térmico en horno | D81: HOR-01 | E81: 6 | F81: 45 | G81: 0 | H81: POR_LOTE | I81: 40 | J81: HIPOTESIS_TECNICA | K81: ESTIMADO
A82: PRD-019 | B82: 8 | C82: Colgado, traslado y enfriamiento | D82: MAN-01 | E82: 7 | F82: 8 | G82: 2.36 | H82: POR_UNIDAD | I82: 0 | J82: HIPOTESIS_TECNICA | K82: ESTIMADO
A83: PRD-019 | B83: 9 | C83: Ensamblaje | D83: ARM-01 | E83: 8 | F83: 6 | G83: 27 | H83: POR_UNIDAD | I83: 0 | J83: HEREDADO_SIN_CRONOMETRAJE | K83: ESTIMADO
A84: PRD-019 | B84: 10 | C84: Inspección de calidad | D84: CAL-01 | E84: 9 | F84: 2 | G84: 3.45 | H84: POR_UNIDAD | I84: 0 | J84: HIPOTESIS_TECNICA | K84: ESTIMADO
A85: PRD-019 | B85: 11 | C85: Embalaje | D85: EMP-01 | E85: 10 | F85: 2 | G85: 4.67 | H85: POR_UNIDAD | I85: 0 | J85: HIPOTESIS_TECNICA | K85: ESTIMADO
A86: PRD-020 | B86: 1 | C86: Corte de planchas de acero | D86: CCH-01 | F86: 8 | G86: 35.92 | H86: POR_UNIDAD | I86: 0 | J86: HEREDADO_SIN_CRONOMETRAJE | K86: ESTIMADO
A87: PRD-020 | B87: 2 | C87: Corte de tubos y perfiles | D87: CPR-01 | E87: 1 | F87: 8 | G87: 32.28 | H87: POR_UNIDAD | I87: 0 | J87: HEREDADO_SIN_CRONOMETRAJE | K87: ESTIMADO
A88: PRD-020 | B88: 3 | C88: Perforación | D88: PER-01 | E88: 2 | F88: 10 | G88: 54.8 | H88: POR_UNIDAD | I88: 0 | J88: HEREDADO_SIN_CRONOMETRAJE | K88: ESTIMADO
A89: PRD-020 | B89: 4 | C89: Plegado | D89: PLE-01 | E89: 3 | F89: 12 | G89: 85 | H89: POR_UNIDAD | I89: 0 | J89: HEREDADO_SIN_CRONOMETRAJE | K89: ESTIMADO
A90: PRD-020 | B90: 5 | C90: Desbarbado | D90: DES-01 | E90: 4 | F90: 3 | G90: 37.5 | H90: POR_UNIDAD | I90: 0 | J90: HEREDADO_SIN_CRONOMETRAJE | K90: ESTIMADO
A91: PRD-020 | B91: 6 | C91: Preparación superficial | D91: PRE-01 | E91: 5 | F91: 6 | G91: 24.4752 | H91: POR_UNIDAD | I91: 0 | J91: HEREDADO_SIN_CRONOMETRAJE | K91: ESTIMADO
A92: PRD-020 | B92: 7 | C92: Aplicación electrostática de polvo | D92: PIN-01 | E92: 6 | F92: 12 | G92: 6.58 | H92: POR_UNIDAD | I92: 0 | J92: HIPOTESIS_TECNICA | K92: ESTIMADO
A93: PRD-020 | B93: 8 | C93: Curado térmico en horno | D93: HOR-01 | E93: 7 | F93: 45 | G93: 0 | H93: POR_LOTE | I93: 40 | J93: HIPOTESIS_TECNICA | K93: ESTIMADO
A94: PRD-020 | B94: 9 | C94: Colgado, traslado y enfriamiento | D94: MAN-01 | E94: 8 | F94: 8 | G94: 2.36 | H94: POR_UNIDAD | I94: 0 | J94: HIPOTESIS_TECNICA | K94: ESTIMADO
A95: PRD-020 | B95: 10 | C95: Ensamblaje | D95: ARM-01 | E95: 9 | F95: 6 | G95: 61.5 | H95: POR_UNIDAD | I95: 0 | J95: HEREDADO_SIN_CRONOMETRAJE | K95: ESTIMADO
A96: PRD-020 | B96: 11 | C96: Inspección de calidad | D96: CAL-01 | E96: 10 | F96: 2 | G96: 3.45 | H96: POR_UNIDAD | I96: 0 | J96: HIPOTESIS_TECNICA | K96: ESTIMADO
A97: PRD-020 | B97: 12 | C97: Embalaje | D97: EMP-01 | E97: 11 | F97: 2 | G97: 4.67 | H97: POR_UNIDAD | I97: 0 | J97: HIPOTESIS_TECNICA | K97: ESTIMADO
A98: PRD-003 | B98: 1 | C98: Corte de tubos y perfiles | D98: CPR-01 | F98: 8 | G98: 68.56 | H98: POR_UNIDAD | I98: 0 | J98: HEREDADO_SIN_CRONOMETRAJE | K98: ESTIMADO
A99: PRD-003 | B99: 2 | C99: Perforación | D99: PER-02 | E99: 1 | F99: 10 | G99: 35.6 | H99: POR_UNIDAD | I99: 0 | J99: HEREDADO_SIN_CRONOMETRAJE | K99: ESTIMADO
A100: PRD-003 | B100: 3 | C100: Soldadura | D100: SOL-02 | E100: 2 | F100: 10 | G100: 89.6 | H100: POR_UNIDAD | I100: 0 | J100: HEREDADO_SIN_CRONOMETRAJE | K100: ESTIMADO
...

Sheet 07_ELEGIBILIDAD
A1: producto_id | B1: paso | C1: recurso_id | D1: tipo_asignacion | E1: elegible | F1: factor_tiempo | G1: naturaleza
A2: PRD-001 | B2: 1 | C2: CCH-01 | D2: PRINCIPAL | E2: 1 | F2: 1 | G2: CALCULADO
A3: PRD-001 | B3: 2 | C3: CPR-01 | D3: PRINCIPAL | E3: 1 | F3: 1 | G3: CALCULADO
A4: PRD-001 | B4: 3 | C4: PER-01 | D4: PRINCIPAL | E4: 1 | F4: 1 | G4: CALCULADO
A5: PRD-001 | B5: 3 | C5: PER-02 | D5: ALT_UTILLAJE | E5: 1 | F5: 1.1 | G5: ESTIMADO
A6: PRD-001 | B6: 4 | C6: PLE-01 | D6: PRINCIPAL | E6: 1 | F6: 1 | G6: CALCULADO
A7: PRD-001 | B7: 5 | C7: SOL-01 | D7: PRINCIPAL | E7: 1 | F7: 1 | G7: CALCULADO
A8: PRD-001 | B8: 5 | C8: SOL-02 | D8: ALT_MISMO_PROCESO | E8: 1 | F8: 1 | G8: ESTIMADO
A9: PRD-001 | B9: 6 | C9: DES-01 | D9: PRINCIPAL | E9: 1 | F9: 1 | G9: CALCULADO
A10: PRD-001 | B10: 7 | C10: PRE-01 | D10: PRINCIPAL | E10: 1 | F10: 1 | G10: CALCULADO
A11: PRD-001 | B11: 8 | C11: PIN-01 | D11: PRINCIPAL | E11: 1 | F11: 1 | G11: CALCULADO
A12: PRD-001 | B12: 9 | C12: HOR-01 | D12: PRINCIPAL | E12: 1 | F12: 1 | G12: CALCULADO
A13: PRD-001 | B13: 10 | C13: MAN-01 | D13: PRINCIPAL | E13: 1 | F13: 1 | G13: CALCULADO
... A474: PRD-050 | B474: 8 | C474: ARM-01 | D474: PRINCIPAL | E474: 1 | F474: 1 | G474: CALCULADO

Sheet 08_PERSONAL
A1: operario_id | B1: turno | C1: hora_entrada | D1: hora_salida | E1: descanso_h | F1: horas_netas_dia | G1: control_horario_h | H1: naturaleza
A2: OP-01 | B2: 1 | C2: 0.33333333 | D2: 0.70833333 | E2: 1 | F2: 8 | G2: =(D2-C2)*24-E2 -> 8 | H2: REAL
A3: OP-02 | B3: 1 | C3: 0.33333333 | D3: 0.70833333 | E3: 1 | F3: 8 | G3: =(D3-C3)*24-E3 -> 8 | H3: REAL
A4: OP-03 | B4: 1 | C4: 0.33333333 | D4: 0.70833333 | E4: 1 | F4: 8 | G4: =(D4-C4)*24-E4 -> 8 | H4: REAL
A5: OP-04 | B5: 1 | C5: 0.33333333 | D5: 0.70833333 | E5: 1 | F5: 8 | G5: =(D5-C5)*24-E5 -> 8 | H5: REAL
A6: OP-05 | B6: 1 | C6: 0.33333333 | D6: 0.70833333 | E6: 1 | F6: 8 | G6: =(D6-C6)*24-E6 -> 8 | H6: REAL
A7: OP-06 | B7: 1 | C7: 0.33333333 | D7: 0.70833333 | E7: 1 | F7: 8 | G7: =(D7-C7)*24-E7 -> 8 | H7: REAL
A8: OP-07 | B8: 1 | C8: 0.33333333 | D8: 0.70833333 | E8: 1 | F8: 8 | G8: =(D8-C8)*24-E8 -> 8 | H8: REAL
A9: OP-08 | B9: 1 | C9: 0.33333333 | D9: 0.70833333 | E9: 1 | F9: 8 | G9: =(D9-C9)*24-E9 -> 8 | H9: REAL
A10: OP-09 | B10: 1 | C10: 0.33333333 | D10: 0.70833333 | E10: 1 | F10: 8 | G10: =(D10-C10)*24-E10 -> 8 | H10: REAL
A11: OP-10 | B11: 1 | C11: 0.33333333 | D11: 0.70833333 | E11: 1 | F11: 8 | G11: =(D11-C11)*24-E11 -> 8 | H11: REAL
A12: OP-11 | B12: 1 | C12: 0.33333333 | D12: 0.70833333 | E12: 1 | F12: 8 | G12: =(D12-C12)*24-E12 -> 8 | H12: REAL
A13: OP-12 | B13: 1 | C13: 0.33333333 | D13: 0.70833333 | E13: 1 | F13: 8 | G13: =(D13-C13)*24-E13 -> 8 | H13: REAL
... A26: OP-25 | B26: 1 | C26: 0.33333333 | D26: 0.70833333 | E26: 1 | F26: 8 | G26: =(D26-C26)*24-E26 -> 8 | H26: REAL

Sheet 09_CALENDARIO
A1: fecha | B1: dia_semana | C1: laborable_base | D1: feriado_nacional | E1: productivo_efectivo | F1: horas_productivas | G1: naturaleza
A2: 45658 | B2: =WEEKDAY(A2,2) -> 3 | C2: 1 | D2: Año Nuevo | E2: =IF(AND(p_aplicar_feriados=1,D2<>""),0,C2) -> 1 | F2: =E2*p_horas_productivas_dia -> 8 | G2: ESTIMADO
A3: 45659 | B3: =WEEKDAY(A3,2) -> 4 | C3: 1 | E3: =IF(AND(p_aplicar_feriados=1,D3<>""),0,C3) -> 1 | F3: =E3*p_horas_productivas_dia -> 8 | G3: ESTIMADO
A4: 45660 | B4: =WEEKDAY(A4,2) -> 5 | C4: 1 | E4: =IF(AND(p_aplicar_feriados=1,D4<>""),0,C4) -> 1 | F4: =E4*p_horas_productivas_dia -> 8 | G4: ESTIMADO
A5: 45661 | B5: =WEEKDAY(A5,2) -> 6 | C5: 0 | E5: =IF(AND(p_aplicar_feriados=1,D5<>""),0,C5) -> 0 | F5: =E5*p_horas_productivas_dia -> 0 | G5: ESTIMADO
A6: 45662 | B6: =WEEKDAY(A6,2) -> 7 | C6: 0 | E6: =IF(AND(p_aplicar_feriados=1,D6<>""),0,C6) -> 0 | F6: =E6*p_horas_productivas_dia -> 0 | G6: ESTIMADO
A7: 45663 | B7: =WEEKDAY(A7,2) -> 1 | C7: 1 | E7: =IF(AND(p_aplicar_feriados=1,D7<>""),0,C7) -> 1 | F7: =E7*p_horas_productivas_dia -> 8 | G7: ESTIMADO
A8: 45664 | B8: =WEEKDAY(A8,2) -> 2 | C8: 1 | E8: =IF(AND(p_aplicar_feriados=1,D8<>""),0,C8) -> 1 | F8: =E8*p_horas_productivas_dia -> 8 | G8: ESTIMADO
A9: 45665 | B9: =WEEKDAY(A9,2) -> 3 | C9: 1 | E9: =IF(AND(p_aplicar_feriados=1,D9<>""),0,C9) -> 1 | F9: =E9*p_horas_productivas_dia -> 8 | G9: ESTIMADO
A10: 45666 | B10: =WEEKDAY(A10,2) -> 4 | C10: 1 | E10: =IF(AND(p_aplicar_feriados=1,D10<>""),0,C10) -> 1 | F10: =E10*p_horas_productivas_dia -> 8 | G10: ESTIMADO
A11: 45667 | B11: =WEEKDAY(A11,2) -> 5 | C11: 1 | E11: =IF(AND(p_aplicar_feriados=1,D11<>""),0,C11) -> 1 | F11: =E11*p_horas_productivas_dia -> 8 | G11: ESTIMADO
A12: 45668 | B12: =WEEKDAY(A12,2) -> 6 | C12: 0 | E12: =IF(AND(p_aplicar_feriados=1,D12<>""),0,C12) -> 0 | F12: =E12*p_horas_productivas_dia -> 0 | G12: ESTIMADO
A13: 45669 | B13: =WEEKDAY(A13,2) -> 7 | C13: 0 | E13: =IF(AND(p_aplicar_feriados=1,D13<>""),0,C13) -> 0 | F13: =E13*p_horas_productivas_dia -> 0 | G13: ESTIMADO
A14: 45670 | B14: =WEEKDAY(A14,2) -> 1 | C14: 1 | E14: =IF(AND(p_aplicar_feriados=1,D14<>""),0,C14) -> 1 | F14: =E14*p_horas_productivas_dia -> 8 | G14: ESTIMADO
... A107: 45763 | B107: =WEEKDAY(A107,2) -> 3 | C107: 1 | E107: =IF(AND(p_aplicar_feriados=1,D107<>""),0,C107) -> 1 | F107: =E107*p_horas_productivas_dia -> 8 | G107: ESTIMADO
A108: 45764 | B108: =WEEKDAY(A108,2) -> 4 | C108: 1 | D108: Jueves Santo | E108: =IF(AND(p_aplicar_feriados=1,D108<>""),0,C108) -> 1 | F108: =E108*p_horas_productivas_dia -> 8 | G108: ESTIMADO
A109: 45765 | B109: =WEEKDAY(A109,2) -> 5 | C109: 1 | D109: Viernes Santo | E109: =IF(AND(p_aplicar_feriados=1,D109<>""),0,C109) -> 1 | F109: =E109*p_horas_productivas_dia -> 8 | G109: ESTIMADO
A110: 45766 | B110: =WEEKDAY(A110,2) -> 6 | C110: 0 | E110: =IF(AND(p_aplicar_feriados=1,D110<>""),0,C110) -> 0 | F110: =E110*p_horas_productivas_dia -> 0 | G110: ESTIMADO
A111: 45767 | B111: =WEEKDAY(A111,2) -> 7 | C111: 0 | E111: =IF(AND(p_aplicar_feriados=1,D111<>""),0,C111) -> 0 | F111: =E111*p_horas_productivas_dia -> 0 | G111: ESTIMADO
A112: 45768 | B112: =WEEKDAY(A112,2) -> 1 | C112: 1 | E112: =IF(AND(p_aplicar_feriados=1,D112<>""),0,C112) -> 1 | F112: =E112*p_horas_productivas_dia -> 8 | G112: ESTIMADO
A113: 45769 | B113: =WEEKDAY(A113,2) -> 2 | C113: 1 | E113: =IF(AND(p_aplicar_feriados=1,D113<>""),0,C113) -> 1 | F113: =E113*p_horas_productivas_dia -> 8 | G113: ESTIMADO
A114: 45770 | B114: =WEEKDAY(A114,2) -> 3 | C114: 1 | E114: =IF(AND(p_aplicar_feriados=1,D114<>""),0,C114) -> 1 | F114: =E114*p_horas_productivas_dia -> 8 | G114: ESTIMADO
A115: 45771 | B115: =WEEKDAY(A115,2) -> 4 | C115: 1 | E115: =IF(AND(p_aplicar_feriados=1,D115<>""),0,C115) -> 1 | F115: =E115*p_horas_productivas_dia -> 8 | G115: ESTIMADO
A116: 45772 | B116: =WEEKDAY(A116,2) -> 5 | C116: 1 | E116: =IF(AND(p_aplicar_feriados=1,D116<>""),0,C116) -> 1 | F116: =E116*p_horas_productivas_dia -> 8 | G116: ESTIMADO
A117: 45773 | B117: =WEEKDAY(A117,2) -> 6 | C117: 0 | E117: =IF(AND(p_aplicar_feriados=1,D117<>""),0,C117) -> 0 | F117: =E117*p_horas_productivas_dia -> 0 | G117: ESTIMADO
A118: 45774 | B118: =WEEKDAY(A118,2) -> 7 | C118: 0 | E118: =IF(AND(p_aplicar_feriados=1,D118<>""),0,C118) -> 0 | F118: =E118*p_horas_productivas_dia -> 0 | G118: ESTIMADO
A119: 45775 | B119: =WEEKDAY(A119,2) -> 1 | C119: 1 | E119: =IF(AND(p_aplicar_feriados=1,D119<>""),0,C119) -> 1 | F119: =E119*p_horas_productivas_dia -> 8 | G119: ESTIMADO
A120: 45776 | B120: =WEEKDAY(A120,2) -> 2 | C120: 1 | E120: =IF(AND(p_aplicar_feriados=1,D120<>""),0,C120) -> 1 | F120: =E120*p_horas_productivas_dia -> 8 | G120: ESTIMADO
A121: 45777 | B121: =WEEKDAY(A121,2) -> 3 | C121: 1 | E121: =IF(AND(p_aplicar_feriados=1,D121<>""),0,C121) -> 1 | F121: =E121*p_horas_productivas_dia -> 8 | G121: ESTIMADO
A122: 45778 | B122: =WEEKDAY(A122,2) -> 4 | C122: 1 | D122: Día del Trabajo | E122: =IF(AND(p_aplicar_feriados=1,D122<>""),0,C122) -> 1 | F122: =E122*p_horas_productivas_dia -> 8 | G122: ESTIMADO
A123: 45779 | B123: =WEEKDAY(A123,2) -> 5 | C123: 1 | E123: =IF(AND(p_aplicar_feriados=1,D123<>""),0,C123) -> 1 | F123: =E123*p_horas_productivas_dia -> 8 | G123: ESTIMADO
A124: 45780 | B124: =WEEKDAY(A124,2) -> 6 | C124: 0 | E124: =IF(AND(p_aplicar_feriados=1,D124<>""),0,C124) -> 0 | F124: =E124*p_horas_productivas_dia -> 0 | G124: ESTIMADO
A125: 45781 | B125: =WEEKDAY(A125,2) -> 7 | C125: 0 | E125: =IF(AND(p_aplicar_feriados=1,D125<>""),0,C125) -> 0 | F125: =E125*p_horas_productivas_dia -> 0 | G125: ESTIMADO
A126: 45782 | B126: =WEEKDAY(A126,2) -> 1 | C126: 1 | E126: =IF(AND(p_aplicar_feriados=1,D126<>""),0,C126) -> 1 | F126: =E126*p_horas_productivas_dia -> 8 | G126: ESTIMADO
A127: 45783 | B127: =WEEKDAY(A127,2) -> 2 | C127: 1 | E127: =IF(AND(p_aplicar_feriados=1,D127<>""),0,C127) -> 1 | F127: =E127*p_horas_productivas_dia -> 8 | G127: ESTIMADO
A128: 45784 | B128: =WEEKDAY(A128,2) -> 3 | C128: 1 | E128: =IF(AND(p_aplicar_feriados=1,D128<>""),0,C128) -> 1 | F128: =E128*p_horas_productivas_dia -> 8 | G128: ESTIMADO
A129: 45785 | B129: =WEEKDAY(A129,2) -> 4 | C129: 1 | E129: =IF(AND(p_aplicar_feriados=1,D129<>""),0,C129) -> 1 | F129: =E129*p_horas_productivas_dia -> 8 | G129: ESTIMADO
A130: 45786 | B130: =WEEKDAY(A130,2) -> 5 | C130: 1 | E130: =IF(AND(p_aplicar_feriados=1,D130<>""),0,C130) -> 1 | F130: =E130*p_horas_productivas_dia -> 8 | G130: ESTIMADO
A131: 45787 | B131: =WEEKDAY(A131,2) -> 6 | C131: 0 | E131: =IF(AND(p_aplicar_feriados=1,D131<>""),0,C131) -> 0 | F131: =E131*p_horas_productivas_dia -> 0 | G131: ESTIMADO
A132: 45788 | B132: =WEEKDAY(A132,2) -> 7 | C132: 0 | E132: =IF(AND(p_aplicar_feriados=1,D132<>""),0,C132) -> 0 | F132: =E132*p_horas_productivas_dia -> 0 | G132: ESTIMADO
A133: 45789 | B133: =WEEKDAY(A133,2) -> 1 | C133: 1 | E133: =IF(AND(p_aplicar_feriados=1,D133<>""),0,C133) -> 1 | F133: =E133*p_horas_productivas_dia -> 8 | G133: ESTIMADO
A134: 45790 | B134: =WEEKDAY(A134,2) -> 2 | C134: 1 | E134: =IF(AND(p_aplicar_feriados=1,D134<>""),0,C134) -> 1 | F134: =E134*p_horas_productivas_dia -> 8 | G134: ESTIMADO
... A158: 45814 | B158: =WEEKDAY(A158,2) -> 5 | C158: 1 | E158: =IF(AND(p_aplicar_feriados=1,D158<>""),0,C158) -> 1 | F158: =E158*p_horas_productivas_dia -> 8 | G158: ESTIMADO
A159: 45815 | B159: =WEEKDAY(A159,2) -> 6 | C159: 0 | D159: Batalla de Arica y Día de la Bandera | E159: =IF(AND(p_aplicar_feriados=1,D159<>""),0,C159) -> 0 | F159: =E159*p_horas_productivas_dia -> 0 | G159: ESTIMADO
A160: 45816 | B160: =WEEKDAY(A160,2) -> 7 | C160: 0 | E160: =IF(AND(p_aplicar_feriados=1,D160<>""),0,C160) -> 0 | F160: =E160*p_horas_productivas_dia -> 0 | G160: ESTIMADO
A161: 45817 | B161: =WEEKDAY(A161,2) -> 1 | C161: 1 | E161: =IF(AND(p_aplicar_feriados=1,D161<>""),0,C161) -> 1 | F161: =E161*p_horas_productivas_dia -> 8 | G161: ESTIMADO
A162: 45818 | B162: =WEEKDAY(A162,2) -> 2 | C162: 1 | E162: =IF(AND(p_aplicar_feriados=1,D162<>""),0,C162) -> 1 | F162: =E162*p_horas_productivas_dia -> 8 | G162: ESTIMADO
A163: 45819 | B163: =WEEKDAY(A163,2) -> 3 | C163: 1 | E163: =IF(AND(p_aplicar_feriados=1,D163<>""),0,C163) -> 1 | F163: =E163*p_horas_productivas_dia -> 8 | G163: ESTIMADO
A164: 45820 | B164: =WEEKDAY(A164,2) -> 4 | C164: 1 | E164: =IF(AND(p_aplicar_feriados=1,D164<>""),0,C164) -> 1 | F164: =E164*p_horas_productivas_dia -> 8 | G164: ESTIMADO
A165: 45821 | B165: =WEEKDAY(A165,2) -> 5 | C165: 1 | E165: =IF(AND(p_aplicar_feriados=1,D165<>""),0,C165) -> 1 | F165: =E165*p_horas_productivas_dia -> 8 | G165: ESTIMADO
A166: 45822 | B166: =WEEKDAY(A166,2) -> 6 | C166: 0 | E166: =IF(AND(p_aplicar_feriados=1,D166<>""),0,C166) -> 0 | F166: =E166*p_horas_productivas_dia -> 0 | G166: ESTIMADO
A167: 45823 | B167: =WEEKDAY(A167,2) -> 7 | C167: 0 | E167: =IF(AND(p_aplicar_feriados=1,D167<>""),0,C167) -> 0 | F167: =E167*p_horas_productivas_dia -> 0 | G167: ESTIMADO
A168: 45824 | B168: =WEEKDAY(A168,2) -> 1 | C168: 1 | E168: =IF(AND(p_aplicar_feriados=1,D168<>""),0,C168) -> 1 | F168: =E168*p_horas_productivas_dia -> 8 | G168: ESTIMADO
A169: 45825 | B169: =WEEKDAY(A169,2) -> 2 | C169: 1 | E169: =IF(AND(p_aplicar_feriados=1,D169<>""),0,C169) -> 1 | F169: =E169*p_horas_productivas_dia -> 8 | G169: ESTIMADO
A170: 45826 | B170: =WEEKDAY(A170,2) -> 3 | C170: 1 | E170: =IF(AND(p_aplicar_feriados=1,D170<>""),0,C170) -> 1 | F170: =E170*p_horas_productivas_dia -> 8 | G170: ESTIMADO
A171: 45827 | B171: =WEEKDAY(A171,2) -> 4 | C171: 1 | E171: =IF(AND(p_aplicar_feriados=1,D171<>""),0,C171) -> 1 | F171: =E171*p_horas_productivas_dia -> 8 | G171: ESTIMADO
... A180: 45836 | B180: =WEEKDAY(A180,2) -> 6 | C180: 0 | E180: =IF(AND(p_aplicar_feriados=1,D180<>""),0,C180) -> 0 | F180: =E180*p_horas_productivas_dia -> 0 | G180: ESTIMADO
A181: 45837 | B181: =WEEKDAY(A181,2) -> 7 | C181: 0 | D181: San Pedro y San Pablo | E181: =IF(AND(p_aplicar_feriados=1,D181<>""),0,C181) -> 0 | F181: =E181*p_horas_productivas_dia -> 0 | G181: ESTIMADO
A182: 45838 | B182: =WEEKDAY(A182,2) -> 1 | C182: 1 | E182: =IF(AND(p_aplicar_feriados=1,D182<>""),0,C182) -> 1 | F182: =E182*p_horas_productivas_dia -> 8 | G182: ESTIMADO
A183: 45839 | B183: =WEEKDAY(A183,2) -> 2 | C183: 1 | E183: =IF(AND(p_aplicar_feriados=1,D183<>""),0,C183) -> 1 | F183: =E183*p_horas_productivas_dia -> 8 | G183: ESTIMADO
A184: 45840 | B184: =WEEKDAY(A184,2) -> 3 | C184: 1 | E184: =IF(AND(p_aplicar_feriados=1,D184<>""),0,C184) -> 1 | F184: =E184*p_horas_productivas_dia -> 8 | G184: ESTIMADO
A185: 45841 | B185: =WEEKDAY(A185,2) -> 4 | C185: 1 | E185: =IF(AND(p_aplicar_feriados=1,D185<>""),0,C185) -> 1 | F185: =E185*p_horas_productivas_dia -> 8 | G185: ESTIMADO
A186: 45842 | B186: =WEEKDAY(A186,2) -> 5 | C186: 1 | E186: =IF(AND(p_aplicar_feriados=1,D186<>""),0,C186) -> 1 | F186: =E186*p_horas_productivas_dia -> 8 | G186: ESTIMADO
A187: 45843 | B187: =WEEKDAY(A187,2) -> 6 | C187: 0 | E187: =IF(AND(p_aplicar_feriados=1,D187<>""),0,C187) -> 0 | F187: =E187*p_horas_productivas_dia -> 0 | G187: ESTIMADO
A188: 45844 | B188: =WEEKDAY(A188,2) -> 7 | C188: 0 | E188: =IF(AND(p_aplicar_feriados=1,D188<>""),0,C188) -> 0 | F188: =E188*p_horas_productivas_dia -> 0 | G188: ESTIMADO
A189: 45845 | B189: =WEEKDAY(A189,2) -> 1 | C189: 1 | E189: =IF(AND(p_aplicar_feriados=1,D189<>""),0,C189) -> 1 | F189: =E189*p_horas_productivas_dia -> 8 | G189: ESTIMADO
A190: 45846 | B190: =WEEKDAY(A190,2) -> 2 | C190: 1 | E190: =IF(AND(p_aplicar_feriados=1,D190<>""),0,C190) -> 1 | F190: =E190*p_horas_productivas_dia -> 8 | G190: ESTIMADO
A191: 45847 | B191: =WEEKDAY(A191,2) -> 3 | C191: 1 | E191: =IF(AND(p_aplicar_feriados=1,D191<>""),0,C191) -> 1 | F191: =E191*p_horas_productivas_dia -> 8 | G191: ESTIMADO
A192: 45848 | B192: =WEEKDAY(A192,2) -> 4 | C192: 1 | E192: =IF(AND(p_aplicar_feriados=1,D192<>""),0,C192) -> 1 | F192: =E192*p_horas_productivas_dia -> 8 | G192: ESTIMADO
A193: 45849 | B193: =WEEKDAY(A193,2) -> 5 | C193: 1 | E193: =IF(AND(p_aplicar_feriados=1,D193<>""),0,C193) -> 1 | F193: =E193*p_horas_productivas_dia -> 8 | G193: ESTIMADO
... A204: 45860 | B204: =WEEKDAY(A204,2) -> 2 | C204: 1 | E204: =IF(AND(p_aplicar_feriados=1,D204<>""),0,C204) -> 1 | F204: =E204*p_horas_productivas_dia -> 8 | G204: ESTIMADO
A205: 45861 | B205: =WEEKDAY(A205,2) -> 3 | C205: 1 | D205: Día de la Fuerza Aérea del Perú | E205: =IF(AND(p_aplicar_feriados=1,D205<>""),0,C205) -> 1 | F205: =E205*p_horas_productivas_dia -> 8 | G205: ESTIMADO
A206: 45862 | B206: =WEEKDAY(A206,2) -> 4 | C206: 1 | E206: =IF(AND(p_aplicar_feriados=1,D206<>""),0,C206) -> 1 | F206: =E206*p_horas_productivas_dia -> 8 | G206: ESTIMADO
A207: 45863 | B207: =WEEKDAY(A207,2) -> 5 | C207: 1 | E207: =IF(AND(p_aplicar_feriados=1,D207<>""),0,C207) -> 1 | F207: =E207*p_horas_productivas_dia -> 8 | G207: ESTIMADO
A208: 45864 | B208: =WEEKDAY(A208,2) -> 6 | C208: 0 | E208: =IF(AND(p_aplicar_feriados=1,D208<>""),0,C208) -> 0 | F208: =E208*p_horas_productivas_dia -> 0 | G208: ESTIMADO
A209: 45865 | B209: =WEEKDAY(A209,2) -> 7 | C209: 0 | E209: =IF(AND(p_aplicar_feriados=1,D209<>""),0,C209) -> 0 | F209: =E209*p_horas_productivas_dia -> 0 | G209: ESTIMADO
A210: 45866 | B210: =WEEKDAY(A210,2) -> 1 | C210: 1 | D210: Fiestas Patrias | E210: =IF(AND(p_aplicar_feriados=1,D210<>""),0,C210) -> 1 | F210: =E210*p_horas_productivas_dia -> 8 | G210: ESTIMADO
A211: 45867 | B211: =WEEKDAY(A211,2) -> 2 | C211: 1 | D211: Fiestas Patrias | E211: =IF(AND(p_aplicar_feriados=1,D211<>""),0,C211) -> 1 | F211: =E211*p_horas_productivas_dia -> 8 | G211: ESTIMADO
A212: 45868 | B212: =WEEKDAY(A212,2) -> 3 | C212: 1 | E212: =IF(AND(p_aplicar_feriados=1,D212<>""),0,C212) -> 1 | F212: =E212*p_horas_productivas_dia -> 8 | G212: ESTIMADO
A213: 45869 | B213: =WEEKDAY(A213,2) -> 4 | C213: 1 | E213: =IF(AND(p_aplicar_feriados=1,D213<>""),0,C213) -> 1 | F213: =E213*p_horas_productivas_dia -> 8 | G213: ESTIMADO
A214: 45870 | B214: =WEEKDAY(A214,2) -> 5 | C214: 1 | E214: =IF(AND(p_aplicar_feriados=1,D214<>""),0,C214) -> 1 | F214: =E214*p_horas_productivas_dia -> 8 | G214: ESTIMADO
A215: 45871 | B215: =WEEKDAY(A215,2) -> 6 | C215: 0 | E215: =IF(AND(p_aplicar_feriados=1,D215<>""),0,C215) -> 0 | F215: =E215*p_horas_productivas_dia -> 0 | G215: ESTIMADO
A216: 45872 | B216: =WEEKDAY(A216,2) -> 7 | C216: 0 | E216: =IF(AND(p_aplicar_feriados=1,D216<>""),0,C216) -> 0 | F216: =E216*p_horas_productivas_dia -> 0 | G216: ESTIMADO
A217: 45873 | B217: =WEEKDAY(A217,2) -> 1 | C217: 1 | E217: =IF(AND(p_aplicar_feriados=1,D217<>""),0,C217) -> 1 | F217: =E217*p_horas_productivas_dia -> 8 | G217: ESTIMADO
A218: 45874 | B218: =WEEKDAY(A218,2) -> 2 | C218: 1 | E218: =IF(AND(p_aplicar_feriados=1,D218<>""),0,C218) -> 1 | F218: =E218*p_horas_productivas_dia -> 8 | G218: ESTIMADO
A219: 45875 | B219: =WEEKDAY(A219,2) -> 3 | C219: 1 | D219: Batalla de Junín | E219: =IF(AND(p_aplicar_feriados=1,D219<>""),0,C219) -> 1 | F219: =E219*p_horas_productivas_dia -> 8 | G219: ESTIMADO
A220: 45876 | B220: =WEEKDAY(A220,2) -> 4 | C220: 1 | E220: =IF(AND(p_aplicar_feriados=1,D220<>""),0,C220) -> 1 | F220: =E220*p_horas_productivas_dia -> 8 | G220: ESTIMADO
A221: 45877 | B221: =WEEKDAY(A221,2) -> 5 | C221: 1 | E221: =IF(AND(p_aplicar_feriados=1,D221<>""),0,C221) -> 1 | F221: =E221*p_horas_productivas_dia -> 8 | G221: ESTIMADO
A222: 45878 | B222: =WEEKDAY(A222,2) -> 6 | C222: 0 | E222: =IF(AND(p_aplicar_feriados=1,D222<>""),0,C222) -> 0 | F222: =E222*p_horas_productivas_dia -> 0 | G222: ESTIMADO
A223: 45879 | B223: =WEEKDAY(A223,2) -> 7 | C223: 0 | E223: =IF(AND(p_aplicar_feriados=1,D223<>""),0,C223) -> 0 | F223: =E223*p_horas_productivas_dia -> 0 | G223: ESTIMADO
A224: 45880 | B224: =WEEKDAY(A224,2) -> 1 | C224: 1 | E224: =IF(AND(p_aplicar_feriados=1,D224<>""),0,C224) -> 1 | F224: =E224*p_horas_productivas_dia -> 8 | G224: ESTIMADO
A225: 45881 | B225: =WEEKDAY(A225,2) -> 2 | C225: 1 | E225: =IF(AND(p_aplicar_feriados=1,D225<>""),0,C225) -> 1 | F225: =E225*p_horas_productivas_dia -> 8 | G225: ESTIMADO
A226: 45882 | B226: =WEEKDAY(A226,2) -> 3 | C226: 1 | E226: =IF(AND(p_aplicar_feriados=1,D226<>""),0,C226) -> 1 | F226: =E226*p_horas_productivas_dia -> 8 | G226: ESTIMADO
A227: 45883 | B227: =WEEKDAY(A227,2) -> 4 | C227: 1 | E227: =IF(AND(p_aplicar_feriados=1,D227<>""),0,C227) -> 1 | F227: =E227*p_horas_productivas_dia -> 8 | G227: ESTIMADO
A228: 45884 | B228: =WEEKDAY(A228,2) -> 5 | C228: 1 | E228: =IF(AND(p_aplicar_feriados=1,D228<>""),0,C228) -> 1 | F228: =E228*p_horas_productivas_dia -> 8 | G228: ESTIMADO
A229: 45885 | B229: =WEEKDAY(A229,2) -> 6 | C229: 0 | E229: =IF(AND(p_aplicar_feriados=1,D229<>""),0,C229) -> 0 | F229: =E229*p_horas_productivas_dia -> 0 | G229: ESTIMADO
A230: 45886 | B230: =WEEKDAY(A230,2) -> 7 | C230: 0 | E230: =IF(AND(p_aplicar_feriados=1,D230<>""),0,C230) -> 0 | F230: =E230*p_horas_productivas_dia -> 0 | G230: ESTIMADO
A231: 45887 | B231: =WEEKDAY(A231,2) -> 1 | C231: 1 | E231: =IF(AND(p_aplicar_feriados=1,D231<>""),0,C231) -> 1 | F231: =E231*p_horas_productivas_dia -> 8 | G231: ESTIMADO
... A242: 45898 | B242: =WEEKDAY(A242,2) -> 5 | C242: 1 | E242: =IF(AND(p_aplicar_feriados=1,D242<>""),0,C242) -> 1 | F242: =E242*p_horas_productivas_dia -> 8 | G242: ESTIMADO
A243: 45899 | B243: =WEEKDAY(A243,2) -> 6 | C243: 0 | D243: Santa Rosa de Lima | E243: =IF(AND(p_aplicar_feriados=1,D243<>""),0,C243) -> 0 | F243: =E243*p_horas_productivas_dia -> 0 | G243: ESTIMADO
...

Sheet 10_CAPACIDAD_MENSUAL
A1: recurso_id | B1: mes | C1: dias_productivos | D1: horas_dia | E1: cantidad | F1: horas_disponibles | G1: naturaleza
A2: CCH-01 | B2: 1 | C2: =SUMPRODUCT((MONTH('09_CALENDARIO'!$A$2:$A$397)=B2)*(YEAR('09_CALENDARIO'!$A$2:$A$397)=p_anio_base)*'09_CALENDARIO'!$E$2:$E$397) -> 23 | D2: =p_horas_productivas_dia -> 8 | E2: =INDEX('05_RECURSOS'!$E$2:$E$18,MATCH(A2,'05_RECURSOS'!$A$2:$A$18,0)) -> 1 | F2: =C2*D2*E2 -> 184 | G2: CALCULADO
A3: CCH-01 | B3: 2 | C3: =SUMPRODUCT((MONTH('09_CALENDARIO'!$A$2:$A$397)=B3)*(YEAR('09_CALENDARIO'!$A$2:$A$397)=p_anio_base)*'09_CALENDARIO'!$E$2:$E$397) -> 20 | D3: =p_horas_productivas_dia -> 8 | E3: =INDEX('05_RECURSOS'!$E$2:$E$18,MATCH(A3,'05_RECURSOS'!$A$2:$A$18,0)) -> 1 | F3: =C3*D3*E3 -> 160 | G3: CALCULADO
A4: CCH-01 | B4: 3 | C4: =SUMPRODUCT((MONTH('09_CALENDARIO'!$A$2:$A$397)=B4)*(YEAR('09_CALENDARIO'!$A$2:$A$397)=p_anio_base)*'09_CALENDARIO'!$E$2:$E$397) -> 21 | D4: =p_horas_productivas_dia -> 8 | E4: =INDEX('05_RECURSOS'!$E$2:$E$18,MATCH(A4,'05_RECURSOS'!$A$2:$A$18,0)) -> 1 | F4: =C4*D4*E4 -> 168 | G4: CALCULADO
A5: CCH-01 | B5: 4 | C5: =SUMPRODUCT((MONTH('09_CALENDARIO'!$A$2:$A$397)=B5)*(YEAR('09_CALENDARIO'!$A$2:$A$397)=p_anio_base)*'09_CALENDARIO'!$E$2:$E$397) -> 22 | D5: =p_horas_productivas_dia -> 8 | E5: =INDEX('05_RECURSOS'!$E$2:$E$18,MATCH(A5,'05_RECURSOS'!$A$2:$A$18,0)) -> 1 | F5: =C5*D5*E5 -> 176 | G5: CALCULADO
A6: CCH-01 | B6: 5 | C6: =SUMPRODUCT((MONTH('09_CALENDARIO'!$A$2:$A$397)=B6)*(YEAR('09_CALENDARIO'!$A$2:$A$397)=p_anio_base)*'09_CALENDARIO'!$E$2:$E$397) -> 22 | D6: =p_horas_productivas_dia -> 8 | E6: =INDEX('05_RECURSOS'!$E$2:$E$18,MATCH(A6,'05_RECURSOS'!$A$2:$A$18,0)) -> 1 | F6: =C6*D6*E6 -> 176 | G6: CALCULADO
A7: CCH-01 | B7: 6 | C7: =SUMPRODUCT((MONTH('09_CALENDARIO'!$A$2:$A$397)=B7)*(YEAR('09_CALENDARIO'!$A$2:$A$397)=p_anio_base)*'09_CALENDARIO'!$E$2:$E$397) -> 21 | D7: =p_horas_productivas_dia -> 8 | E7: =INDEX('05_RECURSOS'!$E$2:$E$18,MATCH(A7,'05_RECURSOS'!$A$2:$A$18,0)) -> 1 | F7: =C7*D7*E7 -> 168 | G7: CALCULADO
A8: CCH-01 | B8: 7 | C8: =SUMPRODUCT((MONTH('09_CALENDARIO'!$A$2:$A$397)=B8)*(YEAR('09_CALENDARIO'!$A$2:$A$397)=p_anio_base)*'09_CALENDARIO'!$E$2:$E$397) -> 23 | D8: =p_horas_productivas_dia -> 8 | E8: =INDEX('05_RECURSOS'!$E$2:$E$18,MATCH(A8,'05_RECURSOS'!$A$2:$A$18,0)) -> 1 | F8: =C8*D8*E8 -> 184 | G8: CALCULADO
A9: CCH-01 | B9: 8 | C9: =SUMPRODUCT((MONTH('09_CALENDARIO'!$A$2:$A$397)=B9)*(YEAR('09_CALENDARIO'!$A$2:$A$397)=p_anio_base)*'09_CALENDARIO'!$E$2:$E$397) -> 21 | D9: =p_horas_productivas_dia -> 8 | E9: =INDEX('05_RECURSOS'!$E$2:$E$18,MATCH(A9,'05_RECURSOS'!$A$2:$A$18,0)) -> 1 | F9: =C9*D9*E9 -> 168 | G9: CALCULADO
A10: CCH-01 | B10: 9 | C10: =SUMPRODUCT((MONTH('09_CALENDARIO'!$A$2:$A$397)=B10)*(YEAR('09_CALENDARIO'!$A$2:$A$397)=p_anio_base)*'09_CALENDARIO'!$E$2:$E$397) -> 22 | D10: =p_horas_productivas_dia -> 8 | E10: =INDEX('05_RECURSOS'!$E$2:$E$18,MATCH(A10,'05_RECURSOS'!$A$2:$A$18,0)) -> 1 | F10: =C10*D10*E10 -> 176 | G10: CALCULADO
A11: CCH-01 | B11: 10 | C11: =SUMPRODUCT((MONTH('09_CALENDARIO'!$A$2:$A$397)=B11)*(YEAR('09_CALENDARIO'!$A$2:$A$397)=p_anio_base)*'09_CALENDARIO'!$E$2:$E$397) -> 23 | D11: =p_horas_productivas_dia -> 8 | E11: =INDEX('05_RECURSOS'!$E$2:$E$18,MATCH(A11,'05_RECURSOS'!$A$2:$A$18,0)) -> 1 | F11: =C11*D11*E11 -> 184 | G11: CALCULADO
A12: CCH-01 | B12: 11 | C12: =SUMPRODUCT((MONTH('09_CALENDARIO'!$A$2:$A$397)=B12)*(YEAR('09_CALENDARIO'!$A$2:$A$397)=p_anio_base)*'09_CALENDARIO'!$E$2:$E$397) -> 20 | D12: =p_horas_productivas_dia -> 8 | E12: =INDEX('05_RECURSOS'!$E$2:$E$18,MATCH(A12,'05_RECURSOS'!$A$2:$A$18,0)) -> 1 | F12: =C12*D12*E12 -> 160 | G12: CALCULADO
A13: CCH-01 | B13: 12 | C13: =SUMPRODUCT((MONTH('09_CALENDARIO'!$A$2:$A$397)=B13)*(YEAR('09_CALENDARIO'!$A$2:$A$397)=p_anio_base)*'09_CALENDARIO'!$E$2:$E$397) -> 23 | D13: =p_horas_productivas_dia -> 8 | E13: =INDEX('05_RECURSOS'!$E$2:$E$18,MATCH(A13,'05_RECURSOS'!$A$2:$A$18,0)) -> 1 | F13: =C13*D13*E13 -> 184 | G13: CALCULADO
... A205: SAL-PIN | B205: 12 | C205: =SUMPRODUCT((MONTH('09_CALENDARIO'!$A$2:$A$397)=B205)*(YEAR('09_CALENDARIO'!$A$2:$A$397)=p_anio_base)*'09_CALENDARIO'!$E$2:$E$397) -> 23 | D205: =p_horas_productivas_dia -> 8 | E205: =INDEX('05_RECURSOS'!$E$2:$E$18,MATCH(A205,'05_RECURSOS'!$A$2:$A$18,0)) -> 1 | F205: =C205*D205*E205 -> 184 | G205: CALCULADO

Sheet 11_PARAMETROS
A1: parametro_id | B1: parametro | C1: valor_num | D1: valor_txt | E1: unidad | F1: naturaleza | G1: nota | H1: usado_por_python
A2: trabajadores_produccion | B2: Número total de trabajadores de producción | C2: 25 | E2: personas | F2: REAL | G2: Confirmado por la empresa (06C v1.2). | H2: 0
A3: turnos_por_dia | B3: Turnos diarios | C3: 1 | E3: turnos | F3: REAL | G3: Confirmado por la empresa. | H3: 0
A4: horas_productivas_dia | B4: Horas productivas por día | C4: 8 | E4: h/día | F4: REAL | G4: Jornada neta confirmada; el modelo la deriva de 'Jornada productiva'. | H4: 0
A5: jornada_productiva | B5: Jornada productiva | D5: 08:00-12:00 y 13:00-17:00 | E5: hora | F5: ESTIMADO | G5: Horario no confirmado por la empresa; define el eje de horas productivas. | H5: 1
A6: refrigerio | B6: Refrigerio | D6: 12:00-13:00 | E6: hora | F6: ESTIMADO | G6: Horario no confirmado. | H6: 0
A7: aplicar_feriados | B7: Aplicar feriados nacionales (1/0) | C7: 0 | E7: 1/0 | F7: CONFIGURACION | G7: 0 = calendario v1.2 (feriados laborables). Práctica real de SAGAPI pendiente de confirmación. | H7: 1
A8: anio_base | B8: Año base del estudio | C8: 2025 | E8: año | F8: CONFIGURACION | H8: 0
A9: hora_liberacion | B9: Hora de liberación | D9: 08:00 | E9: hora | F9: ESTIMADO | G9: Fijada en el código (instancia.py); el valor aquí es informativo. | H9: 0
A10: hora_vencimiento | B10: Hora de vencimiento d_j | D10: 17:00 | E10: hora | F10: ESTIMADO | G10: Cierre del día comprometido o del último día productivo previo (calendario.py). | H10: 0
A11: densidad_acero | B11: Densidad del acero | C11: 7850 | E11: kg/m³ | F11: REFERENCIA | G11: Constante física; reproduce exactamente la masa de chapa de v1.2. | H11: 0
A12: kg_por_m_perfil | B12: Masa lineal del perfil genérico | C12: 1.5 | E12: kg/m | F12: ESTIMADO | G12: Implícito en v1.2 (masa = piezas × longitud × 1,5); sección del perfil por definir. | H12: 0
A13: aprovechamiento_chapa | B13: Factor de aprovechamiento de chapa | C13: 0.92 | E13: fracción | F13: ESTIMADO | G13: Implícito en v1.2 (costo = masa × precio / 0,92); sin medición de merma. | H13: 0
A14: aprovechamiento_perfil | B14: Factor de aprovechamiento de perfil | C14: 0.96 | E14: fracción | F14: ESTIMADO | G14: Implícito en v1.2 (costo = masa × precio / 0,96). | H14: 0
A15: area_plancha_m2 | B15: Área de plancha estándar 1,20 × 2,40 m | C15: 2.88 | E15: m² | F15: ESTIMADO | G15: Formato del material MAT-LAC2; no confirma que todas las chapas se compren en ese formato. | H15: 0
A16: costo_hora_hombre | B16: Costo hora-hombre | C16: 13 | E16: S/ por h | F16: ESTIMADO | G16: Supuesto económico sin planilla. | H16: 0
A17: tarifa_electrica | B17: Tarifa eléctrica | C17: 0.65 | E17: S/ por kWh | F17: ESTIMADO | G17: Verificar con recibo eléctrico. | H17: 0
A18: factor_emision_red | B18: Factor de emisión de la red | E18: kg CO2/kWh | F18: PENDIENTE | G18: Sin dato oficial cargado; el programa no calcula CO2. | H18: 0
A19: ventas_anuales | B19: Ventas anuales aproximadas | C19: 2000000 | E19: S/ | F19: REAL | G19: Declarado por la empresa. | H19: 0
A20: uit_2025 | B20: UIT 2025 | C20: 5350 | E20: S/ | F20: REFERENCIA | G20: Valor oficial 2025. | H20: 0
A21: ciclo_horno_min | B21: Ciclo horno | C21: 40 | E21: min por carga | F21: ESTIMADO | G21: Incluido en el tiempo fijo (45 min) del curado en 06_RUTAS. | H21: 0
A22: capacidad_horno_carga | B22: Capacidad horno por lote | C22: 10 | E22: piezas por carga (declarado) | F22: ESTIMADO | G22: Conflicto de unidades: el lote del modelo es de 10 UNIDADES de producto, no 10 piezas. | H22: 0
A23: categoria_empresarial | B23: Categoría empresarial (Ley 30056) | D23: =IF(C19/C20<=150,"Microempresa",IF(C19/C20<=1700,"Pequeña empresa",IF(C19/C20<=2300,"Mediana empresa","Gran empresa"))) -> Pequeña empresa | E23: - | F23: CALCULADO | G23: Ventas anuales / UIT según Ley 30056. | H23: 0

Sheet 12_REG_ENTREGAS
A1: pedido_real_id | B1: producto_id | C1: cliente_codigo | D1: unidades | E1: fecha_recepcion | F1: fecha_liberacion | G1: fecha_compromiso | H1: fecha_entrega | I1: unidades_conformes | J1: unidades_no_conformes | K1: precio_venta_soles | L1: penalidad_contractual_frac | M1: causa_atraso | N1: fuente_documento

Sheet 13_REG_PARADAS
A1: parada_id | B1: recurso_id | C1: inicio | D1: fin | E1: tipo_parada | F1: causa | G1: pedido_afectado | H1: piezas_perdidas | I1: registrado_por | J1: fuente_documento

Sheet 14_REG_CALIDAD
A1: inspeccion_id | B1: pedido_real_id | C1: producto_id | D1: fecha | E1: cantidad_inspeccionada | F1: conformes | G1: no_conformes | H1: defecto | I1: reproceso_h | J1: material_perdido_soles

Sheet 15_REG_TIEMPOS
A1: medicion_id | B1: producto_id | C1: paso | D1: recurso_id | E1: fecha | F1: unidades_medidas | G1: min_preparacion_obs | H1: min_total_obs | I1: operarios_en_operacion | J1: metodo | K1: observador

Sheet 16_REG_HABILIDADES
A1: operario_id | B1: recurso_id | C1: nivel_0_3 | D1: opera_solo_1_0 | E1: validado_por | F1: fecha_validacion
